Workbook

Sheet （新）processed_results
A1: 文件名 | B1: 处理时间 | C1: 案例编号 | D1: 案例名称 | E1: 地区 | F1: 学段 | G1: 产业应用现状 | H1: 优势和创新点 | I1: 关键技术路径 | J1: 技术要素 | K1: 工具名称 | L1: 企业名称 | M1: 是否自主研发 | N1: 产品形态 | O1: 产品分类 | P1: 文档内容依据 | Q1: 应用场景（一级） | R1: 应用场景（二级） | S1: 培养方向 | T1: 潜在成效 | U1: 关键技术路径 | V1: 技术要素 | W1: 产业应用现状 | X1: 优势和创新点 | Y1: 学科 | Z1: 工具标准名 | AA1: 公司 | AB1: 省份 | AD1: 产品名（校准） | AE1: 分类标准_产业角度（一级） | AF1: 分类标准_产业角度（二级） | AG1: 分类标准_[教育角度] | AH1: 产品属性 | AI1: 产品名_是否大模型 | AJ1: 省份_更新
A2: 第01号案例_1温州市新田园小学 叶诗婧《数“算”生“动”：AI赋能下运算律教学的新样态》.pdf | B2: 46056.45 | C2: 1 | D2: 数“算”生“动”：AI赋能下运算律教学的新样态 | E2: 温州市 | F2: 小学 | G2: 企业产品以“学习支持工具”为主，学校多通过校本化规则实现教学适配，整体处于规模化应用初期 | H2: 通过动态点子图和AI语音交互，将抽象的运算律转化为可操作的探究过程，实现了概念理解从抽象到直观、思维过程从内隐到外显的突破。 | I2: 学习行为采集 → 学情诊断与画像生成 → 个性化反馈与辅导 → 学习改进 | J2: ["语音识别", "动态可视化", "学习行为分析模型", "教育数据挖掘", "人工智能算法"] | K2: AI学习机 | L2: 易点慧科技有限公司 | M2: TRUE | N2: 硬件 + AI系统 | O2: 平台型综合系统 | P2: 文档中提到“AI学习机作为课堂互动工具，实现个性化教学。” | Q2: 助学 | R2: 智能辅导系统 | S2: 智育 | T2: 学生：深化算理理解、提升表达与推理能力；教师：实现精准诊断与即时干预；学校：形成可复制的“AI+概念教学”范式 | U2: 学习行为采集 → 学情诊断与画像生成 → 个性化反馈与辅导 → 学习改进 | V2: 数据采集层（多模态学习数据采集与融合） 画像诊断层（个性化画像生成、过程性反馈解释） 个性化学习层（即时生成反馈） | W2: 企业产品以“学习支持工具”为主，学校多通过校本化规则实现教学适配，整体处于规模化应用初期 | X2: AI点子图可视化 + AI说理，将抽象运算律转化为可操作模型，实现“理解—表达—诊断”闭环 | Y2: 数学 | Z2: AI学习机 | AA2: 0 | AB2: 浙江省 | AD2: =VLOOKUP($K2,「工具标准名」映射表!$B:$I,3,0) -> AI学习机 | AE2: =VLOOKUP($K2,「工具标准名」映射表!$B:$I,4,0) -> 功能应用层 | AF2: =VLOOKUP($K2,「工具标准名」映射表!$B:$I,5,0) -> 功能应用（教学辅助工具） | AG2: =VLOOKUP($K2,「工具标准名」映射表!$B:$I,6,0) -> 软件工具 | AH2: =VLOOKUP($K2,「工具标准名」映射表!$B:$I,7,0) -> 大语言模型 | AI2: =VLOOKUP($K2,「工具标准名」映射表!$B:$I,8,0) -> 是 | AJ2: 浙江省
A3: 第01号案例_1温州市新田园小学 叶诗婧《数“算”生“动”：AI赋能下运算律教学的新样态》.pdf | B3: 46056.45 | C3: 1 | D3: 数“算”生“动”：AI赋能下运算律教学的新样态 | E3: 温州市 | F3: 小学 | G3: 企业产品以“学习支持工具”为主，学校多通过校本化规则实现教学适配，整体处于规模化应用初期 | H3: 通过动态点子图和AI语音交互，将抽象的运算律转化为可操作的探究过程，实现了概念理解从抽象到直观、思维过程从内隐到外显的突破。 | I3: 学习行为采集 → 学情诊断与画像生成 → 个性化反馈与辅导 → 学习改进 | J3: ["语音识别", "动态可视化", "学习行为分析模型", "教育数据挖掘", "人工智能算法"] | K3: AI语音互动平台 | L3: 易点慧科技有限公司 | M3: TRUE | N3: 软件平台 | O3: Web 教学平台（SaaS） | P3: 文档中描述“集成'易点慧'AI语音互动平台。” | Q3: 助学 | R3: 智能辅导系统 | S3: 智育 | T3: 学生：深化算理理解、提升表达与推理能力；教师：实现精准诊断与即时干预；学校：形成可复制的“AI+概念教学”范式 | U3: 学习行为采集 → 学情诊断与画像生成 → 个性化反馈与辅导 → 学习改进 | V3: 数据采集层（多模态学习数据采集与融合） 画像诊断层（个性化画像生成、过程性反馈解释） 个性化学习层（即时生成反馈） | W3: 企业产品以“学习支持工具”为主，学校多通过校本化规则实现教学适配，整体处于规模化应用初期 | X3: AI点子图可视化 + AI说理，将抽象运算律转化为可操作模型，实现“理解—表达—诊断”闭环 | Y3: 数学 | Z3: AI语音互动平台 | AA3: 0 | AB3: 浙江省 | AD3: =VLOOKUP($K3,「工具标准名」映射表!$B:$I,3,0) -> AI语音互动平台 | AE3: =VLOOKUP($K3,「工具标准名」映射表!$B:$I,4,0) -> 功能应用层 | AF3: =VLOOKUP($K3,「工具标准名」映射表!$B:$I,5,0) -> 功能应用（教学辅助工具） | AG3: =VLOOKUP($K3,「工具标准名」映射表!$B:$I,6,0) -> 软件工具 | AH3: =VLOOKUP($K3,「工具标准名」映射表!$B:$I,7,0) -> 大语言模型 | AI3: =VLOOKUP($K3,「工具标准名」映射表!$B:$I,8,0) -> 是 | AJ3: 浙江省
A4: 第01号案例_1温州市新田园小学 叶诗婧《数“算”生“动”：AI赋能下运算律教学的新样态》.pdf | B4: 46056.45 | C4: 1 | D4: 数“算”生“动”：AI赋能下运算律教学的新样态 | E4: 温州市 | F4: 小学 | G4: 企业产品以“学习支持工具”为主，学校多通过校本化规则实现教学适配，整体处于规模化应用初期 | H4: 通过动态点子图和AI语音交互，将抽象的运算律转化为可操作的探究过程，实现了概念理解从抽象到直观、思维过程从内隐到外显的突破。 | I4: 学习行为采集 → 学情诊断与画像生成 → 个性化反馈与辅导 → 学习改进 | J4: ["语音识别", "动态可视化", "学习行为分析模型", "教育数据挖掘", "人工智能算法"] | K4: 动态点子图生成系统 | L4: 未点名企业 | M4: FALSE | N4: 软件平台 | O4: 平台内嵌功能模块 / 插件 | P4: 文档中提到“利用'豆包'和'DeepSeek'生成动态点子图代码。” | Q4: 助学 | R4: 智能辅导系统 | S4: 智育 | T4: 学生：深化算理理解、提升表达与推理能力；教师：实现精准诊断与即时干预；学校：形成可复制的“AI+概念教学”范式 | U4: 学习行为采集 → 学情诊断与画像生成 → 个性化反馈与辅导 → 学习改进 | V4: 数据采集层（多模态学习数据采集与融合） 画像诊断层（个性化画像生成、过程性反馈解释） 个性化学习层（即时生成反馈） | W4: 企业产品以“学习支持工具”为主，学校多通过校本化规则实现教学适配，整体处于规模化应用初期 | X4: AI点子图可视化 + AI说理，将抽象运算律转化为可操作模型，实现“理解—表达—诊断”闭环 | Y4: 数学 | Z4: 动态点子图生成系统 | AA4: 0 | AB4: 浙江省 | AD4: =VLOOKUP($K4,「工具标准名」映射表!$B:$I,3,0) -> 动态点子图生成系统 | AE4: =VLOOKUP($K4,「工具标准名」映射表!$B:$I,4,0) -> 功能应用层 | AF4: =VLOOKUP($K4,「工具标准名」映射表!$B:$I,5,0) -> 功能应用（平台型综合系统） | AG4: =VLOOKUP($K4,「工具标准名」映射表!$B:$I,6,0) -> 软件工具 | AH4: =VLOOKUP($K4,「工具标准名」映射表!$B:$I,7,0) -> 其他 | AI4: =VLOOKUP($K4,「工具标准名」映射表!$B:$I,8,0) -> 否 | AJ4: 浙江省
A5: 第02号案例_2温州市新田园小学朱朝炜《三维联动：人工智能视域下小学足球运球游戏设计与研究》.pdf | B5: 46056.45 | C5: 2 | D5: 人工智能视域下“三维联动”小学足球运球游戏设计与实践 | E5: 温州市 | F5: 小学 | G5: 已在小学足球运球教学中实践应用，覆盖不同学段学生，适合推广至其他体育项目。 | H5: 通过智慧设备与游戏化教学的结合，提升学生的技术掌握度与体能达标率，解决传统教学中的多项痛点。 | I5: 数据采集 → 动态调整 → 多维反馈 → 技术迁移与应用 | J5: ["数据采集", "动态调整", "多维反馈", "技术迁移", "体能监测"] | K5: AI分析系统 | L5: 未点名企业 | M5: FALSE | N5: 软件平台 | O5: 平台型综合系统 | P5: 文档中提到“AI分析系统与足球运球游戏深度融合，实现技术分解重组、体能精准调控、即时决策干涉。” | Q5: 助学 | R5: 游戏化学习 | S5: 体育 | T5: 学生：提升足球运球技术、体能达标率与课堂参与度；教师：实现精准调控与动态反馈；学校：推动体育教学数字化转型与创新实践。 | U5: 数据采集 → 动态调整 → 多维反馈 | V5: 数据采集层（智慧手环、心率带、AI分析系统）；动态调整层（实时心率监测、体能负荷调控）；反馈层（多源数据融合的精准评价体系） | W5: 企业产品以“智慧体育”与“游戏化教学”为主，整体处于数字化转型的探索阶段，具有较大的推广潜力。 | X5: 构建“技术-体能-应用”三维联动框架，通过游戏化教学实现技术、体能与应用的协同发展，填补传统教学中“数据缺失-调控盲目”的空白。 | Y5: 体育 | Z5: AI分析系统 | AA5: 0 | AB5: 浙江省 | AD5: =VLOOKUP($K5,「工具标准名」映射表!$B:$I,3,0) -> AI分析系统 | AE5: =VLOOKUP($K5,「工具标准名」映射表!$B:$I,4,0) -> 功能应用层 | AF5: =VLOOKUP($K5,「工具标准名」映射表!$B:$I,5,0) -> 功能应用（教学辅助工具） | AG5: =VLOOKUP($K5,「工具标准名」映射表!$B:$I,6,0) -> 硬件设备 | AH5: =VLOOKUP($K5,「工具标准名」映射表!$B:$I,7,0) -> AI智能体 | AI5: =VLOOKUP($K5,「工具标准名」映射表!$B:$I,8,0) -> 否 | AJ5: 浙江省
A7: 第03号案例_3【案例】从赋能到内生：智能评测驱动“教学评一致”的机理与路径探寻.pdf | B7: 46056.45 | C7: 3 | D7: 从赋能到内生：智能评测驱动“教学评一致”的机理与路径探寻 | E7: 温州市 | F7: 小学 | G7: 已在温州市多所小学规模化应用，覆盖44个班级、1980名学生 | H7: 实现了智能技术角色从外部工具赋能到系统内生动力的范式转换，重构了“教学评一致性”的实现机理与路径。 | I7: 数据驱动的教学评一体化模式构建 → 智能语音检测 → 实时语音训练与智能评分 → 个性化学习分析报告生成 | J7: ["语音识别", "数据分析", "智能评测", "个性化学习路径设计", "实时反馈"] | K7: 易点慧语音型学习机 | L7: 易点慧科技有限公司 | M7: FALSE | N7: 硬件 + AI系统 | O7: 平台型综合系统 | P7: 文档中提到“本案例深度融合‘易点慧’听说型学习机，构建了数据驱动的‘教学评’一体化教学模式。” | Q7: 助教 | R7: 智能学情诊断与个性化辅导 | S7: 智育 | T7: 学生：提升语音准确率、增强课堂参与度；教师：实现精准教学与动态调整；学校：形成可复制的教学评一致性模式 | U7: 数据采集 → 学情诊断与分析 → 个性化反馈与辅导 → 教学评一致性实现 | V7: 数据采集层（多模态数据采集与分析） 行为识别层（语音评测与互动分析） 画像诊断层（个性化学情报告生成） 智能策略层（动态教学调整与反馈） | W7: 企业产品以“智能评测与个性化辅导工具”为主，已在多所小学规模化应用，整体处于推广阶段 | X7: 实现了智能评测从外部工具赋能到系统内生动力的转变，构建了“教学评一致性”的动态调整机制，提升了教学效率与学生语言应用能力 | Y7: 英语 | Z7: 易点慧AI | AA7: 浙江易点慧教育科技有限公司 | AB7: 浙江省 | AD7: =VLOOKUP($K7,「工具标准名」映射表!$B:$I,3,0) -> 易点慧AI | AE7: =VLOOKUP($K7,「工具标准名」映射表!$B:$I,4,0) -> 技术层 | AF7: =VLOOKUP($K7,「工具标准名」映射表!$B:$I,5,0) -> 技术层（通用大模型） | AG7: =VLOOKUP($K7,「工具标准名」映射表!$B:$I,6,0) -> 软件工具 | AH7: =VLOOKUP($K7,「工具标准名」映射表!$B:$I,7,0) -> AI智能体 | AI7: =VLOOKUP($K7,「工具标准名」映射表!$B:$I,8,0) -> 否 | AJ7: 浙江省
A8: 第04号案例_AI赋能地理课堂——七大洲轮廓记忆消消乐申报书.docx | B8: 46056.45 | C8: 4 | D8: AI赋能地理课堂--七大洲轮廓记忆消消乐 | E8: 重庆市璧山区 | F8: 初中 | G8: 已在初一地理课堂进行尝试应用，具备规模化推广的潜力 | H8: 通过游戏化学习模式激发学生学习兴趣，实现个性化互动与即时反馈，提升知识点记忆效率。 | I8: AI技术优化教学形式 → 实时交互与自适应挑战 → 动态游戏任务 → 学习主动性提升 | J8: ["AI大模型算法", "Web技术", "即时反馈系统", "用户体验优化"] | K8: 七大洲速记挑战 | L8: 未点名企业 | M8: TRUE | N8: Web应用 | O8: 平台型综合系统 | P8: 文档中提到“开发了一个能够融合‘趣味性、互动性、即时反馈与个性化挑战’于一体的AI网络页面作为教学巩固工具” | Q8: 助学 | R8: 智能辅导系统 | S8: 智育 | T8: 学生：提升知识点记忆效率，增强学习主动性；教师：提供即时反馈与个性化巩固工具；学校：探索AI与基础教育深度融合的实践思路。 | U8: 需求分析 → AI互动速记挑战网页开发 → 界面优化与课堂融合实践 → 持续反馈与迭代优化 | V8: 数据采集层（学生操作数据记录） 行为识别层（学习模式分析） 个性化学习层（即时反馈与挑战） | W8: 企业产品以“轻量化教育应用”为主，能够快速部署，适用于教育资源薄弱地区，整体处于推广阶段。 | X8: 将游戏化学习与地理知识结合，创新性地转变学习模式，提供零门槛的教育应用，促进学生主动学习与课堂互动。 | Y8: 地理 | Z8: 七大洲速记挑战 | AA8: 0 | AB8: 重庆市 | AD8: =VLOOKUP($K8,「工具标准名」映射表!$B:$I,3,0) -> 七大洲速记挑战 | AE8: =VLOOKUP($K8,「工具标准名」映射表!$B:$I,4,0) -> 功能应用层 | AF8: =VLOOKUP($K8,「工具标准名」映射表!$B:$I,5,0) -> 功能应用（Web 教学平台（SaaS）） | AG8: =VLOOKUP($K8,「工具标准名」映射表!$B:$I,6,0) -> 软件工具 | AH8: =VLOOKUP($K8,「工具标准名」映射表!$B:$I,7,0) -> AI智能体 | AI8: =VLOOKUP($K8,「工具标准名」映射表!$B:$I,8,0) -> 否 | AJ8: 重庆市
A9: 第07号案例_案例申报书.docx | B9: 46056.45 | C9: 7 | D9: AI作为“认知协作者”赋能高中数学阅读精品课的跨学科构建与实践 | E9: 重庆市北碚区 | F9: 高中 | G9: 模式具有极强的可复制性，已遴选为重庆市2025年精品课，正处于实践总结阶段 | H9: 通过将AI作为认知协作者，提升备课效率与课程质量，创新性地引入虚拟学生角色解决互动难题。 | I9: 需求分析 → AI赋能的设计流程 → 课程实施 → 评价与反馈 | J9: ["人工智能", "自然语言处理", "知识图谱", "虚拟现实技术", "深度学习"] | K9: DeepSeek | L9: 未点名企业 | M9: FALSE | N9: 软件平台 | O9: Web 教学平台（SaaS） | P9: 文档中提到“通过AI工具，以DeepSeek为例，指令AI，梳理其与文艺复兴绘画、工程制图、CAD、BIM技术的内在逻辑关系。” | Q9: 助教 | R9: 课堂管理 | S9: 智育 | T9: 学生：提升数学抽象能力、空间想象能力及科技伦理观念；教师：提高备课效率与课程质量；学校：推动基础教育资源的优质均衡发展。 | U9: 需求分析 → 课程设计 → AI赋能的设计流程与实践 → 课堂实施 → 课后评价与思辨引导 | V9: 数据采集层（AI工具DeepSeek用于内容整合与框架生成） 行为识别层（AI生成课堂任务与互动设计） 画像诊断层（AI生成思辨性问题） | W9: 该模式具有极强的可复制性，适用于各学科、各学段的精品课、公开课及常规课的教学设计，整体处于推广应用阶段。 | X9: 将AI作为“认知协作者”嵌入课程开发全流程，促进教师角色转变为方案设计者与质量把控者，创新性地引入“数字人”模拟学生进行互动，提升课堂沉浸感与互动性。 | Y9: 数学 | Z9: DeepSeek 大模型 | AA9: 杭州深度求索人工智能基础技术研究有限公司 | AB9: 重庆市 | AD9: =VLOOKUP($K9,「工具标准名」映射表!$B:$I,3,0) -> DeepSeek 大模型 | AE9: =VLOOKUP($K9,「工具标准名」映射表!$B:$I,4,0) -> 功能应用层 | AF9: =VLOOKUP($K9,「工具标准名」映射表!$B:$I,5,0) -> 功能应用（教学辅助工具） | AG9: =VLOOKUP($K9,「工具标准名」映射表!$B:$I,6,0) -> 软件工具 | AH9: =VLOOKUP($K9,「工具标准名」映射表!$B:$I,7,0) -> AI智能体 | AI9: =VLOOKUP($K9,「工具标准名」映射表!$B:$I,8,0) -> 否 | AJ9: 重庆市
A10: 第07号案例_案例申报书.docx | B10: 46056.45 | C10: 7 | D10: AI作为“认知协作者”赋能高中数学阅读精品课的跨学科构建与实践 | E10: 重庆市北碚区 | F10: 高中 | G10: 模式具有极强的可复制性，已遴选为重庆市2025年精品课，正处于实践总结阶段 | H10: 通过将AI作为认知协作者，提升备课效率与课程质量，创新性地引入虚拟学生角色解决互动难题。 | I10: 需求分析 → AI赋能的设计流程 → 课程实施 → 评价与反馈 | J10: ["人工智能", "自然语言处理", "知识图谱", "虚拟现实技术", "深度学习"] | K10: 可灵AI | L10: 未点名企业 | M10: FALSE | N10: 软件平台 | O10: Web 教学平台（SaaS） | P10: 文档中描述“利用‘可灵AI’生成数字人，数字人模拟学生分享。” | Q10: 助教 | R10: 课堂管理 | S10: 智育 | T10: 学生：提升数学抽象能力、空间想象能力及科技伦理观念；教师：提高备课效率与课程质量；学校：推动基础教育资源的优质均衡发展。 | U10: 需求分析 → 课程设计 → AI赋能的设计流程与实践 → 课堂实施 → 课后评价与思辨引导 | V10: 数据采集层（AI工具DeepSeek用于内容整合与框架生成） 行为识别层（AI生成课堂任务与互动设计） 画像诊断层（AI生成思辨性问题） | W10: 该模式具有极强的可复制性，适用于各学科、各学段的精品课、公开课及常规课的教学设计，整体处于推广应用阶段。 | X10: 将AI作为“认知协作者”嵌入课程开发全流程，促进教师角色转变为方案设计者与质量把控者，创新性地引入“数字人”模拟学生进行互动，提升课堂沉浸感与互动性。 | Y10: 数学 | Z10: 可灵AI | AA10: 北京快手科技有限公司 | AB10: 重庆市 | AD10: =VLOOKUP($K10,「工具标准名」映射表!$B:$I,3,0) -> 可灵AI | AE10: =VLOOKUP($K10,「工具标准名」映射表!$B:$I,4,0) -> 功能应用层 | AF10: =VLOOKUP($K10,「工具标准名」映射表!$B:$I,5,0) -> 功能应用层（AI智能体） | AG10: =VLOOKUP($K10,「工具标准名」映射表!$B:$I,6,0) -> 软件工具 | AH10: =VLOOKUP($K10,「工具标准名」映射表!$B:$I,7,0) -> AI智能体 | AI10: =VLOOKUP($K10,「工具标准名」映射表!$B:$I,8,0) -> 是 | AJ10: 重庆市
A11: 第07号案例_案例申报书.docx | B11: 46056.45 | C11: 7 | D11: AI作为“认知协作者”赋能高中数学阅读精品课的跨学科构建与实践 | E11: 重庆市北碚区 | F11: 高中 | G11: 模式具有极强的可复制性，已遴选为重庆市2025年精品课，正处于实践总结阶段 | H11: 通过将AI作为认知协作者，提升备课效率与课程质量，创新性地引入虚拟学生角色解决互动难题。 | I11: 需求分析 → AI赋能的设计流程 → 课程实施 → 评价与反馈 | J11: ["人工智能", "自然语言处理", "知识图谱", "虚拟现实技术", "深度学习"] | K11: 豆包 | L11: 未点名企业 | M11: FALSE | N11: 软件平台 | O11: Web 教学平台（SaaS） | P11: 文档中提到“借助‘豆包’图生图技术生成鸟巢高清图片。” | Q11: 助教 | R11: 课堂管理 | S11: 智育 | T11: 学生：提升数学抽象能力、空间想象能力及科技伦理观念；教师：提高备课效率与课程质量；学校：推动基础教育资源的优质均衡发展。 | U11: 需求分析 → 课程设计 → AI赋能的设计流程与实践 → 课堂实施 → 课后评价与思辨引导 | V11: 数据采集层（AI工具DeepSeek用于内容整合与框架生成） 行为识别层（AI生成课堂任务与互动设计） 画像诊断层（AI生成思辨性问题） | W11: 该模式具有极强的可复制性，适用于各学科、各学段的精品课、公开课及常规课的教学设计，整体处于推广应用阶段。 | X11: 将AI作为“认知协作者”嵌入课程开发全流程，促进教师角色转变为方案设计者与质量把控者，创新性地引入“数字人”模拟学生进行互动，提升课堂沉浸感与互动性。 | Y11: 数学 | Z11: 豆包 | AA11: 北京春田知韵科技有限公司 | AB11: 重庆市 | AD11: =VLOOKUP($K11,「工具标准名」映射表!$B:$I,3,0) -> 豆包 | AE11: =VLOOKUP($K11,「工具标准名」映射表!$B:$I,4,0) -> 功能应用层 | AF11: =VLOOKUP($K11,「工具标准名」映射表!$B:$I,5,0) -> 功能应用（教学辅助工具） | AG11: =VLOOKUP($K11,「工具标准名」映射表!$B:$I,6,0) -> 软件工具 | AH11: =VLOOKUP($K11,「工具标准名」映射表!$B:$I,7,0) -> 其他 | AI11: =VLOOKUP($K11,「工具标准名」映射表!$B:$I,8,0) -> 否 | AJ11: 重庆市
A12: 第08号案例_8川外科中-《AI智教分析：教学相长的协同创新》案例.docx | B12: 46056.45 | C12: 8 | D12: AI智教分析：教学相长的协同创新 | E12: 重庆高新区 | F12: 初中 | G12: 项目处于实施阶段，正在构建智能化教学体系，推进教育数字化转型。 | H12: 通过构建学生和教师的数字画像，实现个性化教育和精准教学评估，推动教育决策的科学化。 | I12: 数据采集与汇聚 → 学生与教师数字画像构建 → 个性化教学与精准评估 → 教学决策优化 | J12: ["数据挖掘", "机器学习", "自然语言处理", "图像识别", "时间序列分析"] | K12: 未来教室 | L12: 未点名企业 | M12: FALSE | N12: 硬件 + AI系统 | O12: 平台型综合系统 | P12: 文档中提到“未来教室将全方位、全过程记录的学生课堂行为数据” | Q12: 助学 | R12: 智能辅导系统 | S12: 智育 | T12: 学生：实现个性化学习与成长；教师：提升教学质量与策略调整能力；学校：推动教育资源的合理配置与管理决策的科学化。 | U12: 数据采集与汇聚 → 学生与教师数字画像构建 → 个性化教学与精准评估 → 教学决策优化 | V12: 数据采集层（多源数据采集与融合） 画像诊断层（学生与教师数字画像生成、学习行为分析） 智能策略层（个性化学习路径推荐、教学策略调整） | W12: 企业产品以'学习支持工具'为主，学校通过智能化教学体系实现个性化教育，整体处于探索与应用阶段。 | X12: 构建数据驱动的智能教育生态，形成学生与教师之间的动态反馈闭环，实现个性化教学与精准评估的有效结合。 | Y12: 未提及 | Z12: 未来教室 | AA12: 0 | AB12: 重庆市 | AD12: =VLOOKUP($K12,「工具标准名」映射表!$B:$I,3,0) -> 未来教室 | AE12: =VLOOKUP($K12,「工具标准名」映射表!$B:$I,4,0) -> 功能应用层 | AF12: =VLOOKUP($K12,「工具标准名」映射表!$B:$I,5,0) -> 功能应用（平台型综合系统） | AG12: =VLOOKUP($K12,「工具标准名」映射表!$B:$I,6,0) -> 虚拟教室 | AH12: =VLOOKUP($K12,「工具标准名」映射表!$B:$I,7,0) -> AI智能体 | AI12: =VLOOKUP($K12,「工具标准名」映射表!$B:$I,8,0) -> 否 | AJ12: 重庆市
A13: 第08号案例_8川外科中-《AI智教分析：教学相长的协同创新》案例.docx | B13: 46056.45 | C13: 8 | D13: AI智教分析：教学相长的协同创新 | E13: 重庆高新区 | F13: 初中 | G13: 项目处于实施阶段，正在构建智能化教学体系，推进教育数字化转型。 | H13: 通过构建学生和教师的数字画像，实现个性化教育和精准教学评估，推动教育决策的科学化。 | I13: 数据采集与汇聚 → 学生与教师数字画像构建 → 个性化教学与精准评估 → 教学决策优化 | J13: ["数据挖掘", "机器学习", "自然语言处理", "图像识别", "时间序列分析"] | K13: 壹教云系统 | L13: 未点名企业 | M13: FALSE | N13: 软件平台 | O13: Web 教学平台（SaaS） | P13: 文档中提到“通过壹教云线上作业提交平台，广泛收集学生作业数据” | Q13: 助学 | R13: 智能辅导系统 | S13: 智育 | T13: 学生：实现个性化学习与成长；教师：提升教学质量与策略调整能力；学校：推动教育资源的合理配置与管理决策的科学化。 | U13: 数据采集与汇聚 → 学生与教师数字画像构建 → 个性化教学与精准评估 → 教学决策优化 | V13: 数据采集层（多源数据采集与融合） 画像诊断层（学生与教师数字画像生成、学习行为分析） 智能策略层（个性化学习路径推荐、教学策略调整） | W13: 企业产品以'学习支持工具'为主，学校通过智能化教学体系实现个性化教育，整体处于探索与应用阶段。 | X13: 构建数据驱动的智能教育生态，形成学生与教师之间的动态反馈闭环，实现个性化教学与精准评估的有效结合。 | Y13: 未提及 | Z13: 壹教云系统 | AA13: 0 | AB13: 重庆市 | AD13: =VLOOKUP($K13,「工具标准名」映射表!$B:$I,3,0) -> 壹教云系统 | AE13: =VLOOKUP($K13,「工具标准名」映射表!$B:$I,4,0) -> 功能应用层 | AF13: =VLOOKUP($K13,「工具标准名」映射表!$B:$I,5,0) -> 功能应用（Web 教学平台（SaaS）） | AG13: =VLOOKUP($K13,「工具标准名」映射表!$B:$I,6,0) -> 软件工具 | AH13: =VLOOKUP($K13,「工具标准名」映射表!$B:$I,7,0) -> AI智能体 | AI13: =VLOOKUP($K13,「工具标准名」映射表!$B:$I,8,0) -> 否 | AJ13: 重庆市
A14: 第09号案例_贾晓莹“人工智能 基础教育”典型应用场景案例(2).docx | B14: 46056.45 | C14: 9 | D14: 盛情邀约——海河中学130周年校庆邀请函设计 | E14: 天津市 | F14: 初中 | G14: 该案例在美术课堂中应用，正在探索美育与技术的深度融合，处于推广阶段。 | H14: 通过AI技术与美术教学的结合，提升学生对校史的情感认同，创新了美术与德育的融合教学模式。 | I14: 需求分析 → 技术研发与个性化定制 → 应用优化 → 案例推广 | J14: ["AI数字人", "视频生成技术", "设计辅助工具", "互动问答模式", "动态资源推送"] | K14: 梦AI软件 | L14: 未点名企业 | M14: FALSE | N14: 软件平台 | O14: 平台型综合系统 | P14: 文档中提到“通过轻量级AI工具（即梦AI软件）完成定制” | Q14: 助学 | R14: 情境式学习 | S14: 美育 | T14: 学生：掌握折叠式立体请柬的设计与制作技能，理解校史内涵，建立对母校的情感认同；教师：探索融合教学模式；学校：通过学生创作的邀请函传递校庆温度，增强师生、家校的凝聚力。 | U14: 需求分析 → 技术研发与个性化定制 → 应用优化 → 案例创新突破 | V14: 数据采集层（师生访谈、家校问卷） 行为识别层（教师与学生的互动分析） 智能策略层（个性化教学策略生成） 个性化学习层（动态推送适配资源） | W14: 企业产品以“学习支持工具”为主，学校多通过校本化规则实现教学适配，整体处于规模化应用初期。 | X14: 突破传统单向灌输，构建双师协同与项目式学习，利用AI技术提升课堂参与度，增强学生对校史文化的理解与情感共鸣。 | Y14: 美术 | Z14: 梦AI软件 | AA14: 0 | AB14: 天津市 | AD14: =VLOOKUP($K14,「工具标准名」映射表!$B:$I,3,0) -> #N/A | AE14: =VLOOKUP($K14,「工具标准名」映射表!$B:$I,4,0) -> #N/A | AF14: =VLOOKUP($K14,「工具标准名」映射表!$B:$I,5,0) -> #N/A | AG14: =VLOOKUP($K14,「工具标准名」映射表!$B:$I,6,0) -> #N/A | AH14: =VLOOKUP($K14,「工具标准名」映射表!$B:$I,7,0) -> #N/A | AI14: =VLOOKUP($K14,「工具标准名」映射表!$B:$I,8,0) -> #N/A | AJ14: 天津市
A15: 第09号案例_贾晓莹“人工智能 基础教育”典型应用场景案例(2).docx | B15: 46056.45 | C15: 9 | D15: 盛情邀约——海河中学130周年校庆邀请函设计 | E15: 天津市 | F15: 初中 | G15: 该案例在美术课堂中应用，正在探索美育与技术的深度融合，处于推广阶段。 | H15: 通过AI技术与美术教学的结合，提升学生对校史的情感认同，创新了美术与德育的融合教学模式。 | I15: 需求分析 → 技术研发与个性化定制 → 应用优化 → 案例推广 | J15: ["AI数字人", "视频生成技术", "设计辅助工具", "互动问答模式", "动态资源推送"] | K15: 剪映AI扩图 | L15: 未点名企业 | M15: FALSE | N15: 软件平台 | O15: 平台型综合系统 | P15: 文档中提到“利用AI视频工具（如剪映AI扩图）” | Q15: 助学 | R15: 情境式学习 | S15: 美育 | T15: 学生：掌握折叠式立体请柬的设计与制作技能，理解校史内涵，建立对母校的情感认同；教师：探索融合教学模式；学校：通过学生创作的邀请函传递校庆温度，增强师生、家校的凝聚力。 | U15: 需求分析 → 技术研发与个性化定制 → 应用优化 → 案例创新突破 | V15: 数据采集层（师生访谈、家校问卷） 行为识别层（教师与学生的互动分析） 智能策略层（个性化教学策略生成） 个性化学习层（动态推送适配资源） | W15: 企业产品以“学习支持工具”为主，学校多通过校本化规则实现教学适配，整体处于规模化应用初期。 | X15: 突破传统单向灌输，构建双师协同与项目式学习，利用AI技术提升课堂参与度，增强学生对校史文化的理解与情感共鸣。 | Y15: 美术 | Z15: 剪映AI | AA15: 深圳市脸萌科技有限公司 | AB15: 天津市 | AD15: =VLOOKUP($K15,「工具标准名」映射表!$B:$I,3,0) -> 剪映AI | AE15: =VLOOKUP($K15,「工具标准名」映射表!$B:$I,4,0) -> 功能应用层 | AF15: =VLOOKUP($K15,「工具标准名」映射表!$B:$I,5,0) -> 功能应用层（AI智能体） | AG15: =VLOOKUP($K15,「工具标准名」映射表!$B:$I,6,0) -> 软件工具 | AH15: =VLOOKUP($K15,「工具标准名」映射表!$B:$I,7,0) -> AI智能体 | AI15: =VLOOKUP($K15,「工具标准名」映射表!$B:$I,8,0) -> 是 | AJ15: 天津市
A16: 第09号案例_贾晓莹“人工智能 基础教育”典型应用场景案例(2).docx | B16: 46056.45 | C16: 9 | D16: 盛情邀约——海河中学130周年校庆邀请函设计 | E16: 天津市 | F16: 初中 | G16: 该案例在美术课堂中应用，正在探索美育与技术的深度融合，处于推广阶段。 | H16: 通过AI技术与美术教学的结合，提升学生对校史的情感认同，创新了美术与德育的融合教学模式。 | I16: 需求分析 → 技术研发与个性化定制 → 应用优化 → 案例推广 | J16: ["AI数字人", "视频生成技术", "设计辅助工具", "互动问答模式", "动态资源推送"] | K16: 豆包软件 | L16: 未点名企业 | M16: FALSE | N16: 软件平台 | O16: 教学辅助工具（工具型） | P16: 文档中提到“利用豆包软件定制极简版设计辅助包” | Q16: 助学 | R16: 情境式学习 | S16: 美育 | T16: 学生：掌握折叠式立体请柬的设计与制作技能，理解校史内涵，建立对母校的情感认同；教师：探索融合教学模式；学校：通过学生创作的邀请函传递校庆温度，增强师生、家校的凝聚力。 | U16: 需求分析 → 技术研发与个性化定制 → 应用优化 → 案例创新突破 | V16: 数据采集层（师生访谈、家校问卷） 行为识别层（教师与学生的互动分析） 智能策略层（个性化教学策略生成） 个性化学习层（动态推送适配资源） | W16: 企业产品以“学习支持工具”为主，学校多通过校本化规则实现教学适配，整体处于规模化应用初期。 | X16: 突破传统单向灌输，构建双师协同与项目式学习，利用AI技术提升课堂参与度，增强学生对校史文化的理解与情感共鸣。 | Y16: 美术 | Z16: 豆包 | AA16: 北京春田知韵科技有限公司 | AB16: 天津市 | AD16: =VLOOKUP($K16,「工具标准名」映射表!$B:$I,3,0) -> 豆包 | AE16: =VLOOKUP($K16,「工具标准名」映射表!$B:$I,4,0) -> 功能应用层 | AF16: =VLOOKUP($K16,「工具标准名」映射表!$B:$I,5,0) -> 功能应用（平台型综合系统） | AG16: =VLOOKUP($K16,「工具标准名」映射表!$B:$I,6,0) -> 软件工具 | AH16: =VLOOKUP($K16,「工具标准名」映射表!$B:$I,7,0) -> 其他 | AI16: =VLOOKUP($K16,「工具标准名」映射表!$B:$I,8,0) -> 否 | AJ16: 天津市
A17: 第10号案例_10人工智能赋能初中英语互动教学：破解课程参与难度，提升教学效能.docx | B17: 46056.452 | C17: 10 | D17: 人工智能赋能初中英语互动教学：破解课程参与难度，提升教学效能 | E17: 重庆市璧山区 | F17: 初中 | G17: 当前该模式在本校初中英语教学全面应用，具备规模化推广条件 | H17: 重构低压力-高互动教学模式，提升学生开口率与参与度，实时反馈与个性化推送有效满足学生差异化需求。 | I17: 需求分析 → 技术适配 → 应用优化 → 教学反馈与个性化指导 | J17: ["AI语音评测", "实时数据分析", "个性化学习推送", "自动批改系统", "教育数据安全"] | K17: AI语音互动平台 | L17: 科大讯飞 | M17: FALSE | N17: 软件平台 | O17: Web 教学平台（SaaS） | P17: 文档中提到“选用符合教育数据安全标准的第三方智能平台（如科大讯飞智慧课堂）” | Q17: 助学 | R17: 智能辅导系统 | S17: 智育 | T17: 学生：提升课堂参与度与英语能力；教师：实现实时反馈与精准教学；学校：形成可复制的AI教学模式 | U17: 需求分析 → 技术适配 → 应用优化 → 教学反馈 | V17: 数据采集层（实时语音评测、班级学情报告） 行为识别层（学生参与率与正确率统计） 个性化学习层（智能分层推送、个性化巩固练习） | W17: 企业产品以"学习支持工具"为主，学校多通过校本化规则实现教学适配，整体处于规模化应用初期 | X17: 重构低压力高互动教学模式，提升学生开口率与参与度，确保个性化教学落地，适合薄弱学校推广 | Y17: 英语 | Z17: AI语音互动平台 | AA17: 0 | AB17: 重庆市 | AD17: =VLOOKUP($K17,「工具标准名」映射表!$B:$I,3,0) -> AI语音互动平台 | AE17: =VLOOKUP($K17,「工具标准名」映射表!$B:$I,4,0) -> 功能应用层 | AF17: =VLOOKUP($K17,「工具标准名」映射表!$B:$I,5,0) -> 功能应用（教学辅助工具） | AG17: =VLOOKUP($K17,「工具标准名」映射表!$B:$I,6,0) -> 软件工具 | AH17: =VLOOKUP($K17,「工具标准名」映射表!$B:$I,7,0) -> 大语言模型 | AI17: =VLOOKUP($K17,「工具标准名」映射表!$B:$I,8,0) -> 是 | AJ17: 重庆市
A18: 第11号案例_申报书 隆昌市向阳路小学 黎恩旭 《用彩墨画鱼》.docx | B18: 46056.453 | C18: 11 | D18: AI赋能跨学科融合：小学美术《用彩墨画鱼》全流程智能教学实践 | E18: 隆昌市 | F18: 小学 | G18: 该案例已在本校四年级美术课堂落地，具备大规模推广的成熟条件与广阔前景 | H18: 首创‘AI+IP主题+跨学科三维融合’教学范式，实现抽象知识可视化、互动化、跨学科融合，提升学生核心素养。 | I18: 需求分析 → 技术适配与定制 → 全流程应用实践与优化 → 应用迭代优化 | J18: ["动画建模", "动态转化", "语音合成", "互动答题系统", "3D虚拟展馆"] | K18: 即梦AI | L18: 未点名企业 | M18: FALSE | N18: 软件平台 | O18: Web 教学平台（SaaS） | P18: 文档中提到‘选用即梦AI作为核心技术支撑，定制开发三大功能模块’ | Q18: 助学 | R18: 智能辅导系统 | S18: 美育 | T18: 学生：提升审美感知、艺术表现与文化理解能力；教师：实现跨学科教学的有效融合；学校：形成可复制的‘AI+学科’教学模式，推动基础教育智能化转型。 | U18: 需求分析 → 技术适配与定制 → 全流程应用实践与优化 → 应用迭代优化 | V18: 数据采集层（动态赋能模块、语音合成模块） 行为识别层（互动答题系统、知识认知场景化） 画像诊断层（虚拟展馆展示学生作品） | W18: 该案例已在本校四年级美术课堂落地，具备大规模推广的成熟条件与广阔前景，推动基础教育数字化转型。 | X18: 首创‘AI+IP主题+跨学科三维融合’教学范式，通过动态演示与虚拟展馆展示，打破学科壁垒，实现知识的可视化与互动化，提升学生的参与感与创作成就感。 | Y18: 美术 | Z18: 即梦AI | AA18: 深圳市脸萌科技有限公司 | AB18: 四川省 | AD18: =VLOOKUP($K18,「工具标准名」映射表!$B:$I,3,0) -> 即梦AI | AE18: =VLOOKUP($K18,「工具标准名」映射表!$B:$I,4,0) -> 功能应用层 | AF18: =VLOOKUP($K18,「工具标准名」映射表!$B:$I,5,0) -> 功能应用（生成式AI应用-图像类） | AG18: =VLOOKUP($K18,「工具标准名」映射表!$B:$I,6,0) -> 软件工具 | AH18: =VLOOKUP($K18,「工具标准名」映射表!$B:$I,7,0) -> AI智能体 | AI18: =VLOOKUP($K18,「工具标准名」映射表!$B:$I,8,0) -> 是 | AJ18: 四川省
A19: 第11号案例_申报书 隆昌市向阳路小学 黎恩旭 《用彩墨画鱼》.docx | B19: 46056.453 | C19: 11 | D19: AI赋能跨学科融合：小学美术《用彩墨画鱼》全流程智能教学实践 | E19: 隆昌市 | F19: 小学 | G19: 该案例已在本校四年级美术课堂落地，具备大规模推广的成熟条件与广阔前景 | H19: 首创‘AI+IP主题+跨学科三维融合’教学范式，实现抽象知识可视化、互动化、跨学科融合，提升学生核心素养。 | I19: 需求分析 → 技术适配与定制 → 全流程应用实践与优化 → 应用迭代优化 | J19: ["动画建模", "动态转化", "语音合成", "互动答题系统", "3D虚拟展馆"] | K19: 希沃白板 | L19: 未点名企业 | M19: FALSE | N19: 硬件 + 软件系统 | O19: 教学辅助工具（工具型） | P19: 文档中提到‘联动希沃白板搭建互动答题系统’ | Q19: 助学 | R19: 智能辅导系统 | S19: 美育 | T19: 学生：提升审美感知、艺术表现与文化理解能力；教师：实现跨学科教学的有效融合；学校：形成可复制的‘AI+学科’教学模式，推动基础教育智能化转型。 | U19: 需求分析 → 技术适配与定制 → 全流程应用实践与优化 → 应用迭代优化 | V19: 数据采集层（动态赋能模块、语音合成模块） 行为识别层（互动答题系统、知识认知场景化） 画像诊断层（虚拟展馆展示学生作品） | W19: 该案例已在本校四年级美术课堂落地，具备大规模推广的成熟条件与广阔前景，推动基础教育数字化转型。 | X19: 首创‘AI+IP主题+跨学科三维融合’教学范式，通过动态演示与虚拟展馆展示，打破学科壁垒，实现知识的可视化与互动化，提升学生的参与感与创作成就感。 | Y19: 美术 | Z19: 希沃白板 | AA19: 广州视源电子科技股份有限公司 | AB19: 四川省 | AD19: =VLOOKUP($K19,「工具标准名」映射表!$B:$I,3,0) -> 希沃白板 | AE19: =VLOOKUP($K19,「工具标准名」映射表!$B:$I,4,0) -> 功能应用层 | AF19: =VLOOKUP($K19,「工具标准名」映射表!$B:$I,5,0) -> 功能应用（教学辅助工具） | AG19: =VLOOKUP($K19,「工具标准名」映射表!$B:$I,6,0) -> 软件工具 | AH19: =VLOOKUP($K19,「工具标准名」映射表!$B:$I,7,0) -> AI智能体 | AI19: =VLOOKUP($K19,「工具标准名」映射表!$B:$I,8,0) -> 否 | AJ19: 四川省
A20: 第11号案例_申报书 隆昌市向阳路小学 黎恩旭 《用彩墨画鱼》.docx | B20: 46056.453 | C20: 11 | D20: AI赋能跨学科融合：小学美术《用彩墨画鱼》全流程智能教学实践 | E20: 隆昌市 | F20: 小学 | G20: 该案例已在本校四年级美术课堂落地，具备大规模推广的成熟条件与广阔前景 | H20: 首创‘AI+IP主题+跨学科三维融合’教学范式，实现抽象知识可视化、互动化、跨学科融合，提升学生核心素养。 | I20: 需求分析 → 技术适配与定制 → 全流程应用实践与优化 → 应用迭代优化 | J20: ["动画建模", "动态转化", "语音合成", "互动答题系统", "3D虚拟展馆"] | K20: 微信“元美”小程序 | L20: 未点名企业 | M20: FALSE | N20: 软件平台 | O20: Web 教学平台（SaaS） | P20: 文档中提到‘对接微信“元美”小程序，开发3D虚拟展馆定制模板’ | Q20: 助学 | R20: 智能辅导系统 | S20: 美育 | T20: 学生：提升审美感知、艺术表现与文化理解能力；教师：实现跨学科教学的有效融合；学校：形成可复制的‘AI+学科’教学模式，推动基础教育智能化转型。 | U20: 需求分析 → 技术适配与定制 → 全流程应用实践与优化 → 应用迭代优化 | V20: 数据采集层（动态赋能模块、语音合成模块） 行为识别层（互动答题系统、知识认知场景化） 画像诊断层（虚拟展馆展示学生作品） | W20: 该案例已在本校四年级美术课堂落地，具备大规模推广的成熟条件与广阔前景，推动基础教育数字化转型。 | X20: 首创‘AI+IP主题+跨学科三维融合’教学范式，通过动态演示与虚拟展馆展示，打破学科壁垒，实现知识的可视化与互动化，提升学生的参与感与创作成就感。 | Y20: 美术 | Z20: 微信“元美”小程序 | AA20: 0 | AB20: 四川省 | AD20: =VLOOKUP($K20,「工具标准名」映射表!$B:$I,3,0) -> 微信“元美”小程序 | AE20: =VLOOKUP($K20,「工具标准名」映射表!$B:$I,4,0) -> 功能应用层 | AF20: =VLOOKUP($K20,「工具标准名」映射表!$B:$I,5,0) -> 功能应用层（移动端 App） | AG20: =VLOOKUP($K20,「工具标准名」映射表!$B:$I,6,0) -> 软件工具 | AH20: =VLOOKUP($K20,「工具标准名」映射表!$B:$I,7,0) -> AI智能体 | AI20: =VLOOKUP($K20,「工具标准名」映射表!$B:$I,8,0) -> 否 | AJ20: 四川省
A21: 第11号案例_申报书 隆昌市向阳路小学 黎恩旭 《用彩墨画鱼》.docx | B21: 46056.453 | C21: 11 | D21: AI赋能跨学科融合：小学美术《用彩墨画鱼》全流程智能教学实践 | E21: 隆昌市 | F21: 小学 | G21: 该案例已在本校四年级美术课堂落地，具备大规模推广的成熟条件与广阔前景 | H21: 首创‘AI+IP主题+跨学科三维融合’教学范式，实现抽象知识可视化、互动化、跨学科融合，提升学生核心素养。 | I21: 需求分析 → 技术适配与定制 → 全流程应用实践与优化 → 应用迭代优化 | J21: ["动画建模", "动态转化", "语音合成", "互动答题系统", "3D虚拟展馆"] | K21: Photoshop | L21: 未点名企业 | M21: FALSE | N21: 软件平台 | O21: 教学辅助工具（工具型） | P21: 文档中提到‘融合Photoshop、剪映等工具，完成“丹尼”动画的修图与配音’ | Q21: 助学 | R21: 智能辅导系统 | S21: 美育 | T21: 学生：提升审美感知、艺术表现与文化理解能力；教师：实现跨学科教学的有效融合；学校：形成可复制的‘AI+学科’教学模式，推动基础教育智能化转型。 | U21: 需求分析 → 技术适配与定制 → 全流程应用实践与优化 → 应用迭代优化 | V21: 数据采集层（动态赋能模块、语音合成模块） 行为识别层（互动答题系统、知识认知场景化） 画像诊断层（虚拟展馆展示学生作品） | W21: 该案例已在本校四年级美术课堂落地，具备大规模推广的成熟条件与广阔前景，推动基础教育数字化转型。 | X21: 首创‘AI+IP主题+跨学科三维融合’教学范式，通过动态演示与虚拟展馆展示，打破学科壁垒，实现知识的可视化与互动化，提升学生的参与感与创作成就感。 | Y21: 美术 | Z21: Photoshop | AA21: 0 | AB21: 四川省 | AD21: =VLOOKUP($K21,「工具标准名」映射表!$B:$I,3,0) -> Photoshop | AE21: =VLOOKUP($K21,「工具标准名」映射表!$B:$I,4,0) -> 功能应用层 | AF21: =VLOOKUP($K21,「工具标准名」映射表!$B:$I,5,0) -> 功能应用（Web 教学平台（SaaS）） | AG21: =VLOOKUP($K21,「工具标准名」映射表!$B:$I,6,0) -> 硬件设备 | AH21: =VLOOKUP($K21,「工具标准名」映射表!$B:$I,7,0) -> 其他 | AI21: =VLOOKUP($K21,「工具标准名」映射表!$B:$I,8,0) -> 否 | AJ21: 四川省
A22: 第11号案例_申报书 隆昌市向阳路小学 黎恩旭 《用彩墨画鱼》.docx | B22: 46056.453 | C22: 11 | D22: AI赋能跨学科融合：小学美术《用彩墨画鱼》全流程智能教学实践 | E22: 隆昌市 | F22: 小学 | G22: 该案例已在本校四年级美术课堂落地，具备大规模推广的成熟条件与广阔前景 | H22: 首创‘AI+IP主题+跨学科三维融合’教学范式，实现抽象知识可视化、互动化、跨学科融合，提升学生核心素养。 | I22: 需求分析 → 技术适配与定制 → 全流程应用实践与优化 → 应用迭代优化 | J22: ["动画建模", "动态转化", "语音合成", "互动答题系统", "3D虚拟展馆"] | K22: 剪映 | L22: 未点名企业 | M22: FALSE | N22: 软件平台 | O22: 教学辅助工具（工具型） | P22: 文档中提到‘融合Photoshop、剪映等工具，完成“丹尼”动画的修图与配音’ | Q22: 助学 | R22: 智能辅导系统 | S22: 美育 | T22: 学生：提升审美感知、艺术表现与文化理解能力；教师：实现跨学科教学的有效融合；学校：形成可复制的‘AI+学科’教学模式，推动基础教育智能化转型。 | U22: 需求分析 → 技术适配与定制 → 全流程应用实践与优化 → 应用迭代优化 | V22: 数据采集层（动态赋能模块、语音合成模块） 行为识别层（互动答题系统、知识认知场景化） 画像诊断层（虚拟展馆展示学生作品） | W22: 该案例已在本校四年级美术课堂落地，具备大规模推广的成熟条件与广阔前景，推动基础教育数字化转型。 | X22: 首创‘AI+IP主题+跨学科三维融合’教学范式，通过动态演示与虚拟展馆展示，打破学科壁垒，实现知识的可视化与互动化，提升学生的参与感与创作成就感。 | Y22: 美术 | Z22: 剪映AI | AA22: 深圳市脸萌科技有限公司 | AB22: 四川省 | AD22: =VLOOKUP($K22,「工具标准名」映射表!$B:$I,3,0) -> 剪映AI | AE22: =VLOOKUP($K22,「工具标准名」映射表!$B:$I,4,0) -> 功能应用层 | AF22: =VLOOKUP($K22,「工具标准名」映射表!$B:$I,5,0) -> 功能应用层（AI智能体） | AG22: =VLOOKUP($K22,「工具标准名」映射表!$B:$I,6,0) -> 软件工具 | AH22: =VLOOKUP($K22,「工具标准名」映射表!$B:$I,7,0) -> AI智能体 | AI22: =VLOOKUP($K22,「工具标准名」映射表!$B:$I,8,0) -> 是 | AJ22: 四川省
A23: 第12号案例_12重庆市第八中学校+从“动手实践”到“真实探究”：生成式AI支持下中学科学课程的五轮迭代研究.pdf | B23: 46056.455 | C23: 12 | D23: 从“动手实践”到“真实探究”：生成式AI支持下中学科学课程的五轮迭代研究 | E23: 重庆市 | F23: 初中 | G23: 已在重庆八中宏帆中学科学课程中完成连续五轮实践迭代，形成了较为成熟的协同成长框架，覆盖师生1200余人。 | H23: 构建了“教师—专家—AI—学生学习证据”协同成长框架，系统揭示了教师在专家指导与生成式AI支持下的课程迭代与专业成长路径，推动了课堂教学由“讲授—模仿”向“探究—共创”的转型。 | I23: 教师在专家指导与生成式AI支持下的五轮课程迭代过程 | J23: ["生成式人工智能", "学习设计优化", "动态反馈机制", "科学探究流程", "个性化支持"] | K23: DeepSeek | L23: 未点名企业 | M23: FALSE | N23: AI系统 | O23: AI 能力 / 模型 / API（基础层） | P23: 文档中提到“案例使用的基础大模型DeepSeek” | Q23: 助教 | R23: 教学分析 | S23: 智育 | T23: 学生：提升科学探究能力与创新意识；教师：实现教学设计优化与专业成长；学校：推动STEM教育的本土化发展与教育资源均衡。 | U23: 课程设计优化 → 教师反思与实践 → 生成式AI支持 → 学生探究与反馈 | V23: 数据采集层（学习过程记录、课堂实录） 行为识别层（学生探究行为分析） 画像诊断层（教师教学效果评估） 个性化学习层（AI辅助个性化探究路径） | W23: 企业产品以“AI辅助教学工具”为主，学校通过专家指导与AI支持实现教学适配，整体处于推广应用阶段。 | X23: 构建了“教师—专家—AI—学生学习证据”协同成长框架，系统揭示了教师在专家指导与生成式AI支持下的课程迭代与专业成长路径，推动了课堂教学由“讲授—模仿”向“探究—共创”的转型。 | Y23: 科学 | Z23: DeepSeek 大模型 | AA23: 杭州深度求索人工智能基础技术研究有限公司 | AB23: 重庆市 | AD23: =VLOOKUP($K23,「工具标准名」映射表!$B:$I,3,0) -> DeepSeek 大模型 | AE23: =VLOOKUP($K23,「工具标准名」映射表!$B:$I,4,0) -> 功能应用层 | AF23: =VLOOKUP($K23,「工具标准名」映射表!$B:$I,5,0) -> 功能应用（教学辅助工具） | AG23: =VLOOKUP($K23,「工具标准名」映射表!$B:$I,6,0) -> 软件工具 | AH23: =VLOOKUP($K23,「工具标准名」映射表!$B:$I,7,0) -> AI智能体 | AI23: =VLOOKUP($K23,「工具标准名」映射表!$B:$I,8,0) -> 否 | AJ23: 重庆市
A24: 第13号案例_13九原区第一实验小学 高嘉彤 “人工智能+基础教育”典型应用场景案例”.pdf | B24: 46056.456 | C24: 13 | D24: AI赋能课堂组织管理：助力《圆的周长》探究式教学 | E24: 九原区 | F24: 小学 | G24: 已在校内多个年级探究课中成功复制，具备极强的规模化推广潜力 | H24: 通过集成多种AI工具，构建高效、互动、数据驱动的智能教学环境，实现了从教师主导到学生数据驱动探究的教学模式转变。 | I24: 课堂导入视频生成 → 语音问答与AI编程互动 → 即时练习与反馈生成 → 数据可视化管理 | J24: ["语音识别", "AI编程", "数据分析", "即时反馈", "生成式AI"] | K24: 即梦AI | L24: 未点名企业 | M24: FALSE | N24: 软件平台 | O24: Web 教学平台（SaaS） | P24: 文档中提到“利用即梦AI生成课堂导入视频，提升学生的学习探究兴趣” | Q24: 助教 | R24: 课堂管理 | S24: 智育 | T24: 学生：提升课堂参与度与学习效率；教师：减轻数据统计负担，更专注于教学引导；学校：实现课堂组织管理的高效化与科学化。 | U24: 课堂导入视频生成 → 学生互动程序生成 → 实时反馈与评价 → 教学决策优化 | V24: 数据采集层（即时反馈数据采集与可视化管理） 行为识别层（学生参与度分析） 个性化学习层（即时生成反馈与评价） | W24: 该案例在基础教育领域处于积极探索阶段，利用轻量级AI工具实现课堂教学的数字化转型，具备较强的推广潜力。 | X24: 通过集成多种AI工具，实现了从传统教学模式向数据驱动探究式教学的转变，构建了低门槛的智能教学环境，提升了课堂参与率与反馈效率。 | Y24: 数学 | Z24: 即梦AI | AA24: 深圳市脸萌科技有限公司 | AB24: 内蒙古自治区 | AD24: =VLOOKUP($K24,「工具标准名」映射表!$B:$I,3,0) -> 即梦AI | AE24: =VLOOKUP($K24,「工具标准名」映射表!$B:$I,4,0) -> 功能应用层 | AF24: =VLOOKUP($K24,「工具标准名」映射表!$B:$I,5,0) -> 功能应用（生成式AI应用-图像类） | AG24: =VLOOKUP($K24,「工具标准名」映射表!$B:$I,6,0) -> 软件工具 | AH24: =VLOOKUP($K24,「工具标准名」映射表!$B:$I,7,0) -> AI智能体 | AI24: =VLOOKUP($K24,「工具标准名」映射表!$B:$I,8,0) -> 是 | AJ24: 内蒙古自治区
A25: 第13号案例_13九原区第一实验小学 高嘉彤 “人工智能+基础教育”典型应用场景案例”.pdf | B25: 46056.456 | C25: 13 | D25: AI赋能课堂组织管理：助力《圆的周长》探究式教学 | E25: 九原区 | F25: 小学 | G25: 已在校内多个年级探究课中成功复制，具备极强的规模化推广潜力 | H25: 通过集成多种AI工具，构建高效、互动、数据驱动的智能教学环境，实现了从教师主导到学生数据驱动探究的教学模式转变。 | I25: 课堂导入视频生成 → 语音问答与AI编程互动 → 即时练习与反馈生成 → 数据可视化管理 | J25: ["语音识别", "AI编程", "数据分析", "即时反馈", "生成式AI"] | K25: 豆包 | L25: 未点名企业 | M25: FALSE | N25: 软件平台 | O25: Web 教学平台（SaaS） | P25: 文档中描述“引入豆包的语音问答与AI编程功能，作为‘AI助教’” | Q25: 助教 | R25: 课堂管理 | S25: 智育 | T25: 学生：提升课堂参与度与学习效率；教师：减轻数据统计负担，更专注于教学引导；学校：实现课堂组织管理的高效化与科学化。 | U25: 课堂导入视频生成 → 学生互动程序生成 → 实时反馈与评价 → 教学决策优化 | V25: 数据采集层（即时反馈数据采集与可视化管理） 行为识别层（学生参与度分析） 个性化学习层（即时生成反馈与评价） | W25: 该案例在基础教育领域处于积极探索阶段，利用轻量级AI工具实现课堂教学的数字化转型，具备较强的推广潜力。 | X25: 通过集成多种AI工具，实现了从传统教学模式向数据驱动探究式教学的转变，构建了低门槛的智能教学环境，提升了课堂参与率与反馈效率。 | Y25: 数学 | Z25: 豆包 | AA25: 北京春田知韵科技有限公司 | AB25: 内蒙古自治区 | AD25: =VLOOKUP($K25,「工具标准名」映射表!$B:$I,3,0) -> 豆包 | AE25: =VLOOKUP($K25,「工具标准名」映射表!$B:$I,4,0) -> 功能应用层 | AF25: =VLOOKUP($K25,「工具标准名」映射表!$B:$I,5,0) -> 功能应用（教学辅助工具） | AG25: =VLOOKUP($K25,「工具标准名」映射表!$B:$I,6,0) -> 软件工具 | AH25: =VLOOKUP($K25,「工具标准名」映射表!$B:$I,7,0) -> 其他 | AI25: =VLOOKUP($K25,「工具标准名」映射表!$B:$I,8,0) -> 否 | AJ25: 内蒙古自治区
A26: 第13号案例_13九原区第一实验小学 高嘉彤 “人工智能+基础教育”典型应用场景案例”.pdf | B26: 46056.456 | C26: 13 | D26: AI赋能课堂组织管理：助力《圆的周长》探究式教学 | E26: 九原区 | F26: 小学 | G26: 已在校内多个年级探究课中成功复制，具备极强的规模化推广潜力 | H26: 通过集成多种AI工具，构建高效、互动、数据驱动的智能教学环境，实现了从教师主导到学生数据驱动探究的教学模式转变。 | I26: 课堂导入视频生成 → 语音问答与AI编程互动 → 即时练习与反馈生成 → 数据可视化管理 | J26: ["语音识别", "AI编程", "数据分析", "即时反馈", "生成式AI"] | K26: 问卷星 | L26: 未点名企业 | M26: FALSE | N26: 软件平台 | O26: Web 教学平台（SaaS） | P26: 文档中提到“使用问卷星AI，自动生成分层练习题，并创建在线答题卷” | Q26: 助教 | R26: 课堂管理 | S26: 智育 | T26: 学生：提升课堂参与度与学习效率；教师：减轻数据统计负担，更专注于教学引导；学校：实现课堂组织管理的高效化与科学化。 | U26: 课堂导入视频生成 → 学生互动程序生成 → 实时反馈与评价 → 教学决策优化 | V26: 数据采集层（即时反馈数据采集与可视化管理） 行为识别层（学生参与度分析） 个性化学习层（即时生成反馈与评价） | W26: 该案例在基础教育领域处于积极探索阶段，利用轻量级AI工具实现课堂教学的数字化转型，具备较强的推广潜力。 | X26: 通过集成多种AI工具，实现了从传统教学模式向数据驱动探究式教学的转变，构建了低门槛的智能教学环境，提升了课堂参与率与反馈效率。 | Y26: 数学 | Z26: 问卷星 | AA26: 0 | AB26: 内蒙古自治区 | AD26: =VLOOKUP($K26,「工具标准名」映射表!$B:$I,3,0) -> 问卷星 | AE26: =VLOOKUP($K26,「工具标准名」映射表!$B:$I,4,0) -> 功能应用层 | AF26: =VLOOKUP($K26,「工具标准名」映射表!$B:$I,5,0) -> 功能应用（Web 教学平台（SaaS）） | AG26: =VLOOKUP($K26,「工具标准名」映射表!$B:$I,6,0) -> 软件工具 | AH26: =VLOOKUP($K26,「工具标准名」映射表!$B:$I,7,0) -> AI智能体 | AI26: =VLOOKUP($K26,「工具标准名」映射表!$B:$I,8,0) -> 否 | AJ26: 内蒙古自治区
A27: 第14号案例_14铜梁中学 基于“AI+项目化”的铜梁中学“数项融合”校本课程的开发与应用实践(1026).pdf | B27: 46056.458 | C27: 14 | D27: 基于“AI+项目化”的铜梁中学“数项融合”高中物理校本课程的开发与应用实践 | E27: 重庆市 | F27: 高中 | G27: 铜梁中学已在多所高中实施，整体处于规模化推广阶段 | H27: 通过AI与项目化学习的结合，创新了高中物理教学模式，提升了学生的实践能力与创新能力。 | I27: AI辅助课堂教学与互动 → 虚拟实验与实践教学 → 智能学情诊断与个性化辅导 | J27: ["人工智能算法", "虚拟现实技术", "智能作业批改系统", "智能诊断系统", "项目化学习"] | K27: 国家智慧教育平台 | L27: 未点名企业 | M27: FALSE | N27: 平台型综合系统 | O27: 平台型综合系统 | P27: 文档中提到“以国家智慧教育平台为基础，整合校内外数字资源” | Q27: 助教 | R27: 智能辅导系统 | S27: 智育 | T27: 学生：提升实践能力与创新思维；教师：增强AI辅助教学能力；学校：推动课程改革与教学质量提升。 | U27: AI辅助课堂教学与互动 → 虚拟实验教学 → 智能学情诊断与个性化辅导 → 课程开发与应用 | V27: 数据采集层（多模态学习数据采集与融合） 行为识别层（学习意图识别、学习路径偏差检测） 画像诊断层（个性化画像生成、过程性反馈解释） 个性化学习层（即时生成反馈） | W27: 企业产品以“学习支持工具”为主，学校通过校本化规则实现教学适配，整体处于规模化应用初期。 | X27: 通过“AI+项目化”教学模式，构建了多元智慧学习场景，促进了物理教学的实践与创新，形成了鲜明的项目驱动与AI赋能特色。 | Y27: 物理 | Z27: 国家智慧教育平台 | AA27: 0 | AB27: 重庆市 | AD27: =VLOOKUP($K27,「工具标准名」映射表!$B:$I,3,0) -> 国家智慧教育平台 | AE27: =VLOOKUP($K27,「工具标准名」映射表!$B:$I,4,0) -> 教育数据层 | AF27: =VLOOKUP($K27,「工具标准名」映射表!$B:$I,5,0) -> 功能应用（Web 教学平台（SaaS）） | AG27: =VLOOKUP($K27,「工具标准名」映射表!$B:$I,6,0) -> 在线资源 | AH27: =VLOOKUP($K27,「工具标准名」映射表!$B:$I,7,0) -> 其他 | AI27: =VLOOKUP($K27,「工具标准名」映射表!$B:$I,8,0) -> 否 | AJ27: 重庆市
A28: 第14号案例_14铜梁中学 基于“AI+项目化”的铜梁中学“数项融合”校本课程的开发与应用实践(1026).pdf | B28: 46056.458 | C28: 14 | D28: 基于“AI+项目化”的铜梁中学“数项融合”高中物理校本课程的开发与应用实践 | E28: 重庆市 | F28: 高中 | G28: 铜梁中学已在多所高中实施，整体处于规模化推广阶段 | H28: 通过AI与项目化学习的结合，创新了高中物理教学模式，提升了学生的实践能力与创新能力。 | I28: AI辅助课堂教学与互动 → 虚拟实验与实践教学 → 智能学情诊断与个性化辅导 | J28: ["人工智能算法", "虚拟现实技术", "智能作业批改系统", "智能诊断系统", "项目化学习"] | K28: AI智能作业批改系统 | L28: 未点名企业 | M28: FALSE | N28: 软件平台 | O28: Web 教学平台（SaaS） | P28: 文档中描述“通过AI智能作业批改系统，智能诊断学生的物理学科薄弱知识点” | Q28: 助教 | R28: 智能辅导系统 | S28: 智育 | T28: 学生：提升实践能力与创新思维；教师：增强AI辅助教学能力；学校：推动课程改革与教学质量提升。 | U28: AI辅助课堂教学与互动 → 虚拟实验教学 → 智能学情诊断与个性化辅导 → 课程开发与应用 | V28: 数据采集层（多模态学习数据采集与融合） 行为识别层（学习意图识别、学习路径偏差检测） 画像诊断层（个性化画像生成、过程性反馈解释） 个性化学习层（即时生成反馈） | W28: 企业产品以“学习支持工具”为主，学校通过校本化规则实现教学适配，整体处于规模化应用初期。 | X28: 通过“AI+项目化”教学模式，构建了多元智慧学习场景，促进了物理教学的实践与创新，形成了鲜明的项目驱动与AI赋能特色。 | Y28: 物理 | Z28: AI智能作业批改系统 | AA28: 0 | AB28: 重庆市 | AD28: =VLOOKUP($K28,「工具标准名」映射表!$B:$I,3,0) -> AI智能作业批改系统 | AE28: =VLOOKUP($K28,「工具标准名」映射表!$B:$I,4,0) -> 功能应用层 | AF28: =VLOOKUP($K28,「工具标准名」映射表!$B:$I,5,0) -> 功能应用（教学辅助工具） | AG28: =VLOOKUP($K28,「工具标准名」映射表!$B:$I,6,0) -> 软件工具 | AH28: =VLOOKUP($K28,「工具标准名」映射表!$B:$I,7,0) -> 大语言模型 | AI28: =VLOOKUP($K28,「工具标准名」映射表!$B:$I,8,0) -> 是 | AJ28: 重庆市
A29: 第14号案例_14铜梁中学 基于“AI+项目化”的铜梁中学“数项融合”校本课程的开发与应用实践(1026).pdf | B29: 46056.458 | C29: 14 | D29: 基于“AI+项目化”的铜梁中学“数项融合”高中物理校本课程的开发与应用实践 | E29: 重庆市 | F29: 高中 | G29: 铜梁中学已在多所高中实施，整体处于规模化推广阶段 | H29: 通过AI与项目化学习的结合，创新了高中物理教学模式，提升了学生的实践能力与创新能力。 | I29: AI辅助课堂教学与互动 → 虚拟实验与实践教学 → 智能学情诊断与个性化辅导 | J29: ["人工智能算法", "虚拟现实技术", "智能作业批改系统", "智能诊断系统", "项目化学习"] | K29: DIS数字化实验平台 | L29: 未点名企业 | M29: FALSE | N29: 软件平台 | O29: Web 教学平台（SaaS） | P29: 文档中提到“利用DIS数字化实验平台和VR体验设备开展定量实验和定性实验” | Q29: 助教 | R29: 智能辅导系统 | S29: 智育 | T29: 学生：提升实践能力与创新思维；教师：增强AI辅助教学能力；学校：推动课程改革与教学质量提升。 | U29: AI辅助课堂教学与互动 → 虚拟实验教学 → 智能学情诊断与个性化辅导 → 课程开发与应用 | V29: 数据采集层（多模态学习数据采集与融合） 行为识别层（学习意图识别、学习路径偏差检测） 画像诊断层（个性化画像生成、过程性反馈解释） 个性化学习层（即时生成反馈） | W29: 企业产品以“学习支持工具”为主，学校通过校本化规则实现教学适配，整体处于规模化应用初期。 | X29: 通过“AI+项目化”教学模式，构建了多元智慧学习场景，促进了物理教学的实践与创新，形成了鲜明的项目驱动与AI赋能特色。 | Y29: 物理 | Z29: DIS数字化实验平台 | AA29: 0 | AB29: 重庆市 | AD29: =VLOOKUP($K29,「工具标准名」映射表!$B:$I,3,0) -> DIS数字化实验平台 | AE29: =VLOOKUP($K29,「工具标准名」映射表!$B:$I,4,0) -> 功能应用层 | AF29: =VLOOKUP($K29,「工具标准名」映射表!$B:$I,5,0) -> 功能应用（平台型综合系统） | AG29: =VLOOKUP($K29,「工具标准名」映射表!$B:$I,6,0) -> 软件工具 | AH29: =VLOOKUP($K29,「工具标准名」映射表!$B:$I,7,0) -> 其他 | AI29: =VLOOKUP($K29,「工具标准名」映射表!$B:$I,8,0) -> 否 | AJ29: 重庆市
A30: 第15号案例_15重庆市第八中学校+AI+SFK交互式人工智能教具应用与推广.pdf | B30: 46056.459 | C30: 15 | D30: AI+SFK交互式人工智能教具应用与推广 | E30: 重庆市 | F30: 初中 | G30: 已在重庆市50余所中小学应用验证，形成可复制的推广模式 | H30: 通过模块化设计和双面布局，降低了教学门槛，激发学生兴趣，培养计算思维与探究能力。 | I30: 需求分析 → 教具设计与研发 → 应用实践与反馈优化 → 推广与应用 | J30: ["模块化设计", "传感器与执行机构集成", "项目式教学资源开发", "跨学科融合学习", "用户体验优化"] | K30: AI+SFK交互式人工智能教具 | L30: 未点名企业 | M30: TRUE | N30: 硬件 + 教学资源 | O30: 教学辅助工具（工具型） | P30: 文档中提到“本案例研发了AI+SFK交互式人工智能教具及配套课程体系” | Q30: 助教 | R30: 教学辅助 | S30: 智育 | T30: 学生：激发对人工智能的兴趣，培养计算思维与探究能力；教师：降低教学门槛，提高教学效率；学校：形成可复制、可推广的AI教育新模式。 | U30: 需求分析 → 教具设计与开发 → 应用实践与反馈 → 持续优化与推广 | V30: 理念创新（可触摸的思维）；结构创新（模块化集成）；外观创新（双面布局）；资源创新（项目式教学资源库） | W30: 已在重庆市50余所中小学推广应用，整体处于规模化应用阶段，形成了“本校-集团-区域”三级推广网络。 | X30: 通过软硬件协同、简化操作、双面布局等创新，实现了从传统编程到理解底层逻辑的跨越，提升了教学的互动性与趣味性。 | Y30: 人工智能 | Z30: AI+SFK交互式人工智能教具 | AA30: 0 | AB30: 重庆市 | AD30: =VLOOKUP($K30,「工具标准名」映射表!$B:$I,3,0) -> AI+SFK交互式人工智能教具 | AE30: =VLOOKUP($K30,「工具标准名」映射表!$B:$I,4,0) -> 功能应用层 | AF30: =VLOOKUP($K30,「工具标准名」映射表!$B:$I,5,0) -> 功能应用（教学辅助工具） | AG30: =VLOOKUP($K30,「工具标准名」映射表!$B:$I,6,0) -> 硬件设备 | AH30: =VLOOKUP($K30,「工具标准名」映射表!$B:$I,7,0) -> AI智能体 | AI30: =VLOOKUP($K30,「工具标准名」映射表!$B:$I,8,0) -> 否 | AJ30: 重庆市
A31: 第16号案例_16重庆市人民小学校 革新发展性评价 培育“五星好少年”-申报书.pdf | B31: 46056.461 | C31: 16 | D31: 革新发展性评价 培育“五星好少年” | E31: 重庆市 | F31: 小学 | G31: 已在重庆市人民小学教育集团全面应用，形成可复制的评价体系与技术平台 | H31: 通过建立综合评价指标体系与个性化成长档案，实现学生评价从结果判断向过程赋能的转变，推动德智体美劳全面发展。 | I31: 建立综合评价指标体系 → 引入数字技术建立评价技术系统 → 生成个性化成长档案 → 实现精准赋能 | J31: ["多模态数据融合", "人工智能算法", "物联网技术", "数据可视化", "智能评价系统"] | K31: 劳动萌主小程序 | L31: 未点名企业 | M31: TRUE | N31: 软件平台 | O31: Web 教学平台（SaaS） | P31: 文档中提到“自主研发‘劳动萌主’小程序，打通劳动任务发布、过程记录、多方评价、徽章激励全流程。” | Q31: 助评 | R31: 综合素质评价 | S31: 德智体美劳 | T31: 学生：全面发展、个性化成长；教师：减轻评价负担、精准指导；学校：提升育人效能、获得多项荣誉 | U31: 数据采集 → 评价体系构建 → 个性化成长档案生成 → 过程赋能 | V31: 数据采集层（多模态数据采集与融合） 行为识别层（学生表现实时评价） 画像诊断层（个性化成长画像生成） | W31: 案例已在重庆市人民小学教育集团全面应用，形成可复制的实施方案，具有显著的社会效益与人才发展价值 | X31: 创新性地将物联网数据采集与人工智能算法深度整合，形成全流程技术解决方案，实现综合性、过程性的学生评价的规模化、常态化实施 | Y31: 未提及 | Z31: 劳动萌主小程序 | AA31: 0 | AB31: 重庆市 | AD31: =VLOOKUP($K31,「工具标准名」映射表!$B:$I,3,0) -> 劳动萌主小程序 | AE31: =VLOOKUP($K31,「工具标准名」映射表!$B:$I,4,0) -> 功能应用层 | AF31: =VLOOKUP($K31,「工具标准名」映射表!$B:$I,5,0) -> 功能应用（Web 教学平台（SaaS）） | AG31: =VLOOKUP($K31,「工具标准名」映射表!$B:$I,6,0) -> 软件工具 | AH31: =VLOOKUP($K31,「工具标准名」映射表!$B:$I,7,0) -> AI智能体 | AI31: =VLOOKUP($K31,「工具标准名」映射表!$B:$I,8,0) -> 否 | AJ31: 重庆市
A32: 第16号案例_16重庆市人民小学校 革新发展性评价 培育“五星好少年”-申报书.pdf | B32: 46056.461 | C32: 16 | D32: 革新发展性评价 培育“五星好少年” | E32: 重庆市 | F32: 小学 | G32: 已在重庆市人民小学教育集团全面应用，形成可复制的评价体系与技术平台 | H32: 通过建立综合评价指标体系与个性化成长档案，实现学生评价从结果判断向过程赋能的转变，推动德智体美劳全面发展。 | I32: 建立综合评价指标体系 → 引入数字技术建立评价技术系统 → 生成个性化成长档案 → 实现精准赋能 | J32: ["多模态数据融合", "人工智能算法", "物联网技术", "数据可视化", "智能评价系统"] | K32: 云师智学 | L32: 未点名企业 | M32: FALSE | N32: 软件平台 | O32: 平台型综合系统 | P32: 文档中提到“依托云师智学、班级优化大师等智慧平台，教师采集学生课堂、作业、考试等全链条数据。” | Q32: 助评 | R32: 综合素质评价 | S32: 德智体美劳 | T32: 学生：全面发展、个性化成长；教师：减轻评价负担、精准指导；学校：提升育人效能、获得多项荣誉 | U32: 数据采集 → 评价体系构建 → 个性化成长档案生成 → 过程赋能 | V32: 数据采集层（多模态数据采集与融合） 行为识别层（学生表现实时评价） 画像诊断层（个性化成长画像生成） | W32: 案例已在重庆市人民小学教育集团全面应用，形成可复制的实施方案，具有显著的社会效益与人才发展价值 | X32: 创新性地将物联网数据采集与人工智能算法深度整合，形成全流程技术解决方案，实现综合性、过程性的学生评价的规模化、常态化实施 | Y32: 未提及 | Z32: 云师智学 | AA32: 0 | AB32: 重庆市 | AD32: =VLOOKUP($K32,「工具标准名」映射表!$B:$I,3,0) -> 云师智学 | AE32: =VLOOKUP($K32,「工具标准名」映射表!$B:$I,4,0) -> 功能应用层 | AF32: =VLOOKUP($K32,「工具标准名」映射表!$B:$I,5,0) -> 功能应用（校级 / 区域级系统） | AG32: =VLOOKUP($K32,「工具标准名」映射表!$B:$I,6,0) -> 软件工具 | AH32: =VLOOKUP($K32,「工具标准名」映射表!$B:$I,7,0) -> AI智能体 | AI32: =VLOOKUP($K32,「工具标准名」映射表!$B:$I,8,0) -> 否 | AJ32: 重庆市
A33: 第16号案例_16重庆市人民小学校 革新发展性评价 培育“五星好少年”-申报书.pdf | B33: 46056.461 | C33: 16 | D33: 革新发展性评价 培育“五星好少年” | E33: 重庆市 | F33: 小学 | G33: 已在重庆市人民小学教育集团全面应用，形成可复制的评价体系与技术平台 | H33: 通过建立综合评价指标体系与个性化成长档案，实现学生评价从结果判断向过程赋能的转变，推动德智体美劳全面发展。 | I33: 建立综合评价指标体系 → 引入数字技术建立评价技术系统 → 生成个性化成长档案 → 实现精准赋能 | J33: ["多模态数据融合", "人工智能算法", "物联网技术", "数据可视化", "智能评价系统"] | K33: 量子大健康云平台 | L33: 未点名企业 | M33: FALSE | N33: 软件平台 | O33: 平台型综合系统 | P33: 文档中提到“建设‘量子大健康云平台’，开展三年周期的体质监测与动态干预。” | Q33: 助评 | R33: 综合素质评价 | S33: 德智体美劳 | T33: 学生：全面发展、个性化成长；教师：减轻评价负担、精准指导；学校：提升育人效能、获得多项荣誉 | U33: 数据采集 → 评价体系构建 → 个性化成长档案生成 → 过程赋能 | V33: 数据采集层（多模态数据采集与融合） 行为识别层（学生表现实时评价） 画像诊断层（个性化成长画像生成） | W33: 案例已在重庆市人民小学教育集团全面应用，形成可复制的实施方案，具有显著的社会效益与人才发展价值 | X33: 创新性地将物联网数据采集与人工智能算法深度整合，形成全流程技术解决方案，实现综合性、过程性的学生评价的规模化、常态化实施 | Y33: 未提及 | Z33: 量子大健康云平台 | AA33: 0 | AB33: 重庆市 | AD33: =VLOOKUP($K33,「工具标准名」映射表!$B:$I,3,0) -> 量子大健康云平台 | AE33: =VLOOKUP($K33,「工具标准名」映射表!$B:$I,4,0) -> 功能应用层 | AF33: =VLOOKUP($K33,「工具标准名」映射表!$B:$I,5,0) -> 功能应用（平台型综合系统） | AG33: =VLOOKUP($K33,「工具标准名」映射表!$B:$I,6,0) -> 软件工具 | AH33: =VLOOKUP($K33,「工具标准名」映射表!$B:$I,7,0) -> AI智能体 | AI33: =VLOOKUP($K33,「工具标准名」映射表!$B:$I,8,0) -> 否 | AJ33: 重庆市
A34: 第17号案例_17重庆市第八中学校+AI+校园全域智学成长平台.pdf | B34: 46056.463 | C34: 17 | D34: AI+校园全域智学成长平台 | E34: 重庆市 | F34: 高中 | G34: 已在重庆市部分区县高中成功落地，验证了其低成本、高效益的规模化推广潜力。 | H34: 通过构建全量数据融合的精准教学新范式，打破数据孤岛，实现动态学情画像与个性化教学干预，显著提升教学质量与效率。 | I34: 数据采集与分析 → 动态学情画像构建 → 精准教学干预 → 学习路径优化 | J34: ["数据治理", "动态学情画像", "智能批改", "个性化学习规划", "多模型联合调度"] | K34: AI+校园全域智学成长平台 | L34: 重庆智学慧阅科技有限责任公司 | M34: TRUE | N34: 软件平台 | O34: 平台型综合系统 | P34: 文档中提到“打造‘AI+校园全域智学成长平台’，以全域数据采集与分析为基础” | Q34: 助学 | R34: 智能学情诊断与个性化辅导 | S34: 智育 | T34: 学生：实现个性化学习规划，提升学习效率与信心；教师：减轻批改负担，提升教学质量；学校：构建公平优质的教育新生态。 | U34: 数据采集 → 动态学情画像构建 → 精准教学干预 → 个性化学习路径优化 | V34: 数据采集层（动态学情画像构建） 行为识别层（学生思维路径与认知负荷分析） 画像诊断层（多维动态学生能力画像） 智能策略层（个性化学习路径推荐） | W34: 企业产品以“学习支持工具”为主，已在重庆市部分区县高中成功落地，具备低成本、高效益的规模化推广潜力。 | X34: 重构基于全量数据融合的精准教学新范式，打破数据孤岛，实现动态能力画像与个性化教学干预，提升教学质量与效率。 | Y34: 未提及 | Z34: AI+校园全域智学成长平台 | AA34: 0 | AB34: 重庆市 | AD34: =VLOOKUP($K34,「工具标准名」映射表!$B:$I,3,0) -> AI+校园全域智学成长平台 | AE34: =VLOOKUP($K34,「工具标准名」映射表!$B:$I,4,0) -> 功能应用层 | AF34: =VLOOKUP($K34,「工具标准名」映射表!$B:$I,5,0) -> 功能应用（校级 / 区域级系统） | AG34: =VLOOKUP($K34,「工具标准名」映射表!$B:$I,6,0) -> 软件工具 | AH34: =VLOOKUP($K34,「工具标准名」映射表!$B:$I,7,0) -> 其他 | AI34: =VLOOKUP($K34,「工具标准名」映射表!$B:$I,8,0) -> 是 | AJ34: 重庆市
A35: 第18号案例_18重庆市第八中学校+AI赋能教育评价创新——基于三创教育理念的任务链与成长画像实践.pdf | B35: 46056.464 | C35: 18 | D35: AI赋能教育评价创新——基于三创教育理念的任务链与成长画像实践 | E35: 重庆市 | F35: 初中 | G35: 本案例已在多个年级常态化实施，显著提升了教师诊断教学能力与学生的学习主动性，推动“教、学、评”一体化改革，为AI赋能教育评价提供了可复制的路径与模型。 | H35: 通过AI技术实现学习行为采集、学习过程分析、成长画像生成与个性化反馈闭环，促进评价从“选拔工具”变为“学习引擎”，让学生在评价中学习、在反馈中成长。 | I35: 数据采集 → 智能分析 → 成长画像生成 → 反馈与应用 | J35: ["自然语言理解", "模式识别算法", "多模态数据采集", "个性化反馈", "动态评价"] | K35: YEEAI系统 | L35: 北京易知简教育科技有限公司 | M35: TRUE | N35: 软件平台 | O35: 平台型综合系统 | P35: 文档中提到“通过北京易知简教育科技有限公司研发的YEEAI系统，构建以‘任务链驱动、多源数据采集、成长画像反馈’为核心的形成性评价体系” | Q35: 助评 | R35: 学生成长数据分析与预警 | S35: 智育 | T35: 学生：提升学习主动性与自我反思能力；教师：增强精准教学能力；学校：推动‘教、学、评’一体化改革，形成可复制的教育评价创新路径。 | U35: 学习行为采集 → 学习过程分析 → 成长画像生成 → 个性化反馈 | V35: 数据采集层（多模态行为数据自动采集） 智能分析层（自然语言理解与模式识别算法） 画像诊断层（个体发展曲线与班级群体分析生成） 反馈与应用层（项目实施报告与个人成长画像查看） | W35: 企业产品以‘教育评价工具’为主，学校通过校企合作实现教学适配，整体处于规模化应用初期。 | X35: 构建AI支持的任务链学习模式，实现动态评价与个性化反馈，促进教师与学生的双向赋能，形成‘理念引领、技术支撑、场景共建’的协同创新机制。 | Y35: 未提及 | Z35: YEEAI系统 | AA35: 0 | AB35: 重庆市 | AD35: =VLOOKUP($K35,「工具标准名」映射表!$B:$I,3,0) -> YEEAI系统 | AE35: =VLOOKUP($K35,「工具标准名」映射表!$B:$I,4,0) -> 功能应用层 | AF35: =VLOOKUP($K35,「工具标准名」映射表!$B:$I,5,0) -> 功能应用（平台型综合系统） | AG35: =VLOOKUP($K35,「工具标准名」映射表!$B:$I,6,0) -> 软件工具 | AH35: =VLOOKUP($K35,「工具标准名」映射表!$B:$I,7,0) -> AI智能体 | AI35: =VLOOKUP($K35,「工具标准名」映射表!$B:$I,8,0) -> 否 | AJ35: 重庆市
A36: 第19号案例_19重庆市第八中学校+互动艺术与机器人社团综合互评系统.pdf | B36: 46056.465 | C36: 19 | D36: 互动艺术与机器人社团综合互评系统 | E36: 重庆市 | F36: 初中 | G36: 该项目自2025年初以来，目前已稳定服务2届学生，处于推广阶段 | H36: 通过多源数据融合分析，构建多维度标准化评价体系，提升评价深度与准确性，形成可复制的‘多主体互评’操作规范。 | I36: 数据收集与整合 → 多源数据分析 → 个性化综合评估 → 生成可视化发展报告 | J36: ["自然语言处理", "数据融合分析", "情感倾向分析", "能力维度评价", "团队协作能力评估"] | K36: 互动艺术与机器人社团综合互评系统 | L36: 未点名企业 | M36: TRUE | N36: 软件平台 | O36: 平台型综合系统 | P36: 文档中提到‘利用豆包大模型创建了“互动艺术与机器人社团综合互评系统”智能体作为整个评价体系的载体’ | Q36: 助学 | R36: 学生成长数据分析与预警 | S36: 智育 | T36: 学生：提供个性化综合评估与提升建议；教师：依据数据支撑定制教学方案；学校：提升社团在国际赛事中的竞争力。 | U36: 数据收集 → 多源数据融合分析 → 个性化综合评估 → 可视化发展报告生成 | V36: 数据采集层（多源数据整合与记录） 行为识别层（学生互评与教师评价分析） 画像诊断层（综合素质与能力评估生成） | W36: 项目已稳定服务2届学生，具备快速复制至其他实践性社团的潜力，整体处于推广阶段。 | X36: 构建了基于AI的多维度标准化评价体系，首次将学生互评与跨队互评纳入综合素质评价，提升了评价的客观性与准确性。 | Y36: 科技 | Z36: 互动艺术与机器人社团综合互评系统 | AA36: 0 | AB36: 重庆市 | AD36: =VLOOKUP($K36,「工具标准名」映射表!$B:$I,3,0) -> 互动艺术与机器人社团综合互评系统 | AE36: =VLOOKUP($K36,「工具标准名」映射表!$B:$I,4,0) -> 功能应用层 | AF36: =VLOOKUP($K36,「工具标准名」映射表!$B:$I,5,0) -> 功能应用（Web 教学平台（SaaS）） | AG36: =VLOOKUP($K36,「工具标准名」映射表!$B:$I,6,0) -> 软件工具 | AH36: =VLOOKUP($K36,「工具标准名」映射表!$B:$I,7,0) -> 其他 | AI36: =VLOOKUP($K36,「工具标准名」映射表!$B:$I,8,0) -> 否 | AJ36: 重庆市
A37: 第20号案例_20成都市泡桐树小学境界分校 AI赋能学生评价创新实践——“六度育人图谱”驱动的全场景综合素质发展体系构建.docx | B37: 46056.465 | C37: 20 | D37: AI赋能学生评价创新实践——“六度育人图谱”驱动的全场景综合素质发展体系构建 | E37: 成都市 | F37: 小学 | G37: 案例已实现全校全覆盖，成效显著，具备极强的可复制性 | H37: 实现了‘技术 - 课堂 - 生活’的深度融合创新，推动教育教学模式从‘单向评价’向‘协同共育’转变，建立了‘评价—诊断—改进—提升’的良性循环路径。 | I37: 理念转化 → 技术落地 → 场景应用 → 优化迭代 | J37: ["数据采集", "语音识别", "图像识别", "机器学习算法", "大数据分析"] | K37: AI成长学生发展平台 | L37: 未点名企业 | M37: TRUE | N37: 软件平台 | O37: 平台型综合系统 | P37: 文档中提到‘自主研发“AI成长学生发展平台”，构建“1个核心平台+2大应用场景+3维联动机制”生态体系’ | Q37: 助评 | R37: 综合素质评价 | S37: 德育 | T37: 学生：全面发展素质提升；教师：提高评价效率与精准度；学校：形成可复制的评价体系与管理模式。 | U37: 理念转化 → 技术落地 → 场景应用 → 优化迭代 | V37: 数据采集层（多终端设备与智能识别技术实现全场景数据采集） 行为识别层（AI实时捕捉学生状态与表现） 画像诊断层（生成学生成长树与班级素养雷达图） | W37: 案例已实现全校全覆盖，具备极强的可复制性，整体处于规模化应用初期 | X37: 实现了“技术 - 课堂 - 生活”的深度融合创新，打破传统教研局限，提升评价效率与精准度，推动教育教学模式从“单向评价”向“协同共育”转变。 | Y37: 未提及 | Z37: AI成长学生发展平台 | AA37: 0 | AB37: 四川省 | AD37: =VLOOKUP($K37,「工具标准名」映射表!$B:$I,3,0) -> AI成长学生发展平台 | AE37: =VLOOKUP($K37,「工具标准名」映射表!$B:$I,4,0) -> 功能应用层 | AF37: =VLOOKUP($K37,「工具标准名」映射表!$B:$I,5,0) -> 功能应用（校级 / 区域级系统） | AG37: =VLOOKUP($K37,「工具标准名」映射表!$B:$I,6,0) -> 软件工具 | AH37: =VLOOKUP($K37,「工具标准名」映射表!$B:$I,7,0) -> AI智能体 | AI37: =VLOOKUP($K37,「工具标准名」映射表!$B:$I,8,0) -> 否 | AJ37: 四川省
... A43: 第23号案例_23人工智能+基础教育”典型应用场景案例申报书(天台岗万国城小学).pdf | B43: 46056.465 | C43: 23 | D43: 生成式AI+知识图谱支持的小学生个性化学习路径构建与实践 | E43: 重庆市南岸区 | F43: 小学 | G43: 已在学校两个年级中的8个班开展常态化应用，整体处于规模化推广阶段 | H43: 通过生成式AI与知识图谱的结合，实现个性化学习路径的动态生成与实时反馈，提升学生自主学习能力与教学效率。 | I43: 生成式AI工具生成学情诊断报告 → 知识图谱构建与关联关系推送 → 实时反馈与个性化学习路径推荐 | J43: ["生成式AI", "知识图谱", "学习路径推荐算法", "智能体伴学系统", "数据分析"] | K43: 智能体伴学系统 | L43: 未点名企业 | M43: FALSE | N43: 软件平台 | O43: 平台型综合系统 | P43: 文档中提到“利用生成式AI实现学习清单的自动生成，利用智能体开展作业智能批改与个性化答疑” | Q43: 助学 | R43: 智能辅导系统 | S43: 智育 | T43: 学生：提升自主学习能力与个性化学习效果；教师：提高备课效率与精准教学能力；学校：形成可复制的个性化学习实践模式。 | U43: 生成式AI工具生成学情诊断报告 → 知识图谱构建与资源推送 → 实时反馈与个性化学习闭环 | V43: 数据采集层（动态生成学情诊断报告、知识图谱构建） 画像诊断层（个性化学习路径推荐、实时反馈机制） 个性化学习层（智能体伴学与个性化辅导） | W43: 企业产品以“支持个性化学习”为主，学校通过校本化规则实现教学适配，整体处于规模化应用初期。 | X43: 构建了“三层三阶”的个性化学习模型，突破传统教学模式，实现从“教为中心”向“学为中心”的转型，形成完整的学习阶段闭环。 | Y43: 语文、数学 | Z43: 智能体伴学系统 | AA43: 0 | AB43: 重庆市 | AD43: =VLOOKUP($K43,「工具标准名」映射表!$B:$I,3,0) -> 智能体伴学系统 | AE43: =VLOOKUP($K43,「工具标准名」映射表!$B:$I,4,0) -> 功能应用层 | AF43: =VLOOKUP($K43,「工具标准名」映射表!$B:$I,5,0) -> 功能应用（校级 / 区域级系统） | AG43: =VLOOKUP($K43,「工具标准名」映射表!$B:$I,6,0) -> 软件工具 | AH43: =VLOOKUP($K43,「工具标准名」映射表!$B:$I,7,0) -> AI智能体 | AI43: =VLOOKUP($K43,「工具标准名」映射表!$B:$I,8,0) -> 否 | AJ43: 重庆市
A44: 第24号案例_24北京十一学校顺义学校（杨镇一中）丁洁 指数衰减模型的跨学科探索——AI辅助下的核污水放射性衰变分析.docx | B44: 46056.465 | C44: 24 | D44: 指数衰减模型的跨学科探索——AI辅助下的核污水放射性衰变分析 | E44: 北京 | F44: 高中 | G44: 该模式已显示出提升课堂效率、深化学生探究能力的明确效果，通过教师培训即可快速规模化应用。 | H44: 案例成功地将数学、物理、社会热点及科技伦理融为一体，体现了STEM教育和项目式学习的核心思想，凸显了数学在解决真实世界问题中的价值。 | I44: 数据整合与精准学情分析 → 动态探究与高效互动 → 拓展探究与能力培养 | J44: ["数据分析", "动态数学软件", "AI工具", "模型构建", "批判性思维"] | K44: 豆包 | L44: 未点名企业 | M44: FALSE | N44: 软件平台 | O44: Web 教学平台（SaaS） | P44: 文档中提到“学生遇到如‘贝克勒尔单位’等即时性问题，可通过豆包等工具快速获得解答” | Q44: 助学 | R44: 智能辅导系统 | S44: 智育 | T44: 学生：提升高阶思维能力、科学素养与批判性思维；教师：实现精准备课与教学；学校：推动跨学科项目式学习的实施。 | U44: 数据整合与精准学情分析 → 动态探究与高效互动 → 拓展探究与能力培养 | V44: 数据采集层（跨学科数据整合、实时半衰期数据获取） 行为识别层（学情分析与反馈） 个性化学习层（AI工具辅助学习与资源推荐） | W44: 案例展示了AI技术在基础教育中的系统性应用，推动了跨学科教学的探索与实践，整体处于推广阶段。 | X44: 通过真实社会问题驱动，整合数学、物理与环境科学，利用AI工具提升学生的自主探究能力与批判性思维，体现了STEM教育与项目式学习的核心思想。 | Y44: 数学/物理/环境科学 | Z44: 豆包 | AA44: 北京春田知韵科技有限公司 | AB44: 北京市 | AD44: =VLOOKUP($K44,「工具标准名」映射表!$B:$I,3,0) -> 豆包 | AE44: =VLOOKUP($K44,「工具标准名」映射表!$B:$I,4,0) -> 功能应用层 | AF44: =VLOOKUP($K44,「工具标准名」映射表!$B:$I,5,0) -> 功能应用（教学辅助工具） | AG44: =VLOOKUP($K44,「工具标准名」映射表!$B:$I,6,0) -> 软件工具 | AH44: =VLOOKUP($K44,「工具标准名」映射表!$B:$I,7,0) -> 其他 | AI44: =VLOOKUP($K44,「工具标准名」映射表!$B:$I,8,0) -> 否 | AJ44: 北京市
A45: 第24号案例_24北京十一学校顺义学校（杨镇一中）丁洁 指数衰减模型的跨学科探索——AI辅助下的核污水放射性衰变分析.docx | B45: 46056.465 | C45: 24 | D45: 指数衰减模型的跨学科探索——AI辅助下的核污水放射性衰变分析 | E45: 北京 | F45: 高中 | G45: 该模式已显示出提升课堂效率、深化学生探究能力的明确效果，通过教师培训即可快速规模化应用。 | H45: 案例成功地将数学、物理、社会热点及科技伦理融为一体，体现了STEM教育和项目式学习的核心思想，凸显了数学在解决真实世界问题中的价值。 | I45: 数据整合与精准学情分析 → 动态探究与高效互动 → 拓展探究与能力培养 | J45: ["数据分析", "动态数学软件", "AI工具", "模型构建", "批判性思维"] | K45: Deepseek | L45: 未点名企业 | M45: FALSE | N45: 软件平台 | O45: Web 教学平台（SaaS） | P45: 文档中提到“学生利用AI工具（如豆包、Deepseek）快速搜集跨学科数据” | Q45: 助学 | R45: 智能辅导系统 | S45: 智育 | T45: 学生：提升高阶思维能力、科学素养与批判性思维；教师：实现精准备课与教学；学校：推动跨学科项目式学习的实施。 | U45: 数据整合与精准学情分析 → 动态探究与高效互动 → 拓展探究与能力培养 | V45: 数据采集层（跨学科数据整合、实时半衰期数据获取） 行为识别层（学情分析与反馈） 个性化学习层（AI工具辅助学习与资源推荐） | W45: 案例展示了AI技术在基础教育中的系统性应用，推动了跨学科教学的探索与实践，整体处于推广阶段。 | X45: 通过真实社会问题驱动，整合数学、物理与环境科学，利用AI工具提升学生的自主探究能力与批判性思维，体现了STEM教育与项目式学习的核心思想。 | Y45: 数学/物理/环境科学 | Z45: DeepSeek 大模型 | AA45: 杭州深度求索人工智能基础技术研究有限公司 | AB45: 北京市 | AD45: =VLOOKUP($K45,「工具标准名」映射表!$B:$I,3,0) -> DeepSeek 大模型 | AE45: =VLOOKUP($K45,「工具标准名」映射表!$B:$I,4,0) -> 功能应用层 | AF45: =VLOOKUP($K45,「工具标准名」映射表!$B:$I,5,0) -> 功能应用（教学辅助工具） | AG45: =VLOOKUP($K45,「工具标准名」映射表!$B:$I,6,0) -> 软件工具 | AH45: =VLOOKUP($K45,「工具标准名」映射表!$B:$I,7,0) -> AI智能体 | AI45: =VLOOKUP($K45,「工具标准名」映射表!$B:$I,8,0) -> 否 | AJ45: 北京市
A46: 第24号案例_24北京十一学校顺义学校（杨镇一中）丁洁 指数衰减模型的跨学科探索——AI辅助下的核污水放射性衰变分析.docx | B46: 46056.465 | C46: 24 | D46: 指数衰减模型的跨学科探索——AI辅助下的核污水放射性衰变分析 | E46: 北京 | F46: 高中 | G46: 该模式已显示出提升课堂效率、深化学生探究能力的明确效果，通过教师培训即可快速规模化应用。 | H46: 案例成功地将数学、物理、社会热点及科技伦理融为一体，体现了STEM教育和项目式学习的核心思想，凸显了数学在解决真实世界问题中的价值。 | I46: 数据整合与精准学情分析 → 动态探究与高效互动 → 拓展探究与能力培养 | J46: ["数据分析", "动态数学软件", "AI工具", "模型构建", "批判性思维"] | K46: GeoGebra | L46: 未点名企业 | M46: FALSE | N46: 软件平台 | O46: Web 教学平台（SaaS） | P46: 文档中提到“利用GeoGebra动态数学软件绘制指数函数图像” | Q46: 助学 | R46: 智能辅导系统 | S46: 智育 | T46: 学生：提升高阶思维能力、科学素养与批判性思维；教师：实现精准备课与教学；学校：推动跨学科项目式学习的实施。 | U46: 数据整合与精准学情分析 → 动态探究与高效互动 → 拓展探究与能力培养 | V46: 数据采集层（跨学科数据整合、实时半衰期数据获取） 行为识别层（学情分析与反馈） 个性化学习层（AI工具辅助学习与资源推荐） | W46: 案例展示了AI技术在基础教育中的系统性应用，推动了跨学科教学的探索与实践，整体处于推广阶段。 | X46: 通过真实社会问题驱动，整合数学、物理与环境科学，利用AI工具提升学生的自主探究能力与批判性思维，体现了STEM教育与项目式学习的核心思想。 | Y46: 数学/物理/环境科学 | Z46: GeoGebra | AA46: 0 | AB46: 北京市 | AD46: =VLOOKUP($K46,「工具标准名」映射表!$B:$I,3,0) -> GeoGebra | AE46: =VLOOKUP($K46,「工具标准名」映射表!$B:$I,4,0) -> 功能应用层 | AF46: =VLOOKUP($K46,「工具标准名」映射表!$B:$I,5,0) -> 功能应用（平台型综合系统） | AG46: =VLOOKUP($K46,「工具标准名」映射表!$B:$I,6,0) -> 软件工具 | AH46: =VLOOKUP($K46,「工具标准名」映射表!$B:$I,7,0) -> 其他 | AI46: =VLOOKUP($K46,「工具标准名」映射表!$B:$I,8,0) -> 否 | AJ46: 北京市
A47: 第26号案例_26重庆市第八中学校+人工智能赋能学生评价——AI助力教师撰写评语的实践探索.pdf | B47: 46056.466 | C47: 26 | D47: 人工智能赋能学生评价——AI助力教师撰写评语的实践探索 | E47: 重庆市 | F47: 初中 | G47: 该案例已在重庆市第八中学校实施，显示出良好的推广潜力，正在向其他学校扩展。 | H47: 通过AI工具减轻教师的工作负担，提高评语撰写效率，同时保持评语的个性化和温度，推动教育评价的创新。 | I47: AI评语生成 → 教师审核与情感润色 → 个性化反馈与优化 | J47: ["自然语言生成", "个性化表达", "语义优化", "数据安全", "人机协作"] | K47: 豆包 | L47: 未点名企业 | M47: FALSE | N47: 软件平台 | O47: Web 教学平台（SaaS） | P47: 文档中提到“用豆包搭建专属‘评语智能体’” | Q47: 助评 | R47: 学生评估 | S47: 德育 | T47: 学生：获得个性化、鼓励性的评语；教师：减轻评语撰写负担，提高工作效率；学校：提升教育评价质量与教师满意度。 | U47: AI评语生成 → 教师审核与润色 → 个性化反馈 | V47: 数据采集层（学生信息与关键词输入） 行为识别层（评语生成模型） 个性化学习层（教师个性化修改与润色） | W47: 企业产品以“评语撰写工具”为主，学校通过AI辅助实现评语个性化，整体处于推广应用阶段。 | X47: 通过AI辅助撰写评语，显著提高教师工作效率，减轻重复性劳动，促进教师对教育语言的反思与表达能力提升，同时确保评语的个性化与温度。 | Y47: 未提及 | Z47: 豆包 | AA47: 北京春田知韵科技有限公司 | AB47: 重庆市 | AD47: =VLOOKUP($K47,「工具标准名」映射表!$B:$I,3,0) -> 豆包 | AE47: =VLOOKUP($K47,「工具标准名」映射表!$B:$I,4,0) -> 功能应用层 | AF47: =VLOOKUP($K47,「工具标准名」映射表!$B:$I,5,0) -> 功能应用（教学辅助工具） | AG47: =VLOOKUP($K47,「工具标准名」映射表!$B:$I,6,0) -> 软件工具 | AH47: =VLOOKUP($K47,「工具标准名」映射表!$B:$I,7,0) -> 其他 | AI47: =VLOOKUP($K47,「工具标准名」映射表!$B:$I,8,0) -> 否 | AJ47: 重庆市
A48: 第26号案例_26重庆市第八中学校+人工智能赋能学生评价——AI助力教师撰写评语的实践探索.pdf | B48: 46056.466 | C48: 26 | D48: 人工智能赋能学生评价——AI助力教师撰写评语的实践探索 | E48: 重庆市 | F48: 初中 | G48: 该案例已在重庆市第八中学校实施，显示出良好的推广潜力，正在向其他学校扩展。 | H48: 通过AI工具减轻教师的工作负担，提高评语撰写效率，同时保持评语的个性化和温度，推动教育评价的创新。 | I48: AI评语生成 → 教师审核与情感润色 → 个性化反馈与优化 | J48: ["自然语言生成", "个性化表达", "语义优化", "数据安全", "人机协作"] | K48: AA班级助手 | L48: 未点名企业 | M48: FALSE | N48: 软件平台 | O48: Web 教学平台（SaaS） | P48: 文档中提到“用‘AA班级助手’降低操作门槛” | Q48: 助评 | R48: 学生评估 | S48: 德育 | T48: 学生：获得个性化、鼓励性的评语；教师：减轻评语撰写负担，提高工作效率；学校：提升教育评价质量与教师满意度。 | U48: AI评语生成 → 教师审核与润色 → 个性化反馈 | V48: 数据采集层（学生信息与关键词输入） 行为识别层（评语生成模型） 个性化学习层（教师个性化修改与润色） | W48: 企业产品以“评语撰写工具”为主，学校通过AI辅助实现评语个性化，整体处于推广应用阶段。 | X48: 通过AI辅助撰写评语，显著提高教师工作效率，减轻重复性劳动，促进教师对教育语言的反思与表达能力提升，同时确保评语的个性化与温度。 | Y48: 未提及 | Z48: AA班级助手 | AA48: 0 | AB48: 重庆市 | AD48: =VLOOKUP($K48,「工具标准名」映射表!$B:$I,3,0) -> 豆包 | AE48: =VLOOKUP($K48,「工具标准名」映射表!$B:$I,4,0) -> 功能应用层 | AF48: =VLOOKUP($K48,「工具标准名」映射表!$B:$I,5,0) -> 功能应用（教学辅助工具） | AG48: =VLOOKUP($K48,「工具标准名」映射表!$B:$I,6,0) -> 软件工具 | AH48: =VLOOKUP($K48,「工具标准名」映射表!$B:$I,7,0) -> AI智能体 | AI48: =VLOOKUP($K48,「工具标准名」映射表!$B:$I,8,0) -> 是 | AJ48: 重庆市
A49: 第27号案例_【申报书】西南大学附属中学校-马彬琼-“缙云AI”历史主观题智能批阅平台.docx | B49: 46056.466 | C49: 27 | D49: 缙云AI历史主观题智能批阅平台 | E49: 重庆市 | F49: 初中/高中 | G49: 已在64所学校推广使用两年，覆盖多个省市，处于规模化应用阶段 | H49: 实现主观题的智能化评阅，减轻教师负担，提供精准反馈与个性化提升路径，填补文科主观题智能评价技术空白。 | I49: 主观题评阅需求分析 → AI模型适配与训练 → 智能批阅与反馈生成 → 教学调整与优化 | J49: ["大型语言模型（LLM）", "自然语言处理", "智能评阅算法", "数据分析与可视化"] | K49: 缙云AI | L49: 西南大学附属中学校 | M49: TRUE | N49: 软件平台 | O49: 平台型综合系统 | P49: 文档中提到“基于现有基础大模型创建的个性化智能体‘缙云AI’，用于历史主观题的智能批阅” | Q49: 助评 | R49: 学生评估 | S49: 智育 | T49: 学生：明确主观题错因及提分路径；教师：减轻评阅负担、提高评阅效率；教育管理者：优化学业质量评估、提升教学质量。 | U49: 需求分析 → 技术研发与实施 → 应用优化 → 案例创新突破 | V49: 数据采集层（历史主观题作答数据采集） 行为识别层（学生作答模式分析） 画像诊断层（个性化评分与反馈生成） 智能策略层（AI初评与教师复核协同） | W49: 企业产品以'智能评阅工具'为主，已在多个省份推广，整体处于规模化应用阶段。 | X49: 突破了主观题传统人工评阅模式，实现全题型智能化评阅，减轻教师负担，提供实时反馈与精准诊断，满足学生个性化提分需求。 | Y49: 历史 | Z49: 缙云AI | AA49: 0 | AB49: 重庆市 | AD49: =VLOOKUP($K49,「工具标准名」映射表!$B:$I,3,0) -> 缙云AI | AE49: =VLOOKUP($K49,「工具标准名」映射表!$B:$I,4,0) -> 功能应用层 | AF49: =VLOOKUP($K49,「工具标准名」映射表!$B:$I,5,0) -> 功能应用层（AI智能体） | AG49: =VLOOKUP($K49,「工具标准名」映射表!$B:$I,6,0) -> 软件工具 | AH49: =VLOOKUP($K49,「工具标准名」映射表!$B:$I,7,0) -> AI智能体 | AI49: =VLOOKUP($K49,「工具标准名」映射表!$B:$I,8,0) -> 否 | AJ49: 重庆市
A50: 第27号案例_【申报书】西南大学附属中学校-马彬琼-“缙云AI”历史主观题智能批阅平台.docx | B50: 46056.466 | C50: 27 | D50: 缙云AI历史主观题智能批阅平台 | E50: 重庆市 | F50: 初中/高中 | G50: 已在64所学校推广使用两年，覆盖多个省市，处于规模化应用阶段 | H50: 实现主观题的智能化评阅，减轻教师负担，提供精准反馈与个性化提升路径，填补文科主观题智能评价技术空白。 | I50: 主观题评阅需求分析 → AI模型适配与训练 → 智能批阅与反馈生成 → 教学调整与优化 | J50: ["大型语言模型（LLM）", "自然语言处理", "智能评阅算法", "数据分析与可视化"] | K50: U云校智慧平台 | L50: 未点名企业 | M50: FALSE | N50: 软件平台 | O50: 平台型综合系统 | P50: 文档中提到“借助U云校智慧平台，该智能体已经在多个省的学校推广使用” | Q50: 助评 | R50: 学生评估 | S50: 智育 | T50: 学生：明确主观题错因及提分路径；教师：减轻评阅负担、提高评阅效率；教育管理者：优化学业质量评估、提升教学质量。 | U50: 需求分析 → 技术研发与实施 → 应用优化 → 案例创新突破 | V50: 数据采集层（历史主观题作答数据采集） 行为识别层（学生作答模式分析） 画像诊断层（个性化评分与反馈生成） 智能策略层（AI初评与教师复核协同） | W50: 企业产品以'智能评阅工具'为主，已在多个省份推广，整体处于规模化应用阶段。 | X50: 突破了主观题传统人工评阅模式，实现全题型智能化评阅，减轻教师负担，提供实时反馈与精准诊断，满足学生个性化提分需求。 | Y50: 历史 | Z50: U云校智慧平台 | AA50: 0 | AB50: 重庆市 | AD50: =VLOOKUP($K50,「工具标准名」映射表!$B:$I,3,0) -> U云校智慧平台 | AE50: =VLOOKUP($K50,「工具标准名」映射表!$B:$I,4,0) -> 功能应用层 | AF50: =VLOOKUP($K50,「工具标准名」映射表!$B:$I,5,0) -> 功能应用（教学辅助工具） | AG50: =VLOOKUP($K50,「工具标准名」映射表!$B:$I,6,0) -> 硬件设备 | AH50: =VLOOKUP($K50,「工具标准名」映射表!$B:$I,7,0) -> 其他 | AI50: =VLOOKUP($K50,「工具标准名」映射表!$B:$I,8,0) -> 否 | AJ50: 重庆市
A51: 第29号案例_AI赋能：学生体质健康智能化管理平台的构建与实施案例.docx | B51: 46056.466 | C51: 29 | D51: AI赋能：学生体质健康智能化管理平台的构建与实施案例 | E51: 北京市西城区 | F51: 小学 | G51: 本案例构建的“AI+体育健康”管理模式，具备高度的可复制性与广泛的推广前景，推动了国家体质健康测试工作的现代化发展。 | H51: 成功将人工智能技术与基础教育中的体质健康管理深度融合，提升了工作效率，为学生的终身健康奠定了坚实的基础。 | I51: 智能物联 → 数据汇聚与清洗 → AI赋能分析 → 精准干预与反馈 | J51: ["人工智能算法", "数据清洗与处理", "动态成长模型", "个体数字画像生成", "多维分析与智能评定"] | K51: DeepSeek | L51: 未点名企业 | M51: FALSE | N51: 软件平台 | O51: 平台型综合系统 | P51: 文档中提到“结合‘平台’DeepSeek的模型能力，平台不仅对体质薄弱进行自动识别，还需具备对篮球等专项体育苗子的选拔潜力进行数据化评估的能力。” | Q51: 助学 | R51: 智能辅导系统 | S51: 体育 | T51: 学生：实现个性化体质健康管理与提升；教师：减轻工作负担，提升教学效果；学校：推动健康教育现代化，形成可复制的管理模式。 | U51: 数据采集 → 数据分析与评估 → 个性化干预 → 管理闭环 | V51: 数据采集层（智能设备自动化数据采集） 画像诊断层（动态更新的学生体质数据库） 个性化学习层（个性化体质报告与干预建议） | W51: 企业产品以“健康管理工具”为主，学校通过智能化手段实现数据驱动的健康管理，整体处于初步推广阶段。 | X51: 构建了“测、评、导、促”一体化闭环，推动体育教育从普适化向个性化转变，实现了数据驱动的精准干预与家校协同的新生态。 | Y51: 体育 | Z51: DeepSeek 大模型 | AA51: 杭州深度求索人工智能基础技术研究有限公司 | AB51: 北京市 | AD51: =VLOOKUP($K51,「工具标准名」映射表!$B:$I,3,0) -> DeepSeek 大模型 | AE51: =VLOOKUP($K51,「工具标准名」映射表!$B:$I,4,0) -> 功能应用层 | AF51: =VLOOKUP($K51,「工具标准名」映射表!$B:$I,5,0) -> 功能应用（教学辅助工具） | AG51: =VLOOKUP($K51,「工具标准名」映射表!$B:$I,6,0) -> 软件工具 | AH51: =VLOOKUP($K51,「工具标准名」映射表!$B:$I,7,0) -> AI智能体 | AI51: =VLOOKUP($K51,「工具标准名」映射表!$B:$I,8,0) -> 否 | AJ51: 北京市
A52: 第29号案例_AI赋能：学生体质健康智能化管理平台的构建与实施案例.docx | B52: 46056.466 | C52: 29 | D52: AI赋能：学生体质健康智能化管理平台的构建与实施案例 | E52: 北京市西城区 | F52: 小学 | G52: 本案例构建的“AI+体育健康”管理模式，具备高度的可复制性与广泛的推广前景，推动了国家体质健康测试工作的现代化发展。 | H52: 成功将人工智能技术与基础教育中的体质健康管理深度融合，提升了工作效率，为学生的终身健康奠定了坚实的基础。 | I52: 智能物联 → 数据汇聚与清洗 → AI赋能分析 → 精准干预与反馈 | J52: ["人工智能算法", "数据清洗与处理", "动态成长模型", "个体数字画像生成", "多维分析与智能评定"] | K52: AIoT智能训练站 | L52: 未点名企业 | M52: FALSE | N52: 硬件 + AI系统 | O52: 教学辅助工具（工具型） | P52: 文档中描述“根据《国家学生体质健康标准》测试要求，我们部署了一套完整的智能体测设备，包括：平台算力服务器、健康管理体测仪、AIoT智能训练站。” | Q52: 助学 | R52: 智能辅导系统 | S52: 体育 | T52: 学生：实现个性化体质健康管理与提升；教师：减轻工作负担，提升教学效果；学校：推动健康教育现代化，形成可复制的管理模式。 | U52: 数据采集 → 数据分析与评估 → 个性化干预 → 管理闭环 | V52: 数据采集层（智能设备自动化数据采集） 画像诊断层（动态更新的学生体质数据库） 个性化学习层（个性化体质报告与干预建议） | W52: 企业产品以“健康管理工具”为主，学校通过智能化手段实现数据驱动的健康管理，整体处于初步推广阶段。 | X52: 构建了“测、评、导、促”一体化闭环，推动体育教育从普适化向个性化转变，实现了数据驱动的精准干预与家校协同的新生态。 | Y52: 体育 | Z52: AIoT智能训练站 | AA52: 0 | AB52: 北京市 | AD52: =VLOOKUP($K52,「工具标准名」映射表!$B:$I,3,0) -> AIoT智能训练站 | AE52: =VLOOKUP($K52,「工具标准名」映射表!$B:$I,4,0) -> 功能应用层 | AF52: =VLOOKUP($K52,「工具标准名」映射表!$B:$I,5,0) -> 功能应用（校级 / 区域级系统） | AG52: =VLOOKUP($K52,「工具标准名」映射表!$B:$I,6,0) -> 软件工具 | AH52: =VLOOKUP($K52,「工具标准名」映射表!$B:$I,7,0) -> 其他 | AI52: =VLOOKUP($K52,「工具标准名」映射表!$B:$I,8,0) -> 是 | AJ52: 北京市
A53: 第30号案例_海盐职业教育中心彭韦浩+“人工智能+基础教育”典型应用场景案例申报书.docx | B53: 46056.466 | C53: 30 | D53: 基于自然语言交互的AI成绩查询与学情分析助手 | E53: 海盐 | F53: 中职 | G53: 已在本学部试点稳定运行，计划逐步推广到本校使用 | H53: 推动了从‘经验驱动’教学向‘数据智能驱动’教学的转变，赋能学生进行‘自主诊断式’学习，构建了基于精准数据的家校沟通桥梁。 | I53: 数据对接与定制 → 自然语言理解与知识库问答 → 智能引导式对话流程 → 可视化呈现与分析维度深化 | J53: ["自然语言处理", "数据可视化", "教育数据分析", "对话系统设计", "用户体验优化"] | K53: 海盐AI智库 | L53: 未点名企业 | M53: FALSE | N53: 软件平台 | O53: 平台型综合系统 | P53: 文档中提到‘基于成熟的“海盐AI智库”（MaxKB）平台进行开发’ | Q53: 助学 | R53: 智能辅导系统 | S53: 智育 | T53: 学生：快速进行自我诊断，激发学习动力；教师：获取班级学情数据支持教学评估；家长：随时查询子女成绩，全面了解学习状况。 | U53: 数据对接与定制 → 自然语言处理（NLP）模型微调 → 智能引导式对话流程设计 → 可视化呈现与分析维度深化 | V53: 数据采集层（学生信息库与成绩数据库对接） 行为识别层（自然语言理解与知识库问答能力） 画像诊断层（学情画像生成与分析） 个性化学习层（智能引导式对话与反馈） | W53: 已在本学部试点稳定运行，计划逐步推广，整体处于规模化应用初期 | X53: 实现了教育领域自然语言交互的实用化落地，推动了从经验驱动教学向数据智能驱动教学的转变，构建了基于精准数据的家校沟通桥梁。 | Y53: 未提及 | Z53: 海盐AI智库 | AA53: 0 | AB53: 浙江省 | AD53: =VLOOKUP($K53,「工具标准名」映射表!$B:$I,3,0) -> 海盐AI智库 | AE53: =VLOOKUP($K53,「工具标准名」映射表!$B:$I,4,0) -> 功能应用层 | AF53: =VLOOKUP($K53,「工具标准名」映射表!$B:$I,5,0) -> 功能应用（平台型综合系统） | AG53: =VLOOKUP($K53,「工具标准名」映射表!$B:$I,6,0) -> 软件工具 | AH53: =VLOOKUP($K53,「工具标准名」映射表!$B:$I,7,0) -> AI智能体 | AI53: =VLOOKUP($K53,「工具标准名」映射表!$B:$I,8,0) -> 否 | AJ53: 浙江省
A54: 第31号案例_“人工智能+基础教育”典型应用场景案例申报书.docx | B54: 46056.466 | C54: 31 | D54: AI在试卷数据分析中的应用 | E54: 吉林市 | F54: 高中 | G54: 目前已覆盖学校1个年级12个班，处于规模化应用初期 | H54: 通过AI实现低门槛、高精度的试卷数据自动化解析，显著提升教师工作效率和学生学习效果。 | I54: 数据导入 → 智能分析 → 报告生成 → 教学调整 | J54: ["数据导入模块", "智能分析模块", "报告生成模块", "错因分类模型", "知识点匹配"] | K54: 豆包大模型 | L54: 未点名企业 | M54: FALSE | N54: 软件平台 | O54: 平台型综合系统 | P54: 文档中提到“依托豆包大模型搭建试卷数据分析体系，实现‘1小时内完成年级级试卷分析+个性化错题归因’” | Q54: 助教 | R54: 教学分析 | S54: 智育 | T54: 学生：提供个性化补弱方向，提升学习效率；教师：节省手工分析时间，增强教学针对性；学校：实现数据驱动精准教学，提升整体教学质量。 | U54: 数据导入 → 智能分析 → 报告生成 → 教学调整 | V54: 数据采集层（支持多格式数据导入） 行为识别层（试卷题型识别、知识点匹配） 画像诊断层（错因分类、个性化补弱建议） | W54: 企业产品以'学习支持工具'为主，已在吉林省基础教育领域实现初步应用，具备较强的可复制性与推广性。 | X54: 实现低门槛、高精度的试卷数据自动化解析，简化操作流程，推动教育信息化落地，建立长效学情追踪机制。 | Y54: 数学 | Z54: 豆包 | AA54: 北京春田知韵科技有限公司 | AB54: 吉林省 | AD54: =VLOOKUP($K54,「工具标准名」映射表!$B:$I,3,0) -> 豆包 | AE54: =VLOOKUP($K54,「工具标准名」映射表!$B:$I,4,0) -> 功能应用层 | AF54: =VLOOKUP($K54,「工具标准名」映射表!$B:$I,5,0) -> 功能应用（平台型综合系统） | AG54: =VLOOKUP($K54,「工具标准名」映射表!$B:$I,6,0) -> 软件工具 | AH54: =VLOOKUP($K54,「工具标准名」映射表!$B:$I,7,0) -> 其他 | AI54: =VLOOKUP($K54,「工具标准名」映射表!$B:$I,8,0) -> 否 | AJ54: 吉林省
A55: 第32号案例_4、AI赋能家校社协同心理健康教育.pdf | B55: 46056.467 | C55: 32 | D55: AI赋能家校社协同心理健康教育 | E55: 嘉兴市秀洲区 | F55: 小学至初中 | G55: 已在学校常态化运行1年，形成可直接复用的设备部署与流程管理方案 | H55: 构建了‘AI+校家社’三维协同模型，通过无感监测与个性化服务提升了心理健康教育的效率与效果。 | I55: AI动态监测 → 情绪识别与风险预警 → 个性化心理服务与家庭协同 | J55: ["多模态情绪识别", "数据加密与隐私保护", "动态数据分析", "人工智能算法", "心理健康风险评估"] | K55: 朵拉润心小屋 | L55: 未点名企业 | M55: FALSE | N55: 硬件 + AI系统 | O55: 平台型综合系统 | P55: 文档中提到‘在心理教室、图书馆等安静区域设置“朵拉润心小屋”终端’ | Q55: 助育 | R55: 智能心理支持 | S55: 德育 | T55: 学生：提升心理健康识别率与情绪调节能力；教师：提高心理健康服务效率；学校：形成可复制的心理健康教育模式。 | U55: 情绪识别 → 实时风险预警 → 个性化干预 → 家校协同 | V55: 数据采集层（多模态情绪识别技术、无感监测） 状态感知层（实时情绪状态监测、风险识别） 智能策略层（个性化干预方案推送、家校协同机制） | W55: 企业产品以“心理健康支持工具”为主，学校通过校家社协同实现心理健康教育，整体处于规模化应用阶段。 | X55: 构建“AI+校家社”三维协同模型，实现动态监测与精准干预，提升家校沟通效率，推动心理健康服务从被动干预向主动预防转型。 | Y55: 心理健康教育 | Z55: 朵拉润心小屋 | AA55: 0 | AB55: 浙江省 | AD55: =VLOOKUP($K55,「工具标准名」映射表!$B:$I,3,0) -> 朵拉润心小屋 | AE55: =VLOOKUP($K55,「工具标准名」映射表!$B:$I,4,0) -> 功能应用层 | AF55: =VLOOKUP($K55,「工具标准名」映射表!$B:$I,5,0) -> 功能应用（平台型综合系统） | AG55: =VLOOKUP($K55,「工具标准名」映射表!$B:$I,6,0) -> 软件工具 | AH55: =VLOOKUP($K55,「工具标准名」映射表!$B:$I,7,0) -> 其他 | AI55: =VLOOKUP($K55,「工具标准名」映射表!$B:$I,8,0) -> 否 | AJ55: 浙江省
A56: 第32号案例_4、AI赋能家校社协同心理健康教育.pdf | B56: 46056.467 | C56: 32 | D56: AI赋能家校社协同心理健康教育 | E56: 嘉兴市秀洲区 | F56: 小学至初中 | G56: 已在学校常态化运行1年，形成可直接复用的设备部署与流程管理方案 | H56: 构建了‘AI+校家社’三维协同模型，通过无感监测与个性化服务提升了心理健康教育的效率与效果。 | I56: AI动态监测 → 情绪识别与风险预警 → 个性化心理服务与家庭协同 | J56: ["多模态情绪识别", "数据加密与隐私保护", "动态数据分析", "人工智能算法", "心理健康风险评估"] | K56: 明智家长小程序 | L56: 未点名企业 | M56: FALSE | N56: 软件平台 | O56: Web 教学平台（SaaS） | P56: 文档中提到‘“明智家长”小程序分学段设计线上workshops’ | Q56: 助育 | R56: 智能心理支持 | S56: 德育 | T56: 学生：提升心理健康识别率与情绪调节能力；教师：提高心理健康服务效率；学校：形成可复制的心理健康教育模式。 | U56: 情绪识别 → 实时风险预警 → 个性化干预 → 家校协同 | V56: 数据采集层（多模态情绪识别技术、无感监测） 状态感知层（实时情绪状态监测、风险识别） 智能策略层（个性化干预方案推送、家校协同机制） | W56: 企业产品以“心理健康支持工具”为主，学校通过校家社协同实现心理健康教育，整体处于规模化应用阶段。 | X56: 构建“AI+校家社”三维协同模型，实现动态监测与精准干预，提升家校沟通效率，推动心理健康服务从被动干预向主动预防转型。 | Y56: 心理健康教育 | Z56: 明智家长小程序 | AA56: 0 | AB56: 浙江省 | AD56: =VLOOKUP($K56,「工具标准名」映射表!$B:$I,3,0) -> 明智家长小程序 | AE56: =VLOOKUP($K56,「工具标准名」映射表!$B:$I,4,0) -> 功能应用层 | AF56: =VLOOKUP($K56,「工具标准名」映射表!$B:$I,5,0) -> 功能应用层（移动端 App） | AG56: =VLOOKUP($K56,「工具标准名」映射表!$B:$I,6,0) -> 软件工具 | AH56: =VLOOKUP($K56,「工具标准名」映射表!$B:$I,7,0) -> AI智能体 | AI56: =VLOOKUP($K56,「工具标准名」映射表!$B:$I,8,0) -> 否 | AJ56: 浙江省
A57: 第33号案例_上海市尚文中学 龚笛《AI赋能初中数学学生成长数据融合建模与精准预警干预系统研究》.docx | B57: 46056.467 | C57: 33 | D57: AI赋能初中数学学生成长数据融合建模与精准预警干预系统研究 | E57: 上海市 | F57: 初中 | G57: 已在尚文中学初二年级完整运行一学期，形成可复制、可评估、可改进的“数据驱动-三级预警-分层干预”范式。 | H57: 通过构建全链条智能化闭环，实现精准识别学生认知偏差，动态生成分层干预策略，提升个性化教学效率与质量。 | I57: 数据采集 → 模型构建 → 问题预警 → 干预改进 | J57: ["广义Cook距离", "随机森林算法", "知识图谱技术", "分位数回归", "数据融合"] | K57: 墨水屏数字化学习终端 | L57: 未点名企业 | M57: FALSE | N57: 硬件 | O57: 教学辅助工具（工具型） | P57: 文档中提到“依托‘墨水屏’数字化学习终端与‘人人通’平台，实现作业数据采集、存储与分析的全流程自动化。” | Q57: 助学 | R57: 智能辅导系统 | S57: 智育 | T57: 学生：提升作业质量与逻辑推理能力；教师：减轻批改负担，提供精准教学工具；学校：形成可复制的AI教学模式。 | U57: 数据采集 → 模型构建 → 问题预警 → 分层干预 | V57: 数据采集层（作业数据采集、存储与分析自动化） 模型构建层（广义Cook距离、随机森林算法） 预警机制层（三级预警机制、动态干预策略） | W57: 系统已在尚文中学初二年级运行，覆盖27名学生，形成可复制的教学模式，整体处于推广阶段。 | X57: 构建全链条智能化闭环，精准识别学生认知偏差，创新三级预警与分层干预机制，提升个性化教学效率与质量。 | Y57: 数学 | Z57: 墨水屏数字化学习终端 | AA57: 0 | AB57: 上海市 | AD57: =VLOOKUP($K57,「工具标准名」映射表!$B:$I,3,0) -> 墨水屏数字化学习终端 | AE57: =VLOOKUP($K57,「工具标准名」映射表!$B:$I,4,0) -> 功能应用层 | AF57: =VLOOKUP($K57,「工具标准名」映射表!$B:$I,5,0) -> 功能应用（Web 教学平台（SaaS）） | AG57: =VLOOKUP($K57,「工具标准名」映射表!$B:$I,6,0) -> 硬件设备 | AH57: =VLOOKUP($K57,「工具标准名」映射表!$B:$I,7,0) -> AI智能体 | AI57: =VLOOKUP($K57,「工具标准名」映射表!$B:$I,8,0) -> 否 | AJ57: 上海市
A58: 第33号案例_上海市尚文中学 龚笛《AI赋能初中数学学生成长数据融合建模与精准预警干预系统研究》.docx | B58: 46056.467 | C58: 33 | D58: AI赋能初中数学学生成长数据融合建模与精准预警干预系统研究 | E58: 上海市 | F58: 初中 | G58: 已在尚文中学初二年级完整运行一学期，形成可复制、可评估、可改进的“数据驱动-三级预警-分层干预”范式。 | H58: 通过构建全链条智能化闭环，实现精准识别学生认知偏差，动态生成分层干预策略，提升个性化教学效率与质量。 | I58: 数据采集 → 模型构建 → 问题预警 → 干预改进 | J58: ["广义Cook距离", "随机森林算法", "知识图谱技术", "分位数回归", "数据融合"] | K58: 人人通平台 | L58: 未点名企业 | M58: FALSE | N58: 软件平台 | O58: 平台型综合系统 | P58: 文档中提到“依托‘墨水屏’数字化学习终端与‘人人通’平台，实现作业数据采集、存储与分析的全流程自动化。” | Q58: 助学 | R58: 智能辅导系统 | S58: 智育 | T58: 学生：提升作业质量与逻辑推理能力；教师：减轻批改负担，提供精准教学工具；学校：形成可复制的AI教学模式。 | U58: 数据采集 → 模型构建 → 问题预警 → 分层干预 | V58: 数据采集层（作业数据采集、存储与分析自动化） 模型构建层（广义Cook距离、随机森林算法） 预警机制层（三级预警机制、动态干预策略） | W58: 系统已在尚文中学初二年级运行，覆盖27名学生，形成可复制的教学模式，整体处于推广阶段。 | X58: 构建全链条智能化闭环，精准识别学生认知偏差，创新三级预警与分层干预机制，提升个性化教学效率与质量。 | Y58: 数学 | Z58: 人人通平台 | AA58: 0 | AB58: 上海市 | AD58: =VLOOKUP($K58,「工具标准名」映射表!$B:$I,3,0) -> 人人通资源分享平台 | AE58: =VLOOKUP($K58,「工具标准名」映射表!$B:$I,4,0) -> 功能应用层 | AF58: =VLOOKUP($K58,「工具标准名」映射表!$B:$I,5,0) -> 功能应用（平台型综合系统） | AG58: =VLOOKUP($K58,「工具标准名」映射表!$B:$I,6,0) -> 软件工具 | AH58: =VLOOKUP($K58,「工具标准名」映射表!$B:$I,7,0) -> AI智能体 | AI58: =VLOOKUP($K58,「工具标准名」映射表!$B:$I,8,0) -> 否 | AJ58: 上海市
A59: 第34号案例_1.“人工智能+基础教育”典型应用场景案例申报书.docx | B59: 46056.467 | C59: 34 | D59: 基于AI的小学生创新素养评价系统实践 | E59: 四川省 | F59: 小学 | G59: 已在省内14个市州112所学校推广，惠及11.04万学生，处于规模化应用阶段 | H59: 通过构建创新素养评价体系与AI杏运平台，实现多维度数据采集与分析，推动评价与教学深度融合，提升学生创新能力。 | I59: 数据采集 → 实时分析与反馈 → 个性化评价生成 → 教学优化与改进 | J59: ["数据采集技术", "云端数据管理", "自动化分析", "多维度素养画像生成", "数据驱动决策"] | K59: AI杏运 | L59: 未点名企业 | M59: TRUE | N59: 软件平台 | O59: 平台型综合系统 | P59: 文档中提到“自主研发‘AI杏运’教育评价信息化平台，以人工智能技术为支撑，实现学生创新行为的即时记录” | Q59: 助评 | R59: 综合素质评价 | S59: 智育 | T59: 学生：激发创新精神与探索欲望，提供个性化成长反馈；教师：提升教学针对性与专业能力；学校：推动教育公平与个性化发展，形成可复制的评价改革范式。 | U59: 数据采集 → 实时跟踪与分析 → 个性化反馈与指导 → 教学改进 | V59: 数据采集层（多渠道数据采集：课堂平板、教师移动端等） 行为识别层（实时跟踪学生课堂互动与创新实践） 画像诊断层（生成个性化成长轨迹与素养画像） | W59: 企业产品以“评价支持工具”为主，已在省内112所学校推广，整体处于规模化应用阶段。 | X59: 构建了多维度创新素养评价体系，突破传统静态评价局限，实现评价与教学深度融合，推动教育从分数导向转向全面育人导向。 | Y59: 未提及 | Z59: AI杏运 | AA59: 0 | AB59: 四川省 | AD59: =VLOOKUP($K59,「工具标准名」映射表!$B:$I,3,0) -> AI杏运 | AE59: =VLOOKUP($K59,「工具标准名」映射表!$B:$I,4,0) -> 功能应用层 | AF59: =VLOOKUP($K59,「工具标准名」映射表!$B:$I,5,0) -> 功能应用（校级 / 区域级系统） | AG59: =VLOOKUP($K59,「工具标准名」映射表!$B:$I,6,0) -> 软件工具 | AH59: =VLOOKUP($K59,「工具标准名」映射表!$B:$I,7,0) -> AI智能体 | AI59: =VLOOKUP($K59,「工具标准名」映射表!$B:$I,8,0) -> 否 | AJ59: 四川省
A60: 第35号案例_AI赋能“以体育人”探索智慧体育新样态.docx | B60: 46056.467 | C60: 35 | D60: AI赋能“以体育人”探索智慧体育新样态 | E60: 包头市青山区 | F60: 小学 | G60: 学校已成为自治区教研室数字化体育项目实验校，整体处于推广与应用阶段 | H60: 通过AI技术实现精准的运动数据分析与个性化干预，提升学生的运动参与度与体质健康。 | I60: 无感人脸识别 → 动作解析与反馈生成 → 数据分析与个性化干预 → 体育教学优化 | J60: ["人脸识别", "动作识别", "数据分析", "AI算法", "云计算"] | K60: AI体测吧 | L60: 未点名企业 | M60: FALSE | N60: 硬件 + AI系统 | O60: 平台型综合系统 | P60: 文档中提到“借助AI智慧体测吧，完成学生身体形态类、身体机能类、运动项目类所需要测试项目的数据。” | Q60: 助学 | R60: 智能辅导系统 | S60: 体育 | T60: 学生：提升运动技能与体质健康；教师：实现精准体育教学与数据分析；学校：构建智慧体育教育新生态。 | U60: 数据采集 → 动作解析与反馈生成 → 个性化运动干预 → 体育教学改进 | V60: 数据采集层（无感人脸识别、运动数据实时采集） 行为识别层（动作解析与标准动作比对） 画像诊断层（个性化运动能力分析与反馈） 个性化学习层（针对性运动建议与干预） | W60: 企业产品以“智慧体育工具”为主，学校通过数字化手段实现体育教学的精准化与个性化，整体处于探索与应用阶段。 | X60: 通过AI技术实现体育教学的精准化与个性化，构建全新的运动场景与数据分析体系，提升学生运动兴趣与参与度。 | Y60: 体育 | Z60: AI体测吧 | AA60: 0 | AB60: 内蒙古自治区 | AD60: =VLOOKUP($K60,「工具标准名」映射表!$B:$I,3,0) -> AI体测吧 | AE60: =VLOOKUP($K60,「工具标准名」映射表!$B:$I,4,0) -> 功能应用层 | AF60: =VLOOKUP($K60,「工具标准名」映射表!$B:$I,5,0) -> 功能应用（校级 / 区域级系统） | AG60: =VLOOKUP($K60,「工具标准名」映射表!$B:$I,6,0) -> 软件工具 | AH60: =VLOOKUP($K60,「工具标准名」映射表!$B:$I,7,0) -> AI智能体 | AI60: =VLOOKUP($K60,「工具标准名」映射表!$B:$I,8,0) -> 否 | AJ60: 内蒙古自治区
A61: 第35号案例_AI赋能“以体育人”探索智慧体育新样态.docx | B61: 46056.467 | C61: 35 | D61: AI赋能“以体育人”探索智慧体育新样态 | E61: 包头市青山区 | F61: 小学 | G61: 学校已成为自治区教研室数字化体育项目实验校，整体处于推广与应用阶段 | H61: 通过AI技术实现精准的运动数据分析与个性化干预，提升学生的运动参与度与体质健康。 | I61: 无感人脸识别 → 动作解析与反馈生成 → 数据分析与个性化干预 → 体育教学优化 | J61: ["人脸识别", "动作识别", "数据分析", "AI算法", "云计算"] | K61: 智能大数据仓 | L61: 未点名企业 | M61: FALSE | N61: 软件平台 | O61: 平台型综合系统 | P61: 文档中描述“智慧大数据云平台整合校园运动数据，通过云服务器实现可视化分析与科学决策。” | Q61: 助学 | R61: 智能辅导系统 | S61: 体育 | T61: 学生：提升运动技能与体质健康；教师：实现精准体育教学与数据分析；学校：构建智慧体育教育新生态。 | U61: 数据采集 → 动作解析与反馈生成 → 个性化运动干预 → 体育教学改进 | V61: 数据采集层（无感人脸识别、运动数据实时采集） 行为识别层（动作解析与标准动作比对） 画像诊断层（个性化运动能力分析与反馈） 个性化学习层（针对性运动建议与干预） | W61: 企业产品以“智慧体育工具”为主，学校通过数字化手段实现体育教学的精准化与个性化，整体处于探索与应用阶段。 | X61: 通过AI技术实现体育教学的精准化与个性化，构建全新的运动场景与数据分析体系，提升学生运动兴趣与参与度。 | Y61: 体育 | Z61: 智能大数据仓 | AA61: 0 | AB61: 内蒙古自治区 | AD61: =VLOOKUP($K61,「工具标准名」映射表!$B:$I,3,0) -> 智能大数据仓 | AE61: =VLOOKUP($K61,「工具标准名」映射表!$B:$I,4,0) -> 教育数据层 | AF61: =VLOOKUP($K61,「工具标准名」映射表!$B:$I,5,0) -> 教育数据层（资源数据） | AG61: =VLOOKUP($K61,「工具标准名」映射表!$B:$I,6,0) -> 在线资源 | AH61: =VLOOKUP($K61,「工具标准名」映射表!$B:$I,7,0) -> 大语言模型 | AI61: =VLOOKUP($K61,「工具标准名」映射表!$B:$I,8,0) -> 否 | AJ61: 内蒙古自治区
A62: 第36号案例_36杭州市钱学森学校 “人工智能+基础教育”典型应用场景案例.docx | B62: 46056.467 | C62: 36 | D62: 爱心小叮当系统 | E62: 杭州市 | F62: 小学 | G62: 已覆盖全校4个年级24个班1000余位学生，已辐射全省26个学校，整体处于推广阶段 | H62: 通过自动无感采集与大数据分析，建立学生心理预警模型，促进家校社联动，提升心理健康关注度。 | I62: 数据采集 → 情绪状态识别 → 心理健康动态分析 → 预警与干预 | J62: ["情感计算", "人工智能算法", "数据分析", "情绪识别", "心理健康监测"] | K62: 爱心小叮当 | L62: 未点名企业 | M62: FALSE | N62: 软件平台 | O62: 平台型综合系统 | P62: 文档中提到“爱心小叮当系统在校园的公共空间中布设人工智能装备，无感拍摄学生在自然状态下的面部表情” | Q62: 助育 | R62: 智能心理支持 | S62: 德育 | T62: 学生：增进心理健康，提升情绪愉悦度；教师：提供数据支持，增强心理辅导的针对性；学校：改善心理健康教育效果，形成全员心理健康教育的机制。 | U62: 数据采集 → 情绪识别与分析 → 心理预警模型建立 → 家校社联动 | V62: 数据采集层（无感拍摄、情绪状态识别） 行为识别层（情绪状态监测与分析） 智能策略层（心理预警模型推送） | W62: 企业产品以“心理健康支持工具”为主，学校通过校本化规则实现教学适配，整体处于推广应用阶段。 | X62: 自动无感采集学生表情数据，建立可靠的心理预警模型，促进家校社联动，提升心理健康关注度和干预效果。 | Y62: 心理健康 | Z62: 爱心小叮当 | AA62: 0 | AB62: 浙江省 | AD62: =VLOOKUP($K62,「工具标准名」映射表!$B:$I,3,0) -> 爱心小叮当 | AE62: =VLOOKUP($K62,「工具标准名」映射表!$B:$I,4,0) -> 功能应用层 | AF62: =VLOOKUP($K62,「工具标准名」映射表!$B:$I,5,0) -> 功能应用（教学辅助工具） | AG62: =VLOOKUP($K62,「工具标准名」映射表!$B:$I,6,0) -> 硬件设备 | AH62: =VLOOKUP($K62,「工具标准名」映射表!$B:$I,7,0) -> 其他 | AI62: =VLOOKUP($K62,「工具标准名」映射表!$B:$I,8,0) -> 否 | AJ62: 浙江省
A63: 第37号案例_成都市泡桐树小学境界分校 AI赋能学生评价创新实践——“六度育人图谱”驱动的全场景综合素质发展体系构建 .docx | B63: 46056.467 | C63: 37 | D63: AI赋能学生评价创新实践——“六度育人图谱”驱动的全场景综合素质发展体系构建 | E63: 成都市 | F63: 小学 | G63: 案例已实现全校全覆盖，且成效显著，具备极强的可复制性 | H63: 实现了“技术 - 课堂 - 生活”的深度融合创新，推动教育教学模式从“单向评价”向“协同共育”转变。 | I63: 理念转化 → 技术落地 → 场景应用 → 优化迭代 | J63: ["数据采集", "语音识别", "图像识别", "大数据分析", "机器学习算法"] | K63: AI成长学生发展平台 | L63: 未点名企业 | M63: TRUE | N63: 软件平台 | O63: 平台型综合系统 | P63: 文档中提到“自主研发‘AI成长学生发展平台’，构建‘1个核心平台+2大应用场景+3维联动机制’生态体系” | Q63: 助评 | R63: 综合素质评价 | S63: 德育 | T63: 学生：全面发展，关注道德修养、艺术能力、劳动习惯等素养；教师：提升评价效率，精准定位学生薄弱点；学校：形成可复制的评价体系，提升家校共育水平。 | U63: 理念转化 → 技术落地 → 场景应用 → 优化迭代 | V63: 数据采集层（全场景数据采集、无感采集）；行为识别层（实时捕捉学生状态、生成评价建议）；画像诊断层（生成学生成长树个人画像、班级素养雷达图） | W63: 案例已实现全校全覆盖，具备标准化流程，支持个性化定制，整体处于推广阶段。 | X63: 实现了技术与教育教学模式的深度融合，打破传统评价局限，建立了“评价—诊断—改进—提升”的良性循环路径，推动基础教育从“经验驱动”向“数据驱动”转型。 | Y63: 未提及 | Z63: AI成长学生发展平台 | AA63: 0 | AB63: 四川省 | AD63: =VLOOKUP($K63,「工具标准名」映射表!$B:$I,3,0) -> AI成长学生发展平台 | AE63: =VLOOKUP($K63,「工具标准名」映射表!$B:$I,4,0) -> 功能应用层 | AF63: =VLOOKUP($K63,「工具标准名」映射表!$B:$I,5,0) -> 功能应用（校级 / 区域级系统） | AG63: =VLOOKUP($K63,「工具标准名」映射表!$B:$I,6,0) -> 软件工具 | AH63: =VLOOKUP($K63,「工具标准名」映射表!$B:$I,7,0) -> AI智能体 | AI63: =VLOOKUP($K63,「工具标准名」映射表!$B:$I,8,0) -> 否 | AJ63: 四川省
A64: 第37号案例_成都市泡桐树小学境界分校 AI赋能学生评价创新实践——“六度育人图谱”驱动的全场景综合素质发展体系构建 .docx | B64: 46056.467 | C64: 37 | D64: AI赋能学生评价创新实践——“六度育人图谱”驱动的全场景综合素质发展体系构建 | E64: 成都市 | F64: 小学 | G64: 案例已实现全校全覆盖，且成效显著，具备极强的可复制性 | H64: 实现了“技术 - 课堂 - 生活”的深度融合创新，推动教育教学模式从“单向评价”向“协同共育”转变。 | I64: 理念转化 → 技术落地 → 场景应用 → 优化迭代 | J64: ["数据采集", "语音识别", "图像识别", "大数据分析", "机器学习算法"] | K64: 泡小境界评价培训小程序 | L64: 未点名企业 | M64: TRUE | N64: 软件平台 | O64: 移动端 App | P64: 文档中提到“依托‘泡小境界评价培训’小程序，针对教师群体开展分层培训” | Q64: 助评 | R64: 综合素质评价 | S64: 德育 | T64: 学生：全面发展，关注道德修养、艺术能力、劳动习惯等素养；教师：提升评价效率，精准定位学生薄弱点；学校：形成可复制的评价体系，提升家校共育水平。 | U64: 理念转化 → 技术落地 → 场景应用 → 优化迭代 | V64: 数据采集层（全场景数据采集、无感采集）；行为识别层（实时捕捉学生状态、生成评价建议）；画像诊断层（生成学生成长树个人画像、班级素养雷达图） | W64: 案例已实现全校全覆盖，具备标准化流程，支持个性化定制，整体处于推广阶段。 | X64: 实现了技术与教育教学模式的深度融合，打破传统评价局限，建立了“评价—诊断—改进—提升”的良性循环路径，推动基础教育从“经验驱动”向“数据驱动”转型。 | Y64: 未提及 | Z64: 泡小境界评价培训小程序 | AA64: 0 | AB64: 四川省 | AD64: =VLOOKUP($K64,「工具标准名」映射表!$B:$I,3,0) -> 泡小境界评价培训小程序 | AE64: =VLOOKUP($K64,「工具标准名」映射表!$B:$I,4,0) -> 功能应用层 | AF64: =VLOOKUP($K64,「工具标准名」映射表!$B:$I,5,0) -> 功能应用层（移动端 App） | AG64: =VLOOKUP($K64,「工具标准名」映射表!$B:$I,6,0) -> 软件工具 | AH64: =VLOOKUP($K64,「工具标准名」映射表!$B:$I,7,0) -> AI智能体 | AI64: =VLOOKUP($K64,「工具标准名」映射表!$B:$I,8,0) -> 否 | AJ64: 四川省
A65: 第38号案例_1.基于SEED平台多维评价数据构建小学生个性化成长课程的实践研究-案例申报书.docx | B65: 46056.467 | C65: 38 | D65: 基于SEED平台多维评价数据构建小学生个性化成长课程的实践研究 | E65: 成都市 | F65: 小学 | G65: 该实践模式已在本校全面实施，并成功入选2025全球智慧教育优秀案例，具有示范引领作用。 | H65: 实现了从宏观评价到个体分析的精准赋能，构建了数据驱动的个性化教育模式，推动教育评价与课程教学的深度融合。 | I65: 数据初始分析与画像建立 → 课程初步设计与资源规划 → 课程实施与教学实践 → 三位一体教学模式构建与优化 | J65: ["数据挖掘技术", "统计分析方法", "AI情绪识别", "知识图谱", "生成式AI"] | K65: SEED平台 | L65: 未点名企业 | M65: FALSE | N65: 软件平台 | O65: 平台型综合系统 | P65: 文档中提到“基于SEED平台的多维评价数据，构建小学生个性化成长课程” | Q65: 助学 | R65: 智能辅导系统 | S65: 智育 | T65: 学生：提升综合素质与个性化发展；教师：提供数据驱动的教学依据；学校：实现教育个性化与家校社协同育人。 | U65: 数据初始分析 → 画像建立 → 课程设计与资源规划 → 课程实施与教学实践 → 教学反馈与优化 | V65: 数据采集层（多维评价数据采集与分析） 画像诊断层（个性化发展需求画像生成） 个性化学习层（动态课程追踪与反馈） | W65: 企业产品以“学习支持工具”为主，学校多通过校本化规则实现教学适配，整体处于规模化应用初期。 | X65: 实现从宏观评价到个体分析的精准赋能，构建数据驱动的个性化教育模式，推动教育评价与课程教学的深度融合。 | Y65: 综合素质 | Z65: SEED平台 | AA65: 0 | AB65: 四川省 | AD65: =VLOOKUP($K65,「工具标准名」映射表!$B:$I,3,0) -> #N/A | AE65: =VLOOKUP($K65,「工具标准名」映射表!$B:$I,4,0) -> #N/A | AF65: =VLOOKUP($K65,「工具标准名」映射表!$B:$I,5,0) -> #N/A | AG65: =VLOOKUP($K65,「工具标准名」映射表!$B:$I,6,0) -> #N/A | AH65: =VLOOKUP($K65,「工具标准名」映射表!$B:$I,7,0) -> #N/A | AI65: =VLOOKUP($K65,「工具标准名」映射表!$B:$I,8,0) -> #N/A | AJ65: 四川省
A66: 第39号案例_（王宏伟）.“人工智能+基础教育”典型应用场景案例申报书.docx | B66: 46056.467 | C66: 39 | D66: 素养为本·数据为翼：嘉实新儿童综合评价实践探索 | E66: 嘉兴市 | F66: 小学 | G66: 已在嘉兴市实验小学实施，形成一定规模的应用，具备推广价值。 | H66: 通过自主研发的学生综合评价数字平台，实现多维度数据采集与分析，全面呈现学生个性化发展轨迹，推动综合素质评价改革。 | I66: 数据采集 → 数据分析建模 → 结果反馈与呈现 | J66: ["数据采集", "数据分析建模", "个性化画像生成", "过程性评价", "人工智能技术"] | K66: 学生综合评价数字平台 | L66: 未点名企业 | M66: TRUE | N66: 软件平台 | O66: 平台型综合系统 | P66: 文档中提到“学校自主研发‘学生综合评价数字平台’，多渠道收集学生学习全过程中的数据” | Q66: 助评 | R66: 综合素质评价 | S66: 智育 | T66: 学生：形成全面的个性化发展画像，促进五育并举；教师：提供便捷的数据录入与分析工具，支持教学改进；学校：推动综合评价改革，提升教育质量。 | U66: 数据采集 → 数据分析建模 → 结果反馈 | V66: 数据采集层（多维度、无感便捷的数据采集） 数据分析层（依标分项等级化、科学智能化分析） 结果反馈层（直观、结构化的结果呈现） | W66: 学校综合评价改革处于推进阶段，已形成68万多条学生个性成长数据，支持教师开展综合评价。 | X66: 通过数字平台实现多主体、多渠道的评价数据分析与反馈，促进学、教、评、改一体化，推动综合素养评价的创新与实践。 | Y66: 未提及 | Z66: 学生综合评价数字平台 | AA66: 0 | AB66: 浙江省 | AD66: =VLOOKUP($K66,「工具标准名」映射表!$B:$I,3,0) -> 学生综合评价数字平台 | AE66: =VLOOKUP($K66,「工具标准名」映射表!$B:$I,4,0) -> 教育数据层 | AF66: =VLOOKUP($K66,「工具标准名」映射表!$B:$I,5,0) -> 教育数据层（资源数据） | AG66: =VLOOKUP($K66,「工具标准名」映射表!$B:$I,6,0) -> 在线资源 | AH66: =VLOOKUP($K66,「工具标准名」映射表!$B:$I,7,0) -> 大语言模型 | AI66: =VLOOKUP($K66,「工具标准名」映射表!$B:$I,8,0) -> 是 | AJ66: 浙江省
... A77: 第46号案例_人工智能+教育典型案例胡甘霖(1).docx | B77: 46056.468 | C77: 46 | D77: 基于“AI+数据驱动”的智慧体育教学模式创新与实践 | E77: 重庆市渝中区 | F77: 小学 | G77: 目前该模式已在教育集团内部分校区常态化应用，覆盖全体学生，处于推广阶段 | H77: 创建了“数据驱动的精准体育教学范式”，实现了从“经验教学”到“精准干预”的转变，形成了“数据驱动决策”的教学新范式。 | I77: 数据采集→分析建模→智能反馈→精准干预 | J77: ["数据采集", "AI视觉识别", "大数据分析", "个性化运动处方生成", "运动数据监测"] | K77: 学生国家体测数据仓 | L77: 未点名企业 | M77: TRUE | N77: 数据平台 | O77: 校级 / 区域级系统 | P77: 文档中描述“自主研发‘学生国家体测数据仓’与‘体育锻炼数据大脑’” | Q77: 助学 | R77: 智能辅导系统 | S77: 体育 | T77: 学生：提升体质健康水平与运动兴趣；教师：实现精准教学与实时反馈；学校：形成可复制的智慧体育教学模式 | U77: 数据采集 → 分析建模 → 智能反馈 → 精准干预 | V77: 数据采集层（运动手环监测心率、运动密度；AI视觉识别技术采集运动数据） 应用交互层（教师端平板App，实时心率热力图与系统预警） 数据分析层（学生国家体测数据仓与体育锻炼数据大脑，生成个性化运动处方） | W77: 该模式已在教育集团内部分校区常态化应用，覆盖全体学生，整体处于推广阶段 | X77: 创建了数据驱动的精准体育教学范式，实现从经验判断到证据决策的转变；通过游戏化、竞赛化的课外锻炼激励模式，提升学生内在运动兴趣；实现无感化、伴随式的数据采集，解决教育场景中数据采集难的瓶颈 | Y77: 体育 | Z77: 学生国家体测数据仓 | AA77: 0 | AB77: 重庆市 | AD77: =VLOOKUP($K77,「工具标准名」映射表!$B:$I,3,0) -> 学生国家体测数据仓 | AE77: =VLOOKUP($K77,「工具标准名」映射表!$B:$I,4,0) -> 教育数据层 | AF77: =VLOOKUP($K77,「工具标准名」映射表!$B:$I,5,0) -> 教育数据层（资源数据） | AG77: =VLOOKUP($K77,「工具标准名」映射表!$B:$I,6,0) -> 在线资源 | AH77: =VLOOKUP($K77,「工具标准名」映射表!$B:$I,7,0) -> 大语言模型 | AI77: =VLOOKUP($K77,「工具标准名」映射表!$B:$I,8,0) -> 是 | AJ77: 重庆市
A78: 第47号案例_“人工智能+基础教育”典型应用场景案例申报书.长春市南关区树勋小学.docx | B78: 46056.468 | C78: 47 | D78: 基于AI赋能的小学“作业超市” 实践应用 | E78: 长春市南关区 | F78: 小学 | G78: 当前已在树勋小学全年级应用，并辐射至结对联盟学校，累计服务学生3200余人，具有推广价值。 | H78: 通过AI赋能实现精准分层作业设计与批改，提升教师效率与学生学习效果，真正实现个性化学习。 | I78: 智能分层作业生成 → 智能批改与反馈 → 学情诊断与优化 → 应用优化 | J78: ["深度学习", "OCR技术", "自然语言处理", "数据分析", "个性化学习系统"] | K78: deepseek | L78: 未点名企业 | M78: FALSE | N78: 软件平台 | O78: Web 教学平台（SaaS） | P78: 文档中提到“用deepseek可以实现语数外三科作业的分层设计。” | Q78: 助学 | R78: 智能辅导系统 | S78: 智育 | T78: 学生：个性化学习与即时反馈提升；教师：减负增效与精准教学；学校：形成可复制的“AI+作业设计”模式 | U78: 智能作业生成 → 智能批改与反馈 → 学情诊断与优化 → 应用优化 | V78: 数据采集层（作业数据收集与分析） 行为识别层（学生作业表现分析） 画像诊断层（班级学情报告生成） 个性化学习层（智能作业推荐与反馈） | W78: 企业产品以“学习支持工具”为主，学校通过校本化规则实现教学适配，整体处于规模化应用初期 | X78: 通过AI实现作业的智能分层与批改，打破传统统一作业模式，提升教师批改效率，促进个性化学习与家校协同 | Y78: 语文 | Z78: DeepSeek 大模型 | AA78: 杭州深度求索人工智能基础技术研究有限公司 | AB78: 吉林省 | AD78: =VLOOKUP($K78,「工具标准名」映射表!$B:$I,3,0) -> DeepSeek 大模型 | AE78: =VLOOKUP($K78,「工具标准名」映射表!$B:$I,4,0) -> 功能应用层 | AF78: =VLOOKUP($K78,「工具标准名」映射表!$B:$I,5,0) -> 功能应用（教学辅助工具） | AG78: =VLOOKUP($K78,「工具标准名」映射表!$B:$I,6,0) -> 软件工具 | AH78: =VLOOKUP($K78,「工具标准名」映射表!$B:$I,7,0) -> AI智能体 | AI78: =VLOOKUP($K78,「工具标准名」映射表!$B:$I,8,0) -> 否 | AJ78: 吉林省
A79: 第47号案例_“人工智能+基础教育”典型应用场景案例申报书.长春市南关区树勋小学.docx | B79: 46056.468 | C79: 47 | D79: 基于AI赋能的小学“作业超市” 实践应用 | E79: 长春市南关区 | F79: 小学 | G79: 当前已在树勋小学全年级应用，并辐射至结对联盟学校，累计服务学生3200余人，具有推广价值。 | H79: 通过AI赋能实现精准分层作业设计与批改，提升教师效率与学生学习效果，真正实现个性化学习。 | I79: 智能分层作业生成 → 智能批改与反馈 → 学情诊断与优化 → 应用优化 | J79: ["深度学习", "OCR技术", "自然语言处理", "数据分析", "个性化学习系统"] | K79: 豆包爱学 | L79: 未点名企业 | M79: FALSE | N79: 软件平台 | O79: Web 教学平台（SaaS） | P79: 文档中描述“豆包爱学具备作业生成、思维导图生成、作业批改、口语测评等功能。” | Q79: 助学 | R79: 智能辅导系统 | S79: 智育 | T79: 学生：个性化学习与即时反馈提升；教师：减负增效与精准教学；学校：形成可复制的“AI+作业设计”模式 | U79: 智能作业生成 → 智能批改与反馈 → 学情诊断与优化 → 应用优化 | V79: 数据采集层（作业数据收集与分析） 行为识别层（学生作业表现分析） 画像诊断层（班级学情报告生成） 个性化学习层（智能作业推荐与反馈） | W79: 企业产品以“学习支持工具”为主，学校通过校本化规则实现教学适配，整体处于规模化应用初期 | X79: 通过AI实现作业的智能分层与批改，打破传统统一作业模式，提升教师批改效率，促进个性化学习与家校协同 | Y79: 语文 | Z79: 豆包 | AA79: 北京春田知韵科技有限公司 | AB79: 吉林省 | AD79: =VLOOKUP($K79,「工具标准名」映射表!$B:$I,3,0) -> 豆包 | AE79: =VLOOKUP($K79,「工具标准名」映射表!$B:$I,4,0) -> 功能应用层 | AF79: =VLOOKUP($K79,「工具标准名」映射表!$B:$I,5,0) -> 功能应用（教学辅助工具） | AG79: =VLOOKUP($K79,「工具标准名」映射表!$B:$I,6,0) -> 软件工具 | AH79: =VLOOKUP($K79,「工具标准名」映射表!$B:$I,7,0) -> 其他 | AI79: =VLOOKUP($K79,「工具标准名」映射表!$B:$I,8,0) -> 否 | AJ79: 吉林省
A80: 第47号案例_“人工智能+基础教育”典型应用场景案例申报书.长春市南关区树勋小学.docx | B80: 46056.468 | C80: 47 | D80: 基于AI赋能的小学“作业超市” 实践应用 | E80: 长春市南关区 | F80: 小学 | G80: 当前已在树勋小学全年级应用，并辐射至结对联盟学校，累计服务学生3200余人，具有推广价值。 | H80: 通过AI赋能实现精准分层作业设计与批改，提升教师效率与学生学习效果，真正实现个性化学习。 | I80: 智能分层作业生成 → 智能批改与反馈 → 学情诊断与优化 → 应用优化 | J80: ["深度学习", "OCR技术", "自然语言处理", "数据分析", "个性化学习系统"] | K80: 作业帮 | L80: 未点名企业 | M80: FALSE | N80: 软件平台 | O80: Web 教学平台（SaaS） | P80: 文档中提到“作业帮都可以通过OCR技术识别手写字体，自动错误，并配合题目讲解。” | Q80: 助学 | R80: 智能辅导系统 | S80: 智育 | T80: 学生：个性化学习与即时反馈提升；教师：减负增效与精准教学；学校：形成可复制的“AI+作业设计”模式 | U80: 智能作业生成 → 智能批改与反馈 → 学情诊断与优化 → 应用优化 | V80: 数据采集层（作业数据收集与分析） 行为识别层（学生作业表现分析） 画像诊断层（班级学情报告生成） 个性化学习层（智能作业推荐与反馈） | W80: 企业产品以“学习支持工具”为主，学校通过校本化规则实现教学适配，整体处于规模化应用初期 | X80: 通过AI实现作业的智能分层与批改，打破传统统一作业模式，提升教师批改效率，促进个性化学习与家校协同 | Y80: 语文 | Z80: 作业帮 | AA80: 0 | AB80: 吉林省 | AD80: =VLOOKUP($K80,「工具标准名」映射表!$B:$I,3,0) -> 作业帮 | AE80: =VLOOKUP($K80,「工具标准名」映射表!$B:$I,4,0) -> 功能应用层 | AF80: =VLOOKUP($K80,「工具标准名」映射表!$B:$I,5,0) -> 功能应用层（移动端 App） | AG80: =VLOOKUP($K80,「工具标准名」映射表!$B:$I,6,0) -> 软件工具 | AH80: =VLOOKUP($K80,「工具标准名」映射表!$B:$I,7,0) -> AI智能体 | AI80: =VLOOKUP($K80,「工具标准名」映射表!$B:$I,8,0) -> 否 | AJ80: 吉林省
A81: 第47号案例_“人工智能+基础教育”典型应用场景案例申报书.长春市南关区树勋小学.docx | B81: 46056.468 | C81: 47 | D81: 基于AI赋能的小学“作业超市” 实践应用 | E81: 长春市南关区 | F81: 小学 | G81: 当前已在树勋小学全年级应用，并辐射至结对联盟学校，累计服务学生3200余人，具有推广价值。 | H81: 通过AI赋能实现精准分层作业设计与批改，提升教师效率与学生学习效果，真正实现个性化学习。 | I81: 智能分层作业生成 → 智能批改与反馈 → 学情诊断与优化 → 应用优化 | J81: ["深度学习", "OCR技术", "自然语言处理", "数据分析", "个性化学习系统"] | K81: 小猿搜题 | L81: 未点名企业 | M81: FALSE | N81: 软件平台 | O81: Web 教学平台（SaaS） | P81: 文档中提到“小猿搜题都可以找出错题并讲解，推荐整理错题集。” | Q81: 助学 | R81: 智能辅导系统 | S81: 智育 | T81: 学生：个性化学习与即时反馈提升；教师：减负增效与精准教学；学校：形成可复制的“AI+作业设计”模式 | U81: 智能作业生成 → 智能批改与反馈 → 学情诊断与优化 → 应用优化 | V81: 数据采集层（作业数据收集与分析） 行为识别层（学生作业表现分析） 画像诊断层（班级学情报告生成） 个性化学习层（智能作业推荐与反馈） | W81: 企业产品以“学习支持工具”为主，学校通过校本化规则实现教学适配，整体处于规模化应用初期 | X81: 通过AI实现作业的智能分层与批改，打破传统统一作业模式，提升教师批改效率，促进个性化学习与家校协同 | Y81: 语文 | Z81: 小猿AI | AA81: 北京猿力未来科技有限公司 | AB81: 吉林省 | AD81: =VLOOKUP($K81,「工具标准名」映射表!$B:$I,3,0) -> 小猿AI | AE81: =VLOOKUP($K81,「工具标准名」映射表!$B:$I,4,0) -> 技术层 | AF81: =VLOOKUP($K81,「工具标准名」映射表!$B:$I,5,0) -> 技术层（通用大模型） | AG81: =VLOOKUP($K81,「工具标准名」映射表!$B:$I,6,0) -> 软件工具 | AH81: =VLOOKUP($K81,「工具标准名」映射表!$B:$I,7,0) -> AI智能体 | AI81: =VLOOKUP($K81,「工具标准名」映射表!$B:$I,8,0) -> 否 | AJ81: 吉林省
A82: 第50号案例_1.“人工智能+基础教育”典型应用场景案例申报书(1).docx | B82: 46056.469 | C82: 50 | D82: 五育融合背景下小学智能德育评价体系的构建与应用 | E82: 上海 | F82: 小学 | G82: 已在上海大学附属浦东实验小学实施，具备一定的推广价值，整体处于应用探索阶段 | H82: 通过智能德育评价体系的构建，实现了德育评价的科学化与系统化，促进了学生全面发展。 | I82: 需求分析 → 技术研发 → 个性化定制 → 应用优化 | J82: ["教育数据挖掘", "智能评价算法", "个性化学习路径", "德育评价模型"] | K82: 智能德育评价系统 | L82: 未点名企业 | M82: FALSE | N82: 软件平台 | O82: 平台型综合系统 | P82: 文档中提到“构建智能德育评价体系，支持个性化反馈与评价” | Q82: 助评 | R82: 五育融合学生画像 | S82: 德育 | T82: 学生：提升德育素养与综合素质；教师：实现精准德育评价与反馈；学校：推动德育教育的系统化与科学化。 | U82: 需求分析 → 技术研发 → 个性化定制 → 应用优化 | V82: 数据采集层（多模态德育数据采集与融合） 画像诊断层（个性化德育画像生成、过程性反馈解释） 个性化学习层（即时生成德育反馈） | W82: 企业产品以“德育支持工具”为主，学校多通过校本化规则实现德育适配，整体处于规模化应用初期。 | X82: 通过五育融合的理念，构建智能德育评价体系，实现德育评价的科学化、系统化，推动德育教育的创新与发展。 | Y82: 德育 | Z82: 智能德育评价系统 | AA82: 0 | AB82: 上海市 | AD82: =VLOOKUP($K82,「工具标准名」映射表!$B:$I,3,0) -> 智能德育评价系统 | AE82: =VLOOKUP($K82,「工具标准名」映射表!$B:$I,4,0) -> 教育数据层 | AF82: =VLOOKUP($K82,「工具标准名」映射表!$B:$I,5,0) -> 教育数据层（资源数据） | AG82: =VLOOKUP($K82,「工具标准名」映射表!$B:$I,6,0) -> 在线资源 | AH82: =VLOOKUP($K82,「工具标准名」映射表!$B:$I,7,0) -> 大语言模型 | AI82: =VLOOKUP($K82,「工具标准名」映射表!$B:$I,8,0) -> 否 | AJ82: 上海市
A83: 第51号案例_上海市崇明中学附属东门中学-由月华-AI赋能学校家庭教育指导优质资源应用.pdf | B83: 46056.469 | C83: 51 | D83: AI赋能学校家庭教育指导优质资源应用 | E83: 上海市 | F83: 初中 | G83: 当前在本校六年级试点应用阶段，逐步推广至其他年级，具备向其他学校及跨区域规模化推广的潜力。 | H83: 构建了“AI+学校+家庭”的三方协同互动模式，提升家庭教育指导质量与效率，具有推广价值。 | I83: 需求分析 → 个性化定制 → 应用优化 → 反馈调整 | J83: ["大数据分析", "智能算法", "个性化推荐", "资源整合", "智能检索"] | K83: 朗旭爸爸 | L83: 未点名企业 | M83: FALSE | N83: AI智能体 | O83: AI 能力 / 模型 / API（基础层） | P83: 文档中提到“特别开发‘朗旭爸爸’和‘朗旭妈妈’两个AI智能体” | Q83: 助育 | R83: 智能德育（家庭教育指导） | S83: 德育 | T83: 提升家庭教育指导质量与效率，促进家校协同育人，形成可推广的家庭教育指导模式 | U83: 需求分析 → 个性化定制 → 应用优化 | V83: 数据采集层（问卷与访谈数据收集） 行为识别层（家长与教师需求分析） 画像诊断层（资源推荐与个性化服务） 智能策略层（动态更新与反馈优化） | W83: 当前在六年级试点应用，具备向其他年级及学校推广的潜力，整体处于推广阶段 | X83: 构建'AI+学校+家庭'的三方协同互动模式，打破传统家庭教育指导的单向输出，利用大数据分析实现个性化推荐，提升教育质量 | Y83: 未提及 | Z83: 朗旭爸爸 | AA83: 0 | AB83: 上海市 | AD83: =VLOOKUP($K83,「工具标准名」映射表!$B:$I,3,0) -> 朗旭爸爸 | AE83: =VLOOKUP($K83,「工具标准名」映射表!$B:$I,4,0) -> 功能应用层 | AF83: =VLOOKUP($K83,「工具标准名」映射表!$B:$I,5,0) -> 功能应用层（AI智能体） | AG83: =VLOOKUP($K83,「工具标准名」映射表!$B:$I,6,0) -> 软件工具 | AH83: =VLOOKUP($K83,「工具标准名」映射表!$B:$I,7,0) -> AI智能体 | AI83: =VLOOKUP($K83,「工具标准名」映射表!$B:$I,8,0) -> 否 | AJ83: 上海市
A84: 第51号案例_上海市崇明中学附属东门中学-由月华-AI赋能学校家庭教育指导优质资源应用.pdf | B84: 46056.469 | C84: 51 | D84: AI赋能学校家庭教育指导优质资源应用 | E84: 上海市 | F84: 初中 | G84: 当前在本校六年级试点应用阶段，逐步推广至其他年级，具备向其他学校及跨区域规模化推广的潜力。 | H84: 构建了“AI+学校+家庭”的三方协同互动模式，提升家庭教育指导质量与效率，具有推广价值。 | I84: 需求分析 → 个性化定制 → 应用优化 → 反馈调整 | J84: ["大数据分析", "智能算法", "个性化推荐", "资源整合", "智能检索"] | K84: 朗旭妈妈 | L84: 未点名企业 | M84: FALSE | N84: AI智能体 | O84: AI 能力 / 模型 / API（基础层） | P84: 文档中提到“特别开发‘朗旭爸爸’和‘朗旭妈妈’两个AI智能体” | Q84: 助育 | R84: 智能德育（家庭教育指导） | S84: 德育 | T84: 提升家庭教育指导质量与效率，促进家校协同育人，形成可推广的家庭教育指导模式 | U84: 需求分析 → 个性化定制 → 应用优化 | V84: 数据采集层（问卷与访谈数据收集） 行为识别层（家长与教师需求分析） 画像诊断层（资源推荐与个性化服务） 智能策略层（动态更新与反馈优化） | W84: 当前在六年级试点应用，具备向其他年级及学校推广的潜力，整体处于推广阶段 | X84: 构建'AI+学校+家庭'的三方协同互动模式，打破传统家庭教育指导的单向输出，利用大数据分析实现个性化推荐，提升教育质量 | Y84: 未提及 | Z84: 朗旭妈妈 | AA84: 0 | AB84: 上海市 | AD84: =VLOOKUP($K84,「工具标准名」映射表!$B:$I,3,0) -> 朗旭妈妈 | AE84: =VLOOKUP($K84,「工具标准名」映射表!$B:$I,4,0) -> 功能应用层 | AF84: =VLOOKUP($K84,「工具标准名」映射表!$B:$I,5,0) -> 功能应用层（AI智能体） | AG84: =VLOOKUP($K84,「工具标准名」映射表!$B:$I,6,0) -> 软件工具 | AH84: =VLOOKUP($K84,「工具标准名」映射表!$B:$I,7,0) -> AI智能体 | AI84: =VLOOKUP($K84,「工具标准名」映射表!$B:$I,8,0) -> 否 | AJ84: 上海市
A85: 第52号案例_27、上海市杨浦区复旦科技园小学+刘艳+“AI + 导师”协同育人新模式：全员导师制下的AI心理助手落地实践.pdf | B85: 46056.469 | C85: 52 | D85: “AI+导师”协同育人新模式：全员导师制下的AI心理助手落地实践 | E85: 上海市杨浦区 | F85: 小学 | G85: 目前覆盖20所学校近万名学生，心理问题识别响应时间从3天缩短至2小时，导师生成综合评价报告效率提升70%。 | H85: 首创“AI+全员导师制”协同育人模式，将AI技术融入心理教育与综合素质评价全流程，实现从“经验育人”向“数据驱动育人”转变。 | I85: 需求分析 → 技术研发与个性化定制 → 应用优化 → 个性化定制 | J85: ["自然语言处理", "行为识别技术", "心理状态评估模型", "语音交互技术", "情绪识别系统"] | K85: AI心理助手 | L85: 未点名企业 | M85: FALSE | N85: 软件平台 | O85: 平台型综合系统 | P85: 文档中提到“通过构建AI心情管理系统，实现三大核心目标” | Q85: 助育 | R85: 智能心理支持 | S85: 德育 | T85: 学生：提升情绪自我认知与管理能力，降低心理危机事件发生率；教师：提供精准的学生心理数据支撑与干预建议；学校：构建预防、疏导、干预一体化的心理健康服务体系。 | U85: AI心理分析与综合评价系统研发 → AI心理助手开发 → 适配全员导师制功能 → 应用优化 → 个性化定制 | V85: 数据采集层（自然语言处理、行为识别技术）；画像诊断层（心理状态评估模型、个性化报告生成）；个性化学习层（AI心理助手、情绪调节课程、自动推送疏导建议） | W85: 目前覆盖20所学校近万名学生，整体处于推广阶段，计划扩展至上海10个区，覆盖50所中小学。 | X85: 首创“AI+全员导师制”协同育人模式，实现从“经验育人”向“数据驱动育人”转变；多源数据融合技术应用于基础教育综合评价，提升心理问题识别效率和响应速度。 | Y85: 心理健康教育 | Z85: AI心理助手 | AA85: 0 | AB85: 上海市 | AD85: =VLOOKUP($K85,「工具标准名」映射表!$B:$I,3,0) -> AI心理助手 | AE85: =VLOOKUP($K85,「工具标准名」映射表!$B:$I,4,0) -> 功能应用层 | AF85: =VLOOKUP($K85,「工具标准名」映射表!$B:$I,5,0) -> 功能应用（校级 / 区域级系统） | AG85: =VLOOKUP($K85,「工具标准名」映射表!$B:$I,6,0) -> 软件工具 | AH85: =VLOOKUP($K85,「工具标准名」映射表!$B:$I,7,0) -> AI智能体 | AI85: =VLOOKUP($K85,「工具标准名」映射表!$B:$I,8,0) -> 否 | AJ85: 上海市
A86: 第52号案例_27、上海市杨浦区复旦科技园小学+刘艳+“AI + 导师”协同育人新模式：全员导师制下的AI心理助手落地实践.pdf | B86: 46056.469 | C86: 52 | D86: “AI+导师”协同育人新模式：全员导师制下的AI心理助手落地实践 | E86: 上海市杨浦区 | F86: 小学 | G86: 目前覆盖20所学校近万名学生，心理问题识别响应时间从3天缩短至2小时，导师生成综合评价报告效率提升70%。 | H86: 首创“AI+全员导师制”协同育人模式，将AI技术融入心理教育与综合素质评价全流程，实现从“经验育人”向“数据驱动育人”转变。 | I86: 需求分析 → 技术研发与个性化定制 → 应用优化 → 个性化定制 | J86: ["自然语言处理", "行为识别技术", "心理状态评估模型", "语音交互技术", "情绪识别系统"] | K86: 校园消息站 | L86: 未点名企业 | M86: FALSE | N86: Web 教学平台 | O86: 平台型综合系统 | P86: 文档中提到“案例使用的基础大模型校园消息站” | Q86: 助育 | R86: 智能心理支持 | S86: 德育 | T86: 学生：提升情绪自我认知与管理能力，降低心理危机事件发生率；教师：提供精准的学生心理数据支撑与干预建议；学校：构建预防、疏导、干预一体化的心理健康服务体系。 | U86: AI心理分析与综合评价系统研发 → AI心理助手开发 → 适配全员导师制功能 → 应用优化 → 个性化定制 | V86: 数据采集层（自然语言处理、行为识别技术）；画像诊断层（心理状态评估模型、个性化报告生成）；个性化学习层（AI心理助手、情绪调节课程、自动推送疏导建议） | W86: 目前覆盖20所学校近万名学生，整体处于推广阶段，计划扩展至上海10个区，覆盖50所中小学。 | X86: 首创“AI+全员导师制”协同育人模式，实现从“经验育人”向“数据驱动育人”转变；多源数据融合技术应用于基础教育综合评价，提升心理问题识别效率和响应速度。 | Y86: 心理健康教育 | Z86: 校园消息站 | AA86: 0 | AB86: 上海市 | AD86: =VLOOKUP($K86,「工具标准名」映射表!$B:$I,3,0) -> 校园消息站 | AE86: =VLOOKUP($K86,「工具标准名」映射表!$B:$I,4,0) -> 功能应用层 | AF86: =VLOOKUP($K86,「工具标准名」映射表!$B:$I,5,0) -> 功能应用（校级 / 区域级系统） | AG86: =VLOOKUP($K86,「工具标准名」映射表!$B:$I,6,0) -> 软件工具 | AH86: =VLOOKUP($K86,「工具标准名」映射表!$B:$I,7,0) -> AI智能体 | AI86: =VLOOKUP($K86,「工具标准名」映射表!$B:$I,8,0) -> 否 | AJ86: 上海市
A87: 第53号案例_附件1：“人工智能+基础教育”典型应用场景案例申报书.docx | B87: 46056.469 | C87: 53 | D87: 楷模铸魂 智能赋能：天津市翔宇力仁学校德育与综合素质评价创新实践案例 | E87: 天津市 | F87: 小学/初中/高中 | G87: 系统已覆盖全校36个小学班、22个初中班、17个高中班，服务学生超3000人，实现“周恩来班”建设100%数字化管理，具备在同类民办学校规模化推广条件。 | H87: 通过AI技术实现德育评价的数字化与个性化，打破了传统评价的时效性和准确性限制，提升了德育工作的效率与效果。 | I87: 德育数据采集 → 多维度评价与自动核算 → 成长分析与预警 | J87: ["自然语言处理", "数据采集与分析", "AI评分系统", "跨学段目标模型", "情感分析"] | K87: 综合素质评价系统 | L87: 未点名企业 | M87: FALSE | N87: 软件平台 | O87: 平台型综合系统 | P87: 文档中提到“联合科技企业定制‘楷模精神+AI赋能’的综合素质评价系统” | Q87: 助评 | R87: 综合素质评价 | S87: 德育 | T87: 学生：实现德育目标贯通，提升综合素质；教师：减轻评价工作量，提升评价效率；学校：形成可复制的德育数字化管理模式。 | U87: 德育数据采集 → 多维度评价 → 成长分析 → 反馈与优化 | V87: 数据采集层（对接校园活动平台、班级管理系统，自动抓取学生数据） 评价层（设定多维度评价指标，支持在线评价与AI自动核算） 分析层（嵌入德育目标模型，匹配阶段性目标） | W87: 系统已覆盖全校36个小学班、22个初中班、17个高中班，服务学生超3000人，整体处于规模化推广阶段。 | X87: 实现小初高德育评价一体化，首次在民办学校实现跨学段德育目标贯通，提升评价效率与精准度，形成“数据驱动-精准评价-个性培养”的管理模式。 | Y87: 德育 | Z87: 综合素质评价系统 | AA87: 0 | AB87: 天津市 | AD87: =VLOOKUP($K87,「工具标准名」映射表!$B:$I,3,0) -> 综合素质评价系统 | AE87: =VLOOKUP($K87,「工具标准名」映射表!$B:$I,4,0) -> 教育数据层 | AF87: =VLOOKUP($K87,「工具标准名」映射表!$B:$I,5,0) -> 教育数据层（资源数据） | AG87: =VLOOKUP($K87,「工具标准名」映射表!$B:$I,6,0) -> 在线资源 | AH87: =VLOOKUP($K87,「工具标准名」映射表!$B:$I,7,0) -> 大语言模型 | AI87: =VLOOKUP($K87,「工具标准名」映射表!$B:$I,8,0) -> 是 | AJ87: 天津市
A88: 第55号案例_徐州市第七中学+创建学生成长知识库，提升德育管理水平.docx | B88: 46056.469 | C88: 55 | D88: 创建学生成长知识库，提升德育管理水平 | E88: 徐州市 | F88: 高中 | G88: 私有化知识库的建立让我们更好地利用我们手头资源，能够做到精确回答，整体处于初步应用阶段。 | H88: 运用最新AI语言大模型技术，将静态的、分散的教学资料转化为动态、可交互的智能知识体系，推动教育从知识传授向能力培养和个性化支持转变。 | I88: 本地部署大模型 → 创建学生个人成长档案知识库 → 整合成网页聊天系统 → 实现快速信息获取与个性化辅导 | J88: ["AI语言大模型", "知识库管理", "信息检索系统", "数据隐私保护", "局域网访问控制"] | K88: deepseek | L88: 未点名企业 | M88: FALSE | N88: AI模型 | O88: AI 能力 / 模型 / API（基础层） | P88: 文档中提到“利用ollama部署本地deepseek大模型” | Q88: 助教 | R88: 学生信息智能管理 | S88: 德育 | T88: 学生：便于信息共享与个性化辅导；教师：快速了解学生情况，提升教学针对性；学校：优化德育管理流程，提升整体教育质量。 | U88: 知识库创建 → 信息整合与共享 → 个性化查询与反馈 → 教学支持与管理 | V88: 数据采集层（学生信息采集与整合） 行为识别层（学生需求识别与分析） 画像诊断层（学生成长档案生成与动态更新） 个性化学习层（即时生成反馈与建议） | W88: 企业产品以“知识管理工具”为主，学校逐步探索个性化德育管理，整体处于初步应用阶段。 | X88: 通过本地部署的知识库系统，实现学生信息的动态管理与快速查询，提升德育管理的效率与针对性，同时保护学生隐私。 | Y88: 德育 | Z88: DeepSeek 大模型 | AA88: 杭州深度求索人工智能基础技术研究有限公司 | AB88: 江苏省 | AD88: =VLOOKUP($K88,「工具标准名」映射表!$B:$I,3,0) -> DeepSeek 大模型 | AE88: =VLOOKUP($K88,「工具标准名」映射表!$B:$I,4,0) -> 功能应用层 | AF88: =VLOOKUP($K88,「工具标准名」映射表!$B:$I,5,0) -> 功能应用（教学辅助工具） | AG88: =VLOOKUP($K88,「工具标准名」映射表!$B:$I,6,0) -> 软件工具 | AH88: =VLOOKUP($K88,「工具标准名」映射表!$B:$I,7,0) -> AI智能体 | AI88: =VLOOKUP($K88,「工具标准名」映射表!$B:$I,8,0) -> 否 | AJ88: 江苏省
A89: 第55号案例_徐州市第七中学+创建学生成长知识库，提升德育管理水平.docx | B89: 46056.469 | C89: 55 | D89: 创建学生成长知识库，提升德育管理水平 | E89: 徐州市 | F89: 高中 | G89: 私有化知识库的建立让我们更好地利用我们手头资源，能够做到精确回答，整体处于初步应用阶段。 | H89: 运用最新AI语言大模型技术，将静态的、分散的教学资料转化为动态、可交互的智能知识体系，推动教育从知识传授向能力培养和个性化支持转变。 | I89: 本地部署大模型 → 创建学生个人成长档案知识库 → 整合成网页聊天系统 → 实现快速信息获取与个性化辅导 | J89: ["AI语言大模型", "知识库管理", "信息检索系统", "数据隐私保护", "局域网访问控制"] | K89: RAGFlow | L89: 未点名企业 | M89: FALSE | N89: 知识库软件 | O89: 平台型综合系统 | P89: 文档中提到“本地部署RAGFlow知识库软件” | Q89: 助教 | R89: 学生信息智能管理 | S89: 德育 | T89: 学生：便于信息共享与个性化辅导；教师：快速了解学生情况，提升教学针对性；学校：优化德育管理流程，提升整体教育质量。 | U89: 知识库创建 → 信息整合与共享 → 个性化查询与反馈 → 教学支持与管理 | V89: 数据采集层（学生信息采集与整合） 行为识别层（学生需求识别与分析） 画像诊断层（学生成长档案生成与动态更新） 个性化学习层（即时生成反馈与建议） | W89: 企业产品以“知识管理工具”为主，学校逐步探索个性化德育管理，整体处于初步应用阶段。 | X89: 通过本地部署的知识库系统，实现学生信息的动态管理与快速查询，提升德育管理的效率与针对性，同时保护学生隐私。 | Y89: 德育 | Z89: RAGFlow | AA89: 0 | AB89: 江苏省 | AD89: =VLOOKUP($K89,「工具标准名」映射表!$B:$I,3,0) -> RAGFlow | AE89: =VLOOKUP($K89,「工具标准名」映射表!$B:$I,4,0) -> 功能应用层 | AF89: =VLOOKUP($K89,「工具标准名」映射表!$B:$I,5,0) -> 功能应用（平台型综合系统） | AG89: =VLOOKUP($K89,「工具标准名」映射表!$B:$I,6,0) -> 软件工具 | AH89: =VLOOKUP($K89,「工具标准名」映射表!$B:$I,7,0) -> 其他 | AI89: =VLOOKUP($K89,「工具标准名」映射表!$B:$I,8,0) -> 否 | AJ89: 江苏省
A90: 第56号案例_重庆教科院谭舒予-“人工智能+基础教育”典型应用场景案例申报书.pdf | B90: 46056.47 | C90: 56 | D90: 人工智能赋能综合素质教育评价的实践探索 | E90: 重庆市 | F90: 小学 | G90: 企业产品以“学习支持工具”为主，学校多通过校本化规则实现教学适配，整体处于规模化应用初期。 | H90: 通过构建综合素质评价平台，实现教育评价从经验性到数字化、从单一性到综合性、从结果性到过程性、从诊断性到反馈性的转变，有效辅助教育决策与学生成长记录。 | I90: 过程性数据采集 + AI智能分析 + 动态反馈干预 | J90: ["数据采集", "智能分析", "个性化反馈", "生成式AI", "多源数据融合"] | K90: 五彩博雅少年综合素质评价平台 | L90: 重庆市教育科学研究院 | M90: TRUE | N90: 软件平台 | O90: 平台型综合系统 | P90: 文档中提到“搭建‘五彩博雅少年’学生综合素质评价平台” | Q90: 助评 | R90: 综合素质评价 | S90: 德育 | T90: 学生：全面记录成长档案，促进自我反思与发展；教师：提供精准德育决策支持；学校：优化教育决策，提升教育质量。 | U90: 过程性数据采集 → AI智能分析 → 动态反馈干预 → 综合素质评价 | V90: 数据采集层（多维数据采集：课堂表现、校园活动、家校共育）；评价中心（智能分析生成成长报告，多主体协同评价）；学生画像（可视化成长轨迹，个性化发展建议） | W90: 企业产品以'智能德育与综合素质评价'为主，整体处于数字化转型和应用推广阶段。 | X90: 构建德育AI教研员，实时录制课堂德育片段并生成分析报告；打造'数据-分析-反馈-干预'闭环，解决传统评价碎片化问题；创新家校协同评价模式，提升家长参与度和信息对称性。 | Y90: 德育 | Z90: 五彩博雅少年综合素质评价平台 | AA90: 0 | AB90: 重庆市 | AD90: =VLOOKUP($K90,「工具标准名」映射表!$B:$I,3,0) -> 五彩博雅少年综合素质评价平台 | AE90: =VLOOKUP($K90,「工具标准名」映射表!$B:$I,4,0) -> 功能应用层 | AF90: =VLOOKUP($K90,「工具标准名」映射表!$B:$I,5,0) -> 功能应用（校级 / 区域级系统） | AG90: =VLOOKUP($K90,「工具标准名」映射表!$B:$I,6,0) -> 软件工具 | AH90: =VLOOKUP($K90,「工具标准名」映射表!$B:$I,7,0) -> AI智能体 | AI90: =VLOOKUP($K90,「工具标准名」映射表!$B:$I,8,0) -> 否 | AJ90: 重庆市
A91: 第56号案例_重庆教科院谭舒予-“人工智能+基础教育”典型应用场景案例申报书.pdf | B91: 46056.47 | C91: 56 | D91: 人工智能赋能综合素质教育评价的实践探索 | E91: 重庆市 | F91: 小学 | G91: 企业产品以“学习支持工具”为主，学校多通过校本化规则实现教学适配，整体处于规模化应用初期。 | H91: 通过构建综合素质评价平台，实现教育评价从经验性到数字化、从单一性到综合性、从结果性到过程性、从诊断性到反馈性的转变，有效辅助教育决策与学生成长记录。 | I91: 过程性数据采集 + AI智能分析 + 动态反馈干预 | J91: ["数据采集", "智能分析", "个性化反馈", "生成式AI", "多源数据融合"] | K91: DeepSeek | L91: 未点名企业 | M91: FALSE | N91: AI模型 | O91: AI 能力 / 模型 / API（基础层） | P91: 文档中提到“依托DeepSeek大模型，实现‘学生画像自动生成+个性化建议智能推送’技术创新” | Q91: 助评 | R91: 综合素质评价 | S91: 德育 | T91: 学生：全面记录成长档案，促进自我反思与发展；教师：提供精准德育决策支持；学校：优化教育决策，提升教育质量。 | U91: 过程性数据采集 → AI智能分析 → 动态反馈干预 → 综合素质评价 | V91: 数据采集层（多维数据采集：课堂表现、校园活动、家校共育）；评价中心（智能分析生成成长报告，多主体协同评价）；学生画像（可视化成长轨迹，个性化发展建议） | W91: 企业产品以'智能德育与综合素质评价'为主，整体处于数字化转型和应用推广阶段。 | X91: 构建德育AI教研员，实时录制课堂德育片段并生成分析报告；打造'数据-分析-反馈-干预'闭环，解决传统评价碎片化问题；创新家校协同评价模式，提升家长参与度和信息对称性。 | Y91: 德育 | Z91: DeepSeek 大模型 | AA91: 杭州深度求索人工智能基础技术研究有限公司 | AB91: 重庆市 | AD91: =VLOOKUP($K91,「工具标准名」映射表!$B:$I,3,0) -> DeepSeek 大模型 | AE91: =VLOOKUP($K91,「工具标准名」映射表!$B:$I,4,0) -> 功能应用层 | AF91: =VLOOKUP($K91,「工具标准名」映射表!$B:$I,5,0) -> 功能应用（教学辅助工具） | AG91: =VLOOKUP($K91,「工具标准名」映射表!$B:$I,6,0) -> 软件工具 | AH91: =VLOOKUP($K91,「工具标准名」映射表!$B:$I,7,0) -> AI智能体 | AI91: =VLOOKUP($K91,「工具标准名」映射表!$B:$I,8,0) -> 否 | AJ91: 重庆市
A92: 第56号案例_重庆教科院谭舒予-“人工智能+基础教育”典型应用场景案例申报书.pdf | B92: 46056.47 | C92: 56 | D92: 人工智能赋能综合素质教育评价的实践探索 | E92: 重庆市 | F92: 小学 | G92: 企业产品以“学习支持工具”为主，学校多通过校本化规则实现教学适配，整体处于规模化应用初期。 | H92: 通过构建综合素质评价平台，实现教育评价从经验性到数字化、从单一性到综合性、从结果性到过程性、从诊断性到反馈性的转变，有效辅助教育决策与学生成长记录。 | I92: 过程性数据采集 + AI智能分析 + 动态反馈干预 | J92: ["数据采集", "智能分析", "个性化反馈", "生成式AI", "多源数据融合"] | K92: 希沃易课堂 | L92: 未点名企业 | M92: FALSE | N92: 软件平台 | O92: 平台型综合系统 | P92: 文档中提到“案例使用的基础大模型DeepSeek、希沃易课堂” | Q92: 助评 | R92: 综合素质评价 | S92: 德育 | T92: 学生：全面记录成长档案，促进自我反思与发展；教师：提供精准德育决策支持；学校：优化教育决策，提升教育质量。 | U92: 过程性数据采集 → AI智能分析 → 动态反馈干预 → 综合素质评价 | V92: 数据采集层（多维数据采集：课堂表现、校园活动、家校共育）；评价中心（智能分析生成成长报告，多主体协同评价）；学生画像（可视化成长轨迹，个性化发展建议） | W92: 企业产品以'智能德育与综合素质评价'为主，整体处于数字化转型和应用推广阶段。 | X92: 构建德育AI教研员，实时录制课堂德育片段并生成分析报告；打造'数据-分析-反馈-干预'闭环，解决传统评价碎片化问题；创新家校协同评价模式，提升家长参与度和信息对称性。 | Y92: 德育 | Z92: 希沃易课堂 | AA92: 广州视源电子科技股份有限公司 | AB92: 重庆市 | AD92: =VLOOKUP($K92,「工具标准名」映射表!$B:$I,3,0) -> 希沃易课堂 | AE92: =VLOOKUP($K92,「工具标准名」映射表!$B:$I,4,0) -> 功能应用层 | AF92: =VLOOKUP($K92,「工具标准名」映射表!$B:$I,5,0) -> 功能应用（平台型综合系统） | AG92: =VLOOKUP($K92,「工具标准名」映射表!$B:$I,6,0) -> 虚拟教室 | AH92: =VLOOKUP($K92,「工具标准名」映射表!$B:$I,7,0) -> AI智能体 | AI92: =VLOOKUP($K92,「工具标准名」映射表!$B:$I,8,0) -> 否 | AJ92: 重庆市
A93: 第57号案例_玉德AI银行：数据与智能双驱动的家校社协同育人新范式.docx | B93: 46056.47 | C93: 57 | D93: 玉德AI银行：数据与智能双驱动的家校社协同育人新范式 | E93: 重庆两江新区 | F93: 小学 | G93: 当前应用已覆盖全校学生，生成成长画像2000余份，记录行为数据10万余条，具备极强的规模化推广条件。 | H93: 创建了“AI原生驱动”的家校社协同德育新范式，重塑了育人流程，实现了人机协同的智能化管理与服务，注入了深厚的文化底蕴和时代活力。 | I93: 数据采集与整合 → AI模型训练与应用 → 行为数据分析与智能反馈 → 德育评价与优化 | J93: ["数据中台", "聚类分析", "关联规则算法", "机器学习", "自然语言处理"] | K93: 行远银行 | L93: 未点名企业 | M93: TRUE | N93: 软件平台 | O93: 平台型综合系统 | P93: 文档中提到“在钉钉平台上构建了‘玉德AI银行’智能评价体系” | Q93: 助育 | R93: 智能评价体系 | S93: 德育 | T93: 学生：实现德育目标的量化与可视化；教师：减轻重复负担，聚焦育人本质；学校：推动教育管理的科学性与育人效能提升。 | U93: 数据采集 → 行为数据分析 → AI智能反馈 → 德育评价优化 | V93: 数据采集层（多源异构数据汇聚与清洗） 行为识别层（学生行为模式识别） 画像诊断层（学生成长画像生成） 个性化学习层（智能反馈与指导） | W93: 企业产品以“智能评价工具”为主，已覆盖全校学生，具备规模化推广条件，整体处于应用推广阶段。 | X93: 创建了“AI原生驱动”的家校社协同德育新范式，成功将传统文化与AI技术深度融合，实现德育评价的量化与智能化，推动教育管理的科学化与高效化。 | Y93: 未提及 | Z93: 行远银行 | AA93: 0 | AB93: 重庆市 | AD93: =VLOOKUP($K93,「工具标准名」映射表!$B:$I,3,0) -> 行远银行 | AE93: =VLOOKUP($K93,「工具标准名」映射表!$B:$I,4,0) -> 功能应用层 | AF93: =VLOOKUP($K93,「工具标准名」映射表!$B:$I,5,0) -> 功能应用（平台型综合系统） | AG93: =VLOOKUP($K93,「工具标准名」映射表!$B:$I,6,0) -> 软件工具 | AH93: =VLOOKUP($K93,「工具标准名」映射表!$B:$I,7,0) -> AI智能体 | AI93: =VLOOKUP($K93,「工具标准名」映射表!$B:$I,8,0) -> 否 | AJ93: 重庆市
A94: 第57号案例_玉德AI银行：数据与智能双驱动的家校社协同育人新范式.docx | B94: 46056.47 | C94: 57 | D94: 玉德AI银行：数据与智能双驱动的家校社协同育人新范式 | E94: 重庆两江新区 | F94: 小学 | G94: 当前应用已覆盖全校学生，生成成长画像2000余份，记录行为数据10万余条，具备极强的规模化推广条件。 | H94: 创建了“AI原生驱动”的家校社协同德育新范式，重塑了育人流程，实现了人机协同的智能化管理与服务，注入了深厚的文化底蕴和时代活力。 | I94: 数据采集与整合 → AI模型训练与应用 → 行为数据分析与智能反馈 → 德育评价与优化 | J94: ["数据中台", "聚类分析", "关联规则算法", "机器学习", "自然语言处理"] | K94: 行远银行AI助手 | L94: 未点名企业 | M94: TRUE | N94: 软件平台 | O94: 平台内嵌功能模块 / 插件 | P94: 文档中描述“搭建个性化AI——行远银行AI助手，通过提示词工程与微调” | Q94: 助育 | R94: 智能评价体系 | S94: 德育 | T94: 学生：实现德育目标的量化与可视化；教师：减轻重复负担，聚焦育人本质；学校：推动教育管理的科学性与育人效能提升。 | U94: 数据采集 → 行为数据分析 → AI智能反馈 → 德育评价优化 | V94: 数据采集层（多源异构数据汇聚与清洗） 行为识别层（学生行为模式识别） 画像诊断层（学生成长画像生成） 个性化学习层（智能反馈与指导） | W94: 企业产品以“智能评价工具”为主，已覆盖全校学生，具备规模化推广条件，整体处于应用推广阶段。 | X94: 创建了“AI原生驱动”的家校社协同德育新范式，成功将传统文化与AI技术深度融合，实现德育评价的量化与智能化，推动教育管理的科学化与高效化。 | Y94: 未提及 | Z94: 行远银行AI助手 | AA94: 0 | AB94: 重庆市 | AD94: =VLOOKUP($K94,「工具标准名」映射表!$B:$I,3,0) -> 行远银行AI助手 | AE94: =VLOOKUP($K94,「工具标准名」映射表!$B:$I,4,0) -> 功能应用层 | AF94: =VLOOKUP($K94,「工具标准名」映射表!$B:$I,5,0) -> 功能应用（平台型综合系统） | AG94: =VLOOKUP($K94,「工具标准名」映射表!$B:$I,6,0) -> 软件工具 | AH94: =VLOOKUP($K94,「工具标准名」映射表!$B:$I,7,0) -> AI智能体 | AI94: =VLOOKUP($K94,「工具标准名」映射表!$B:$I,8,0) -> 否 | AJ94: 重庆市
A95: 第59号案例_申报书：重庆市南岸区天台岗融创小学校（徐勇 徐倩）+“成长指南针”——人工智能赋能小学生“五育并举”的实践探索.docx | B95: 46056.47 | C95: 59 | D95: “成长指南针”——人工智能赋能小学生“五育并举”的实践探索 | E95: 重庆市南岸区 | F95: 小学 | G95: 体系已覆盖全校各年级学生，累计生成评价数据超2万次，教师特色活动评价工具使用率达100%。 | H95: 构建了基础评价、特色评价和家庭评价的三维体系，实现了家校协同与评价数据双向流通，促进了学生全面发展与自主学习。 | I95: 软硬件适配与集成 → 评价体系特色化设计 → 数据管理与智能分析 | J95: ["数据管理", "智能分析", "AI算法", "用户端应用程序"] | K95: 成长指南针 | L95: 未点名企业 | M95: FALSE | N95: 软件平台 | O95: 平台型综合系统 | P95: 文档中提到“对接‘成长指南针’平台，开发教师端、家长端评价应用程序。” | Q95: 助评 | R95: 综合素质评价 | S95: 德育 | T95: 学生：激发自主学习热情、促进全面发展、增强自信心与成就感；教师：引导教学方式转变、加强师生互动与沟通；学校：营造积极向上的校园文化、提高管理效率、提升声誉与影响力 | U95: 需求分析 → 技术应用与个性化定制 → 应用优化 → 案例创新突破 | V95: 数据采集层（评价数据实时同步、成长档案智能更新） 行为识别层（教师端、家长端评价应用程序） 画像诊断层（学生个人、班级成长雷达图生成） | W95: 体系已覆盖全校各年级学生，累计生成评价数据超2万次，教师特色活动评价工具使用率达100%，家长端活跃用户占比持续提升，整体处于规模化应用阶段 | X95: 构建‘基础评价+特色评价+家庭评价’三维体系，实现家校协同机制创新，打破传统家校沟通壁垒，提供多元化的成长激励 | Y95: 综合素质 | Z95: 成长指南针 | AA95: 0 | AB95: 重庆市 | AD95: =VLOOKUP($K95,「工具标准名」映射表!$B:$I,3,0) -> 成长指南针（自研） | AE95: =VLOOKUP($K95,「工具标准名」映射表!$B:$I,4,0) -> 功能应用层 | AF95: =VLOOKUP($K95,「工具标准名」映射表!$B:$I,5,0) -> 功能应用（平台型综合系统） | AG95: =VLOOKUP($K95,「工具标准名」映射表!$B:$I,6,0) -> 软件工具 | AH95: =VLOOKUP($K95,「工具标准名」映射表!$B:$I,7,0) -> 其他 | AI95: =VLOOKUP($K95,「工具标准名」映射表!$B:$I,8,0) -> 否 | AJ95: 重庆市
A96: 第61号案例_“人工智能+基础教育”典型应用场景案例申报书(南湖区教育体育局).docx | B96: 46056.47 | C96: 61 | D96: 双闭环驱动：南湖区AI+教育全域赋能新范式 | E96: 嘉兴市南湖区 | F96: 初中 | G96: 已在全区33所中小学推广应用，处于常态化应用阶段 | H96: 通过构建区域教育数字基座与AI工具的深度融合，实现了个性化教学与精准教研的双闭环，提升了教学效率与学生参与度。 | I96: 需求分析 → 技术研发与定制 → 应用优化 → 创新突破 | J96: ["数据采集", "AI教学助手", "智能批阅系统", "教育大模型", "课堂实录分析"] | K96: 教师AI备授课助手 | L96: 未点名企业 | M96: FALSE | N96: 软件平台 | O96: 平台型综合系统 | P96: 文档中提到“全区推动全学科教师应用AI备授课助手，依托大模型海量优质教学资源数据库” | Q96: 助学 | R96: 智能辅导系统 | S96: 智育 | T96: 学生：提供个性化学习路径与资源，支持全面发展；教师：减轻备课、批改等重复性劳动，赋能精准教学与专业成长；学校：提升区域教育治理能力，推动教育数字化转型。 | U96: 数据采集 → 学情诊断与画像生成 → 个性化反馈与辅导 → 学习改进 | V96: 数据采集层（多模态学习数据采集与融合） 行为识别层（学习意图识别、学习路径偏差检测） 画像诊断层（个性化画像生成、过程性反馈解释） 个性化学习层（即时生成反馈） | W96: 企业产品以"学习支持工具"为主，学校多通过校本化规则实现教学适配，整体处于规模化应用初期。 | X96: 推进区域“课前智构—课上智启—课后智溯”教学闭环模式，实现个性化教学与精准反馈，提升教师备授课效率与学生课堂互动率，构建共建共享的良性资源生态体系。 | Y96: 未提及 | Z96: 教师AI备授课助手 | AA96: 0 | AB96: 浙江省 | AD96: =VLOOKUP($K96,「工具标准名」映射表!$B:$I,3,0) -> 教师AI备授课助手 | AE96: =VLOOKUP($K96,「工具标准名」映射表!$B:$I,4,0) -> 功能应用层 | AF96: =VLOOKUP($K96,「工具标准名」映射表!$B:$I,5,0) -> 功能应用层（AI智能体） | AG96: =VLOOKUP($K96,「工具标准名」映射表!$B:$I,6,0) -> 软件工具 | AH96: =VLOOKUP($K96,「工具标准名」映射表!$B:$I,7,0) -> AI智能体 | AI96: =VLOOKUP($K96,「工具标准名」映射表!$B:$I,8,0) -> 否 | AJ96: 浙江省
A97: 第61号案例_“人工智能+基础教育”典型应用场景案例申报书(南湖区教育体育局).docx | B97: 46056.47 | C97: 61 | D97: 双闭环驱动：南湖区AI+教育全域赋能新范式 | E97: 嘉兴市南湖区 | F97: 初中 | G97: 已在全区33所中小学推广应用，处于常态化应用阶段 | H97: 通过构建区域教育数字基座与AI工具的深度融合，实现了个性化教学与精准教研的双闭环，提升了教学效率与学生参与度。 | I97: 需求分析 → 技术研发与定制 → 应用优化 → 创新突破 | J97: ["数据采集", "AI教学助手", "智能批阅系统", "教育大模型", "课堂实录分析"] | K97: 智能云阅卷系统 | L97: 未点名企业 | M97: FALSE | N97: 软件平台 | O97: 平台型综合系统 | P97: 文档中提到“引进优质应用系统，包括智能云阅卷系统” | Q97: 助学 | R97: 智能辅导系统 | S97: 智育 | T97: 学生：提供个性化学习路径与资源，支持全面发展；教师：减轻备课、批改等重复性劳动，赋能精准教学与专业成长；学校：提升区域教育治理能力，推动教育数字化转型。 | U97: 数据采集 → 学情诊断与画像生成 → 个性化反馈与辅导 → 学习改进 | V97: 数据采集层（多模态学习数据采集与融合） 行为识别层（学习意图识别、学习路径偏差检测） 画像诊断层（个性化画像生成、过程性反馈解释） 个性化学习层（即时生成反馈） | W97: 企业产品以"学习支持工具"为主，学校多通过校本化规则实现教学适配，整体处于规模化应用初期。 | X97: 推进区域“课前智构—课上智启—课后智溯”教学闭环模式，实现个性化教学与精准反馈，提升教师备授课效率与学生课堂互动率，构建共建共享的良性资源生态体系。 | Y97: 未提及 | Z97: 智能云阅卷系统 | AA97: 0 | AB97: 浙江省 | AD97: =VLOOKUP($K97,「工具标准名」映射表!$B:$I,3,0) -> 智能云阅卷系统 | AE97: =VLOOKUP($K97,「工具标准名」映射表!$B:$I,4,0) -> 功能应用层 | AF97: =VLOOKUP($K97,「工具标准名」映射表!$B:$I,5,0) -> 功能应用（校级 / 区域级系统） | AG97: =VLOOKUP($K97,「工具标准名」映射表!$B:$I,6,0) -> 软件工具 | AH97: =VLOOKUP($K97,「工具标准名」映射表!$B:$I,7,0) -> AI智能体 | AI97: =VLOOKUP($K97,「工具标准名」映射表!$B:$I,8,0) -> 否 | AJ97: 浙江省
A98: 第61号案例_“人工智能+基础教育”典型应用场景案例申报书(南湖区教育体育局).docx | B98: 46056.47 | C98: 61 | D98: 双闭环驱动：南湖区AI+教育全域赋能新范式 | E98: 嘉兴市南湖区 | F98: 初中 | G98: 已在全区33所中小学推广应用，处于常态化应用阶段 | H98: 通过构建区域教育数字基座与AI工具的深度融合，实现了个性化教学与精准教研的双闭环，提升了教学效率与学生参与度。 | I98: 需求分析 → 技术研发与定制 → 应用优化 → 创新突破 | J98: ["数据采集", "AI教学助手", "智能批阅系统", "教育大模型", "课堂实录分析"] | K98: 数智作业平台 | L98: 未点名企业 | M98: FALSE | N98: 软件平台 | O98: 平台型综合系统 | P98: 文档中提到“依托数智作业平台，全区统筹规划” | Q98: 助学 | R98: 智能辅导系统 | S98: 智育 | T98: 学生：提供个性化学习路径与资源，支持全面发展；教师：减轻备课、批改等重复性劳动，赋能精准教学与专业成长；学校：提升区域教育治理能力，推动教育数字化转型。 | U98: 数据采集 → 学情诊断与画像生成 → 个性化反馈与辅导 → 学习改进 | V98: 数据采集层（多模态学习数据采集与融合） 行为识别层（学习意图识别、学习路径偏差检测） 画像诊断层（个性化画像生成、过程性反馈解释） 个性化学习层（即时生成反馈） | W98: 企业产品以"学习支持工具"为主，学校多通过校本化规则实现教学适配，整体处于规模化应用初期。 | X98: 推进区域“课前智构—课上智启—课后智溯”教学闭环模式，实现个性化教学与精准反馈，提升教师备授课效率与学生课堂互动率，构建共建共享的良性资源生态体系。 | Y98: 未提及 | Z98: 数智作业平台 | AA98: 0 | AB98: 浙江省 | AD98: =VLOOKUP($K98,「工具标准名」映射表!$B:$I,3,0) -> 数智作业平台 | AE98: =VLOOKUP($K98,「工具标准名」映射表!$B:$I,4,0) -> 功能应用层 | AF98: =VLOOKUP($K98,「工具标准名」映射表!$B:$I,5,0) -> 功能应用（Web 教学平台（SaaS）） | AG98: =VLOOKUP($K98,「工具标准名」映射表!$B:$I,6,0) -> 软件工具 | AH98: =VLOOKUP($K98,「工具标准名」映射表!$B:$I,7,0) -> AI智能体 | AI98: =VLOOKUP($K98,「工具标准名」映射表!$B:$I,8,0) -> 否 | AJ98: 浙江省
A99: 第61号案例_“人工智能+基础教育”典型应用场景案例申报书(南湖区教育体育局).docx | B99: 46056.47 | C99: 61 | D99: 双闭环驱动：南湖区AI+教育全域赋能新范式 | E99: 嘉兴市南湖区 | F99: 初中 | G99: 已在全区33所中小学推广应用，处于常态化应用阶段 | H99: 通过构建区域教育数字基座与AI工具的深度融合，实现了个性化教学与精准教研的双闭环，提升了教学效率与学生参与度。 | I99: 需求分析 → 技术研发与定制 → 应用优化 → 创新突破 | J99: ["数据采集", "AI教学助手", "智能批阅系统", "教育大模型", "课堂实录分析"] | K99: AI智慧黑板 | L99: 未点名企业 | M99: FALSE | N99: 硬件 + AI系统 | O99: 平台型综合系统 | P99: 文档中提到“全区统筹引入基于教育专用大模型的AI智慧黑板” | Q99: 助学 | R99: 智能辅导系统 | S99: 智育 | T99: 学生：提供个性化学习路径与资源，支持全面发展；教师：减轻备课、批改等重复性劳动，赋能精准教学与专业成长；学校：提升区域教育治理能力，推动教育数字化转型。 | U99: 数据采集 → 学情诊断与画像生成 → 个性化反馈与辅导 → 学习改进 | V99: 数据采集层（多模态学习数据采集与融合） 行为识别层（学习意图识别、学习路径偏差检测） 画像诊断层（个性化画像生成、过程性反馈解释） 个性化学习层（即时生成反馈） | W99: 企业产品以"学习支持工具"为主，学校多通过校本化规则实现教学适配，整体处于规模化应用初期。 | X99: 推进区域“课前智构—课上智启—课后智溯”教学闭环模式，实现个性化教学与精准反馈，提升教师备授课效率与学生课堂互动率，构建共建共享的良性资源生态体系。 | Y99: 未提及 | Z99: AI智慧黑板 | AA99: 0 | AB99: 浙江省 | AD99: =VLOOKUP($K99,「工具标准名」映射表!$B:$I,3,0) -> AI智慧黑板 | AE99: =VLOOKUP($K99,「工具标准名」映射表!$B:$I,4,0) -> 功能应用层 | AF99: =VLOOKUP($K99,「工具标准名」映射表!$B:$I,5,0) -> 功能应用（校级 / 区域级系统） | AG99: =VLOOKUP($K99,「工具标准名」映射表!$B:$I,6,0) -> 软件工具 | AH99: =VLOOKUP($K99,「工具标准名」映射表!$B:$I,7,0) -> 大语言模型 | AI99: =VLOOKUP($K99,「工具标准名」映射表!$B:$I,8,0) -> 是 | AJ99: 浙江省
A100: 第62号案例_（冯怡）人工智能+基础教育案例.docx | B100: 46056.47 | C100: 62 | D100: AI智批驱动下习作教学的进阶式应用 | E100: 嘉兴市 | F100: 小学 | G100: AI智批技术在习作教学中应用逐渐推广，教师反馈积极，整体处于初步应用阶段 | H100: 通过AI智批技术实现即时反馈与精准问题诊断，提升学生写作能力，减轻教师批改负担，促进个性化教学。 | I100: AI批改与反馈 → 问题诊断与管理体系构建 → 分层修改策略实施 → 学生写作能力提升 | J100: ["AI批改系统", "即时反馈机制", "问题诊断模型", "个性化学习路径", "数据分析与管理"] | K100: AI智批系统 | L100: 未点名企业 | M100: FALSE | N100: 软件平台 | O100: 平台型综合系统 | P100: 文档中提到“AI智批凭借高效评价与即时反馈，为习作教学带来转机” | Q100: 助学 | R100: 智能辅导系统 | S100: 智育 | T100: 学生：拓宽写作思路、提升写作技能与自信；教师：减轻批改负担、提升教学效率；学校：推动语文教育智能化与个性化发展。 | U100: 习作数据采集 → AI智能批改与反馈 → 问题诊断与管理 → 分层修改与提升 | V100: 数据采集层（习作数据收集与分析） 行为识别层（学生习作问题识别与分析） 画像诊断层（学生写作能力画像生成） 个性化学习层（即时生成反馈与修改建议） | W100: 企业产品以“智能批改工具”为主，学校逐步探索AI在习作教学中的应用，整体处于推广阶段。 | X100: 通过AI精准选材与即时反馈，构建问题管理体系与分层修改策略，突破传统习作教学的局限，提升学生写作水平与自信心。 | Y100: 语文 | Z100: AI智批系统 | AA100: 0 | AB100: 浙江省 | AD100: =VLOOKUP($K100,「工具标准名」映射表!$B:$I,3,0) -> AI智批系统 | AE100: =VLOOKUP($K100,「工具标准名」映射表!$B:$I,4,0) -> 功能应用层 | AF100: =VLOOKUP($K100,「工具标准名」映射表!$B:$I,5,0) -> 功能应用（教学辅助工具） | AG100: =VLOOKUP($K100,「工具标准名」映射表!$B:$I,6,0) -> 软件工具 | AH100: =VLOOKUP($K100,「工具标准名」映射表!$B:$I,7,0) -> 大语言模型 | AI100: =VLOOKUP($K100,「工具标准名」映射表!$B:$I,8,0) -> 是 | AJ100: 浙江省
A101: 第63号案例_“人工智能+基础教育”典型案例申报表.pdf | B101: 46056.47 | C101: 63 | D101: 未提及 | E101: 未提及 | F101: 未提及 | G101: 未提及 | H101: 未提及 | I101: 未提及 | J101: [] | Q101: 未提及 | R101: 未提及 | S101: 未提及 | T101: 未提及 | U101: 未提及 | V101: 未提及 | W101: 未提及 | X101: 未提及 | Y101: 未提及 | Z101: #N/A | AA101: #N/A | AB101: 未提及 | AD101: =VLOOKUP($K101,「工具标准名」映射表!$B:$I,3,0) -> #N/A | AE101: =VLOOKUP($K101,「工具标准名」映射表!$B:$I,4,0) -> #N/A | AF101: =VLOOKUP($K101,「工具标准名」映射表!$B:$I,5,0) -> #N/A | AG101: =VLOOKUP($K101,「工具标准名」映射表!$B:$I,6,0) -> #N/A | AH101: =VLOOKUP($K101,「工具标准名」映射表!$B:$I,7,0) -> #N/A | AI101: =VLOOKUP($K101,「工具标准名」映射表!$B:$I,8,0) -> #N/A | AJ101: 未提及
A102: 第64号案例_人工智能+作业批改 典型应用场景案例.docx | B102: 46056.47 | C102: 64 | D102: AI赋能初中道德与法治学科作业批改 | E102: 保定市清苑区 | F102: 初中 | G102: 目前已在清苑镇中学试点应用，整体处于推广阶段 | H102: 通过AI技术实现作业的自动批改与即时反馈，提升学生学习效率，减轻教师批改负担，增强家校沟通。 | I102: 学生提交 → AI批改 → 学情分析 → 教师干预 → 家长同步 | J102: ["人工智能算法", "数据分析", "即时反馈机制", "学习行为分析"] | K102: 蜜蜂家校 | L102: 未点名企业 | M102: FALSE | N102: 软件平台 | O102: Web 教学平台（SaaS） | P102: 文档中提到“依托‘蜜蜂家校’小程序平台，开展了AI智能作业批改项目的试点实施。” | Q102: 助教 | R102: 作业管理 | S102: 智育 | T102: 学生：提升作业独立完成率与即时巩固效果；教师：减轻批改负担，实现精准教学；学校：构建高效、透明的家校沟通桥梁。 | U102: 学生提交 → AI批改 → 学情分析 → 教师干预 → 家长同步 | V102: 数据采集层（作业上传与提交） 行为识别层（AI批改与分析） 画像诊断层（生成学习报告与个性反馈） | W102: 企业产品以“学习支持工具”为主，学校多通过校本化规则实现教学适配，整体处于规模化应用初期。 | X102: 通过AI实现作业的自动批改与及时反馈，减轻教师负担，提升教学效率，构建家校教育合力。 | Y102: 道德与法治 | Z102: 蜜蜂家校 | AA102: 0 | AB102: 河北省 | AD102: =VLOOKUP($K102,「工具标准名」映射表!$B:$I,3,0) -> 蜜蜂家校 | AE102: =VLOOKUP($K102,「工具标准名」映射表!$B:$I,4,0) -> 功能应用层 | AF102: =VLOOKUP($K102,「工具标准名」映射表!$B:$I,5,0) -> 功能应用层（移动端 App） | AG102: =VLOOKUP($K102,「工具标准名」映射表!$B:$I,6,0) -> 软件工具 | AH102: =VLOOKUP($K102,「工具标准名」映射表!$B:$I,7,0) -> AI智能体 | AI102: =VLOOKUP($K102,「工具标准名」映射表!$B:$I,8,0) -> 否 | AJ102: 河北省
A103: 第65号案例_成都七中初中附属小学+数智赋能小学作业治理：精准画像与个性化.docx | B103: 46056.471 | C103: 65 | D103: 数智赋能小学作业治理：精准画像与个性化 | E103: 成都 | F103: 小学 | G103: 已在成都七中初中附属小学常态化应用，形成可复制的校本经验，整体处于推广阶段 | H103: 通过AI点阵笔与铺码纸质作业的无缝融合，实现了书写过程的无感知、伴随式数据采集，为个性化教学提供了创新解决方案。 | I103: 数据采集 → 智能分析 → 决策输出 → 个性化反馈 | J103: ["微图式点阵映射技术", "智能批阅引擎", "学情分析模型", "数据驱动教学", "个性化学习路径"] | K103: AI学情分析平台 | L103: 未点名企业 | M103: FALSE | N103: 软件平台 | O103: 平台型综合系统 | P103: 文档中提到“以AI学情分析平台为核心的软硬件一体化系统” | Q103: 助学 | R103: 智能辅导系统 | S103: 智育 | T103: 学生：实现个性化学习与精准辅导；教师：减轻批改负担，提高教学效率；学校：形成可复制的智慧教育新范式。 | U103: 数据采集 → 学情分析 → 个性化反馈 → 教学改进 | V103: 数据采集层（无感化数据采集、作业智能批改） 画像诊断层（学情画像生成、个性化反馈） 个性化学习层（个性化错题集生成） | W103: 企业产品以“学习支持工具”为主，学校多通过校本化规则实现教学适配，整体处于规模化应用初期。 | X103: 通过AI点阵笔与铺码纸质作业的无缝融合，实现了书写过程的无感知、伴随式数据采集，构建了“数据驱动备课—AI辅助授课—智能精准练习—数据支撑教研—教学策略优化——个性化辅导”的全流程闭环。 | Y103: 语文、数学、英语 | Z103: AI学情分析平台 | AA103: 0 | AB103: 四川省 | AD103: =VLOOKUP($K103,「工具标准名」映射表!$B:$I,3,0) -> AI学情分析平台 | AE103: =VLOOKUP($K103,「工具标准名」映射表!$B:$I,4,0) -> 功能应用层 | AF103: =VLOOKUP($K103,「工具标准名」映射表!$B:$I,5,0) -> 功能应用（校级 / 区域级系统） | AG103: =VLOOKUP($K103,「工具标准名」映射表!$B:$I,6,0) -> 软件工具 | AH103: =VLOOKUP($K103,「工具标准名」映射表!$B:$I,7,0) -> 大语言模型 | AI103: =VLOOKUP($K103,「工具标准名」映射表!$B:$I,8,0) -> 是 | AJ103: 四川省
A104: 第65号案例_成都七中初中附属小学+数智赋能小学作业治理：精准画像与个性化.docx | B104: 46056.471 | C104: 65 | D104: 数智赋能小学作业治理：精准画像与个性化 | E104: 成都 | F104: 小学 | G104: 已在成都七中初中附属小学常态化应用，形成可复制的校本经验，整体处于推广阶段 | H104: 通过AI点阵笔与铺码纸质作业的无缝融合，实现了书写过程的无感知、伴随式数据采集，为个性化教学提供了创新解决方案。 | I104: 数据采集 → 智能分析 → 决策输出 → 个性化反馈 | J104: ["微图式点阵映射技术", "智能批阅引擎", "学情分析模型", "数据驱动教学", "个性化学习路径"] | K104: AI点阵笔 | L104: 未点名企业 | M104: FALSE | N104: 硬件 | O104: 教学辅助工具（工具型） | P104: 文档中提到“AI点阵笔与铺码习题册为前端” | Q104: 助学 | R104: 智能辅导系统 | S104: 智育 | T104: 学生：实现个性化学习与精准辅导；教师：减轻批改负担，提高教学效率；学校：形成可复制的智慧教育新范式。 | U104: 数据采集 → 学情分析 → 个性化反馈 → 教学改进 | V104: 数据采集层（无感化数据采集、作业智能批改） 画像诊断层（学情画像生成、个性化反馈） 个性化学习层（个性化错题集生成） | W104: 企业产品以“学习支持工具”为主，学校多通过校本化规则实现教学适配，整体处于规模化应用初期。 | X104: 通过AI点阵笔与铺码纸质作业的无缝融合，实现了书写过程的无感知、伴随式数据采集，构建了“数据驱动备课—AI辅助授课—智能精准练习—数据支撑教研—教学策略优化——个性化辅导”的全流程闭环。 | Y104: 语文、数学、英语 | Z104: AI点阵笔 | AA104: 0 | AB104: 四川省 | AD104: =VLOOKUP($K104,「工具标准名」映射表!$B:$I,3,0) -> AI点阵笔 | AE104: =VLOOKUP($K104,「工具标准名」映射表!$B:$I,4,0) -> 功能应用层 | AF104: =VLOOKUP($K104,「工具标准名」映射表!$B:$I,5,0) -> 功能应用（校级 / 区域级系统） | AG104: =VLOOKUP($K104,「工具标准名」映射表!$B:$I,6,0) -> 软件工具 | AH104: =VLOOKUP($K104,「工具标准名」映射表!$B:$I,7,0) -> 大语言模型 | AI104: =VLOOKUP($K104,「工具标准名」映射表!$B:$I,8,0) -> 是 | AJ104: 四川省
A105: 第66号案例_成都东部新区第七中学校（成都七中东部学校）+从即时诊断到动态干预：基于智慧纸笔的智能批改与个性化辅导实践 申报书.pdf | B105: 46056.471 | C105: 66 | D105: 从即时诊断到动态干预：基于智慧纸笔的智能批改与个性化辅导实践 | E105: 成都东部新区 | F105: 初中 | G105: 已在学校实现常态化应用，教师批改负担平均减轻约50%，具备良好的跨区域、跨学段推广潜力。 | H105: 构建了以数据为驱动力的智能作业体系，显著提升了教学的精准性与学习的个性化水平，为基础教育减负提质提供了可复制的实践路径。 | I105: 作业设计 → 作业完成与采集 → 智能批改与诊断 → 学情分析与反馈 → 系统优化与培训 | J105: ["数据采集", "智能批改", "学情分析", "个性化学习", "自然语言处理"] | K105: 智慧纸笔 | L105: 未点名企业 | M105: FALSE | N105: 硬件 + AI系统 | O105: 教学辅助工具（工具型） | P105: 文档中提到“以智慧纸笔为核心工具，构建覆盖作业设计、分发、完成、批改、分析与反馈的全流程智能化体系。” | Q105: 助学 | R105: 智能作业设计与批改 | S105: 智育 | T105: 学生：提升作业反馈时效与个性化学习；教师：减轻批改负担，提升教学精准度；学校：推动作业管理的数字化转型。 | U105: 作业设计 → 作业完成与采集 → 智能批改与诊断 → 学情分析与反馈 → 系统优化与培训 | V105: 数据采集层（实时记录学生书写轨迹、答题时长、修改频次） 行为识别层（实时统计正确率、错误选项分布） 画像诊断层（生成个性化错题集与辅导资源） 个性化学习层（推送个性化学习资源与反馈） | W105: 企业产品以“智能作业管理工具”为主，已在学校实现常态化应用，具备良好的推广潜力。 | X105: 构建“纸质书写+数字赋能”的智能作业闭环，突破传统批改局限，实现作业数据全流程数字化，显著提升作业反馈时效与精准度。 | Y105: 未提及 | Z105: 智慧纸笔 | AA105: 0 | AB105: 四川省 | AD105: =VLOOKUP($K105,「工具标准名」映射表!$B:$I,3,0) -> 智慧纸笔 | AE105: =VLOOKUP($K105,「工具标准名」映射表!$B:$I,4,0) -> 功能应用层 | AF105: =VLOOKUP($K105,「工具标准名」映射表!$B:$I,5,0) -> 功能应用（校级 / 区域级系统） | AG105: =VLOOKUP($K105,「工具标准名」映射表!$B:$I,6,0) -> 软件工具 | AH105: =VLOOKUP($K105,「工具标准名」映射表!$B:$I,7,0) -> AI智能体 | AI105: =VLOOKUP($K105,「工具标准名」映射表!$B:$I,8,0) -> 否 | AJ105: 四川省
A106: 第67号案例_成都石室东部新区实验学校-“人工智能+基础教育”典型应用案例申报书.pdf | B106: 46056.471 | C106: 67 | D106: 数智赋能，因材施教：成都石室东部新区实验学校“AI+作业”创新实践报告 | E106: 成都 | F106: 高中/初中 | G106: 企业产品以“学习支持工具”为主，学校多通过校本化规则实现教学适配，整体处于规模化应用初期 | H106: 通过数据驱动与智能算法的结合，显著提升作业设计与批改效率，形成个性化辅导与学习反馈的良性循环。 | I106: 数据驱动 + 智能算法 + 场景适配 → 作业设计与批改 → 学情反馈与个性化辅导 | J106: ["人工智能", "大数据", "知识图谱", "智能算法", "数据采集"] | K106: 数智作业系统 | L106: 未点名企业 | M106: FALSE | N106: 软件平台 | O106: 平台型综合系统 | P106: 文档中提到“构建'数据驱动+智能算法+场景适配'的数智作业系统” | Q106: 助教 | R106: 作业管理 | S106: 智育 | T106: 学生：提高作业完成效率，增强自主学习能力；教师：减少批改时间，提升个性化辅导比例；学校：形成可复制的教育数字化转型范式。 | U106: 数据驱动 → 智能算法应用 → 场景适配 → 个性化作业反馈 | V106: 基础设施层（云计算平台支撑）；数据支撑层（多源数据采集模块）；智能算法层（作业生成器、AI批阅引擎、学情分析模型、知识图谱引擎）；应用服务层（教师工作台、学生作业端、管理看板、数据开放接口） | W106: 企业产品以“智能作业系统”为主，学校通过数据驱动教学实现教学适配，整体处于推广阶段 | X106: 三维弹性作业设计模式、三级批阅体系、5分钟动态学情反馈机制、错题生命周期管理，形成“技术赋能-减负增效-质量提升”的良性循环 | Y106: 物理/英语 | Z106: 数智作业系统 | AA106: 0 | AB106: 四川省 | AD106: =VLOOKUP($K106,「工具标准名」映射表!$B:$I,3,0) -> 数智作业系统 | AE106: =VLOOKUP($K106,「工具标准名」映射表!$B:$I,4,0) -> 功能应用层 | AF106: =VLOOKUP($K106,「工具标准名」映射表!$B:$I,5,0) -> 功能应用（Web 教学平台（SaaS）） | AG106: =VLOOKUP($K106,「工具标准名」映射表!$B:$I,6,0) -> 软件工具 | AH106: =VLOOKUP($K106,「工具标准名」映射表!$B:$I,7,0) -> AI智能体 | AI106: =VLOOKUP($K106,「工具标准名」映射表!$B:$I,8,0) -> 否 | AJ106: 四川省
A107: 第67号案例_成都石室东部新区实验学校-“人工智能+基础教育”典型应用案例申报书.pdf | B107: 46056.471 | C107: 67 | D107: 数智赋能，因材施教：成都石室东部新区实验学校“AI+作业”创新实践报告 | E107: 成都 | F107: 高中/初中 | G107: 企业产品以“学习支持工具”为主，学校多通过校本化规则实现教学适配，整体处于规模化应用初期 | H107: 通过数据驱动与智能算法的结合，显著提升作业设计与批改效率，形成个性化辅导与学习反馈的良性循环。 | I107: 数据驱动 + 智能算法 + 场景适配 → 作业设计与批改 → 学情反馈与个性化辅导 | J107: ["人工智能", "大数据", "知识图谱", "智能算法", "数据采集"] | K107: 精准教学大数据系统 | L107: 未点名企业 | M107: FALSE | N107: Web 教学平台 | O107: 校级 / 区域级系统 | P107: 文档中提到“案例网址 文通云|精准教学大数据系统” | Q107: 助教 | R107: 作业管理 | S107: 智育 | T107: 学生：提高作业完成效率，增强自主学习能力；教师：减少批改时间，提升个性化辅导比例；学校：形成可复制的教育数字化转型范式。 | U107: 数据驱动 → 智能算法应用 → 场景适配 → 个性化作业反馈 | V107: 基础设施层（云计算平台支撑）；数据支撑层（多源数据采集模块）；智能算法层（作业生成器、AI批阅引擎、学情分析模型、知识图谱引擎）；应用服务层（教师工作台、学生作业端、管理看板、数据开放接口） | W107: 企业产品以“智能作业系统”为主，学校通过数据驱动教学实现教学适配，整体处于推广阶段 | X107: 三维弹性作业设计模式、三级批阅体系、5分钟动态学情反馈机制、错题生命周期管理，形成“技术赋能-减负增效-质量提升”的良性循环 | Y107: 物理/英语 | Z107: 精准教学大数据系统 | AA107: 0 | AB107: 四川省 | AD107: =VLOOKUP($K107,「工具标准名」映射表!$B:$I,3,0) -> 精准教学大数据系统 | AE107: =VLOOKUP($K107,「工具标准名」映射表!$B:$I,4,0) -> 功能应用层 | AF107: =VLOOKUP($K107,「工具标准名」映射表!$B:$I,5,0) -> 功能应用（Web 教学平台（SaaS）） | AG107: =VLOOKUP($K107,「工具标准名」映射表!$B:$I,6,0) -> 软件工具 | AH107: =VLOOKUP($K107,「工具标准名」映射表!$B:$I,7,0) -> AI智能体 | AI107: =VLOOKUP($K107,「工具标准名」映射表!$B:$I,8,0) -> 否 | AJ107: 四川省
A108: 第68号案例_成都市实验小学+趣味化·个性化·智能化：“天天跳绳”App重塑小学体育作业新样态.docx | B108: 46056.471 | C108: 68 | D108: 趣味化·个性化·智能化：“天天跳绳”App重塑小学体育作业新样态 | E108: 成都市 | F108: 小学 | G108: 该模式已在我校实现常态化应用，具有操作简便、成本低廉、效果显著的特点，目前已取得一些成效。 | H108: 创建了“趣味化引导+个性化定制+智能化评估”的体育作业新模式，实现了从统一化布置向差异化指导的转变。 | I108: 智能作业设计 → 智能执行与监管 → 智能评估与反馈 → 家校协同与优化 | J108: ["计算机视觉", "AI动作识别", "数据分析", "个性化推荐系统", "多模态数据融合"] | K108: 天天跳绳App | L108: 未点名企业 | M108: FALSE | N108: 软件平台 | O108: Web 教学平台（SaaS） | P108: 文档中提到“利用‘天天跳绳’App的AI技术，构建一个能实现个性化设计、智能化监管、数据化反馈的体育作业新范式” | Q108: 助学 | R108: 智能辅导系统 | S108: 体育 | T108: 学生：提升体质健康水平、增强作业完成率与主动参与率；教师：减轻作业布置与管理负担；学校：促进家校协同，提升整体教学效果。 | U108: 智能作业设计 → 智能执行与监管 → 智能评估与反馈 → 家校协同与优化 | V108: 数据采集层（动作识别与数据采集） 行为识别层（动作规范性分析） 画像诊断层（学生体质数字画像生成） 个性化学习层（个性化作业推荐） | W108: 该模式已在学校实现常态化应用，具备操作简便、成本低廉、效果显著的特点，目前已取得显著成效。 | X108: 创建了趣味化引导、个性化定制与智能化评估的体育作业新模式，构建了教师主导、AI辅助、学生主体与家长参与的四维协同育人机制，极大解放了教师的生产力。 | Y108: 体育 | Z108: 天天跳绳App | AA108: 0 | AB108: 四川省 | AD108: =VLOOKUP($K108,「工具标准名」映射表!$B:$I,3,0) -> 天天跳绳 | AE108: =VLOOKUP($K108,「工具标准名」映射表!$B:$I,4,0) -> 功能应用层 | AF108: =VLOOKUP($K108,「工具标准名」映射表!$B:$I,5,0) -> 功能应用层（移动端 App） | AG108: =VLOOKUP($K108,「工具标准名」映射表!$B:$I,6,0) -> 软件工具 | AH108: =VLOOKUP($K108,「工具标准名」映射表!$B:$I,7,0) -> AI智能体 | AI108: =VLOOKUP($K108,「工具标准名」映射表!$B:$I,8,0) -> 否 | AJ108: 四川省
A109: 第69号案例_成都信息工程大学红樱实验学校+基于智能批阅系统的作业设计与批改实践申报书.docx | B109: 46056.471 | C109: 69 | D109: 基于智能批阅系统的作业设计与批改实践 | E109: 成都 | F109: 小学 | G109: 已在我校1-6年级全面应用，覆盖57个班级、近3000名学生及80余名教师，运行稳定且成效显著。 | H109: 通过三维分层作业设计与智能批阅系统的结合，提升作业批改效率与质量，实现个性化教学与精准反馈。 | I109: 精准设计 → 智能批阅 → 数据采集 → 动态分析 → 靶向改进 | J109: ["智能作业批阅", "数据分析", "个性化作业设计", "教育数据挖掘", "人工智能算法"] | K109: 希沃作业学情采集分析系统 | L109: 希沃科技有限公司 | M109: FALSE | N109: 软件平台 | O109: 平台型综合系统 | P109: 文档中提到“引入了希沃作业学情采集分析系统，集成了智能布置、智能批改、智能分析、智能管理等多项功能。” | Q109: 助教 | R109: 作业管理 | S109: 智育 | T109: 学生：作业适配性好，知识点掌握率提升；教师：减轻批改负担，数据实用；学校：推动教育教学评价的科学、多元与个性化。 | U109: 精准设计 → 智能批阅 → 数据采集 → 动态分析 → 靶向改进 | V109: 智能布置层（精准匹配作业） 智能批改层（AI自动批改） 智能分析层（数据驱动分析） 智能管理层（闭环管理） | W109: 企业产品以"智能作业管理工具"为主，学校通过校本化规则实现教学适配，整体处于规模化应用阶段。 | X109: 首创“三维分层+智能匹配”作业体系，打破传统作业批改瓶颈，提升作业批改效率与质量，形成可复制的智能作业应用模式。 | Y109: 未提及 | Z109: 希沃作业学情采集分析系统 | AA109: 广州视源电子科技股份有限公司 | AB109: 四川省 | AD109: =VLOOKUP($K109,「工具标准名」映射表!$B:$I,3,0) -> 希沃作业学情采集分析系统 | AE109: =VLOOKUP($K109,「工具标准名」映射表!$B:$I,4,0) -> 教育数据层 | AF109: =VLOOKUP($K109,「工具标准名」映射表!$B:$I,5,0) -> 教育数据层（行为数据） | AG109: =VLOOKUP($K109,「工具标准名」映射表!$B:$I,6,0) -> 软件工具 | AH109: =VLOOKUP($K109,「工具标准名」映射表!$B:$I,7,0) -> AI智能体 | AI109: =VLOOKUP($K109,「工具标准名」映射表!$B:$I,8,0) -> 否 | AJ109: 四川省
A110: 第69号案例_成都信息工程大学红樱实验学校+基于智能批阅系统的作业设计与批改实践申报书.docx | B110: 46056.471 | C110: 69 | D110: 基于智能批阅系统的作业设计与批改实践 | E110: 成都 | F110: 小学 | G110: 已在我校1-6年级全面应用，覆盖57个班级、近3000名学生及80余名教师，运行稳定且成效显著。 | H110: 通过三维分层作业设计与智能批阅系统的结合，提升作业批改效率与质量，实现个性化教学与精准反馈。 | I110: 精准设计 → 智能批阅 → 数据采集 → 动态分析 → 靶向改进 | J110: ["智能作业批阅", "数据分析", "个性化作业设计", "教育数据挖掘", "人工智能算法"] | K110: 判判智能批阅系统 | L110: 未点名企业 | M110: FALSE | N110: 软件平台 | O110: 平台型综合系统 | P110: 文档中描述“判判智能批阅系统支持客观题与主观题自动批改。” | Q110: 助教 | R110: 作业管理 | S110: 智育 | T110: 学生：作业适配性好，知识点掌握率提升；教师：减轻批改负担，数据实用；学校：推动教育教学评价的科学、多元与个性化。 | U110: 精准设计 → 智能批阅 → 数据采集 → 动态分析 → 靶向改进 | V110: 智能布置层（精准匹配作业） 智能批改层（AI自动批改） 智能分析层（数据驱动分析） 智能管理层（闭环管理） | W110: 企业产品以"智能作业管理工具"为主，学校通过校本化规则实现教学适配，整体处于规模化应用阶段。 | X110: 首创“三维分层+智能匹配”作业体系，打破传统作业批改瓶颈，提升作业批改效率与质量，形成可复制的智能作业应用模式。 | Y110: 未提及 | Z110: 判判智能批阅系统 | AA110: 0 | AB110: 四川省 | AD110: =VLOOKUP($K110,「工具标准名」映射表!$B:$I,3,0) -> 判判智能批阅系统 | AE110: =VLOOKUP($K110,「工具标准名」映射表!$B:$I,4,0) -> 功能应用层 | AF110: =VLOOKUP($K110,「工具标准名」映射表!$B:$I,5,0) -> 功能应用（Web 教学平台（SaaS）） | AG110: =VLOOKUP($K110,「工具标准名」映射表!$B:$I,6,0) -> 软件工具 | AH110: =VLOOKUP($K110,「工具标准名」映射表!$B:$I,7,0) -> AI智能体 | AI110: =VLOOKUP($K110,「工具标准名」映射表!$B:$I,8,0) -> 否 | AJ110: 四川省
A111: 第70号案例_大同市云州区苏家寨中心学校曹宇香基于AI的小学数学精准化学习与辅助系统案例申报书.docx | B111: 46056.471 | C111: 70 | D111: 作业设批辅助官——基于AI的小学数学精准化学习与辅导系统 | E111: 大同市云州区 | F111: 小学 | G111: 企业产品以“学习支持工具”为主，学校多通过校本化规则实现教学适配，整体处于规模化应用初期 | H111: 通过AI动态组卷与个性化作业设计，提升学生学习兴趣与效率，减轻教师批改负担，实现精准教学。 | I111: 智能作业设计 → 学生完成与提交 → AI自动批改与即时反馈 → 学情分析与教师干预 | J111: ["知识图谱", "图像识别技术", "大数据分析技术", "智能推荐算法"] | K111: 智能作业设计与批改系统 | L111: 未点名企业 | M111: FALSE | N111: 软件平台 | O111: 平台型综合系统 | P111: 文档中提到“构建一个‘以学生为中心’的个性化作业闭环” | Q111: 助学 | R111: 智能辅导系统 | S111: 智育 | T111: 学生：从“被动订正”到“主动突破”，减少无效刷题，提升学习效率与数学思维；教师：减轻批改与分析负担，实现精准教学；学校：推动小学数学从“统一教学”向“个性化学习”转型，体现“以生为本”的教育理念。 | U111: 智能作业设计 → 学生完成与提交 → AI自动批改与即时反馈 → 学情分析与教师干预 | V111: 知识图谱（构建小学数学知识体系，明确知识点间的关联与层级） 图像识别技术（理解并识别学生的手写答案，实现错题自动录入与题目信息提取） 大数据分析技术（对作业数据进行深度分析，形成学情画像，构建错题知识库） 智能推荐算法（基于学生学情，精准推送讲解内容与变式练习） | W111: 企业产品以“学习支持工具”为主，整体处于规模化应用初期，学校通过校本化规则实现教学适配。 | X111: 实现“动态设计、即时批改、精准反馈、数据驱动”的新型学习模式，为教师减负、为学生增效，推动个性化学习。 | Y111: 数学 | Z111: 智能作业设计与批改系统 | AA111: 0 | AB111: 山西省 | AD111: =VLOOKUP($K111,「工具标准名」映射表!$B:$I,3,0) -> 智能作业设计与批改系统 | AE111: =VLOOKUP($K111,「工具标准名」映射表!$B:$I,4,0) -> 功能应用层 | AF111: =VLOOKUP($K111,「工具标准名」映射表!$B:$I,5,0) -> 功能应用（校级 / 区域级系统） | AG111: =VLOOKUP($K111,「工具标准名」映射表!$B:$I,6,0) -> 软件工具 | AH111: =VLOOKUP($K111,「工具标准名」映射表!$B:$I,7,0) -> AI智能体 | AI111: =VLOOKUP($K111,「工具标准名」映射表!$B:$I,8,0) -> 否 | AJ111: 山西省
A112: 第71号案例_海盐高级中学+杨晶“人工智能+基础教育”典型应用场景案例申报书.docx | B112: 46056.471 | C112: 71 | D112: AI+教师协同的高中数学单元分层作业创新实践案例 | E112: 海盐 | F112: 高中 | G112: 案例构建了AI与教师协同的分层作业设计模式，推动了因材施教的落地，具有可复制的推广价值。 | H112: 通过AI与教师的协同，形成了高效的分层作业设计流程，解决了传统作业设计中的效率低和适配差的问题。 | I112: AI主导课标分析与作业生成 → 教师审核与优化 → 动态反馈与迭代 | J112: ["课程标准分析", "作业生成算法", "学情分析", "个性化作业设计", "动态反馈机制"] | K112: AI作业生成系统 | L112: 未点名企业 | M112: FALSE | N112: 软件平台 | O112: 平台型综合系统 | P112: 文档中提到“AI根据‘知识巩固—理解深化—能力进阶’的递进逻辑，设计以学生核心素养发展为核心的高中数学‘三阶递进式’单元作业初稿。” | Q112: 助教 | R112: 作业管理 | S112: 智育 | T112: 学生：获得匹配自身能力层次的作业，提升学习信心；教师：减轻作业设计与批改负担，专注于个性化辅导；学校：推动因材施教落地，提升教学效果。 | U112: AI主导课标分析 → 教师审核大概念 → AI建模核心素养水平 → AI拆解单元目标 → AI设计分层作业 → AI分析学情反馈 | V112: 数据采集层（学生作业数据采集与分析） 行为识别层（学生学习状态与能力识别） 画像诊断层（个性化学情报告生成） 个性化学习层（动态调整作业内容） | W112: 企业产品以“学习支持工具”为主，学校多通过校本化规则实现教学适配，整体处于规模化应用初期。 | X112: 构建了“AI做基础支撑+教师做精准把控”的分层作业设计模式，形成了“课标分析-目标分解-作业生成-学情反馈-作业优化”的协同闭环，提升了作业设计效率与精准适配性。 | Y112: 数学 | Z112: AI作业生成系统 | AA112: 0 | AB112: 浙江省 | AD112: =VLOOKUP($K112,「工具标准名」映射表!$B:$I,3,0) -> AI作业生成系统 | AE112: =VLOOKUP($K112,「工具标准名」映射表!$B:$I,4,0) -> 功能应用层 | AF112: =VLOOKUP($K112,「工具标准名」映射表!$B:$I,5,0) -> 功能应用（教学辅助工具） | AG112: =VLOOKUP($K112,「工具标准名」映射表!$B:$I,6,0) -> 软件工具 | AH112: =VLOOKUP($K112,「工具标准名」映射表!$B:$I,7,0) -> 大语言模型 | AI112: =VLOOKUP($K112,「工具标准名」映射表!$B:$I,8,0) -> 是 | AJ112: 浙江省
A113: 第73号案例_成都七中华溪AI助力高中英语数字化教学效能提升的实践研究.docx | B113: 46056.472 | C113: 73 | D113: AI助力高中英语数字化教学效能提升的实践研究 | E113: 成都 | F113: 高中 | G113: 案例处于推广阶段，已在多所学校试点应用，形成可复制的教学模型。 | H113: 通过AI技术实现精准批改与个性化反馈，显著提升教师工作效率与学生写作能力，形成闭环的教学管理体系。 | I113: 精准批改 → 即时反馈 → 数据驱动 → 个性化辅导 | J113: ["自然语言处理", "智能数据分析", "OCR技术", "个性化学习路径生成", "多维度分析报告"] | K113: 天学网AI智能批改平台 | L113: 未点名企业 | M113: FALSE | N113: 软件平台 | O113: Web 教学平台（SaaS） | P113: 文档中提到“通过天学网AI智能批改模型实现以下核心功能” | Q113: 助学 | R113: 智能辅导系统 | S113: 智育 | T113: 学生：写作能力提升，反馈效率提高；教师：批改效率提升，教学决策精准；学校：形成可复制的AI+英语教学模型。 | U113: 精准批改 → 即时反馈 → 数据驱动 → 个性化辅导 | V113: 数据采集层（智能批改模型、OCR技术） 行为识别层（语法、词汇、句式及内容逻辑错误检测） 画像诊断层（个性化学习路径生成、错误批改建议） 个性化学习层（实时反馈与修改建议） | W113: 企业产品以'学习支持工具'为主，学校多通过校本化规则实现教学适配，整体处于规模化应用初期。 | X113: 闭环设计结合智能批改与个性化提升建议，数据驱动精准教学，提升教师工作效率与学生写作能力。 | Y113: 英语 | Z113: 天学网AI智能批改平台 | AA113: 0 | AB113: 四川省 | AD113: =VLOOKUP($K113,「工具标准名」映射表!$B:$I,3,0) -> 天学网AI智能批改平台 | AE113: =VLOOKUP($K113,「工具标准名」映射表!$B:$I,4,0) -> 功能应用层 | AF113: =VLOOKUP($K113,「工具标准名」映射表!$B:$I,5,0) -> 功能应用（教学辅助工具） | AG113: =VLOOKUP($K113,「工具标准名」映射表!$B:$I,6,0) -> 软件工具 | AH113: =VLOOKUP($K113,「工具标准名」映射表!$B:$I,7,0) -> AI智能体 | AI113: =VLOOKUP($K113,「工具标准名」映射表!$B:$I,8,0) -> 否 | AJ113: 四川省
A114: 第74号案例_姜海达《表现性评价视域下AI导航的高中作文精准教学实践》申报书10.20.pdf | B114: 46056.472 | C114: 74 | D114: 表现性评价视域下AI导航的高中作文精准教学实践 | E114: 北京市通州区 | F114: 高中 | G114: 已在校内多个班级成功实践，具备极强推广性 | H114: 通过表现性评价理论构建的智能教学模式，有效提升了学生作文修改效率和教师批改负担，形成可复制的实践范式。 | I114: 标准解构 → 人机协同 → 动态分层 | J114: ["表现性评价", "人工智能技术", "动态分层指导", "标准化教学设计", "智能辅助修改"] | K114: Deepseek | L114: 未点名企业 | M114: FALSE | N114: 软件平台 | O114: Web 教学平台（SaaS） | P114: 文档中提到使用Deepseek进行作文教学的智能辅助修改 | Q114: 助学 | R114: 智能作业设计与批改 | S114: 智育 | T114: 学生：作文修改效率提升约3倍，从‘辞藻堆砌’转向‘思维生长’；教师：批改负担减轻约50%，从‘疲劳驾驶’转变为‘智慧导航’；学校：形成可复制、可推广的实践范式。 | U114: 标准解构 → 人机协同 → 动态分层 | V114: 标准翻译层（评分维度-AI诊断关键词-典型指令模板映射库） 四步法教学模型层（问病-开方-试药-自检） 动态分层策略层（针对不同文学生实施差异化指导） | W114: 企业产品以‘智能作业设计与批改’为主，已在校内多个班级成功实践，具备极强推广性。 | X114: 构建了‘标准驱动·人机协同·动态分层’的智能教学新范式，利用通用大模型Deepseek实现了教学过程的深度变革，确保技术服务于思维发展而非替代思考。 | Y114: 语文 | Z114: DeepSeek 大模型 | AA114: 杭州深度求索人工智能基础技术研究有限公司 | AB114: 北京市 | AD114: =VLOOKUP($K114,「工具标准名」映射表!$B:$I,3,0) -> DeepSeek 大模型 | AE114: =VLOOKUP($K114,「工具标准名」映射表!$B:$I,4,0) -> 功能应用层 | AF114: =VLOOKUP($K114,「工具标准名」映射表!$B:$I,5,0) -> 功能应用（教学辅助工具） | AG114: =VLOOKUP($K114,「工具标准名」映射表!$B:$I,6,0) -> 软件工具 | AH114: =VLOOKUP($K114,「工具标准名」映射表!$B:$I,7,0) -> AI智能体 | AI114: =VLOOKUP($K114,「工具标准名」映射表!$B:$I,8,0) -> 否 | AJ114: 北京市
A115: 第74号案例_姜海达《表现性评价视域下AI导航的高中作文精准教学实践》申报书10.20.pdf | B115: 46056.472 | C115: 74 | D115: 表现性评价视域下AI导航的高中作文精准教学实践 | E115: 北京市通州区 | F115: 高中 | G115: 已在校内多个班级成功实践，具备极强推广性 | H115: 通过表现性评价理论构建的智能教学模式，有效提升了学生作文修改效率和教师批改负担，形成可复制的实践范式。 | I115: 标准解构 → 人机协同 → 动态分层 | J115: ["表现性评价", "人工智能技术", "动态分层指导", "标准化教学设计", "智能辅助修改"] | K115: 豆包 | L115: 未点名企业 | M115: FALSE | N115: 软件平台 | O115: Web 教学平台（SaaS） | P115: 文档中提到使用豆包进行作文教学的智能辅助修改 | Q115: 助学 | R115: 智能作业设计与批改 | S115: 智育 | T115: 学生：作文修改效率提升约3倍，从‘辞藻堆砌’转向‘思维生长’；教师：批改负担减轻约50%，从‘疲劳驾驶’转变为‘智慧导航’；学校：形成可复制、可推广的实践范式。 | U115: 标准解构 → 人机协同 → 动态分层 | V115: 标准翻译层（评分维度-AI诊断关键词-典型指令模板映射库） 四步法教学模型层（问病-开方-试药-自检） 动态分层策略层（针对不同文学生实施差异化指导） | W115: 企业产品以‘智能作业设计与批改’为主，已在校内多个班级成功实践，具备极强推广性。 | X115: 构建了‘标准驱动·人机协同·动态分层’的智能教学新范式，利用通用大模型Deepseek实现了教学过程的深度变革，确保技术服务于思维发展而非替代思考。 | Y115: 语文 | Z115: 豆包 | AA115: 北京春田知韵科技有限公司 | AB115: 北京市 | AD115: =VLOOKUP($K115,「工具标准名」映射表!$B:$I,3,0) -> 豆包 | AE115: =VLOOKUP($K115,「工具标准名」映射表!$B:$I,4,0) -> 功能应用层 | AF115: =VLOOKUP($K115,「工具标准名」映射表!$B:$I,5,0) -> 功能应用（教学辅助工具） | AG115: =VLOOKUP($K115,「工具标准名」映射表!$B:$I,6,0) -> 软件工具 | AH115: =VLOOKUP($K115,「工具标准名」映射表!$B:$I,7,0) -> 其他 | AI115: =VLOOKUP($K115,「工具标准名」映射表!$B:$I,8,0) -> 否 | AJ115: 北京市
A116: 第74号案例_姜海达《表现性评价视域下AI导航的高中作文精准教学实践》申报书10.20.pdf | B116: 46056.472 | C116: 74 | D116: 表现性评价视域下AI导航的高中作文精准教学实践 | E116: 北京市通州区 | F116: 高中 | G116: 已在校内多个班级成功实践，具备极强推广性 | H116: 通过表现性评价理论构建的智能教学模式，有效提升了学生作文修改效率和教师批改负担，形成可复制的实践范式。 | I116: 标准解构 → 人机协同 → 动态分层 | J116: ["表现性评价", "人工智能技术", "动态分层指导", "标准化教学设计", "智能辅助修改"] | K116: 文心一言 | L116: 未点名企业 | M116: FALSE | N116: 软件平台 | O116: Web 教学平台（SaaS） | P116: 文档中提到使用文心一言进行作文教学的智能辅助修改 | Q116: 助学 | R116: 智能作业设计与批改 | S116: 智育 | T116: 学生：作文修改效率提升约3倍，从‘辞藻堆砌’转向‘思维生长’；教师：批改负担减轻约50%，从‘疲劳驾驶’转变为‘智慧导航’；学校：形成可复制、可推广的实践范式。 | U116: 标准解构 → 人机协同 → 动态分层 | V116: 标准翻译层（评分维度-AI诊断关键词-典型指令模板映射库） 四步法教学模型层（问病-开方-试药-自检） 动态分层策略层（针对不同文学生实施差异化指导） | W116: 企业产品以‘智能作业设计与批改’为主，已在校内多个班级成功实践，具备极强推广性。 | X116: 构建了‘标准驱动·人机协同·动态分层’的智能教学新范式，利用通用大模型Deepseek实现了教学过程的深度变革，确保技术服务于思维发展而非替代思考。 | Y116: 语文 | Z116: 文心大模型 | AA116: 百度集团 | AB116: 北京市 | AD116: =VLOOKUP($K116,「工具标准名」映射表!$B:$I,3,0) -> 文心一言 | AE116: =VLOOKUP($K116,「工具标准名」映射表!$B:$I,4,0) -> 技术层 | AF116: =VLOOKUP($K116,「工具标准名」映射表!$B:$I,5,0) -> 技术层（通用大模型） | AG116: =VLOOKUP($K116,「工具标准名」映射表!$B:$I,6,0) -> 软件工具 | AH116: =VLOOKUP($K116,「工具标准名」映射表!$B:$I,7,0) -> 大语言模型 | AI116: =VLOOKUP($K116,「工具标准名」映射表!$B:$I,8,0) -> 是 | AJ116: 北京市
...

Sheet 省份产品
A1: 文件名 | B1: 工具标准名 | C1: 省份
A2: 第01号案例_1温州市新田园小学 叶诗婧《数“算”生“动”：AI赋能下运算律教学的新样态》.pdf | B2: AI学习机 | C2: 浙江省
A3: 第01号案例_1温州市新田园小学 叶诗婧《数“算”生“动”：AI赋能下运算律教学的新样态》.pdf | B3: AI语音互动平台 | C3: 浙江省
A4: 第01号案例_1温州市新田园小学 叶诗婧《数“算”生“动”：AI赋能下运算律教学的新样态》.pdf | B4: 动态点子图生成系统 | C4: 浙江省
A5: 第02号案例_2温州市新田园小学朱朝炜《三维联动：人工智能视域下小学足球运球游戏设计与研究》.pdf | B5: 智慧手环 | C5: 浙江省
A6: 第02号案例_2温州市新田园小学朱朝炜《三维联动：人工智能视域下小学足球运球游戏设计与研究》.pdf | B6: AI分析系统 | C6: 浙江省
A7: 第03号案例_3【案例】从赋能到内生：智能评测驱动“教学评一致”的机理与路径探寻.pdf | B7: 易点慧AI | C7: 浙江省
A8: 第04号案例_AI赋能地理课堂——七大洲轮廓记忆消消乐申报书.docx | B8: 七大洲速记挑战 | C8: 重庆市
A9: 第07号案例_案例申报书.docx | B9: DeepSeek 大模型 | C9: 重庆市
A10: 第07号案例_案例申报书.docx | B10: 可灵AI | C10: 重庆市
A11: 第07号案例_案例申报书.docx | B11: 豆包 | C11: 重庆市
A12: 第08号案例_8川外科中-《AI智教分析：教学相长的协同创新》案例.docx | B12: 未来教室 | C12: 重庆市
... A100: 第62号案例_（冯怡）人工智能+基础教育案例.docx | B100: AI智批系统 | C100: 浙江省
A101: 第63号案例_“人工智能+基础教育”典型案例申报表.pdf | B101: #N/A | C101: 未提及
A102: 第64号案例_人工智能+作业批改 典型应用场景案例.docx | B102: 蜜蜂家校 | C102: 河北省
A103: 第65号案例_成都七中初中附属小学+数智赋能小学作业治理：精准画像与个性化.docx | B103: AI学情分析平台 | C103: 四川省
A104: 第65号案例_成都七中初中附属小学+数智赋能小学作业治理：精准画像与个性化.docx | B104: AI点阵笔 | C104: 四川省
A105: 第66号案例_成都东部新区第七中学校（成都七中东部学校）+从即时诊断到动态干预：基于智慧纸笔的智能批改与个性化辅导实践 申报书.pdf | B105: 智慧纸笔 | C105: 四川省
A106: 第67号案例_成都石室东部新区实验学校-“人工智能+基础教育”典型应用案例申报书.pdf | B106: 数智作业系统 | C106: 四川省
A107: 第67号案例_成都石室东部新区实验学校-“人工智能+基础教育”典型应用案例申报书.pdf | B107: 精准教学大数据系统 | C107: 四川省
A108: 第68号案例_成都市实验小学+趣味化·个性化·智能化：“天天跳绳”App重塑小学体育作业新样态.docx | B108: 天天跳绳App | C108: 四川省
A109: 第69号案例_成都信息工程大学红樱实验学校+基于智能批阅系统的作业设计与批改实践申报书.docx | B109: 希沃作业学情采集分析系统 | C109: 四川省
A110: 第69号案例_成都信息工程大学红樱实验学校+基于智能批阅系统的作业设计与批改实践申报书.docx | B110: 判判智能批阅系统 | C110: 四川省
A111: 第70号案例_大同市云州区苏家寨中心学校曹宇香基于AI的小学数学精准化学习与辅助系统案例申报书.docx | B111: 智能作业设计与批改系统 | C111: 山西省
A112: 第71号案例_海盐高级中学+杨晶“人工智能+基础教育”典型应用场景案例申报书.docx | B112: AI作业生成系统 | C112: 浙江省
A113: 第73号案例_成都七中华溪AI助力高中英语数字化教学效能提升的实践研究.docx | B113: 天学网AI智能批改平台 | C113: 四川省
... A182: 第110号案例_人工智能+基础教育 应用案例 AI 慧眼识出入 无感智护校园安 申报书.docx | B182: 智慧校园请假系统 | C182: 陕西省
A183: 第112号案例_典型应用案例申报书-石外.docx | B183: #N/A | C183: 河北省
A184: 第113号案例_《人工智能+基础教育》全域校园人机伴生智慧管理模式申报书.pdf | B184: 钉钉AI | C184: 未提及
A185: 第113号案例_《人工智能+基础教育》全域校园人机伴生智慧管理模式申报书.pdf | B185: 通义千问大模型 | C185: 未提及
A186: 第114号案例_“人工智能+基础教育”典型应用场景案例申报书.pdf | B186: 红色智慧行政助理 | C186: 重庆市
A187: 第114号案例_“人工智能+基础教育”典型应用场景案例申报书.pdf | B187: 百度飞桨PaddlePaddle | C187: 重庆市
A188: 第115号案例_附件.docx | B188: #N/A | C188: 浙江省
A189: 第116号案例_山东师大附中案例申报书（智慧物联，用AI提升高中学校资产管理实效——以山东师范大学附属中学为例）.docx | B189: 锦大模型 | C189: 山东省
A190: 第116号案例_山东师大附中案例申报书（智慧物联，用AI提升高中学校资产管理实效——以山东师范大学附属中学为例）.docx | B190: 资产管理平台 | C190: 山东省
A191: 第117号案例_1.“人工智能+基础教育”典型应用场景案例申报书.docx | B191: 豆包 | C191: 重庆市
A192: 第117号案例_1.“人工智能+基础教育”典型应用场景案例申报书.docx | B192: 通义千问大模型 | C192: 重庆市
A193: 第117号案例_1.“人工智能+基础教育”典型应用场景案例申报书.docx | B193: 文心大模型 | C193: 重庆市
A194: 第117号案例_1.“人工智能+基础教育”典型应用场景案例申报书.docx | B194: 可灵AI | C194: 重庆市
A195: 第117号案例_1.“人工智能+基础教育”典型应用场景案例申报书.docx | B195: 即梦AI | C195: 重庆市
A196: 第118号案例_118东营市河口区河口街道中心小学人工智能 + 基础教育”案例.docx | B196: AI学情分析平台 | C196: 山东省
A197: 第118号案例_118东营市河口区河口街道中心小学人工智能 + 基础教育”案例.docx | B197: AI互动工具 | C197: 山东省
A198: 第118号案例_118东营市河口区河口街道中心小学人工智能 + 基础教育”案例.docx | B198: 智能作业系统 | C198: 山东省
A199: 第118号案例_118东营市河口区河口街道中心小学人工智能 + 基础教育”案例.docx | B199: 智慧校园管理平台 | C199: 山东省
A200: 第118号案例_118东营市河口区河口街道中心小学人工智能 + 基础教育”案例.docx | B200: AI教学质量分析系统 | C200: 山东省
... A219: 第127号案例_申报书.docx | B219: DeepSeek 大模型 | C219: 河北省
A220: 第130号案例_AI双向赋能实验课堂.pdf | B220: #N/A | C220: 山东省
A221: 第131号案例_海盐县实验小学教育集团姚怡然+“人工智能+基础教育”典型应用场景案例申报书 .docx | B221: 央馆领航AI | C221: 浙江省
A222: 第132号案例_附件1.“人工智能+基础教育”典型应用场景案例申报书（海盐县武原中学教育集团沈利娟）.docx | B222: AI课堂顾问 | C222: 浙江省
A223: 第133号案例_1.“人工智能+基础教育”典型应.docx | B223: 豆包 | C223: 黑龙江省
A224: 第133号案例_1.“人工智能+基础教育”典型应.docx | B224: 即梦AI | C224: 黑龙江省
A225: 第134号案例_关于征集“人工智能+基础教育”典型应用场景案例的通知.docx | B225: 减数分裂模拟器 | C225: 辽宁省
A226: 第135号案例_“人工智能+基础教育”典型应用场景案例申报书.docx | B226: DeepSeek 大模型 | C226: 未提及
A227: 第136号案例_AI赋能,穿越千年——沉浸式“唐三彩”博物馆虚拟研学实践-----刘巧.宋婷婷.docx | B227: 小云雀 | C227: 重庆市
A228: 第137号案例_申报书+陆高原+AI 助力高中化学实验教学创新-氢氧化亚铁的制备” 实践案例.pdf | B228: 豆包 | C228: 上海市
A229: 第137号案例_申报书+陆高原+AI 助力高中化学实验教学创新-氢氧化亚铁的制备” 实践案例.pdf | B229: 高中化学实验方案AI评估模块 | C229: 上海市
A230: 第137号案例_申报书+陆高原+AI 助力高中化学实验教学创新-氢氧化亚铁的制备” 实践案例.pdf | B230: 三个助手 | C230: 上海市
A231: 第138号案例_人工智能赋能高中信息技术教学——基于交互式网页的教学练一体化实践案例（徐雪婷）.pdf | B231: DeepSeek 大模型 | C231: 上海市
A232: 第139号案例_1.上外松外-温胜利-探秘AI理解语言的奥秘.pdf | B232: 腾讯青少年人工智能教育平台 | C232: 上海市
... A334: 第193号案例_曹杨二中东校-郭莉+AI循证赋能初中道德与法治政治认同素养评价的实践探索.docx | B334: VR/AR技术 | C334: 上海市
A335: 第194号案例_《智能交互·数据驱动·精准赋能：校园智慧体育应用场景构建》案例申报书.docx | B335: #N/A | C335: 未提及
A336: 第195号案例_重庆市聚奎中学校 案例申报书.docx | B336: 生成式教学智能体 | C336: 重庆市
A337: 第195号案例_重庆市聚奎中学校 案例申报书.docx | B337: 扣子AI | C337: 重庆市
A338: 第196号案例_196北京实验学校附属中学 王永洪 人工智能终端小猿学练机教学应用与过程性评价实践研究.docx | B338: 小猿AI | C338: 北京市
A339: 第198号案例_198和田洛浦县三中+郑巧灵+ 智能学情诊断与个性化辅导25.10.23.docx | B339: 智能学情诊断与个性化辅导系统 | C339: 新疆维吾尔自治区
A340: 第199号案例_199徽山县韩庄镇中心小学-数据驱动下的农村小学精准教学与个性化辅导实践案例.docx | B340: AI作业本 | C340: 山东省
A341: 第199号案例_199徽山县韩庄镇中心小学-数据驱动下的农村小学精准教学与个性化辅导实践案例.docx | B341: 学情快评 | C341: 山东省
A342: 第200号案例_200济南实验高级中学.“人工智能+基础教育”典型应.docx | B342: 麻吉星教学系统 | C342: 山东省
A343: 第200号案例_200济南实验高级中学.“人工智能+基础教育”典型应.docx | B343: AI错题本平台 | C343: 山东省
A344: 第201号案例_201山东师范大学附属中学-李成金-“人工智能+基础教育”典型案例申报书.docx | B344: 辅立码课平台 | C344: 山东省
A345: 第202号案例_202申报书_“设计机车动力系统”课时案例_“自制热力机车竞赛”AI-PBL单元教学.pdf | B345: DeepSeek 大模型 | C345: 重庆市
A346: 第202号案例_202申报书_“设计机车动力系统”课时案例_“自制热力机车竞赛”AI-PBL单元教学.pdf | B346: 豆包 | C346: 重庆市
A347: 第202号案例_202申报书_“设计机车动力系统”课时案例_“自制热力机车竞赛”AI-PBL单元教学.pdf | B347: Padlet | C347: 重庆市
... A445: 第245号案例_（俞鹰）“人工智能+基础教育”典型应用场景案例申报书+案例.docx | B445: AI星火 | C445: 浙江省
A446: 第246号案例_附件1.“人工智能+基础教育”典型应用场景案例申报书.docx | B446: #N/A | C446: 浙江省
A447: 第247号案例_（苏贤芳）人工智能+基础教育”典型应用场景案例申报书.docx | B447: AI情境创设工具 | C447: 浙江省
A448: 第247号案例_（苏贤芳）人工智能+基础教育”典型应用场景案例申报书.docx | B448: 数字人 | C448: 浙江省
A449: 第247号案例_（苏贤芳）人工智能+基础教育”典型应用场景案例申报书.docx | B449: AI智能反馈系统 | C449: 浙江省
A450: 第248号案例_包头市田家炳中学+云多+AI学助力高中物理力学三大观点教学案例.pdf | B450: 科大讯飞智慧教育平台 | C450: 内蒙古自治区
A451: 第248号案例_包头市田家炳中学+云多+AI学助力高中物理力学三大观点教学案例.pdf | B451: 即梦AI | C451: 内蒙古自治区
A452: 第248号案例_包头市田家炳中学+云多+AI学助力高中物理力学三大观点教学案例.pdf | B452: DeepSeek 大模型 | C452: 内蒙古自治区
A453: 第248号案例_包头市田家炳中学+云多+AI学助力高中物理力学三大观点教学案例.pdf | B453: 剪辑 | C453: 内蒙古自治区
A454: 第249号案例_AI 破界・丈量亿度：《一亿有多大》创新实践案例（闻爱丽）.docx | B454: 豆包 | C454: 浙江省
A455: 第251号案例_附件1人工智能基础教育典型应用案例申报书.docx | B455: AI课堂循证系统 | C455: 上海市
A456: 第252号案例_范佳慧 附件1.“人工智能+基础教育”典型应用场景案例申报书.pdf | B456: AI听说课堂 | C456: 浙江省
A457: 第252号案例_范佳慧 附件1.“人工智能+基础教育”典型应用场景案例申报书.pdf | B457: 智言语音测评 | C457: 浙江省
A458: 第252号案例_范佳慧 附件1.“人工智能+基础教育”典型应用场景案例申报书.pdf | B458: 豆包 | C458: 浙江省
... A592: 第313号案例_“人工智能+基础教育”典型应用场景案例申报书（成都市石笋街小学校）.pdf | B592: Hiteach5平台 | C592: 四川省
A593: 第314号案例_关于征集“人工智能_基础教育”典型应用场景案例的通知.docx | B593: #N/A | C593: 四川省
A594: 第315号案例_成都市双林小学—申报书.pdf | B594: 希沃AI | C594: 四川省
A595: 第315号案例_成都市双林小学—申报书.pdf | B595: 国家智慧教育平台 | C595: 四川省
A596: 第316号案例_“人工智能+基础教育”典型应用场景案例申报书（棠湖小学）.docx | B596: 棠棠教育智能体 | C596: 四川省
A597: 第317号案例_成都市双庆小学校+AI赋能与文化探究融合的教学新模式——以《天府之国 锦城成都》跨学科案例为例.docx | B597: 领航社 AI助手 | C597: 四川省
A598: 第317号案例_成都市双庆小学校+AI赋能与文化探究融合的教学新模式——以《天府之国 锦城成都》跨学科案例为例.docx | B598: 智慧教室环境 | C598: 四川省
A599: 第318号案例_成都市天涯石小学 郭娟娟、李聪、夏莉“人工智能+基础教育”典型应用场景案例申报书.pdf | B599: AI课堂智慧分析平台 | C599: 四川省
A600: 第319号案例_”人工智能+基础教育“典型应用场景案例：为了学生健康全面发展——“学练测评”全流程智慧体育教学模式建构与实践探索2025.10.26 .docx | B600: 智汇云智慧体育平台 | C600: 四川省
A601: 第319号案例_”人工智能+基础教育“典型应用场景案例：为了学生健康全面发展——“学练测评”全流程智慧体育教学模式建构与实践探索2025.10.26 .docx | B601: 智慧体育仓 | C601: 四川省
A602: 第319号案例_”人工智能+基础教育“典型应用场景案例：为了学生健康全面发展——“学练测评”全流程智慧体育教学模式建构与实践探索2025.10.26 .docx | B602: 智慧体育小程序 | C602: 四川省
A603: 第320号案例_“人工智能+基础教育”典型应用场景案例申报书.docx | B603: #N/A | C603: 四川省
A604: 第321号案例_2.“人工智能+基础教育”典型应用场景案例申报书.docx | B604: 文心大模型 | C604: 四川省
...

Sheet Sheet1
A1: 文件名 | B1: 处理时间 | C1: 案例编号 | D1: 案例名称 | E1: 学段 | F1: 学科 | G1: 地区 | H1: 应用场景（一级） | I1: 应用场景（二级） | J1: 培养方向 | K1: 潜在成效 | L1: 关键技术路径 | M1: 技术要素 | N1: 典型工具与平台形态 | O1: 产业应用现状 | P1: 优势和创新点
A2: 第01号案例_1温州市新田园小学 叶诗婧《数“算”生“动”：AI赋能下运算律教学的新样态》.pdf | B2: 46042.644 | C2: 1 | D2: 数“算”生“动”：AI赋能下运算律教学的新样态 | E2: 小学 | F2: 数学 | G2: 温州市 | H2: 助学 | I2: 智能辅导系统 | J2: 智育 | K2: 学生：深化算理理解、提升表达与推理能力；教师：实现精准诊断与即时干预；学校：形成可复制的“AI+概念教学”范式 | L2: 学习行为采集 → 学情诊断与画像生成 → 个性化反馈与辅导 → 学习改进 | M2: 数据采集层（多模态学习数据采集与融合） 画像诊断层（个性化画像生成、过程性反馈解释） 个性化学习层（即时生成反馈） | N2: 易点慧 AI 学伴 / AI 学习机（易点慧科技有限公司，案例01）；校本化智能辅导系统（未点名企业） | O2: 企业产品以“学习支持工具”为主，学校多通过校本化规则实现教学适配，整体处于规模化应用初期 | P2: AI点子图可视化 + AI说理，将抽象运算律转化为可操作模型，实现“理解—表达—诊断”闭环
A3: 第02号案例_2温州市新田园小学朱朝炜《三维联动：人工智能视域下小学足球运球游戏设计与研究》.pdf | B3: 46042.644 | C3: 2 | D3: 人工智能视域下“三维联动”小学足球运球游戏设计与实践 | E3: 小学 | F3: 体育 | G3: 温州市 | H3: 助学 | I3: 游戏化学习 | J3: 体育 | K3: 学生：提升足球运球技术、体能达标率与课堂参与度；教师：实现精准调控与动态反馈；学校：推动体育教学数字化转型与创新实践。 | L3: 数据采集 → 动态调整 → 多维反馈 | M3: 数据采集层（智慧手环、心率带、AI分析系统）；动态调整层（实时心率监测、体能负荷调控）；反馈层（多源数据融合的精准评价体系） | N3: 智慧体育设备（未点名企业） | O3: 企业产品以“智慧体育”与“游戏化教学”为主，整体处于数字化转型的探索阶段，具有较大的推广潜力。 | P3: 构建“技术-体能-应用”三维联动框架，通过游戏化教学实现技术、体能与应用的协同发展，填补传统教学中“数据缺失-调控盲目”的空白。
A4: 第03号案例_3【案例】从赋能到内生：智能评测驱动“教学评一致”的机理与路径探寻.pdf | B4: 46042.644 | C4: 3 | D4: 从赋能到内生：智能评测驱动下“教学评一致”的机理与路径探寻 | E4: 小学 | F4: 英语 | G4: 温州市 | H4: 助教 | I4: 智能学情诊断与个性化辅导 | J4: 智育 | K4: 学生：提升语音准确率、增强课堂参与度；教师：实现精准教学与动态调整；学校：形成可复制的教学评一致性模式 | L4: 数据采集 → 学情诊断与分析 → 个性化反馈与辅导 → 教学评一致性实现 | M4: 数据采集层（多模态数据采集与分析） 行为识别层（语音评测与互动分析） 画像诊断层（个性化学情报告生成） 智能策略层（动态教学调整与反馈） | N4: 易点慧语音型学习机（易点慧科技有限公司，案例03） | O4: 企业产品以“智能评测与个性化辅导工具”为主，已在多所小学规模化应用，整体处于推广阶段 | P4: 实现了智能评测从外部工具赋能到系统内生动力的转变，构建了“教学评一致性”的动态调整机制，提升了教学效率与学生语言应用能力
A5: 第04号案例_AI赋能地理课堂——七大洲轮廓记忆消消乐申报书.docx | B5: 46042.644 | C5: 4 | D5: AI赋能地理课堂——七大洲轮廓记忆消消乐 | E5: 初中 | F5: 地理 | G5: 重庆市璧山区 | H5: 助学 | I5: 智能辅导系统 | J5: 智育 | K5: 学生：提升知识点记忆效率，增强学习主动性；教师：提供即时反馈与个性化巩固工具；学校：探索AI与基础教育深度融合的实践思路。 | L5: 需求分析 → AI互动速记挑战网页开发 → 界面优化与课堂融合实践 → 持续反馈与迭代优化 | M5: 数据采集层（学生操作数据记录） 行为识别层（学习模式分析） 个性化学习层（即时反馈与挑战） | N5: AI互动速记挑战网页（未点名企业） | O5: 企业产品以“轻量化教育应用”为主，能够快速部署，适用于教育资源薄弱地区，整体处于推广阶段。 | P5: 将游戏化学习与地理知识结合，创新性地转变学习模式，提供零门槛的教育应用，促进学生主动学习与课堂互动。
C6: 5
C7: 6
A8: 第07号案例_案例申报书.docx | B8: 46042.644 | C8: 7 | D8: AI作为“认知协作者”赋能高中数学阅读精品课的跨学科构建与实践 | E8: 高中 | F8: 数学 | G8: 重庆市北碚区 | H8: 助教 | I8: 课堂管理 | J8: 智育 | K8: 学生：提升数学抽象能力、空间想象能力及科技伦理观念；教师：提高备课效率与课程质量；学校：推动基础教育资源的优质均衡发展。 | L8: 需求分析 → 课程设计 → AI赋能的设计流程与实践 → 课堂实施 → 课后评价与思辨引导 | M8: 数据采集层（AI工具DeepSeek用于内容整合与框架生成） 行为识别层（AI生成课堂任务与互动设计） 画像诊断层（AI生成思辨性问题） | N8: DeepSeek（未点名企业）；可灵AI（未点名企业）；豆包（未点名企业） | O8: 该模式具有极强的可复制性，适用于各学科、各学段的精品课、公开课及常规课的教学设计，整体处于推广应用阶段。 | P8: 将AI作为“认知协作者”嵌入课程开发全流程，促进教师角色转变为方案设计者与质量把控者，创新性地引入“数字人”模拟学生进行互动，提升课堂沉浸感与互动性。
A9: 第08号案例_8川外科中-《AI智教分析：教学相长的协同创新》案例.docx | B9: 46042.644 | C9: 8 | D9: AI智教分析：教学相长的协同创新 | E9: 未提及 | F9: 未提及 | G9: 重庆高新区 | H9: 助学 | I9: 智能辅导系统 | J9: 智育 | K9: 学生：实现个性化学习与成长；教师：提升教学质量与策略调整能力；学校：推动教育资源的合理配置与管理决策的科学化。 | L9: 数据采集与汇聚 → 学生与教师数字画像构建 → 个性化教学与精准评估 → 教学决策优化 | M9: 数据采集层（多源数据采集与融合） 画像诊断层（学生与教师数字画像生成、学习行为分析） 智能策略层（个性化学习路径推荐、教学策略调整） | N9: 未来教室（未点名企业）；壹教云系统（未点名企业） | O9: 企业产品以'学习支持工具'为主，学校通过智能化教学体系实现个性化教育，整体处于探索与应用阶段。 | P9: 构建数据驱动的智能教育生态，形成学生与教师之间的动态反馈闭环，实现个性化教学与精准评估的有效结合。
A10: 第09号案例_贾晓莹“人工智能 基础教育”典型应用场景案例(2).docx | B10: 46042.644 | C10: 9 | D10: 盛情邀约——海河中学130周年校庆邀请函设计 | E10: 初中 | F10: 美术 | G10: 天津 | H10: 助学 | I10: 情境式学习 | J10: 美育 | K10: 学生：掌握折叠式立体请柬的设计与制作技能，理解校史内涵，建立对母校的情感认同；教师：探索融合教学模式；学校：通过学生创作的邀请函传递校庆温度，增强师生、家校的凝聚力。 | L10: 需求分析 → 技术研发与个性化定制 → 应用优化 → 案例创新突破 | M10: 数据采集层（师生访谈、家校问卷） 行为识别层（教师与学生的互动分析） 智能策略层（个性化教学策略生成） 个性化学习层（动态推送适配资源） | N10: 梦AI软件（未点名企业）；豆包软件（未点名企业）；剪映AI扩图（未点名企业）；百度文心一格（未点名企业） | O10: 企业产品以“学习支持工具”为主，学校多通过校本化规则实现教学适配，整体处于规模化应用初期。 | P10: 突破传统单向灌输，构建双师协同与项目式学习，利用AI技术提升课堂参与度，增强学生对校史文化的理解与情感共鸣。
A11: 第10号案例_10人工智能赋能初中英语互动教学：破解课程参与难度，提升教学效能.docx | B11: 46042.644 | C11: 10 | D11: 人工智能赋能初中英语互动教学：破解课程参与难度，提升教学效能 | E11: 初中 | F11: 英语 | G11: 重庆市璧山区 | H11: 助学 | I11: 智能辅导系统 | J11: 智育 | K11: 学生：提升课堂参与度与英语能力；教师：实现实时反馈与精准教学；学校：形成可复制的AI教学模式 | L11: 需求分析 → 技术适配 → 应用优化 → 教学反馈 | M11: 数据采集层（实时语音评测、班级学情报告） 行为识别层（学生参与率与正确率统计） 个性化学习层（智能分层推送、个性化巩固练习） | N11: AI语音互动平台（科大讯飞智慧课堂，未点名企业） | O11: 企业产品以"学习支持工具"为主，学校多通过校本化规则实现教学适配，整体处于规模化应用初期 | P11: 重构低压力高互动教学模式，提升学生开口率与参与度，确保个性化教学落地，适合薄弱学校推广
A12: 第11号案例_申报书 隆昌市向阳路小学 黎恩旭 《用彩墨画鱼》.docx | B12: 46042.644 | C12: 11 | D12: AI赋能跨学科融合：小学美术《用彩墨画鱼》全流程智能教学实践 | E12: 小学 | F12: 美术 | G12: 隆昌市 | H12: 助学 | I12: 智能辅导系统 | J12: 美育 | K12: 学生：提升审美感知、艺术表现与文化理解能力；教师：实现跨学科教学的有效融合；学校：形成可复制的‘AI+学科’教学模式，推动基础教育智能化转型。 | L12: 需求分析 → 技术适配与定制 → 全流程应用实践与优化 → 应用迭代优化 | M12: 数据采集层（动态赋能模块、语音合成模块） 行为识别层（互动答题系统、知识认知场景化） 画像诊断层（虚拟展馆展示学生作品） | N12: 即梦AI（未标注）；希沃白板（未标注）；微信‘元美’小程序（未标注）；Photoshop（未标注）；剪映（未标注） | O12: 该案例已在本校四年级美术课堂落地，具备大规模推广的成熟条件与广阔前景，推动基础教育数字化转型。 | P12: 首创‘AI+IP主题+跨学科三维融合’教学范式，通过动态演示与虚拟展馆展示，打破学科壁垒，实现知识的可视化与互动化，提升学生的参与感与创作成就感。
A13: 第12号案例_12重庆市第八中学校+从“动手实践”到“真实探究”：生成式AI支持下中学科学课程的五轮迭代研究.pdf | B13: 46042.645 | C13: 12 | D13: 从“动手实践”到“真实探究”：生成式AI支持下中学科学课程的五轮迭代研究 | E13: 初中 | F13: 科学 | G13: 重庆 | H13: 助教 | I13: 教学分析 | J13: 智育 | K13: 学生：提升科学探究能力与创新意识；教师：实现教学设计优化与专业成长；学校：推动STEM教育的本土化发展与教育资源均衡。 | L13: 课程设计优化 → 教师反思与实践 → 生成式AI支持 → 学生探究与反馈 | M13: 数据采集层（学习过程记录、课堂实录） 行为识别层（学生探究行为分析） 画像诊断层（教师教学效果评估） 个性化学习层（AI辅助个性化探究路径） | N13: 基础大模型（DeepSeek，未标注） | O13: 企业产品以“AI辅助教学工具”为主，学校通过专家指导与AI支持实现教学适配，整体处于推广应用阶段。 | P13: 构建了“教师—专家—AI—学生学习证据”协同成长框架，系统揭示了教师在专家指导与生成式AI支持下的课程迭代与专业成长路径，推动了课堂教学由“讲授—模仿”向“探究—共创”的转型。
A14: 第13号案例_13九原区第一实验小学 高嘉彤 “人工智能+基础教育”典型应用场景案例”.pdf | B14: 46042.645 | C14: 13 | D14: AI赋能课堂组织管理：助力《圆的周长》探究式教学 | E14: 小学 | F14: 数学 | G14: 九原区 | H14: 助教 | I14: 课堂管理 | J14: 智育 | K14: 学生：提升课堂参与度与学习效率；教师：减轻数据统计负担，更专注于教学引导；学校：实现课堂组织管理的高效化与科学化。 | L14: 课堂导入视频生成 → 学生互动程序生成 → 实时反馈与评价 → 教学决策优化 | M14: 数据采集层（即时反馈数据采集与可视化管理） 行为识别层（学生参与度分析） 个性化学习层（即时生成反馈与评价） | N14: 即梦AI（未标注）；豆包（未标注）；问卷星（未标注） | O14: 该案例在基础教育领域处于积极探索阶段，利用轻量级AI工具实现课堂教学的数字化转型，具备较强的推广潜力。 | P14: 通过集成多种AI工具，实现了从传统教学模式向数据驱动探究式教学的转变，构建了低门槛的智能教学环境，提升了课堂参与率与反馈效率。
A15: 第14号案例_14铜梁中学 基于“AI+项目化”的铜梁中学“数项融合”校本课程的开发与应用实践(1026).pdf | B15: 46042.645 | C15: 14 | D15: 基于“AI+项目化”的铜梁中学“数项融合”高中物理校本课程的开发与应用实践 | E15: 高中 | F15: 物理 | G15: 重庆市 | H15: 助教 | I15: 智能辅导系统 | J15: 智育 | K15: 学生：提升实践能力与创新思维；教师：增强AI辅助教学能力；学校：推动课程改革与教学质量提升。 | L15: AI辅助课堂教学与互动 → 虚拟实验教学 → 智能学情诊断与个性化辅导 → 课程开发与应用 | M15: 数据采集层（多模态学习数据采集与融合） 行为识别层（学习意图识别、学习路径偏差检测） 画像诊断层（个性化画像生成、过程性反馈解释） 个性化学习层（即时生成反馈） | N15: AIGC（未标注）；国家智慧教育平台（未标注） | O15: 企业产品以“学习支持工具”为主，学校通过校本化规则实现教学适配，整体处于规模化应用初期。 | P15: 通过“AI+项目化”教学模式，构建了多元智慧学习场景，促进了物理教学的实践与创新，形成了鲜明的项目驱动与AI赋能特色。
A16: 第15号案例_15重庆市第八中学校+AI+SFK交互式人工智能教具应用与推广.pdf | B16: 46042.645 | C16: 15 | D16: AI+SFK交互式人工智能教具应用与推广 | E16: 初中 | F16: 人工智能 | G16: 重庆市 | H16: 助教 | I16: 教学辅助 | J16: 智育 | K16: 学生：激发对人工智能的兴趣，培养计算思维与探究能力；教师：降低教学门槛，提高教学效率；学校：形成可复制、可推广的AI教育新模式。 | L16: 需求分析 → 教具设计与开发 → 应用实践与反馈 → 持续优化与推广 | M16: 理念创新（可触摸的思维）；结构创新（模块化集成）；外观创新（双面布局）；资源创新（项目式教学资源库） | N16: AI+SFK交互式人工智能教具（未点名企业） | O16: 已在重庆市50余所中小学推广应用，整体处于规模化应用阶段，形成了“本校-集团-区域”三级推广网络。 | P16: 通过软硬件协同、简化操作、双面布局等创新，实现了从传统编程到理解底层逻辑的跨越，提升了教学的互动性与趣味性。
A17: 第16号案例_16重庆市人民小学校 革新发展性评价 培育“五星好少年”-申报书.pdf | B17: 46042.645 | C17: 16 | D17: 革新发展性评价 培育“五星好少年” | E17: 小学 | F17: 未提及 | G17: 重庆市 | H17: 助评 | I17: 综合素质评价 | J17: 德智体美劳 | K17: 学生：全面发展、个性化成长；教师：减轻评价负担、精准指导；学校：提升育人效能、获得多项荣誉 | L17: 数据采集 → 评价体系构建 → 个性化成长档案生成 → 过程赋能 | M17: 数据采集层（多模态数据采集与融合） 行为识别层（学生表现实时评价） 画像诊断层（个性化成长画像生成） | N17: yolo7（未标注企业）；劳动萌主小程序（未标注企业） | O17: 案例已在重庆市人民小学教育集团全面应用，形成可复制的实施方案，具有显著的社会效益与人才发展价值 | P17: 创新性地将物联网数据采集与人工智能算法深度整合，形成全流程技术解决方案，实现综合性、过程性的学生评价的规模化、常态化实施
A18: 第17号案例_17重庆市第八中学校+AI+校园全域智学成长平台.pdf | B18: 46042.646 | C18: 17 | D18: AI+校园全域智学成长平台 | E18: 高中 | F18: 未提及 | G18: 重庆市 | H18: 助学 | I18: 智能学情诊断与个性化辅导 | J18: 智育 | K18: 学生：实现个性化学习规划，提升学习效率与信心；教师：减轻批改负担，提升教学质量；学校：构建公平优质的教育新生态。 | L18: 数据采集 → 动态学情画像构建 → 精准教学干预 → 个性化学习路径优化 | M18: 数据采集层（动态学情画像构建） 行为识别层（学生思维路径与认知负荷分析） 画像诊断层（多维动态学生能力画像） 智能策略层（个性化学习路径推荐） | N18: AI+校园全域智学成长平台（未点名企业） | O18: 企业产品以“学习支持工具”为主，已在重庆市部分区县高中成功落地，具备低成本、高效益的规模化推广潜力。 | P18: 重构基于全量数据融合的精准教学新范式，打破数据孤岛，实现动态能力画像与个性化教学干预，提升教学质量与效率。
A19: 第18号案例_18重庆市第八中学校+AI赋能教育评价创新——基于三创教育理念的任务链与成长画像实践.pdf | B19: 46042.646 | C19: 18 | D19: AI赋能教育评价创新——基于三创教育理念的任务链与成长画像实践 | E19: 初中 | F19: 未提及 | G19: 重庆市 | H19: 助评 | I19: 学生成长数据分析与预警 | J19: 智育 | K19: 学生：提升学习主动性与自我反思能力；教师：增强精准教学能力；学校：推动‘教、学、评’一体化改革，形成可复制的教育评价创新路径。 | L19: 学习行为采集 → 学习过程分析 → 成长画像生成 → 个性化反馈 | M19: 数据采集层（多模态行为数据自动采集） 智能分析层（自然语言理解与模式识别算法） 画像诊断层（个体发展曲线与班级群体分析生成） 反馈与应用层（项目实施报告与个人成长画像查看） | N19: YEEAI系统（北京易知简教育科技有限公司，案例18） | O19: 企业产品以‘教育评价工具’为主，学校通过校企合作实现教学适配，整体处于规模化应用初期。 | P19: 构建AI支持的任务链学习模式，实现动态评价与个性化反馈，促进教师与学生的双向赋能，形成‘理念引领、技术支撑、场景共建’的协同创新机制。
... A25: 第24号案例_24北京十一学校顺义学校（杨镇一中）丁洁 指数衰减模型的跨学科探索——AI辅助下的核污水放射性衰变分析.docx | B25: 46042.647 | C25: 24 | D25: 指数衰减模型的跨学科探索——AI辅助下的核污水放射性衰变分析 | E25: 高中 | F25: 数学/物理/环境科学 | G25: 北京 | H25: 助学 | I25: 智能辅导系统 | J25: 智育 | K25: 学生：提升高阶思维能力、科学素养与批判性思维；教师：实现精准备课与教学；学校：推动跨学科项目式学习的实施。 | L25: 数据整合与精准学情分析 → 动态探究与高效互动 → 拓展探究与能力培养 | M25: 数据采集层（跨学科数据整合、实时半衰期数据获取） 行为识别层（学情分析与反馈） 个性化学习层（AI工具辅助学习与资源推荐） | N25: 豆包（未点名企业）；Deepseek（未点名企业）；GeoGebra（未点名企业） | O25: 案例展示了AI技术在基础教育中的系统性应用，推动了跨学科教学的探索与实践，整体处于推广阶段。 | P25: 通过真实社会问题驱动，整合数学、物理与环境科学，利用AI工具提升学生的自主探究能力与批判性思维，体现了STEM教育与项目式学习的核心思想。
C26: 25
A27: 第26号案例_26重庆市第八中学校+人工智能赋能学生评价——AI助力教师撰写评语的实践探索.pdf | B27: 46042.647 | C27: 26 | D27: 人工智能赋能学生评价——AI助力教师撰写评语的实践探索 | E27: 初中 | F27: 未提及 | G27: 重庆市 | H27: 助评 | I27: 学生评估 | J27: 德育 | K27: 学生：获得个性化、鼓励性的评语；教师：减轻评语撰写负担，提高工作效率；学校：提升教育评价质量与教师满意度。 | L27: AI评语生成 → 教师审核与润色 → 个性化反馈 | M27: 数据采集层（学生信息与关键词输入） 行为识别层（评语生成模型） 个性化学习层（教师个性化修改与润色） | N27: 豆包（未标注企业）；AA班级助手（未标注企业） | O27: 企业产品以“评语撰写工具”为主，学校通过AI辅助实现评语个性化，整体处于推广应用阶段。 | P27: 通过AI辅助撰写评语，显著提高教师工作效率，减轻重复性劳动，促进教师对教育语言的反思与表达能力提升，同时确保评语的个性化与温度。
A28: 第27号案例_【申报书】西南大学附属中学校-马彬琼-“缙云AI”历史主观题智能批阅平台.docx | B28: 46042.647 | C28: 27 | D28: 缙云AI历史主观题智能批阅平台 | E28: 初中 | F28: 历史 | G28: 重庆市 | H28: 助评 | I28: 学生评估 | J28: 智育 | K28: 学生：明确主观题错因及提分路径；教师：减轻评阅负担、提高评阅效率；教育管理者：优化学业质量评估、提升教学质量。 | L28: 需求分析 → 技术研发与实施 → 应用优化 → 案例创新突破 | M28: 数据采集层（历史主观题作答数据采集） 行为识别层（学生作答模式分析） 画像诊断层（个性化评分与反馈生成） 智能策略层（AI初评与教师复核协同） | N28: 缙云AI（未标注企业） | O28: 企业产品以'智能评阅工具'为主，已在多个省份推广，整体处于规模化应用阶段。 | P28: 突破了主观题传统人工评阅模式，实现全题型智能化评阅，减轻教师负担，提供实时反馈与精准诊断，满足学生个性化提分需求。
C29: 28
A30: 第29号案例_AI赋能：学生体质健康智能化管理平台的构建与实施案例.docx | B30: 46042.647 | C30: 29 | D30: AI赋能：学生体质健康智能化管理平台的构建与实施案例 | E30: 小学 | F30: 体育 | G30: 北京市西城区 | H30: 助学 | I30: 智能辅导系统 | J30: 体育 | K30: 学生：实现个性化体质健康管理与提升；教师：减轻工作负担，提升教学效果；学校：推动健康教育现代化，形成可复制的管理模式。 | L30: 数据采集 → 数据分析与评估 → 个性化干预 → 管理闭环 | M30: 数据采集层（智能设备自动化数据采集） 画像诊断层（动态更新的学生体质数据库） 个性化学习层（个性化体质报告与干预建议） | N30: 学生体质健康管理平台（未点名企业） | O30: 企业产品以“健康管理工具”为主，学校通过智能化手段实现数据驱动的健康管理，整体处于初步推广阶段。 | P30: 构建了“测、评、导、促”一体化闭环，推动体育教育从普适化向个性化转变，实现了数据驱动的精准干预与家校协同的新生态。
A31: 第30号案例_海盐职业教育中心彭韦浩+“人工智能+基础教育”典型应用场景案例申报书.docx | B31: 46042.647 | C31: 30 | D31: 基于自然语言交互的AI成绩查询与学情分析助手 | E31: 未提及 | F31: 未提及 | G31: 海盐职业教育中心 | H31: 助学 | I31: 智能辅导系统 | J31: 智育 | K31: 学生：快速进行自我诊断，激发学习动力；教师：获取班级学情数据支持教学评估；家长：随时查询子女成绩，全面了解学习状况。 | L31: 数据对接与定制 → 自然语言处理（NLP）模型微调 → 智能引导式对话流程设计 → 可视化呈现与分析维度深化 | M31: 数据采集层（学生信息库与成绩数据库对接） 行为识别层（自然语言理解与知识库问答能力） 画像诊断层（学情画像生成与分析） 个性化学习层（智能引导式对话与反馈） | N31: 海盐AI智库（未标注） | O31: 已在本学部试点稳定运行，计划逐步推广，整体处于规模化应用初期 | P31: 实现了教育领域自然语言交互的实用化落地，推动了从经验驱动教学向数据智能驱动教学的转变，构建了基于精准数据的家校沟通桥梁。
A32: 第31号案例_“人工智能+基础教育”典型应用场景案例申报书.docx | B32: 46042.648 | C32: 31 | D32: AI在试卷数据分析中的应用 | E32: 高中 | F32: 数学 | G32: 吉林市 | H32: 助教 | I32: 教学分析 | J32: 智育 | K32: 学生：提供个性化补弱方向，提升学习效率；教师：节省手工分析时间，增强教学针对性；学校：实现数据驱动精准教学，提升整体教学质量。 | L32: 数据导入 → 智能分析 → 报告生成 → 教学调整 | M32: 数据采集层（支持多格式数据导入） 行为识别层（试卷题型识别、知识点匹配） 画像诊断层（错因分类、个性化补弱建议） | N32: 试卷数据分析体系（未点名企业） | O32: 企业产品以'学习支持工具'为主，已在吉林省基础教育领域实现初步应用，具备较强的可复制性与推广性。 | P32: 实现低门槛、高精度的试卷数据自动化解析，简化操作流程，推动教育信息化落地，建立长效学情追踪机制。
A33: 第32号案例_4、AI赋能家校社协同心理健康教育.pdf | B33: 46042.648 | C33: 32 | D33: AI赋能家校社协同心理健康教育 | E33: 小学至初中 | F33: 心理健康教育 | G33: 嘉兴市秀洲区 | H33: 助育 | I33: 智能心理支持 | J33: 德育 | K33: 学生：提升心理健康识别率与情绪调节能力；教师：提高心理健康服务效率；学校：形成可复制的心理健康教育模式。 | L33: 情绪识别 → 实时风险预警 → 个性化干预 → 家校协同 | M33: 数据采集层（多模态情绪识别技术、无感监测） 状态感知层（实时情绪状态监测、风险识别） 智能策略层（个性化干预方案推送、家校协同机制） | N33: 情绪无感识别设备（未点名企业）；朵拉润心小屋（未点名企业）；明智家长小程序（未点名企业） | O33: 企业产品以“心理健康支持工具”为主，学校通过校家社协同实现心理健康教育，整体处于规模化应用阶段。 | P33: 构建“AI+校家社”三维协同模型，实现动态监测与精准干预，提升家校沟通效率，推动心理健康服务从被动干预向主动预防转型。
A34: 第33号案例_上海市尚文中学 龚笛《AI赋能初中数学学生成长数据融合建模与精准预警干预系统研究》.docx | B34: 46042.648 | C34: 33 | D34: AI赋能初中数学学生成长数据融合建模与精准预警干预系统研究 | E34: 初中 | F34: 数学 | G34: 上海 | H34: 助学 | I34: 智能辅导系统 | J34: 智育 | K34: 学生：提升作业质量与逻辑推理能力；教师：减轻批改负担，提供精准教学工具；学校：形成可复制的AI教学模式。 | L34: 数据采集 → 模型构建 → 问题预警 → 分层干预 | M34: 数据采集层（作业数据采集、存储与分析自动化） 模型构建层（广义Cook距离、随机森林算法） 预警机制层（三级预警机制、动态干预策略） | N34: 墨水屏数字化学习终端（未点名企业）；人人通平台（未点名企业） | O34: 系统已在尚文中学初二年级运行，覆盖27名学生，形成可复制的教学模式，整体处于推广阶段。 | P34: 构建全链条智能化闭环，精准识别学生认知偏差，创新三级预警与分层干预机制，提升个性化教学效率与质量。
A35: 第34号案例_1.“人工智能+基础教育”典型应用场景案例申报书.docx | B35: 46042.648 | C35: 34 | D35: 基于AI的小学生创新素养评价系统实践——以“AI杏运”平台为例 | E35: 小学 | F35: 未提及 | G35: 四川省 | H35: 助评 | I35: 综合素质评价 | J35: 智育 | K35: 学生：激发创新精神与探索欲望，提供个性化成长反馈；教师：提升教学针对性与专业能力；学校：推动教育公平与个性化发展，形成可复制的评价改革范式。 | L35: 数据采集 → 实时跟踪与分析 → 个性化反馈与指导 → 教学改进 | M35: 数据采集层（多渠道数据采集：课堂平板、教师移动端等） 行为识别层（实时跟踪学生课堂互动与创新实践） 画像诊断层（生成个性化成长轨迹与素养画像） | N35: AI杏运教育评价信息化平台（未标注） | O35: 企业产品以“评价支持工具”为主，已在省内112所学校推广，整体处于规模化应用阶段。 | P35: 构建了多维度创新素养评价体系，突破传统静态评价局限，实现评价与教学深度融合，推动教育从分数导向转向全面育人导向。
A36: 第35号案例_AI赋能“以体育人”探索智慧体育新样态.docx | B36: 46042.648 | C36: 35 | D36: AI赋能“以体育人”探索智慧体育新样态 | E36: 小学 | F36: 体育 | G36: 包头市青山区 | H36: 助学 | I36: 智能辅导系统 | J36: 体育 | K36: 学生：提升运动技能与体质健康；教师：实现精准体育教学与数据分析；学校：构建智慧体育教育新生态。 | L36: 数据采集 → 动作解析与反馈生成 → 个性化运动干预 → 体育教学改进 | M36: 数据采集层（无感人脸识别、运动数据实时采集） 行为识别层（动作解析与标准动作比对） 画像诊断层（个性化运动能力分析与反馈） 个性化学习层（针对性运动建议与干预） | N36: 智慧体育运动场景（未点名企业）；AI体测吧（未点名企业） | O36: 企业产品以“智慧体育工具”为主，学校通过数字化手段实现体育教学的精准化与个性化，整体处于探索与应用阶段。 | P36: 通过AI技术实现体育教学的精准化与个性化，构建全新的运动场景与数据分析体系，提升学生运动兴趣与参与度。
A37: 第36号案例_36杭州市钱学森学校 “人工智能+基础教育”典型应用场景案例.docx | B37: 46042.649 | C37: 36 | D37: “爱心小叮当”系统 | E37: 小学 | F37: 心理健康 | G37: 杭州市 | H37: 助育 | I37: 智能心理支持 | J37: 德育 | K37: 学生：增进心理健康，提升情绪愉悦度；教师：提供数据支持，增强心理辅导的针对性；学校：改善心理健康教育效果，形成全员心理健康教育的机制。 | L37: 数据采集 → 情绪识别与分析 → 心理预警模型建立 → 家校社联动 | M37: 数据采集层（无感拍摄、情绪状态识别） 行为识别层（情绪状态监测与分析） 智能策略层（心理预警模型推送） | N37: 爱心小叮当系统（未点名企业） | O37: 企业产品以“心理健康支持工具”为主，学校通过校本化规则实现教学适配，整体处于推广应用阶段。 | P37: 自动无感采集学生表情数据，建立可靠的心理预警模型，促进家校社联动，提升心理健康关注度和干预效果。
A38: 第37号案例_成都市泡桐树小学境界分校 AI赋能学生评价创新实践——“六度育人图谱”驱动的全场景综合素质发展体系构建 .docx | B38: 46042.649 | C38: 37 | D38: AI赋能学生评价创新实践——“六度育人图谱”驱动的全场景综合素质发展体系构建 | E38: 小学 | F38: 未提及 | G38: 成都市 | H38: 助评 | I38: 综合素质评价 | J38: 德育 | K38: 学生：全面发展，关注道德修养、艺术能力、劳动习惯等素养；教师：提升评价效率，精准定位学生薄弱点；学校：形成可复制的评价体系，提升家校共育水平。 | L38: 理念转化 → 技术落地 → 场景应用 → 优化迭代 | M38: 数据采集层（全场景数据采集、无感采集）；行为识别层（实时捕捉学生状态、生成评价建议）；画像诊断层（生成学生成长树个人画像、班级素养雷达图） | N38: AI成长学生发展平台（未标注企业）；泡小境界评价培训小程序（未标注企业） | O38: 案例已实现全校全覆盖，具备标准化流程，支持个性化定制，整体处于推广阶段。 | P38: 实现了技术与教育教学模式的深度融合，打破传统评价局限，建立了“评价—诊断—改进—提升”的良性循环路径，推动基础教育从“经验驱动”向“数据驱动”转型。
A39: 第38号案例_1.基于SEED平台多维评价数据构建小学生个性化成长课程的实践研究-案例申报书.docx | B39: 46042.649 | C39: 38 | D39: 基于SEED平台多维评价数据构建小学生个性化成长课程的实践研究 | E39: 小学 | F39: 综合素质 | G39: 成都市 | H39: 助学 | I39: 智能辅导系统 | J39: 智育 | K39: 学生：提升综合素质与个性化发展；教师：提供数据驱动的教学依据；学校：实现教育个性化与家校社协同育人。 | L39: 数据初始分析 → 画像建立 → 课程设计与资源规划 → 课程实施与教学实践 → 教学反馈与优化 | M39: 数据采集层（多维评价数据采集与分析） 画像诊断层（个性化发展需求画像生成） 个性化学习层（动态课程追踪与反馈） | N39: SEED平台（未标注企业） | O39: 企业产品以“学习支持工具”为主，学校多通过校本化规则实现教学适配，整体处于规模化应用初期。 | P39: 实现从宏观评价到个体分析的精准赋能，构建数据驱动的个性化教育模式，推动教育评价与课程教学的深度融合。
A40: 第39号案例_（王宏伟）.“人工智能+基础教育”典型应用场景案例申报书.docx | B40: 46042.649 | C40: 39 | D40: 素养为本·数据为翼：嘉实新儿童综合评价实践探索 | E40: 小学 | F40: 未提及 | G40: 嘉兴市 | H40: 助评 | I40: 综合素质评价 | J40: 智育 | K40: 学生：形成全面的个性化发展画像，促进五育并举；教师：提供便捷的数据录入与分析工具，支持教学改进；学校：推动综合评价改革，提升教育质量。 | L40: 数据采集 → 数据分析建模 → 结果反馈 | M40: 数据采集层（多维度、无感便捷的数据采集） 数据分析层（依标分项等级化、科学智能化分析） 结果反馈层（直观、结构化的结果呈现） | N40: 学生综合评价数字平台（未点名企业） | O40: 学校综合评价改革处于推进阶段，已形成68万多条学生个性成长数据，支持教师开展综合评价。 | P40: 通过数字平台实现多主体、多渠道的评价数据分析与反馈，促进学、教、评、改一体化，推动综合素养评价的创新与实践。
A41: 第40号案例_“人工智能+基础教育”典型应用场景案例申报（云芯）.pdf | B41: 46042.649 | C41: 40 | D41: 破茧成“芯”：当数字画像照亮成长盲区——成都高新云芯学校学生综合素质评价之“24品格”教育评价案例 | E41: 未提及 | F41: 未提及 | G41: 成都 | H41: 助评 | I41: 综合素质评价 | J41: 德育 | K41: 学生：提升综合素质与内驱力；教师：提高评价效率与科学性；学校：实现管理精度与数据治理转型 | L41: 行为数据动态采集 → AI分析与可视化反馈 → 个性化成长报告生成 → 精准干预策略推荐 | M41: 数据采集层（动态行为数据采集、覆盖率提升至98%） 行为识别层（AI分析学生行为特征） 画像诊断层（生成个性化成长报告、情感化反馈） 智能策略层（推荐精准干预方案） | N41: 智慧教育平台（未点名企业） | O41: 案例已在34个班级、1600名学生中全面应用，具备区域推广价值，整体处于推广阶段 | P41: 实现从经验判断到数据驱动的评价模式转变，构建可量化的行为指标体系，生成个性化、情感化的成长报告，提升评价效率与科学性
... A48: 第47号案例_“人工智能+基础教育”典型应用场景案例申报书.长春市南关区树勋小学.docx | B48: 46042.649 | C48: 47 | D48: 基于AI赋能的小学“作业超市” 实践应用 | E48: 小学 | F48: 语文 | G48: 长春市南关区 | H48: 助学 | I48: 智能辅导系统 | J48: 智育 | K48: 学生：个性化学习与即时反馈提升；教师：减负增效与精准教学；学校：形成可复制的“AI+作业设计”模式 | L48: 智能作业生成 → 智能批改与反馈 → 学情诊断与优化 → 应用优化 | M48: 数据采集层（作业数据收集与分析） 行为识别层（学生作业表现分析） 画像诊断层（班级学情报告生成） 个性化学习层（智能作业推荐与反馈） | N48: deepseek（未点名企业）；豆包（未点名企业）；作业帮（未点名企业）；小猿搜题（未点名企业） | O48: 企业产品以“学习支持工具”为主，学校通过校本化规则实现教学适配，整体处于规模化应用初期 | P48: 通过AI实现作业的智能分层与批改，打破传统统一作业模式，提升教师批改效率，促进个性化学习与家校协同
C49: 48
C50: 49
A51: 第50号案例_1.“人工智能+基础教育”典型应用场景案例申报书(1).docx | B51: 46042.649 | C51: 50 | D51: 五育融合背景下小学智能德育评价体系的构建与应用 | E51: 小学 | F51: 德育 | G51: 上海 | H51: 助评 | I51: 五育融合学生画像 | J51: 德育 | K51: 学生：提升德育素养与综合素质；教师：实现精准德育评价与反馈；学校：推动德育教育的系统化与科学化。 | L51: 需求分析 → 技术研发 → 个性化定制 → 应用优化 | M51: 数据采集层（多模态德育数据采集与融合） 画像诊断层（个性化德育画像生成、过程性反馈解释） 个性化学习层（即时生成德育反馈） | N51: 智能德育评价系统（未点名企业） | O51: 企业产品以“德育支持工具”为主，学校多通过校本化规则实现德育适配，整体处于规模化应用初期。 | P51: 通过五育融合的理念，构建智能德育评价体系，实现德育评价的科学化、系统化，推动德育教育的创新与发展。
A52: 第51号案例_上海市崇明中学附属东门中学-由月华-AI赋能学校家庭教育指导优质资源应用.pdf | B52: 46042.649 | C52: 51 | D52: AI赋能学校家庭教育指导优质资源应用 | E52: 未提及 | F52: 未提及 | G52: 上海市崇明中学附属东门中学 | H52: 助育 | I52: 智能德育（家庭教育指导） | J52: 德育 | K52: 提升家庭教育指导质量与效率，促进家校协同育人，形成可推广的家庭教育指导模式 | L52: 需求分析 → 个性化定制 → 应用优化 | M52: 数据采集层（问卷与访谈数据收集） 行为识别层（家长与教师需求分析） 画像诊断层（资源推荐与个性化服务） 智能策略层（动态更新与反馈优化） | N52: 豆包（未标注） | O52: 当前在六年级试点应用，具备向其他年级及学校推广的潜力，整体处于推广阶段 | P52: 构建'AI+学校+家庭'的三方协同互动模式，打破传统家庭教育指导的单向输出，利用大数据分析实现个性化推荐，提升教育质量
A53: 第52号案例_27、上海市杨浦区复旦科技园小学+刘艳+“AI + 导师”协同育人新模式：全员导师制下的AI心理助手落地实践.pdf | B53: 46042.649 | C53: 52 | D53: AI+导师协同育人新模式：全员导师制下的AI心理助手落地实践 | E53: 小学 | F53: 心理健康教育 | G53: 上海市杨浦区 | H53: 助育 | I53: 智能心理支持 | J53: 德育 | K53: 学生：提升情绪自我认知与管理能力，降低心理危机事件发生率；教师：提供精准的学生心理数据支撑与干预建议；学校：构建预防、疏导、干预一体化的心理健康服务体系。 | L53: AI心理分析与综合评价系统研发 → AI心理助手开发 → 适配全员导师制功能 → 应用优化 → 个性化定制 | M53: 数据采集层（自然语言处理、行为识别技术）；画像诊断层（心理状态评估模型、个性化报告生成）；个性化学习层（AI心理助手、情绪调节课程、自动推送疏导建议） | N53: AI心情管理系统（未点名企业） | O53: 目前覆盖20所学校近万名学生，整体处于推广阶段，计划扩展至上海10个区，覆盖50所中小学。 | P53: 首创“AI+全员导师制”协同育人模式，实现从“经验育人”向“数据驱动育人”转变；多源数据融合技术应用于基础教育综合评价，提升心理问题识别效率和响应速度。
A54: 第53号案例_附件1：“人工智能+基础教育”典型应用场景案例申报书.docx | B54: 46042.649 | C54: 53 | D54: 楷模铸魂 智能赋能：天津市翔宇力仁学校德育与综合素质评价创新实践案例 | E54: 小学/初中/高中 | F54: 德育 | G54: 天津 | H54: 助评 | I54: 综合素质评价 | J54: 德育 | K54: 学生：实现德育目标贯通，提升综合素质；教师：减轻评价工作量，提升评价效率；学校：形成可复制的德育数字化管理模式。 | L54: 德育数据采集 → 多维度评价 → 成长分析 → 反馈与优化 | M54: 数据采集层（对接校园活动平台、班级管理系统，自动抓取学生数据） 评价层（设定多维度评价指标，支持在线评价与AI自动核算） 分析层（嵌入德育目标模型，匹配阶段性目标） | N54: 综合素质评价系统（未点名企业） | O54: 系统已覆盖全校36个小学班、22个初中班、17个高中班，服务学生超3000人，整体处于规模化推广阶段。 | P54: 实现小初高德育评价一体化，首次在民办学校实现跨学段德育目标贯通，提升评价效率与精准度，形成“数据驱动-精准评价-个性培养”的管理模式。
C55: 54
A56: 第55号案例_徐州市第七中学+创建学生成长知识库，提升德育管理水平.docx | B56: 46042.649 | C56: 55 | D56: 创建学生成长知识库，提升德育管理水平 | E56: 高中 | F56: 德育 | G56: 徐州市 | H56: 助教 | I56: 学生信息智能管理 | J56: 德育 | K56: 学生：便于信息共享与个性化辅导；教师：快速了解学生情况，提升教学针对性；学校：优化德育管理流程，提升整体教育质量。 | L56: 知识库创建 → 信息整合与共享 → 个性化查询与反馈 → 教学支持与管理 | M56: 数据采集层（学生信息采集与整合） 行为识别层（学生需求识别与分析） 画像诊断层（学生成长档案生成与动态更新） 个性化学习层（即时生成反馈与建议） | N56: RAGFlow知识库软件（未点名企业）；deepseek大模型（未点名企业）；ollama（未点名企业） | O56: 企业产品以“知识管理工具”为主，学校逐步探索个性化德育管理，整体处于初步应用阶段。 | P56: 通过本地部署的知识库系统，实现学生信息的动态管理与快速查询，提升德育管理的效率与针对性，同时保护学生隐私。
A57: 第56号案例_重庆教科院谭舒予-“人工智能+基础教育”典型应用场景案例申报书.pdf | B57: 46042.649 | C57: 56 | D57: 人工智能赋能综合素质教育评价的实践探索 | E57: 小学 | F57: 德育 | G57: 重庆市 | H57: 助评 | I57: 综合素质评价 | J57: 德育 | K57: 学生：全面记录成长档案，促进自我反思与发展；教师：提供精准德育决策支持；学校：优化教育决策，提升教育质量。 | L57: 过程性数据采集 → AI智能分析 → 动态反馈干预 → 综合素质评价 | M57: 数据采集层（多维数据采集：课堂表现、校园活动、家校共育）；评价中心（智能分析生成成长报告，多主体协同评价）；学生画像（可视化成长轨迹，个性化发展建议） | N57: 综合素质教育评价平台（未标注）；DeepSeek（未标注）；希沃易课堂（未标注） | O57: 企业产品以'智能德育与综合素质评价'为主，整体处于数字化转型和应用推广阶段。 | P57: 构建德育AI教研员，实时录制课堂德育片段并生成分析报告；打造'数据-分析-反馈-干预'闭环，解决传统评价碎片化问题；创新家校协同评价模式，提升家长参与度和信息对称性。
A58: 第57号案例_玉德AI银行：数据与智能双驱动的家校社协同育人新范式.docx | B58: 46042.649 | C58: 57 | D58: 玉德AI银行：数据与智能双驱动的家校社协同育人新范式 | E58: 小学 | F58: 未提及 | G58: 重庆 | H58: 助育 | I58: 智能评价体系 | J58: 德育 | K58: 学生：实现德育目标的量化与可视化；教师：减轻重复负担，聚焦育人本质；学校：推动教育管理的科学性与育人效能提升。 | L58: 数据采集 → 行为数据分析 → AI智能反馈 → 德育评价优化 | M58: 数据采集层（多源异构数据汇聚与清洗） 行为识别层（学生行为模式识别） 画像诊断层（学生成长画像生成） 个性化学习层（智能反馈与指导） | N58: 行远银行AI助手（未标注企业）；钉钉平台（未标注企业） | O58: 企业产品以“智能评价工具”为主，已覆盖全校学生，具备规模化推广条件，整体处于应用推广阶段。 | P58: 创建了“AI原生驱动”的家校社协同德育新范式，成功将传统文化与AI技术深度融合，实现德育评价的量化与智能化，推动教育管理的科学化与高效化。
C59: 58
A60: 第59号案例_申报书：重庆市南岸区天台岗融创小学校（徐勇 徐倩）+“成长指南针”——人工智能赋能小学生“五育并举”的实践探索.docx | B60: 46042.649 | C60: 59 | D60: 成长指南针——人工智能赋能小学生“五育并举”的实践探索 | E60: 小学 | F60: 综合素质 | G60: 重庆市南岸区 | H60: 助评 | I60: 综合素质评价 | J60: 德育 | K60: 学生：激发自主学习热情、促进全面发展、增强自信心与成就感；教师：引导教学方式转变、加强师生互动与沟通；学校：营造积极向上的校园文化、提高管理效率、提升声誉与影响力 | L60: 需求分析 → 技术应用与个性化定制 → 应用优化 → 案例创新突破 | M60: 数据采集层（评价数据实时同步、成长档案智能更新） 行为识别层（教师端、家长端评价应用程序） 画像诊断层（学生个人、班级成长雷达图生成） | N60: 成长指南针平台（未点名企业） | O60: 体系已覆盖全校各年级学生，累计生成评价数据超2万次，教师特色活动评价工具使用率达100%，家长端活跃用户占比持续提升，整体处于规模化应用阶段 | P60: 构建‘基础评价+特色评价+家庭评价’三维体系，实现家校协同机制创新，打破传统家校沟通壁垒，提供多元化的成长激励
C61: 60
A62: 第61号案例_“人工智能+基础教育”典型应用场景案例申报书(南湖区教育体育局).docx | B62: 46042.649 | C62: 61 | D62: 双闭环驱动：南湖区AI+教育全域赋能新范式 | E62: 未提及 | F62: 未提及 | G62: 嘉兴市南湖区 | H62: 助学 | I62: 智能辅导系统 | J62: 智育 | K62: 学生：提供个性化学习路径与资源，支持全面发展；教师：减轻备课、批改等重复性劳动，赋能精准教学与专业成长；学校：提升区域教育治理能力，推动教育数字化转型。 | L62: 数据采集 → 学情诊断与画像生成 → 个性化反馈与辅导 → 学习改进 | M62: 数据采集层（多模态学习数据采集与融合） 行为识别层（学习意图识别、学习路径偏差检测） 画像诊断层（个性化画像生成、过程性反馈解释） 个性化学习层（即时生成反馈） | N62: 教师AI备授课助手（未点名企业）；英语AI听说课堂（未点名企业）；智能云阅卷系统（未点名企业）；数智作业平台（未点名企业） | O62: 企业产品以"学习支持工具"为主，学校多通过校本化规则实现教学适配，整体处于规模化应用初期。 | P62: 推进区域“课前智构—课上智启—课后智溯”教学闭环模式，实现个性化教学与精准反馈，提升教师备授课效率与学生课堂互动率，构建共建共享的良性资源生态体系。
A63: 第62号案例_（冯怡）人工智能+基础教育案例.docx | B63: 46042.649 | C63: 62 | D63: AI智批驱动下习作教学的进阶式应用 | E63: 小学 | F63: 语文 | G63: 嘉兴市 | H63: 助学 | I63: 智能辅导系统 | J63: 智育 | K63: 学生：拓宽写作思路、提升写作技能与自信；教师：减轻批改负担、提升教学效率；学校：推动语文教育智能化与个性化发展。 | L63: 习作数据采集 → AI智能批改与反馈 → 问题诊断与管理 → 分层修改与提升 | M63: 数据采集层（习作数据收集与分析） 行为识别层（学生习作问题识别与分析） 画像诊断层（学生写作能力画像生成） 个性化学习层（即时生成反馈与修改建议） | N63: AI智批系统（未点名企业） | O63: 企业产品以“智能批改工具”为主，学校逐步探索AI在习作教学中的应用，整体处于推广阶段。 | P63: 通过AI精准选材与即时反馈，构建问题管理体系与分层修改策略，突破传统习作教学的局限，提升学生写作水平与自信心。
A64: 第63号案例_“人工智能+基础教育”典型案例申报表.pdf | B64: 46042.649 | C64: 63 | D64: 未提及 | E64: 未提及 | F64: 未提及 | G64: 未提及 | H64: 未提及 | I64: 未提及 | J64: 未提及 | K64: 未提及 | L64: 未提及 | M64: 未提及 | N64: 未提及 | O64: 未提及 | P64: 未提及
A65: 第64号案例_人工智能+作业批改 典型应用场景案例.docx | B65: 46042.649 | C65: 64 | D65: AI赋能初中道德与法治学科作业批改 | E65: 初中 | F65: 道德与法治 | G65: 保定市清苑区 | H65: 助教 | I65: 作业管理 | J65: 智育 | K65: 学生：提升作业独立完成率与即时巩固效果；教师：减轻批改负担，实现精准教学；学校：构建高效、透明的家校沟通桥梁。 | L65: 学生提交 → AI批改 → 学情分析 → 教师干预 → 家长同步 | M65: 数据采集层（作业上传与提交） 行为识别层（AI批改与分析） 画像诊断层（生成学习报告与个性反馈） | N65: 蜜蜂家校小程序（未点名企业） | O65: 企业产品以“学习支持工具”为主，学校多通过校本化规则实现教学适配，整体处于规模化应用初期。 | P65: 通过AI实现作业的自动批改与及时反馈，减轻教师负担，提升教学效率，构建家校教育合力。
A66: 第65号案例_成都七中初中附属小学+数智赋能小学作业治理：精准画像与个性化.docx | B66: 46042.649 | C66: 65 | D66: 数智赋能小学作业治理：精准画像与个性化 | E66: 小学 | F66: 语文、数学、英语 | G66: 成都 | H66: 助学 | I66: 智能辅导系统 | J66: 智育 | K66: 学生：实现个性化学习与精准辅导；教师：减轻批改负担，提高教学效率；学校：形成可复制的智慧教育新范式。 | L66: 数据采集 → 学情分析 → 个性化反馈 → 教学改进 | M66: 数据采集层（无感化数据采集、作业智能批改） 画像诊断层（学情画像生成、个性化反馈） 个性化学习层（个性化错题集生成） | N66: AI学情分析平台（未点名企业）；AI点阵笔（未点名企业）；铺码习题册（未点名企业） | O66: 企业产品以“学习支持工具”为主，学校多通过校本化规则实现教学适配，整体处于规模化应用初期。 | P66: 通过AI点阵笔与铺码纸质作业的无缝融合，实现了书写过程的无感知、伴随式数据采集，构建了“数据驱动备课—AI辅助授课—智能精准练习—数据支撑教研—教学策略优化——个性化辅导”的全流程闭环。
A67: 第66号案例_成都东部新区第七中学校（成都七中东部学校）+从即时诊断到动态干预：基于智慧纸笔的智能批改与个性化辅导实践 申报书.pdf | B67: 46042.649 | C67: 66 | D67: 从即时诊断到动态干预：基于智慧纸笔的智能批改与个性化辅导实践 | E67: 初中 | F67: 未提及 | G67: 成都 | H67: 助学 | I67: 智能作业设计与批改 | J67: 智育 | K67: 学生：提升作业反馈时效与个性化学习；教师：减轻批改负担，提升教学精准度；学校：推动作业管理的数字化转型。 | L67: 作业设计 → 作业完成与采集 → 智能批改与诊断 → 学情分析与反馈 → 系统优化与培训 | M67: 数据采集层（实时记录学生书写轨迹、答题时长、修改频次） 行为识别层（实时统计正确率、错误选项分布） 画像诊断层（生成个性化错题集与辅导资源） 个性化学习层（推送个性化学习资源与反馈） | N67: 智慧纸笔（未点名企业） | O67: 企业产品以“智能作业管理工具”为主，已在学校实现常态化应用，具备良好的推广潜力。 | P67: 构建“纸质书写+数字赋能”的智能作业闭环，突破传统批改局限，实现作业数据全流程数字化，显著提升作业反馈时效与精准度。
A68: 第67号案例_成都石室东部新区实验学校-“人工智能+基础教育”典型应用案例申报书.pdf | B68: 46042.649 | C68: 67 | D68: 数智赋能，因材施教：成都石室东部新区实验学校“AI+作业”创新实践报告 | E68: 高中 | F68: 物理/英语 | G68: 成都 | H68: 助教 | I68: 作业管理 | J68: 智育 | K68: 学生：提高作业完成效率，增强自主学习能力；教师：减少批改时间，提升个性化辅导比例；学校：形成可复制的教育数字化转型范式。 | L68: 数据驱动 → 智能算法应用 → 场景适配 → 个性化作业反馈 | M68: 基础设施层（云计算平台支撑）；数据支撑层（多源数据采集模块）；智能算法层（作业生成器、AI批阅引擎、学情分析模型、知识图谱引擎）；应用服务层（教师工作台、学生作业端、管理看板、数据开放接口） | N68: 数智作业系统（未点名企业）；文通云|精准教学大数据系统（未点名企业） | O68: 企业产品以“智能作业系统”为主，学校通过数据驱动教学实现教学适配，整体处于推广阶段 | P68: 三维弹性作业设计模式、三级批阅体系、5分钟动态学情反馈机制、错题生命周期管理，形成“技术赋能-减负增效-质量提升”的良性循环
A69: 第68号案例_成都市实验小学+趣味化·个性化·智能化：“天天跳绳”App重塑小学体育作业新样态.docx | B69: 46042.649 | C69: 68 | D69: 趣味化·个性化·智能化：“天天跳绳”App重塑小学体育作业新样态 | E69: 小学 | F69: 体育 | G69: 成都市 | H69: 助学 | I69: 智能辅导系统 | J69: 体育 | K69: 学生：提升体质健康水平、增强作业完成率与主动参与率；教师：减轻作业布置与管理负担；学校：促进家校协同，提升整体教学效果。 | L69: 智能作业设计 → 智能执行与监管 → 智能评估与反馈 → 家校协同与优化 | M69: 数据采集层（动作识别与数据采集） 行为识别层（动作规范性分析） 画像诊断层（学生体质数字画像生成） 个性化学习层（个性化作业推荐） | N69: 天天跳绳App（未标注企业） | O69: 该模式已在学校实现常态化应用，具备操作简便、成本低廉、效果显著的特点，目前已取得显著成效。 | P69: 创建了趣味化引导、个性化定制与智能化评估的体育作业新模式，构建了教师主导、AI辅助、学生主体与家长参与的四维协同育人机制，极大解放了教师的生产力。
A70: 第69号案例_成都信息工程大学红樱实验学校+基于智能批阅系统的作业设计与批改实践申报书.docx | B70: 46042.649 | C70: 69 | D70: 基于智能批阅系统的作业设计与批改实践 | E70: 小学 | F70: 未提及 | G70: 成都 | H70: 助教 | I70: 作业管理 | J70: 智育 | K70: 学生：作业适配性好，知识点掌握率提升；教师：减轻批改负担，数据实用；学校：推动教育教学评价的科学、多元与个性化。 | L70: 精准设计 → 智能批阅 → 数据采集 → 动态分析 → 靶向改进 | M70: 智能布置层（精准匹配作业） 智能批改层（AI自动批改） 智能分析层（数据驱动分析） 智能管理层（闭环管理） | N70: 希沃作业学情采集分析系统（未点名企业）；判判智能批阅系统（未点名企业） | O70: 企业产品以"智能作业管理工具"为主，学校通过校本化规则实现教学适配，整体处于规模化应用阶段。 | P70: 首创“三维分层+智能匹配”作业体系，打破传统作业批改瓶颈，提升作业批改效率与质量，形成可复制的智能作业应用模式。
A71: 第70号案例_大同市云州区苏家寨中心学校曹宇香基于AI的小学数学精准化学习与辅助系统案例申报书.docx | B71: 46042.649 | C71: 70 | D71: “作业设批辅助官”——基于AI的小学数学精准化学习与辅导系统 | E71: 小学 | F71: 数学 | G71: 大同市云州区 | H71: 助学 | I71: 智能辅导系统 | J71: 智育 | K71: 学生：从“被动订正”到“主动突破”，减少无效刷题，提升学习效率与数学思维；教师：减轻批改与分析负担，实现精准教学；学校：推动小学数学从“统一教学”向“个性化学习”转型，体现“以生为本”的教育理念。 | L71: 智能作业设计 → 学生完成与提交 → AI自动批改与即时反馈 → 学情分析与教师干预 | M71: 知识图谱（构建小学数学知识体系，明确知识点间的关联与层级） 图像识别技术（理解并识别学生的手写答案，实现错题自动录入与题目信息提取） 大数据分析技术（对作业数据进行深度分析，形成学情画像，构建错题知识库） 智能推荐算法（基于学生学情，精准推送讲解内容与变式练习） | N71: 智能作业设计与批改系统（未点名企业） | O71: 企业产品以“学习支持工具”为主，整体处于规模化应用初期，学校通过校本化规则实现教学适配。 | P71: 实现“动态设计、即时批改、精准反馈、数据驱动”的新型学习模式，为教师减负、为学生增效，推动个性化学习。
A72: 第71号案例_海盐高级中学+杨晶“人工智能+基础教育”典型应用场景案例申报书.docx | B72: 46042.649 | C72: 71 | D72: “AI+教师”协同的高中数学单元分层作业创新实践案例 | E72: 高中 | F72: 数学 | G72: 海盐 | H72: 助教 | I72: 作业管理 | J72: 智育 | K72: 学生：获得匹配自身能力层次的作业，提升学习信心；教师：减轻作业设计与批改负担，专注于个性化辅导；学校：推动因材施教落地，提升教学效果。 | L72: AI主导课标分析 → 教师审核大概念 → AI建模核心素养水平 → AI拆解单元目标 → AI设计分层作业 → AI分析学情反馈 | M72: 数据采集层（学生作业数据采集与分析） 行为识别层（学生学习状态与能力识别） 画像诊断层（个性化学情报告生成） 个性化学习层（动态调整作业内容） | N72: AI作业生成系统（未点名企业） | O72: 企业产品以“学习支持工具”为主，学校多通过校本化规则实现教学适配，整体处于规模化应用初期。 | P72: 构建了“AI做基础支撑+教师做精准把控”的分层作业设计模式，形成了“课标分析-目标分解-作业生成-学情反馈-作业优化”的协同闭环，提升了作业设计效率与精准适配性。
C73: 72
A74: 第73号案例_成都七中华溪AI助力高中英语数字化教学效能提升的实践研究.docx | B74: 46042.649 | C74: 73 | D74: 成都七中华溪AI助力高中英语数字化教学效能提升的实践研究 | E74: 高中 | F74: 英语 | G74: 成都 | H74: 助学 | I74: 智能辅导系统 | J74: 智育 | K74: 学生：写作能力提升，反馈效率提高；教师：批改效率提升，教学决策精准；学校：形成可复制的AI+英语教学模型。 | L74: 精准批改 → 即时反馈 → 数据驱动 → 个性化辅导 | M74: 数据采集层（智能批改模型、OCR技术） 行为识别层（语法、词汇、句式及内容逻辑错误检测） 画像诊断层（个性化学习路径生成、错误批改建议） 个性化学习层（实时反馈与修改建议） | N74: 天学网智能批改平台（未点名企业） | O74: 企业产品以'学习支持工具'为主，学校多通过校本化规则实现教学适配，整体处于规模化应用初期。 | P74: 闭环设计结合智能批改与个性化提升建议，数据驱动精准教学，提升教师工作效率与学生写作能力。
A75: 第74号案例_姜海达《表现性评价视域下AI导航的高中作文精准教学实践》申报书10.20.pdf | B75: 46042.649 | C75: 74 | D75: 表现性评价视域下AI导航的高中作文精准教学实践 | E75: 高中 | F75: 语文 | G75: 北京市通州区 | H75: 助学 | I75: 智能作业设计与批改 | J75: 智育 | K75: 学生：作文修改效率提升约3倍，从‘辞藻堆砌’转向‘思维生长’；教师：批改负担减轻约50%，从‘疲劳驾驶’转变为‘智慧导航’；学校：形成可复制、可推广的实践范式。 | L75: 标准解构 → 人机协同 → 动态分层 | M75: 标准翻译层（评分维度-AI诊断关键词-典型指令模板映射库） 四步法教学模型层（问病-开方-试药-自检） 动态分层策略层（针对不同文学生实施差异化指导） | N75: Deepseek（未标注）；豆包（未标注）；文心一言（未标注） | O75: 企业产品以‘智能作业设计与批改’为主，已在校内多个班级成功实践，具备极强推广性。 | P75: 构建了‘标准驱动·人机协同·动态分层’的智能教学新范式，利用通用大模型Deepseek实现了教学过程的深度变革，确保技术服务于思维发展而非替代思考。
A76: 第75号案例_AI赋能，减负增效：小学英语智能作业实践探索 案例.docx | B76: 46042.649 | C76: 75 | D76: AI赋能，减负增效：小学英语智能作业实践探索 | E76: 小学 | F76: 英语 | G76: 未提及 | H76: 助学 | I76: 智能辅导系统 | J76: 智育 | K76: 学生：获得即时反馈，提升学习效果；教师：减轻批改负担，专注于教学设计与个性化指导；学校：提升教育教学质量，落实精准教学。 | L76: 智能设计 → 多维练习 → AI批改 → 学情分析 → 个性化干预 | M76: 数据采集层（多模态学习数据采集与融合） 行为识别层（语音识别与评分） 画像诊断层（智能学情报告生成） 个性化学习层（个性化练习推送） | N76: 蜜蜂家校智能平台（未标注企业） | O76: 案例已在多个年级、班级常态化应用，基于通用平台，推广门槛低，具备广阔应用前景。 | P76: 构建了数据驱动的作业闭环新模式，突破了传统作业流程，实现了多模态学习数据的采集与智能诊断，提升了教师的专业角色与价值。
A77: 第76号案例_AI赋能小学数学三年级分层作业设计与批改案例.docx | B77: 46042.649 | C77: 76 | D77: AI 赋能分层作业设计与批改 | E77: 小学 | F77: 数学 | G77: 天津市静海区 | H77: 助学 | I77: 智能辅导系统 | J77: 智育 | K77: 学生：提升作业正确率与学习效果；教师：减少批改时间，提升教学效率；学校：推动个性化教学模式的实施。 | L77: 需求分析 → 系统选型 → 分层作业生成 → 智能批改与学情反馈 → 教学策略调整 | M77: 数据采集层（课堂互动数据采集） 行为识别层（学生作业表现分析） 画像诊断层（学情报告生成） 个性化学习层（分层作业生成与反馈） | N77: 小猿 AI 作业平台（未点名企业） | O77: 企业产品以'学习支持工具'为主，学校多通过校本化规则实现教学适配，整体处于规模化应用初期。 | P77: 通过AI精准画像与分层作业设计，打破传统作业模式，实现个性化学习与即时反馈，显著提升教师工作效率与学生学习效果。
A78: 第77号案例_附件1.依托 AI 技术的经纬融合视角：初中多学科作业设计与实践案例.docx | B78: 46042.649 | C78: 77 | D78: 依托 AI 技术的经纬融合视角：初中多学科作业设计与实践案例 | E78: 初中 | F78: 数学、英语 | G78: 嘉兴 | H78: 助教 | I78: 作业管理 | J78: 智育 | K78: 学生：提升作业完成效率与学习质量；教师：减轻作业批改负担，提升教学质量；学校：推动教育数字化转型，优化资源配置。 | L78: 需求分析 → 技术研发 → 应用优化 → 案例创新突破 | M78: 数据采集层（作业数据扫描与结构化） 智能批改层（全题型智能批改） 学情诊断层（自动生成讲评讲义，学情分析） 资源沉淀层（校本题库自动生成） | N78: 星火智能批阅机（未标注企业） | O78: 已在初中3个年级29个实验班实现全覆盖，教师使用覆盖率达100%，整体处于规模化应用阶段。 | P78: 实现了全场景闭环应用，打破数据孤岛，推动作业批改从人工主导向AI辅助转变，降低了引入智能教学工具的门槛。
A79: 第78号案例_上海南汇中学申报书.docx | B79: 46042.649 | C79: 78 | D79: 双减导向下AI赋能高中数学作业提质增效路径 | E79: 高中 | F79: 数学 | G79: 上海 | H79: 助学 | I79: 智能辅导系统 | J79: 智育 | K79: 学生：提升数学核心素养，完成难题比例显著提升；教师：减轻重复劳动，确保作业设计精准；学校：助力教育公平，降低教学管理成本。 | L79: 数据分析 → 作业设计优化 → 个性化反馈与辅导 → 学习改进 | M79: 数据采集层（多模态学习数据采集与融合） 行为识别层（学习意图识别、学习路径偏差检测） 画像诊断层（个性化画像生成、过程性反馈解释） 个性化学习层（即时生成反馈） | N79: 豆包（未点名企业） | O79: 企业产品以“学习支持工具”为主，学校通过校本化规则实现教学适配，整体处于规模化应用初期。 | P79: 依托AI技术构建“四维赋能模型”，实现作业设计的目标细化、分层优化、科学性校验与题目拓展，提升作业有效性与学生思维能力。
A80: 第79号案例_AI赋能大规模因材施教——地理主观题智能批阅与自适应练习推送（上海市南洋模范中学） (1).pdf | B80: 46042.649 | C80: 79 | D80: AI赋能大规模因材施教——地理主观题智能批阅与自适应练习推送 | E80: 初中 | F80: 地理 | G80: 上海市 | H80: 助教 | I80: 智能作业设计与批改 | J80: 智育 | K80: 学生：提升答题规范性与准确性，获得个性化反馈与练习；教师：减少机械批阅工作量，提升批阅效率与教学质量。 | L80: OCR识别 → AI批阅 → 数据分析 → 练习推送 | M80: 数据采集层（OCR手写识别技术） 行为识别层（AI批阅技术） 画像诊断层（个性化反馈生成） 个性化学习层（自适应练习推送） | N80: 智能批阅系统（未点名企业） | O80: 系统已在上海市南洋模范中学常态化使用，批阅效率提高60%以上，具备广泛推广潜力。 | P80: 打破传统批阅模式，实现智能精准批阅与个性化练习推送的结合，提升教师教学效率与学生学习效果。
A81: 第80号案例_上海市浦东教育发展研究院 王浩-多智能体协同助力信息技术学科分层作业设计、批改与分析.pdf | B81: 46042.649 | C81: 80 | D81: 多智能体协同助力高中信息技术分层作业设计、批改与分析 | E81: 高中 | F81: 信息技术 | G81: 上海 | H81: 助教 | I81: 智能作业设计与批改 | J81: 智育 | K81: 学生：促进不同能力层次学生学业进步；教师：提升批改效率，实现精准反馈；学校：为教学优化提供数据支撑，具备较强的推广价值。 | L81: 作业生成 → 在线答题工具 → 智能批改 → 多维分析 | M81: 数据采集层（作答数据伴随式采集）；智能批改层（自动判定正误与分析逻辑）；分析层（生成个体与班级的能力层次分析报告） | N81: 作业设计与批改助手（未点名企业） | O81: 企业产品以智能作业设计与批改为主，整体处于推广与应用阶段，具备较强的可复制性 | P81: 通过SOLO分类理论实现分层作业的精准匹配，构建多智能体协同体系，提升作业批改效率与学情分析的深度。
A82: 第81号案例_1.申报书.docx | B82: 46042.649 | C82: 81 | D82: 以数促教、以数促学——人工智能赋能作业精准教学的校本实践 | E82: 初中 | F82: 数学、英语、语文、物理、化学 | G82: 四川 | H82: 助教 | I82: 作业管理 | J82: 智育 | K82: 学生：减轻作业负担，提升学习针对性与效率；教师：减少批改负担，提升教学设计与个性化辅导能力；学校：形成可复制的“人工智能+作业”实践范式，推动教育教学数字化转型。 | L82: 数据采集与分析 → 作业布置与反馈 → 个性化学习支持 → 教学改进 | M82: 数据采集层（学习数据收集与分析）；行为识别层（课堂教学效果反馈）；画像诊断层（个性化学习报告生成）；个性化学习层（智能作业推荐与纠错） | N82: 智学网平台（科大讯飞公司，案例01） | O82: 企业产品以“作业管理工具”为主，学校通过校本化实施实现教学适配，整体处于规模化应用阶段。 | P82: 构建了“校本资源筑基、平台智能支撑、数据驱动教学”的新型作业管理模式，打破传统作业线性流程，实现全流程闭环管理，提升了教学与学习的整体效能。
A83: 第82号案例_“智”规划，“趣”互动：小学英语智能化作业新实践——Unit 3 My weekend plan人工智能应用教学案例.docx | B83: 46042.649 | C83: 82 | D83: “智”规划，“趣”互动：小学英语智能化作业新实践——Unit3 My weekend plan人工智能应用教学案例 | E83: 小学 | F83: 英语 | G83: 甘肃省东乡族自治县 | H83: 助学 | I83: 智能辅导系统 | J83: 智育 | K83: 学生：提升作业兴趣与完成质量；教师：减轻批改负担，提升教学效率；学校：推动教育数字化转型，优化教学管理。 | L83: 智能设计 → 学生完成 → AI初批 → 教师复批 → 学情诊断 → 个性化补救 | M83: 数据采集层（作业完成过程数据采集） 行为识别层（学生作业表现分析） 画像诊断层（个性化学习画像生成） 个性化学习层（即时反馈与补救建议） | N83: 作业智能管理平台（未点名企业）；语音识别技术（未点名企业）；自然语言处理技术（未点名企业） | O83: 该模式已在试点班级取得良好效果，具备广泛的复制推广潜力，整体处于初步应用阶段。 | P83: 作业设计的互动性与即时反馈提升了学生的学习兴趣，批改模式的创新使得教师能更专注于学生的思维过程与创新能力，推动了教育数字化转型。
A84: 第83号案例_附件1：“人工智能+基础教育”典型应用场景案例申报书.docx | B84: 46042.649 | C84: 83 | D84: 《张拉整体结构》劳动+AIGC智能作业设计 | E84: 小学 | F84: 劳动教育 | G84: 天津市河东区 | H84: 助学 | I84: 智能辅导系统 | J84: 智育 | K84: 学生：提升劳动素养，发现和解决问题的能力；教师：实现作业内容个性化、精准化设计，及时调整教学；学校：推动教育数字化转型，提升教学效率。 | L84: 技术工具整合 → 个性化作业定制 → 数据化反馈体系搭建 → 应用优化 | M84: 数据采集层（UMU平台作业完成率、提交时间、互评次数等数据自动采集） 画像诊断层（AI生成学情分析报告，精准标注班级薄弱点） 个性化学习层（AI辅助设计分层作业，教师调整确定作业内容） | N84: 生成式AI工具（豆包、DeepSeek）；UMU在线平台（未点名企业） | O84: 企业产品以“学习支持工具”为主，学校多通过校本化规则实现教学适配，整体处于规模化应用初期 | P84: 建立‘数据驱动、动态个性化’的作业新模式，通过在线平台与生成式AI融通，实现作业设计、实施与反馈的全面优化，推动课堂从标准化向个性化转变。
A85: 第84号案例_薛荫冬--飞书赋能写作教学：构建“数据驱动-精准教学-智能批改”的闭环新模式.docx | B85: 46042.649 | C85: 84 | D85: 飞书赋能写作教学：构建“数据驱动-精准教学-智能批改”的闭环新模式 | E85: 高中 | F85: 英语 | G85: 天津市静海区 | H85: 助学 | I85: 智能辅导系统 | J85: 智育 | K85: 学生：提升写作能力与积极性；教师：减轻批改负担，实现精准教学；学校：形成可复制的教学模式，推动教育数字化转型 | L85: 学情数据采集 → 数据可视化分析 → 精准教学互动 → 智能批改反馈 | M85: 数据采集层（在线表格收集学生初稿） 行为识别层（词云工具生成学情词云图） 画像诊断层（AI助手进行个性化批改） | N85: 飞书（未标注企业） | O85: 企业产品以“学习支持工具”为主，学校多通过校本化规则实现教学适配，整体处于规模化应用初期 | P85: 构建了“课前数据诊断 → 课中精准干预 → 课后智能反馈”的闭环教学模式，提升了教学的科学性与精准性，展示了普通教师如何利用现有工具实现教育数字化转型
C86: 85
A87: 第86号案例_宜宾市叙州区僰道学校《小学语文学科人工智能批改作业实践案例》.pdf | B87: 46042.649 | C87: 86 | D87: 小学语文学科人工智能批改作业实践案例 | E87: 小学 | F87: 语文 | G87: 宜宾市叙州区 | H87: 助教 | I87: 作业管理 | J87: 智育 | K87: 学生：作业订正及时性提升72%，作文修改达标率从65%升至88%；教师：批改时长从4.2小时缩至40分钟，减轻工作负担；学校：实现教师与AI的有效协同，提高教学效率。 | L87: 作业提交 → AI协同批改 → 教师复核优化 | M87: 数据采集层（拍照识别技术实现基础作业批改） 行为识别层（AI对基础作业与习作进行评分与点评） 个性化学习层（教师结合AI反馈进行个性化辅导） | N87: 小猿AI（未标注）；神笔作文批改（未标注） | O87: 企业产品以“智能作业批改工具”为主，学校通过校本化规则实现教学适配，整体处于规模化应用初期。 | P87: 构建分层批改体系，实现“工具互补”，通过数据驱动精准教学，明确AI与教师的功能分工，守护教育温度，促进教育公平与教学效率提升。
A88: 第87号案例_“人工智能+基础教育”典型应用场景案例申报书.pdf | B88: 46042.649 | C88: 87 | D88: 基于AI的作业智能批改与分层个性化设计 | E88: 中职 | F88: 未提及 | G88: 四川省 | H88: 助教 | I88: 作业管理 | J88: 智育 | K88: 学生：提升学习针对性与效率；教师：减轻机械性工作负担，聚焦个性化辅导与教学设计；学校：推动基础教育公平与质量提升。 | L88: 作业批改 → 学情诊断 → 分层设计 → 个性化练习生成 | M88: 数据采集层（作业图像接收） 行为识别层（作业批改与评分） 画像诊断层（学情分析与等级分层） 个性化学习层（个性化练习包生成） | N88: 飞书多维表格（未标注企业） | O88: 企业产品以“智能作业设计与批改”为主，已在部分班级成功试点，具备广泛的可复制性与应用前景。 | P88: 构建了‘AI诊断-自动分层-个性化推送’的闭环教学模式，实现了真正意义上的个性化教学，且采用低门槛的技术方案，推动职业教育数字化转型。
A89: 第88号案例_智能作业设计与批改.pdf | B89: 46042.649 | C89: 88 | D89: AI赋能下的个性化数学作业管理新范式 | E89: 初中 | F89: 数学 | G89: 河北省 | H89: 助学 | I89: 智能作业设计与批改 | J89: 智育 | K89: 学生：获得个性化练习，及时反馈，了解知识薄弱点；教师：减轻批改负担，实现精准教学；学校：提升整体教学效率与质量。 | L89: 需求分析 → 技术研发与个性化定制 → 应用系统开发 → 应用优化 | M89: 数据采集层（动态分析学生能力与知识结构） 行为识别层（识别学生解题逻辑与步骤） 画像诊断层（生成学情分析报告） 个性化学习层（提供个性化作业与反馈） | N89: 智学数学系统（未标注企业） | O89: 企业产品以“智能作业管理工具”为主，正在推动个性化教育转型，整体处于推广应用阶段。 | P89: 实现了数据驱动的规模化因材施教，变革了传统作业模式，提供即时反馈与精准教学，显著降低教师批改负担。
A90: 第89号案例_重庆市合川区杨柳街小学-王仁华“人工智能+基础教育”典型应用 场景案例申报书.docx | B90: 46042.649 | C90: 89 | D90: 小学低段作业管理数字化：重庆市合川区杨柳街小学 AI 减轻教师批改负担实践案例 | E90: 小学 | F90: 未提及 | G90: 重庆市合川区 | H90: 助教 | I90: 作业管理 | J90: 智育 | K90: 学生：提升作业质量与反馈及时性；教师：减少机械性批改时间，提升个性化辅导效率；学校：实现数字化减负与教学质量提升。 | L90: 作业上传与识别 → AI 预批反馈生成 → 教师终审与个性化评语 → 数据分析与教学调整 | M90: 数据采集层（语音样本上传、图文作业拍照上传） 行为识别层（语音识别、图文识别） 智能策略层（自动生成反馈、个性化评语推荐） 数据分析层（作业高频错误统计、个体薄弱项分析） | N90: 希沃家长通（未标注）; 希沃白板 5（未标注） | O90: 企业产品以“学习支持工具”为主，学校多通过校本化规则实现教学适配，整体处于规模化应用初期。 | P90: 通过希沃工具的校本化改造，解决低段非书面作业批改难题，实现教师减负与个性化辅导的平衡，且成本控制在2000-5000元/年，具备全国推广潜力。
A91: 第90号案例_ima人工智能软件作业设计与批改.pdf | B91: 46042.649 | C91: 90 | D91: ima人工智能软件作业设计与批改 | E91: 未提及 | F91: 未提及 | G91: 重庆市渝北区 | H91: 助教 | I91: 作业管理 | J91: 智育 | K91: 学生：快速反馈作业情况，针对性练习；教师：减轻批改负担，提升教学效率；家长：实时了解孩子学习情况，减轻焦虑。 | L91: 作业拍摄 → 作业上传与批改 → 问题分析与反馈 → 练习生成与调整 | M91: 数据采集层（作业拍摄与上传） 行为识别层（作业批改与分析） 个性化学习层（针对性练习生成） | N91: Ima智能工作台（未标注企业） | O91: 企业产品以'智能作业设计与批改'为主，逐步实现个性化教学，整体处于推广应用阶段 | P91: 通过人工智能实现快速批改与个性化练习，减轻教师与家长负担，提升学生学习效率，促进教育公平
A92: 第91号案例_91“人工智能+基础教育”典型应用案例（北京市通州区教师研修中心）.pdf | B92: 46042.649 | C92: 91 | D92: 数智赋能精准教学的区域实践探索 | E92: 未提及 | F92: 未提及 | G92: 北京市通州区 | H92: 助学 | I92: 智能学情诊断与个性化辅导 | J92: 智育 | K92: 学生：提升自主学习能力与问题解决素养；教师：释放时间精力，专注于高阶育人工作；学校：推动教育模式创新，提升教育质量与效率。 | L92: 精准识学 → 精准定标 → 精准导学 → 精准评学 → 精准助学 | M92: 数据采集层（知识图谱数据开展精准补缺） 行为识别层（AI辅助批改个性化留痕点拨） 画像诊断层（构建学生个人知识图谱与班级整体知识图谱） 个性化学习层（生成适配学生个体能力水平的个性化作业） | N92: 千师大模型（未点名企业） | O92: 企业产品以“智能学情诊断与个性化辅导”为主，整体处于规模化应用初期，推动教育数字化转型。 | P92: 通过AI辅助批改与个性化作业生成，构建“错因分析—方向引导—自主提升”的闭环反馈体系，提升学生自主学习能力与深度思维素养。
A93: 第92号案例_92平谷区第八小学“人工智能+基础教育”典型应用场景案例.docx | B93: 46042.649 | C93: 92 | D93: 基于平谷教育在线平台的数学作业设计与批改的探索实践案例 | E93: 小学 | F93: 数学 | G93: 北京市平谷区 | H93: 助教 | I93: 作业管理 | J93: 智育 | K93: 学生：个性化学习、提升学习兴趣；教师：减轻批改负担、提高教学效率；学校：推动教育信息化发展，优化教育资源配置。 | L93: 作业设计 → 作业批改 → 学习反馈 → 教学调整 | M93: 数据采集层（图像识别技术、学习数据记录） 画像诊断层（学习报告生成、个性化反馈） 个性化学习层（动态调整作业难度、即时反馈） | N93: 平谷教育在线平台（未标注企业） | O93: 企业产品以“学习支持工具”为主，学校多通过校本化规则实现教学适配，整体处于规模化应用初期。 | P93: 实现分层作业设计与智能批改，提供即时反馈与精准指导，推动个性化学习与家校协同育人。
A94: 第93号案例_93山东师范大学附属中学-杨阳-“人工智能+基础教育”典型案例申报书.docx | B94: 46042.649 | C94: 93 | D94: 生成式人工智能赋能高中英语写作精准教学 | E94: 高中 | F94: 英语 | G94: 山东 | H94: 助学 | I94: 智能辅导系统 | J94: 智育 | K94: 学生：提升写作能力与兴趣，增加练习频次；教师：减轻批改负担，提升反馈精准度；学校：形成可复制的写作教学模式。 | L94: 需求分析 → 模式构建 → 技术整合 → 个性化反馈 → 数据驱动教学决策 | M94: 数据采集层（实时反馈与数据收集） 行为识别层（写作过程中的错误标注与逻辑分析） 画像诊断层（学生写作能力画像生成） 个性化学习层（个性化提升建议生成） | N94: GAI写作工坊（未点名企业）；DeepSeek（未点名企业） | O94: 企业产品以“学习支持工具”为主，学校多通过校本化规则实现教学适配，整体处于规模化应用初期 | P94: 构建了“GAI写作工坊”模式，实现了写作教学的全流程赋能，推动教师角色转型，提升了教学效率与学生写作素养。
A95: 第94号案例_94上海市奉贤区青少年业余体育学校 曹冰清 《从“使用AI”到“领导AI”：构建培养学生“AI领导力”的语文作业新范式》.docx | B95: 46042.649 | C95: 94 | D95: 从“使用AI”到“领导AI”：构建培养学生“AI领导力”的语文作业新范式 | E95: 初中 | F95: 语文 | G95: 上海市奉贤区 | H95: 助学 | I95: 智能辅导系统 | J95: 智育 | K95: 学生：提升思维深度与批判性；教师：转变为思维教练，促进教学效果；学校：形成可推广的教学模式。 | L95: 问题定位 → 任务设计 → 过程指导 → 反思闭环 | M95: 任务设计层（任务驱动、反思闭环） 过程指导层（设计-交互-评估-反思） AI协作层（AI作为思维协作者） | N95: 学生AI领导力学习单（未点名企业） | O95: 企业产品以“学习支持工具”为主，学校多通过校本化规则实现教学适配，整体处于规模化应用初期 | P95: 创新性地提出“AI领导力”理念，重构教育教学模式，强调学生主体性与批判性思维的培养，形成可迁移的低成本教学方案。
A96: 第95号案例_95重庆市渝北区佳园小学数学智能作业设计与批改案例.docx | B96: 46042.649 | C96: 95 | D96: 佳园小学数学智能作业设计与批改案例 | E96: 小学 | F96: 数学 | G96: 重庆市渝北区 | H96: 助学 | I96: 智能辅导系统 | J96: 智育 | K96: 学生：提升学习兴趣与自主学习能力，数学成绩优秀率提升约15%、及格率提升约10%；教师：减轻作业设计与批改负担，提升教学水平；学校：整体教学质量提升，形成特色教学品牌。 | L96: 需求分析 → 系统搭建 → 应用实施 → 数据应用 → 优化推广 | M96: 数据采集层（学生成绩查询系统、题库整合） 行为识别层（学生能力分层、作业生成） 画像诊断层（作业分析报告生成） 个性化学习层（智能批改与反馈） | N96: 小学数学智能作业设计系统（未点名企业） | O96: 企业产品以“学习支持工具”为主，学校通过智能作业系统实现个性化教学，整体处于推广阶段。 | P96: 个性化分层作业模式与数据驱动的精准教学模式，突破传统作业设计与批改的局限，提升了教学效率与学生学习效果。
A97: 第96号案例_（大连现代学习科学研究院）“人工智能+基础教育”典型应用场景案例申报书.docx | B97: 46042.649 | C97: 96 | D97: 区域教育治理“智慧指挥舱”：AI+数据驱动的办学质量监测新模式 | E97: 未提及 | F97: 未提及 | G97: 大连 | H97: 助管 | I97: 学生信息智能管理 | J97: 智育 | K97: 提升教育评价的公信力与科学性，降低评价工作的人力、时间与管理成本，推动基础教育高质量发展 | L97: 数据可视化 → AI智能评审 → 智慧决策升级 | M97: 数据采集层（监测数据大屏、数据中心） 行为识别层（AI智能评审功能） 智能策略层（基于NLP与大语言模型的评审机制） | N97: 基础教育办学质量智能监测评价系统（未点名企业） | O97: 该系统已在市级区域基础教育阶段学校应用，覆盖率达100%，具备规模化推广条件 | P97: 创建了“人机协同、以机为主”的智能评审新模式，提升了评审效率与结果的公信力，推动了教育评价的技术数字化转型
A98: 第97号案例_“人工智能+基础教育”典型应用场景案例《捕捉校园最美瞬间》.docx | B98: 46042.649 | C98: 97 | D98: 捕捉校园最美瞬间 | E98: 小学 | F98: 美术 | G98: 北京市顺义区 | H98: 助学 | I98: 情境式学习 | J98: 美育 | K98: 学生：提升摄影技能与艺术表达能力；教师：实现教学评一体化与个性化指导；学校：促进校园文化建设与美育发展。 | L98: 学习任务设计 → AI诊断与反馈 → 作品展示与评价 → 技能提升 | M98: 数据采集层（学生作品拍摄数据收集） 行为识别层（分析学生拍摄技巧与构图） 画像诊断层（生成学生摄影技能画像与反馈） | N98: AI助手（未点名企业） | O98: 企业产品以“学习支持工具”为主，学校多通过校本化规则实现教学适配，整体处于规模化应用初期。 | P98: 通过AI助手进行作品诊断，结合问题驱动与场景设计，提升学生的学习兴趣与摄影技能，形成多元化的评价体系。
... A101: 第100号案例_“人工智能+基础教育”典型应用场景案例申报书.docx | B101: 46042.644 | C101: 100 | D101: 校园智慧大棚的智能控制 | E101: 初中 | F101: 综合实践 | G101: 北京市 | H101: 助学 | I101: 智能辅导系统 | J101: 智育 | K101: 学生：提升数据思维、创新能力与解决实际问题的能力；教师：实现跨学科教学与个性化指导；学校：推动AI教育实践与课程改革。 | L101: 数据感知 → 基础规则 → 智能决策 → 执行交互 | M101: 数据采集层（多类传感器部署、数据采集原理理解） 基础规则层（条件判断与编程思想） 智能决策层（历史与实时数据分析、自动生成控制指令） 执行交互层（手动配置与策略对比实验） | N101: 人工智能物联网系统（未点名企业） | O101: 案例已在课堂上服务超过500名学生，具备低成本、高可用性，适合大规模推广。 | P101: 实现AI教学从虚拟到实体的突破，鼓励学生从使用者转变为创造者，促进个性化学习与跨学科融合。
C102: 101
A103: 第102号案例_2.“人工智能+基础教育”典型应用场景案例申报书.docx | B103: 46042.644 | C103: 102 | D103: 基于人工智能技术的校园智能安防实践应用 | E103: 未提及 | F103: 未提及 | G103: 成都市温江区 | H103: 助管 | I103: 校园安全智能监控 | J103: 未提及 | K103: 提升校园安全管理效率，成功预警并制止17起潜在高坠风险事件，人员查找时间由15分钟缩短至3分钟内，隐患整改率达100%。 | L103: 校园安全需求分析 → AI技术引入与系统部署 → 安全管理机制优化 → 实时监测与预警 | M103: 数据采集层（AI感知预警设备、高清摄像头） 行为识别层（危险行为识别算法） 状态感知层（实时状态检测、人员轨迹追踪） 智能策略层（AI预警系统与网格处置机制） | N103: 校园智能安防平台（未点名企业） | O103: 该模式已在温江区多所中小学、幼儿园推广实施，形成可复制、可推广的实践路径，整体处于规模化应用阶段。 | P103: 实现从被动管理向主动预防转变，构建“AI预警+网格处置”的新机制，采用普通高清摄像头加装AI分析模块的轻量化方案，降低实施成本，符合《个人信息保护法》要求的隐私保护机制。
A104: 第103号案例_“人工智能+基础教育”典型应用场景案例申报书-小学智慧校园个性化管理应用实践.docx | B104: 46042.644 | C104: 103 | D104: 数据驱动治理，低代码赋能服务——永丰小学蒲公英数字管理平台的创新实践 | E104: 小学 | F104: 未提及 | G104: 都江堰市 | H104: 助管 | I104: 学生信息智能管理 | J104: 智育 | K104: 学生：提升综合素质与个性化发展；教师：实现精准教学与高效管理；学校：构建数据驱动的智慧校园治理新模式。 | L104: 低代码平台选择 → 模块化开发 → 数据驱动治理 → 持续优化与反馈 | M104: 数据采集层（实时采集与可视化分析） 行为识别层（学生行为记录与德育评价） 智能策略层（个性化评价与反馈生成） | N104: 蒲公英数字管理平台（未点名企业） | O104: 企业产品以“学习支持工具”为主，学校通过低代码平台实现自主定制，整体处于规模化应用阶段。 | P104: 创新的低代码平台开发模式，个性化定制的管理系统，形成了数据驱动的精准治理新范式，提升了师生数字素养与家校协同机制。
A105: 第104号案例_“人工智能+基础教育”典型应用场景案例申报书.docx | B105: 46042.644 | C105: 104 | D105: AI+智能语音控制垃圾桶 | E105: 初中 | F105: 环保教育 | G105: 海口市 | H105: 助学 | I105: 智能辅导系统 | J105: 德育 | K105: 学生：提升垃圾分类准确率与参与积极性；教师：提供数据记录与教学效果量化；学校：形成可复制的‘AI+环保’教育模式 | L105: 语音交互系统优化 → 教育功能设计 → 应用优化与迭代 | M105: 数据采集层（语音识别与自然语言处理） 行为识别层（语音指令识别与反馈） 个性化学习层（学习模式与数据记录） | N105: AI+智能语音控制垃圾桶（未点名企业） | O105: 项目处于推广阶段，已在校园内实施，具备较高的应用前景与社会价值 | P105: 创设沉浸式环保教育体验，探索AI技术基础教育落地新路径，构建‘教育-科技-环保’三元融合模式
A106: 第105号案例_数智协同构建农村小学智慧教育生态申报书.docx | B106: 46042.644 | C106: 105 | D106: 数智协同构建农村小学智慧教育生态 | E106: 小学 | F106: 未提及 | G106: 海盐县 | H106: 助学 | I106: 智能辅导系统 | J106: 智育 | K106: 学生：实现个性化与智能化学习，促进全面发展；教师：提升课堂教学效能与专业成长；学校：构建科学、精准的多元评价体系与管理机制。 | L106: 技术赋能学习 → 技术赋能教学 → 技术赋能研修 → 技术赋能评价 → 技术赋能管理 → 数智协同融合 | M106: 数据采集层（AI课堂分析、智慧体育、电子班牌、智能安防）；行为识别层（实时掌握学生状态、精准调控教学节奏）；画像诊断层（动态反馈与多元评价体系）；个性化学习层（个性化学习支持与反馈） | N106: 智慧黑板（未点名企业）；AI课堂分析（未点名企业）；智慧体育（未点名企业）；电子班牌（未点名企业）；智能安防系统（未点名企业） | O106: 企业产品以'学习支持工具'为主，学校通过数字技术与人工智能实现教学适配，整体处于规模化应用初期 | P106: 构建了一个有机融合、全面覆盖的智慧教育生态体系，利用AI技术实现个性化学习、精准教学、动态反馈与多元评价，提升了教育质量与管理效能。
A107: 第106号案例_海盐县武原中学教育集团秦山中学+王卫+“人工智能+基础教育”典型应用场景案例申报书.pdf | B107: 46042.644 | C107: 106 | D107: AI与物联网技术驱动的后勤管理新模式 | E107: 未提及 | F107: 未提及 | G107: 海盐县 | H107: 助管 | I107: 校园安全智能监控 | J107: 未提及 | K107: 提升管理效率、节能减排、提高安全性、优化教学环境 | L107: 数据采集 → 实时监控与智能控制 → 管理决策优化 | M107: 环境互联层（物联网设备互操作、数据传输） 状态感知层（实时监控、异常情况报警） 智能策略层（智能控制、场景化管理） | N107: 智慧校园管理平台（未点名企业） | O107: 企业产品以“智慧校园管理工具”为主，整体处于规模化应用初期 | P107: 通过AI与物联网技术实现校园后勤管理的智慧化转型，显著提升管理效率和校园安全性，获得教育数字化应用典型案例一等奖
A108: 第107号案例_礼嘉实验小学+《面向未来学校：AI重塑校园治理的新样态》申报书.docx | B108: 46042.644 | C108: 107 | D108: 面向未来学校：AI重塑校园治理的新样态 | E108: 小学 | F108: 未提及 | G108: 重庆两江新区 | H108: 助管 | I108: 教务管理智能化 | J108: 未提及 | K108: 提升管理效率，降低人力成本，增强校园安全，强化家校沟通，提升教师科研支持。 | L108: 低代码搭建管理中枢 → 流程自动化 → 咨询智能化 → 数据化督导 | M108: 数据采集层（实时数据采集与分析） 行为识别层（教师行为分析、课程参与率监测） 智能策略层（AI助理、智能流转） | N108: 钉钉宜搭（未标注企业）; 扣子平台（未标注企业）; DeepSeek（未标注企业）; 希沃校园设备运维系统（未标注企业） | O108: 企业产品以“校园管理工具”为主，整体处于规模化应用初期，已覆盖多个校区。 | P108: 通过低代码与大模型的协同应用，实现了校园管理的流程优化与智能化，提升了管理效率和服务质量，形成了可复制的智慧校园管理样板。
A109: 第108号案例_南昌市第31中学《AI平台系统与特殊教育深度融合》.docx | B109: 46042.644 | C109: 108 | D109: AI智慧云平台系统与特殊教育的深度融合 | E109: 未提及 | F109: 未提及 | G109: 南昌市 | H109: 助学 | I109: 智能辅导系统 | J109: 智育 | K109: 学生：精准评估学习效果，个性化训练；教师：高效管理学生信息与教学方案；学校：提升特殊教育教学质量与管理效率。 | L109: IEP评估模块适配 → 个性化教学方案生成 → 训练习题推送与动态调整 → 家校共育与信息管理 | M109: 数据采集层（IEP档案管理、评估指标设置） 行为识别层（学生能力评估、个性化反馈） 画像诊断层（IEP报告生成、数据对比分析） | N109: AI智慧云平台（未点名企业） | O109: 企业产品以'学习支持工具'为主，聚焦特殊教育领域，整体处于应用推广阶段。 | P109: AI技术深度赋能特殊教育，提供个性化训练与精准评估，构建全方位教学支持体系，涵盖多种教学资源与互动游戏，提升学习体验与教学质量。
C110: 109
A111: 第110号案例_人工智能+基础教育 应用案例 AI 慧眼识出入 无感智护校园安 申报书.docx | B111: 46042.644 | C111: 110 | D111: AI 慧眼识出入 无感智护校园安 | E111: 未提及 | F111: 未提及 | G111: 陕西省丹凤中学 | H111: 助管 | I111: 学生信息智能管理 | J111: 未提及 | K111: 提升校园安全管控能力，减少安全隐患；加强家校协同，缓解家长“监管焦虑”；释放教师管理时间，专注教学工作，间接提升教学质量。 | L111: 感知-分析-推送 → 实时考勤数据同步 → 自动化请假流程 | M111: 数据采集层（人脸识别摄像头采集视频流）；行为识别层（人脸比对与活体检测）；智能策略层（自动匹配审批人与审批规则）；环境互联层（硬件连接与数据传输） | N111: 海威达无感考勤系统（未标注）；海康威视高清人脸识别摄像头（未标注）；希沃电子班牌（未标注） | O111: 该智能校园管理与服务案例在全国范围内多所学校成功应用，适合在基础教育阶段公办、民办学校规模化复制，整体处于推广阶段。 | P111: 构建“AI驱动+家校协同”的智慧管理模式，实现考勤与请假数据实时联动，降低家长与教师使用门槛，提升管理效率。
C112: 111
A113: 第112号案例_典型应用案例申报书-石外.docx | B113: 46042.644 | C113: 112 | D113: AI智慧操场赋能体育教育新生态 | E113: 未提及 | F113: 体育 | G113: 石家庄 | H113: 助育 | I113: 智能体育健康 | J113: 体育 | K113: 未提及 | L113: 未提及 | M113: 未提及 | N113: 未提及 | O113: 未提及 | P113: 未提及
...

Sheet Sheet2
A1: 文件名 | B1: 工具名称 | C1: 工具标准名 | D1: 公司 | E1: 地区 | F1: 省份 | H1: 工具标准名 | I1: 计数项:工具标准名
A2: 第01号案例_1温州市新田园小学 叶诗婧《数“算”生“动”：AI赋能下运算律教学的新样态》.pdf | B2: AI学习机 | C2: =VLOOKUP(B2,「工具标准名」映射表!B:I,2,0) -> AI学习机 | D2: =VLOOKUP(C2,「工具标准名」映射表!$C$1:$O$2046,2,0) -> AI学习机 | E2: 温州市 | F2: =VLOOKUP(E2,省份映射!$B$1:$C$472,2,0) -> 浙江省 | H2: AI学习机 | I2: 1
A3: 第01号案例_1温州市新田园小学 叶诗婧《数“算”生“动”：AI赋能下运算律教学的新样态》.pdf | B3: AI语音互动平台 | C3: =VLOOKUP(B3,「工具标准名」映射表!B:I,2,0) -> AI语音互动平台 | D3: =VLOOKUP(C3,「工具标准名」映射表!$C$1:$O$2046,2,0) -> AI语音互动平台 | E3: 温州市 | F3: =VLOOKUP(E3,省份映射!$B$1:$C$472,2,0) -> 浙江省 | H3: AI语音互动平台 | I3: 3
A4: 第01号案例_1温州市新田园小学 叶诗婧《数“算”生“动”：AI赋能下运算律教学的新样态》.pdf | B4: 动态点子图生成系统 | C4: =VLOOKUP(B4,「工具标准名」映射表!B:I,2,0) -> 动态点子图生成系统 | D4: =VLOOKUP(C4,「工具标准名」映射表!$C$1:$O$2046,2,0) -> 动态点子图生成系统 | E4: 温州市 | F4: =VLOOKUP(E4,省份映射!$B$1:$C$472,2,0) -> 浙江省 | H4: 动态点子图生成系统 | I4: 1
A5: 第02号案例_2温州市新田园小学朱朝炜《三维联动：人工智能视域下小学足球运球游戏设计与研究》.pdf | B5: 智慧手环 | C5: =VLOOKUP(B5,「工具标准名」映射表!B:I,2,0) -> 智慧手环 | D5: =VLOOKUP(C5,「工具标准名」映射表!$C$1:$O$2046,2,0) -> 智慧手环 | E5: 温州市 | F5: =VLOOKUP(E5,省份映射!$B$1:$C$472,2,0) -> 浙江省 | H5: 智慧手环 | I5: 1
A6: 第02号案例_2温州市新田园小学朱朝炜《三维联动：人工智能视域下小学足球运球游戏设计与研究》.pdf | B6: AI分析系统 | C6: =VLOOKUP(B6,「工具标准名」映射表!B:I,2,0) -> AI分析系统 | D6: =VLOOKUP(C6,「工具标准名」映射表!$C$1:$O$2046,2,0) -> AI分析系统 | E6: 温州市 | F6: =VLOOKUP(E6,省份映射!$B$1:$C$472,2,0) -> 浙江省 | H6: AI分析系统 | I6: 1
A7: 第03号案例_3【案例】从赋能到内生：智能评测驱动“教学评一致”的机理与路径探寻.pdf | B7: 易点慧语音型学习机 | C7: =VLOOKUP(B7,「工具标准名」映射表!B:I,2,0) -> 易点慧AI | D7: =VLOOKUP(C7,「工具标准名」映射表!$C$1:$O$2046,2,0) -> 易点慧AI | E7: 温州市 | F7: =VLOOKUP(E7,省份映射!$B$1:$C$472,2,0) -> 浙江省 | H7: 易点慧AI | I7: 4
A8: 第04号案例_AI赋能地理课堂——七大洲轮廓记忆消消乐申报书.docx | B8: 七大洲速记挑战 | C8: =VLOOKUP(B8,「工具标准名」映射表!B:I,2,0) -> 七大洲速记挑战 | D8: =VLOOKUP(C8,「工具标准名」映射表!$C$1:$O$2046,2,0) -> 七大洲速记挑战 | E8: 重庆市璧山区 | F8: =VLOOKUP(E8,省份映射!$B$1:$C$472,2,0) -> 重庆市 | H8: 七大洲速记挑战 | I8: 2
A9: 第07号案例_案例申报书.docx | B9: DeepSeek | C9: =VLOOKUP(B9,「工具标准名」映射表!B:I,2,0) -> DeepSeek 大模型 | D9: =VLOOKUP(C9,「工具标准名」映射表!$C$1:$O$2046,2,0) -> DeepSeek 大模型 | E9: 重庆市北碚区 | F9: =VLOOKUP(E9,省份映射!$B$1:$C$472,2,0) -> 重庆市 | H9: DeepSeek 大模型 | I9: 289
A10: 第07号案例_案例申报书.docx | B10: 可灵AI | C10: =VLOOKUP(B10,「工具标准名」映射表!B:I,2,0) -> 可灵AI | D10: =VLOOKUP(C10,「工具标准名」映射表!$C$1:$O$2046,2,0) -> 可灵AI | E10: 重庆市北碚区 | F10: =VLOOKUP(E10,省份映射!$B$1:$C$472,2,0) -> 重庆市 | H10: 可灵AI | I10: 6
A11: 第07号案例_案例申报书.docx | B11: 豆包 | C11: =VLOOKUP(B11,「工具标准名」映射表!B:I,2,0) -> 豆包 | D11: =VLOOKUP(C11,「工具标准名」映射表!$C$1:$O$2046,2,0) -> 豆包 | E11: 重庆市北碚区 | F11: =VLOOKUP(E11,省份映射!$B$1:$C$472,2,0) -> 重庆市 | H11: 豆包 | I11: 387
A12: 第08号案例_8川外科中-《AI智教分析：教学相长的协同创新》案例.docx | B12: 未来教室 | C12: =VLOOKUP(B12,「工具标准名」映射表!B:I,2,0) -> 未来教室 | D12: =VLOOKUP(C12,「工具标准名」映射表!$C$1:$O$2046,2,0) -> 未来教室 | E12: 重庆高新区 | F12: =VLOOKUP(E12,省份映射!$B$1:$C$472,2,0) -> 重庆市 | H12: 未来教室 | I12: 2
A13: 第08号案例_8川外科中-《AI智教分析：教学相长的协同创新》案例.docx | B13: 壹教云系统 | C13: =VLOOKUP(B13,「工具标准名」映射表!B:I,2,0) -> 壹教云系统 | D13: =VLOOKUP(C13,「工具标准名」映射表!$C$1:$O$2046,2,0) -> 壹教云系统 | E13: 重庆高新区 | F13: =VLOOKUP(E13,省份映射!$B$1:$C$472,2,0) -> 重庆市 | H13: 壹教云系统 | I13: 1
... A100: 第62号案例_（冯怡）人工智能+基础教育案例.docx | B100: AI智批系统 | C100: =VLOOKUP(B100,「工具标准名」映射表!B:I,2,0) -> AI智批系统 | D100: =VLOOKUP(C100,「工具标准名」映射表!$C$1:$O$2046,2,0) -> AI智批系统 | E100: 嘉兴市 | F100: =VLOOKUP(E100,省份映射!$B$1:$C$472,2,0) -> 浙江省 | H100: 讯飞星火 | I100: 11
A101: 第63号案例_“人工智能+基础教育”典型案例申报表.pdf | C101: =VLOOKUP(B101,「工具标准名」映射表!B:I,2,0) -> #N/A | D101: =VLOOKUP(C101,「工具标准名」映射表!$C$1:$O$2046,2,0) -> #N/A | E101: 未提及 | F101: =VLOOKUP(E101,省份映射!$B$1:$C$472,2,0) -> 未提及 | H101: UMU在线平台 | I101: 1
A102: 第64号案例_人工智能+作业批改 典型应用场景案例.docx | B102: 蜜蜂家校 | C102: =VLOOKUP(B102,「工具标准名」映射表!B:I,2,0) -> 蜜蜂家校 | D102: =VLOOKUP(C102,「工具标准名」映射表!$C$1:$O$2046,2,0) -> 蜜蜂家校 | E102: 保定市清苑区 | F102: =VLOOKUP(E102,省份映射!$B$1:$C$472,2,0) -> 河北省 | H102: AICG平台 | I102: 1
A103: 第65号案例_成都七中初中附属小学+数智赋能小学作业治理：精准画像与个性化.docx | B103: AI学情分析平台 | C103: =VLOOKUP(B103,「工具标准名」映射表!B:I,2,0) -> AI学情分析平台 | D103: =VLOOKUP(C103,「工具标准名」映射表!$C$1:$O$2046,2,0) -> AI学情分析平台 | E103: 成都 | F103: =VLOOKUP(E103,省份映射!$B$1:$C$472,2,0) -> 四川省 | H103: 飞书AI | I103: 12
A104: 第65号案例_成都七中初中附属小学+数智赋能小学作业治理：精准画像与个性化.docx | B104: AI点阵笔 | C104: =VLOOKUP(B104,「工具标准名」映射表!B:I,2,0) -> AI点阵笔 | D104: =VLOOKUP(C104,「工具标准名」映射表!$C$1:$O$2046,2,0) -> AI点阵笔 | E104: 成都 | F104: =VLOOKUP(E104,省份映射!$B$1:$C$472,2,0) -> 四川省 | H104: 词云工具 | I104: 1
A105: 第66号案例_成都东部新区第七中学校（成都七中东部学校）+从即时诊断到动态干预：基于智慧纸笔的智能批改与个性化辅导实践 申报书.pdf | B105: 智慧纸笔 | C105: =VLOOKUP(B105,「工具标准名」映射表!B:I,2,0) -> 智慧纸笔 | D105: =VLOOKUP(C105,「工具标准名」映射表!$C$1:$O$2046,2,0) -> 智慧纸笔 | E105: 成都东部新区 | F105: =VLOOKUP(E105,省份映射!$B$1:$C$472,2,0) -> 四川省 | H105: 神笔作文批改 | I105: 3
A106: 第67号案例_成都石室东部新区实验学校-“人工智能+基础教育”典型应用案例申报书.pdf | B106: 数智作业系统 | C106: =VLOOKUP(B106,「工具标准名」映射表!B:I,2,0) -> 数智作业系统 | D106: =VLOOKUP(C106,「工具标准名」映射表!$C$1:$O$2046,2,0) -> 数智作业系统 | E106: 成都 | F106: =VLOOKUP(E106,省份映射!$B$1:$C$472,2,0) -> 四川省 | H106: AI模型 | I106: 1
A107: 第67号案例_成都石室东部新区实验学校-“人工智能+基础教育”典型应用案例申报书.pdf | B107: 精准教学大数据系统 | C107: =VLOOKUP(B107,「工具标准名」映射表!B:I,2,0) -> 精准教学大数据系统 | D107: =VLOOKUP(C107,「工具标准名」映射表!$C$1:$O$2046,2,0) -> 精准教学大数据系统 | E107: 成都 | F107: =VLOOKUP(E107,省份映射!$B$1:$C$472,2,0) -> 四川省 | H107: 智学数学 | I107: 1
A108: 第68号案例_成都市实验小学+趣味化·个性化·智能化：“天天跳绳”App重塑小学体育作业新样态.docx | B108: 天天跳绳App | C108: =VLOOKUP(B108,「工具标准名」映射表!B:I,2,0) -> 天天跳绳App | D108: =VLOOKUP(C108,「工具标准名」映射表!$C$1:$O$2046,2,0) -> 天天跳绳 | E108: 成都市 | F108: =VLOOKUP(E108,省份映射!$B$1:$C$472,2,0) -> 四川省 | H108: 希沃家长通 | I108: 1
A109: 第69号案例_成都信息工程大学红樱实验学校+基于智能批阅系统的作业设计与批改实践申报书.docx | B109: 希沃作业学情采集分析系统 | C109: =VLOOKUP(B109,「工具标准名」映射表!B:I,2,0) -> 希沃作业学情采集分析系统 | D109: =VLOOKUP(C109,「工具标准名」映射表!$C$1:$O$2046,2,0) -> 希沃作业学情采集分析系统 | E109: 成都 | F109: =VLOOKUP(E109,省份映射!$B$1:$C$472,2,0) -> 四川省 | H109: Ima智能工作台 | I109: 1
A110: 第69号案例_成都信息工程大学红樱实验学校+基于智能批阅系统的作业设计与批改实践申报书.docx | B110: 判判智能批阅系统 | C110: =VLOOKUP(B110,「工具标准名」映射表!B:I,2,0) -> 判判智能批阅系统 | D110: =VLOOKUP(C110,「工具标准名」映射表!$C$1:$O$2046,2,0) -> 判判智能批阅系统 | E110: 成都 | F110: =VLOOKUP(E110,省份映射!$B$1:$C$472,2,0) -> 四川省 | H110: 千师大模型 | I110: 2
A111: 第70号案例_大同市云州区苏家寨中心学校曹宇香基于AI的小学数学精准化学习与辅助系统案例申报书.docx | B111: 智能作业设计与批改系统 | C111: =VLOOKUP(B111,「工具标准名」映射表!B:I,2,0) -> 智能作业设计与批改系统 | D111: =VLOOKUP(C111,「工具标准名」映射表!$C$1:$O$2046,2,0) -> 智能作业设计与批改系统 | E111: 大同市云州区 | F111: =VLOOKUP(E111,省份映射!$B$1:$C$472,2,0) -> 山西省 | H111: 定制化扫印批阅一体机 | I111: 2
A112: 第71号案例_海盐高级中学+杨晶“人工智能+基础教育”典型应用场景案例申报书.docx | B112: AI作业生成系统 | C112: =VLOOKUP(B112,「工具标准名」映射表!B:I,2,0) -> AI作业生成系统 | D112: =VLOOKUP(C112,「工具标准名」映射表!$C$1:$O$2046,2,0) -> AI作业生成系统 | E112: 海盐 | F112: =VLOOKUP(E112,省份映射!$B$1:$C$472,2,0) -> 浙江省 | H112: 平谷教育在线平台 | I112: 2
A113: 第73号案例_成都七中华溪AI助力高中英语数字化教学效能提升的实践研究.docx | B113: 天学网AI智能批改平台 | C113: =VLOOKUP(B113,「工具标准名」映射表!B:I,2,0) -> 天学网AI智能批改平台 | D113: =VLOOKUP(C113,「工具标准名」映射表!$C$1:$O$2046,2,0) -> 天学网AI智能批改平台 | E113: 成都 | F113: =VLOOKUP(E113,省份映射!$B$1:$C$472,2,0) -> 四川省 | H113: GAI写作工坊 | I113: 1
... A182: 第110号案例_人工智能+基础教育 应用案例 AI 慧眼识出入 无感智护校园安 申报书.docx | B182: 智慧校园请假系统 | C182: =VLOOKUP(B182,「工具标准名」映射表!B:I,2,0) -> 智慧校园请假系统 | D182: =VLOOKUP(C182,「工具标准名」映射表!$C$1:$O$2046,2,0) -> 智慧校园请假系统 | E182: 陕西省 | F182: =VLOOKUP(E182,省份映射!$B$1:$C$472,2,0) -> 陕西省 | H182: 沉浸式数学游戏 | I182: 1
A183: 第112号案例_典型应用案例申报书-石外.docx | C183: =VLOOKUP(B183,「工具标准名」映射表!B:I,2,0) -> #N/A | D183: =VLOOKUP(C183,「工具标准名」映射表!$C$1:$O$2046,2,0) -> #N/A | E183: 石家庄 | F183: =VLOOKUP(E183,省份映射!$B$1:$C$472,2,0) -> 河北省 | H183: Phyphox | I183: 3
A184: 第113号案例_《人工智能+基础教育》全域校园人机伴生智慧管理模式申报书.pdf | B184: 钉钉办公平台 | C184: =VLOOKUP(B184,「工具标准名」映射表!B:I,2,0) -> 钉钉AI | D184: =VLOOKUP(C184,「工具标准名」映射表!$C$1:$O$2046,2,0) -> 钉钉 | E184: 未提及 | F184: =VLOOKUP(E184,省份映射!$B$1:$C$472,2,0) -> 未提及 | H184: 音频发生器 | I184: 1
A185: 第113号案例_《人工智能+基础教育》全域校园人机伴生智慧管理模式申报书.pdf | B185: 通义千问大模型 | C185: =VLOOKUP(B185,「工具标准名」映射表!B:I,2,0) -> 通义千问大模型 | D185: =VLOOKUP(C185,「工具标准名」映射表!$C$1:$O$2046,2,0) -> 通义千问大模型 | E185: 未提及 | F185: =VLOOKUP(E185,省份映射!$B$1:$C$472,2,0) -> 未提及 | H185: 逐帧播放器 | I185: 1
A186: 第114号案例_“人工智能+基础教育”典型应用场景案例申报书.pdf | B186: 红色智慧行政助理 | C186: =VLOOKUP(B186,「工具标准名」映射表!B:I,2,0) -> 红色智慧行政助理 | D186: =VLOOKUP(C186,「工具标准名」映射表!$C$1:$O$2046,2,0) -> 红色智慧行政助理 | E186: 重庆市沙坪坝区 | F186: =VLOOKUP(E186,省份映射!$B$1:$C$472,2,0) -> 重庆市 | H186: AI智能考评终端 | I186: 1
A187: 第114号案例_“人工智能+基础教育”典型应用场景案例申报书.pdf | B187: 百度飞桨PaddlePaddle | C187: =VLOOKUP(B187,「工具标准名」映射表!B:I,2,0) -> 百度飞桨 | D187: =VLOOKUP(C187,「工具标准名」映射表!$C$1:$O$2046,2,0) -> 百度飞桨 | E187: 重庆市沙坪坝区 | F187: =VLOOKUP(E187,省份映射!$B$1:$C$472,2,0) -> 重庆市 | H187: 虚拟仿真实验室 | I187: 1
A188: 第115号案例_附件.docx | C188: =VLOOKUP(B188,「工具标准名」映射表!B:I,2,0) -> #N/A | D188: =VLOOKUP(C188,「工具标准名」映射表!$C$1:$O$2046,2,0) -> #N/A | E188: 宁波市奉化区 | F188: =VLOOKUP(E188,省份映射!$B$1:$C$472,2,0) -> 浙江省 | H188: AI实验室数据分析系统 | I188: 1
A189: 第116号案例_山东师大附中案例申报书（智慧物联，用AI提升高中学校资产管理实效——以山东师范大学附属中学为例）.docx | B189: 锦大模型 | C189: =VLOOKUP(B189,「工具标准名」映射表!B:I,2,0) -> 锦大模型 | D189: =VLOOKUP(C189,「工具标准名」映射表!$C$1:$O$2046,2,0) -> 锦大模型 | E189: 山东 | F189: =VLOOKUP(E189,省份映射!$B$1:$C$472,2,0) -> 山东省 | H189: Cities Skylines | I189: 2
A190: 第116号案例_山东师大附中案例申报书（智慧物联，用AI提升高中学校资产管理实效——以山东师范大学附属中学为例）.docx | B190: 资产管理平台 | C190: =VLOOKUP(B190,「工具标准名」映射表!B:I,2,0) -> 资产管理平台 | D190: =VLOOKUP(C190,「工具标准名」映射表!$C$1:$O$2046,2,0) -> 资产管理平台 | E190: 山东 | F190: =VLOOKUP(E190,省份映射!$B$1:$C$472,2,0) -> 山东省 | H190: SunoAI | I190: 2
A191: 第117号案例_1.“人工智能+基础教育”典型应用场景案例申报书.docx | B191: 豆包 | C191: =VLOOKUP(B191,「工具标准名」映射表!B:I,2,0) -> 豆包 | D191: =VLOOKUP(C191,「工具标准名」映射表!$C$1:$O$2046,2,0) -> 豆包 | E191: 重庆市渝北区 | F191: =VLOOKUP(E191,省份映射!$B$1:$C$472,2,0) -> 重庆市 | H191: 教室一体机 | I191: 1
A192: 第117号案例_1.“人工智能+基础教育”典型应用场景案例申报书.docx | B192: 通义千问 | C192: =VLOOKUP(B192,「工具标准名」映射表!B:I,2,0) -> 通义千问大模型 | D192: =VLOOKUP(C192,「工具标准名」映射表!$C$1:$O$2046,2,0) -> 通义千问大模型 | E192: 重庆市渝北区 | F192: =VLOOKUP(E192,省份映射!$B$1:$C$472,2,0) -> 重庆市 | H192: 学生评价数智驾驶舱 | I192: 1
A193: 第117号案例_1.“人工智能+基础教育”典型应用场景案例申报书.docx | B193: 文心一言 | C193: =VLOOKUP(B193,「工具标准名」映射表!B:I,2,0) -> 文心一言 | D193: =VLOOKUP(C193,「工具标准名」映射表!$C$1:$O$2046,2,0) -> 文心一言 | E193: 重庆市渝北区 | F193: =VLOOKUP(E193,省份映射!$B$1:$C$472,2,0) -> 重庆市 | H193: AI听说课堂 | I193: 6
A194: 第117号案例_1.“人工智能+基础教育”典型应用场景案例申报书.docx | B194: 可灵 | C194: =VLOOKUP(B194,「工具标准名」映射表!B:I,2,0) -> 可灵AI | D194: =VLOOKUP(C194,「工具标准名」映射表!$C$1:$O$2046,2,0) -> 可灵AI | E194: 重庆市渝北区 | F194: =VLOOKUP(E194,省份映射!$B$1:$C$472,2,0) -> 重庆市 | H194: 豆包AI绘画 | I194: 5
A195: 第117号案例_1.“人工智能+基础教育”典型应用场景案例申报书.docx | B195: 即梦 | C195: =VLOOKUP(B195,「工具标准名」映射表!B:I,2,0) -> 即梦AI | D195: =VLOOKUP(C195,「工具标准名」映射表!$C$1:$O$2046,2,0) -> 即梦AI | E195: 重庆市渝北区 | F195: =VLOOKUP(E195,省份映射!$B$1:$C$472,2,0) -> 重庆市 | H195: AI阅卷系统 | I195: 1
A196: 第118号案例_118东营市河口区河口街道中心小学人工智能 + 基础教育”案例.docx | B196: AI学情分析平台 | C196: =VLOOKUP(B196,「工具标准名」映射表!B:I,2,0) -> AI学情分析平台 | D196: =VLOOKUP(C196,「工具标准名」映射表!$C$1:$O$2046,2,0) -> AI学情分析平台 | E196: 东营市河口区 | F196: =VLOOKUP(E196,省份映射!$B$1:$C$472,2,0) -> 山东省 | H196: AI教研员 | I196: 2
A197: 第118号案例_118东营市河口区河口街道中心小学人工智能 + 基础教育”案例.docx | B197: AI互动工具 | C197: =VLOOKUP(B197,「工具标准名」映射表!B:I,2,0) -> AI互动工具 | D197: =VLOOKUP(C197,「工具标准名」映射表!$C$1:$O$2046,2,0) -> AI互动工具 | E197: 东营市河口区 | F197: =VLOOKUP(E197,省份映射!$B$1:$C$472,2,0) -> 山东省 | H197: 班级优化大师 | I197: 14
A198: 第118号案例_118东营市河口区河口街道中心小学人工智能 + 基础教育”案例.docx | B198: 智能作业系统 | C198: =VLOOKUP(B198,「工具标准名」映射表!B:I,2,0) -> 智能作业系统 | D198: =VLOOKUP(C198,「工具标准名」映射表!$C$1:$O$2046,2,0) -> 智能作业系统 | E198: 东营市河口区 | F198: =VLOOKUP(E198,省份映射!$B$1:$C$472,2,0) -> 山东省 | H198: 希沃课堂诊断系统 | I198: 1
A199: 第118号案例_118东营市河口区河口街道中心小学人工智能 + 基础教育”案例.docx | B199: 智慧校园管理平台 | C199: =VLOOKUP(B199,「工具标准名」映射表!B:I,2,0) -> 智慧校园管理平台 | D199: =VLOOKUP(C199,「工具标准名」映射表!$C$1:$O$2046,2,0) -> 智慧校园管理平台 | E199: 东营市河口区 | F199: =VLOOKUP(E199,省份映射!$B$1:$C$472,2,0) -> 山东省 | H199: 一教一学纸笔互动系统 | I199: 1
A200: 第118号案例_118东营市河口区河口街道中心小学人工智能 + 基础教育”案例.docx | B200: AI教学质量分析系统 | C200: =VLOOKUP(B200,「工具标准名」映射表!B:I,2,0) -> AI教学质量分析系统 | D200: =VLOOKUP(C200,「工具标准名」映射表!$C$1:$O$2046,2,0) -> AI教学质量分析系统 | E200: 东营市河口区 | F200: =VLOOKUP(E200,省份映射!$B$1:$C$472,2,0) -> 山东省 | H200: 睿知云 | I200: 6
... A219: 第127号案例_申报书.docx | B219: DeepSeek | C219: =VLOOKUP(B219,「工具标准名」映射表!B:I,2,0) -> DeepSeek 大模型 | D219: =VLOOKUP(C219,「工具标准名」映射表!$C$1:$O$2046,2,0) -> DeepSeek 大模型 | E219: 沧州市 | F219: =VLOOKUP(E219,省份映射!$B$1:$C$472,2,0) -> 河北省 | H219: 智慧课堂系统 | I219: 1
A220: 第130号案例_AI双向赋能实验课堂.pdf | C220: =VLOOKUP(B220,「工具标准名」映射表!B:I,2,0) -> #N/A | D220: =VLOOKUP(C220,「工具标准名」映射表!$C$1:$O$2046,2,0) -> #N/A | E220: 山东省 | F220: =VLOOKUP(E220,省份映射!$B$1:$C$472,2,0) -> 山东省 | H220: 智能语音评测系统 | I220: 1
A221: 第131号案例_海盐县实验小学教育集团姚怡然+“人工智能+基础教育”典型应用场景案例申报书 .docx | B221: 央馆AI科学实验平台 | C221: =VLOOKUP(B221,「工具标准名」映射表!B:I,2,0) -> 央馆领航AI | D221: =VLOOKUP(C221,「工具标准名」映射表!$C$1:$O$2046,2,0) -> 央馆领航AI | E221: 海盐县 | F221: =VLOOKUP(E221,省份映射!$B$1:$C$472,2,0) -> 浙江省 | H221: AI语音助手 | I221: 1
A222: 第132号案例_附件1.“人工智能+基础教育”典型应用场景案例申报书（海盐县武原中学教育集团沈利娟）.docx | B222: AI课堂顾问 | C222: =VLOOKUP(B222,「工具标准名」映射表!B:I,2,0) -> AI课堂顾问 | D222: =VLOOKUP(C222,「工具标准名」映射表!$C$1:$O$2046,2,0) -> AI课堂顾问 | E222: 海盐县 | F222: =VLOOKUP(E222,省份映射!$B$1:$C$472,2,0) -> 浙江省 | H222: mBot教育机器人套件 | I222: 1
A223: 第133号案例_1.“人工智能+基础教育”典型应.docx | B223: 豆包AI | C223: =VLOOKUP(B223,「工具标准名」映射表!B:I,2,0) -> 豆包 | D223: =VLOOKUP(C223,「工具标准名」映射表!$C$1:$O$2046,2,0) -> 豆包 | E223: 黑龙江省 | F223: =VLOOKUP(E223,省份映射!$B$1:$C$472,2,0) -> 黑龙江省 | H223: mBlock图形化编程软件 | I223: 1
A224: 第133号案例_1.“人工智能+基础教育”典型应.docx | B224: 即梦AI | C224: =VLOOKUP(B224,「工具标准名」映射表!B:I,2,0) -> 即梦AI | D224: =VLOOKUP(C224,「工具标准名」映射表!$C$1:$O$2046,2,0) -> 即梦AI | E224: 黑龙江省 | F224: =VLOOKUP(E224,省份映射!$B$1:$C$472,2,0) -> 黑龙江省 | H224: 极课大数据系统 | I224: 1
A225: 第134号案例_关于征集“人工智能+基础教育”典型应用场景案例的通知.docx | B225: 减数分裂模拟器 | C225: =VLOOKUP(B225,「工具标准名」映射表!B:I,2,0) -> 减数分裂模拟器 | D225: =VLOOKUP(C225,「工具标准名」映射表!$C$1:$O$2046,2,0) -> 减数分裂模拟器 | E225: 大连经济技术开发区 | F225: =VLOOKUP(E225,省份映射!$B$1:$C$472,2,0) -> 辽宁省 | H225: SMI混合学习平台 | I225: 1
A226: 第135号案例_“人工智能+基础教育”典型应用场景案例申报书.docx | B226: DeepSeek | C226: =VLOOKUP(B226,「工具标准名」映射表!B:I,2,0) -> DeepSeek 大模型 | D226: =VLOOKUP(C226,「工具标准名」映射表!$C$1:$O$2046,2,0) -> DeepSeek 大模型 | E226: 未提及 | F226: =VLOOKUP(E226,省份映射!$B$1:$C$472,2,0) -> 未提及 | H226: 智能备课助手 | I226: 4
A227: 第136号案例_AI赋能,穿越千年——沉浸式“唐三彩”博物馆虚拟研学实践-----刘巧.宋婷婷.docx | B227: 小云雀 | C227: =VLOOKUP(B227,「工具标准名」映射表!B:I,2,0) -> 小云雀 | D227: =VLOOKUP(C227,「工具标准名」映射表!$C$1:$O$2046,2,0) -> 小云雀 | E227: 重庆市 | F227: =VLOOKUP(E227,省份映射!$B$1:$C$472,2,0) -> 重庆市 | H227: 智评作业助手 | I227: 1
A228: 第137号案例_申报书+陆高原+AI 助力高中化学实验教学创新-氢氧化亚铁的制备” 实践案例.pdf | B228: 豆包 | C228: =VLOOKUP(B228,「工具标准名」映射表!B:I,2,0) -> 豆包 | D228: =VLOOKUP(C228,「工具标准名」映射表!$C$1:$O$2046,2,0) -> 豆包 | E228: 上海市 | F228: =VLOOKUP(E228,省份映射!$B$1:$C$472,2,0) -> 上海市 | H228: AI创意工具 | I228: 1
A229: 第137号案例_申报书+陆高原+AI 助力高中化学实验教学创新-氢氧化亚铁的制备” 实践案例.pdf | B229: 高中化学实验方案AI评估模块 | C229: =VLOOKUP(B229,「工具标准名」映射表!B:I,2,0) -> 高中化学实验方案AI评估模块 | D229: =VLOOKUP(C229,「工具标准名」映射表!$C$1:$O$2046,2,0) -> 高中化学实验方案AI评估模块 | E229: 上海市 | F229: =VLOOKUP(E229,省份映射!$B$1:$C$472,2,0) -> 上海市 | H229: 千问21.5B人工智能软件 | I229: 1
A230: 第137号案例_申报书+陆高原+AI 助力高中化学实验教学创新-氢氧化亚铁的制备” 实践案例.pdf | B230: 三个助手互动模拟实验平台 | C230: =VLOOKUP(B230,「工具标准名」映射表!B:I,2,0) -> 三个助手 | D230: =VLOOKUP(C230,「工具标准名」映射表!$C$1:$O$2046,2,0) -> 三个助手 | E230: 上海市 | F230: =VLOOKUP(E230,省份映射!$B$1:$C$472,2,0) -> 上海市 | H230: 硅基流动公司API | I230: 1
A231: 第138号案例_人工智能赋能高中信息技术教学——基于交互式网页的教学练一体化实践案例（徐雪婷）.pdf | B231: DeepSeek | C231: =VLOOKUP(B231,「工具标准名」映射表!B:I,2,0) -> DeepSeek 大模型 | D231: =VLOOKUP(C231,「工具标准名」映射表!$C$1:$O$2046,2,0) -> DeepSeek 大模型 | E231: 上海市 | F231: =VLOOKUP(E231,省份映射!$B$1:$C$472,2,0) -> 上海市 | H231: 希沃知识胶囊 | I231: 1
A232: 第139号案例_1.上外松外-温胜利-探秘AI理解语言的奥秘.pdf | B232: 腾讯青少年人工智能教育平台 | C232: =VLOOKUP(B232,「工具标准名」映射表!B:I,2,0) -> 腾讯青少年人工智能教育平台 | D232: =VLOOKUP(C232,「工具标准名」映射表!$C$1:$O$2046,2,0) -> 腾讯青少年人工智能教育平台 | E232: 上海 | F232: =VLOOKUP(E232,省份映射!$B$1:$C$472,2,0) -> 上海市 | H232: AI阅读智能体 | I232: 1
... A288: 第169号案例_北京育才学校“人工智能+基础教育”典型应用场景案例.docx | B288: Edubba平台 | C288: =VLOOKUP(B288,「工具标准名」映射表!B:I,2,0) -> Edubba平台 | D288: =VLOOKUP(C288,「工具标准名」映射表!$C$1:$O$2046,2,0) -> Edubba平台 | E288: 北京市 | F288: =VLOOKUP(E288,省份映射!$B$1:$C$472,2,0) -> 北京市 | H288: 智慧畅言课堂 | I288: 1
A289: 第170号案例_成都七中万达学校-刘桂麟-基于专精知识库的AI答疑系统.docx | B289: AI答疑系统 | C289: =VLOOKUP(B289,「工具标准名」映射表!B:I,2,0) -> AI答疑系统 | D289: =VLOOKUP(C289,「工具标准名」映射表!$C$1:$O$2046,2,0) -> AI答疑系统 | E289: 成都 | F289: =VLOOKUP(E289,省份映射!$B$1:$C$472,2,0) -> 四川省 | H289: 0 | I289: 1
A290: 第170号案例_成都七中万达学校-刘桂麟-基于专精知识库的AI答疑系统.docx | B290: DeepSeek R1 | C290: =VLOOKUP(B290,「工具标准名」映射表!B:I,2,0) -> DeepSeek 大模型 | D290: =VLOOKUP(C290,「工具标准名」映射表!$C$1:$O$2046,2,0) -> DeepSeek 大模型 | E290: 成都 | F290: =VLOOKUP(E290,省份映射!$B$1:$C$472,2,0) -> 四川省 | H290: 数学解题 AI 智问 | I290: 1
A291: 第170号案例_成都七中万达学校-刘桂麟-基于专精知识库的AI答疑系统.docx | B291: 通义千问 | C291: =VLOOKUP(B291,「工具标准名」映射表!B:I,2,0) -> 通义千问大模型 | D291: =VLOOKUP(C291,「工具标准名」映射表!$C$1:$O$2046,2,0) -> 通义千问大模型 | E291: 成都 | F291: =VLOOKUP(E291,省份映射!$B$1:$C$472,2,0) -> 四川省 | H291: AI教学助手 | I291: 1
A292: 第171号案例_东北师大附中初中部“人工智能+基础教育”典型案例(1).pdf | B292: E听说 | C292: =VLOOKUP(B292,「工具标准名」映射表!B:I,2,0) -> E听说 | D292: =VLOOKUP(C292,「工具标准名」映射表!$C$1:$O$2046,2,0) -> E听说 | E292: 吉林省 | F292: =VLOOKUP(E292,省份映射!$B$1:$C$472,2,0) -> 吉林省 | H292: AI智慧体育操场 | I292: 1
A293: 第171号案例_东北师大附中初中部“人工智能+基础教育”典型案例(1).pdf | B293: AI听说课堂 | C293: =VLOOKUP(B293,「工具标准名」映射表!B:I,2,0) -> AI听说课堂 | D293: =VLOOKUP(C293,「工具标准名」映射表!$C$1:$O$2046,2,0) -> AI听说课堂 | E293: 吉林省 | F293: =VLOOKUP(E293,省份映射!$B$1:$C$472,2,0) -> 吉林省 | H293: AI辅助教学系统 | I293: 1
A294: 第171号案例_东北师大附中初中部“人工智能+基础教育”典型案例(1).pdf | B294: 教考平台 | C294: =VLOOKUP(B294,「工具标准名」映射表!B:I,2,0) -> 教考平台 | D294: =VLOOKUP(C294,「工具标准名」映射表!$C$1:$O$2046,2,0) -> 教考平台 | E294: 吉林省 | F294: =VLOOKUP(E294,省份映射!$B$1:$C$472,2,0) -> 吉林省 | H294: Tinkercad | I294: 1
A295: 第172号案例_海盐高级中学+冯凯伦+“人工智能+基础教育”典型应用场景案例申报书.docx | B295: 盐高地理组智能体 | C295: =VLOOKUP(B295,「工具标准名」映射表!B:I,2,0) -> 盐高地理组智能体 | D295: =VLOOKUP(C295,「工具标准名」映射表!$C$1:$O$2046,2,0) -> 盐高地理组智能体 | E295: 海盐 | F295: =VLOOKUP(E295,省份映射!$B$1:$C$472,2,0) -> 浙江省 | H295: 大鱼云展 | I295: 6
A296: 第173号案例_海盐县实验中学教育集团杨晨帆：基于DeepSeek API的智能学情分析工具申报书.docx | B296: 智能学情分析工具 | C296: =VLOOKUP(B296,「工具标准名」映射表!B:I,2,0) -> 智能学情分析工具 | D296: =VLOOKUP(C296,「工具标准名」映射表!$C$1:$O$2046,2,0) -> 智能学情分析工具 | E296: 海盐县 | F296: =VLOOKUP(E296,省份映射!$B$1:$C$472,2,0) -> 浙江省 | H296: AI星火 | I296: 1
A297: 第175号案例_1.“人工智能+基础教育”典型应用场景案例申报书.docx | B297: 智能运动手环 | C297: =VLOOKUP(B297,「工具标准名」映射表!B:I,2,0) -> 智能运动手环 | D297: =VLOOKUP(C297,「工具标准名」映射表!$C$1:$O$2046,2,0) -> 智能运动手环 | E297: 杭州市 | F297: =VLOOKUP(E297,省份映射!$B$1:$C$472,2,0) -> 浙江省 | H297: AI情境创设工具 | I297: 2
A298: 第175号案例_1.“人工智能+基础教育”典型应用场景案例申报书.docx | B298: 教学分析系统 | C298: =VLOOKUP(B298,「工具标准名」映射表!B:I,2,0) -> 教学分析系统 | D298: =VLOOKUP(C298,「工具标准名」映射表!$C$1:$O$2046,2,0) -> 教学分析系统 | E298: 杭州市 | F298: =VLOOKUP(E298,省份映射!$B$1:$C$472,2,0) -> 浙江省 | H298: AI智能反馈系统 | I298: 2
A299: 第175号案例_1.“人工智能+基础教育”典型应用场景案例申报书.docx | B299: 赛事管理系统 | C299: =VLOOKUP(B299,「工具标准名」映射表!B:I,2,0) -> 赛事管理系统 | D299: =VLOOKUP(C299,「工具标准名」映射表!$C$1:$O$2046,2,0) -> 赛事管理系统 | E299: 杭州市 | F299: =VLOOKUP(E299,省份映射!$B$1:$C$472,2,0) -> 浙江省 | H299: 科大讯飞智慧教育平台 | I299: 2
A300: 第175号案例_1.“人工智能+基础教育”典型应用场景案例申报书.docx | B300: 智能体测吧 | C300: =VLOOKUP(B300,「工具标准名」映射表!B:I,2,0) -> 智能体测吧 | D300: =VLOOKUP(C300,「工具标准名」映射表!$C$1:$O$2046,2,0) -> 智能体测吧 | E300: 杭州市 | F300: =VLOOKUP(E300,省份映射!$B$1:$C$472,2,0) -> 浙江省 | H300: AI课堂循证系统 | I300: 2
A301: 第176号案例_AI小车启智：数据驱动下的计算思维个性化培养.docx | B301: Mind+ | C301: =VLOOKUP(B301,「工具标准名」映射表!B:I,2,0) -> Mind+ | D301: =VLOOKUP(C301,「工具标准名」映射表!$C$1:$O$2046,2,0) -> Mind+ | E301: 湖州市 | F301: =VLOOKUP(E301,省份映射!$B$1:$C$472,2,0) -> 浙江省 | H301: 智言语音测评 | I301: 1
... A334: 第193号案例_曹杨二中东校-郭莉+AI循证赋能初中道德与法治政治认同素养评价的实践探索.docx | B334: VR/AR技术 | C334: =VLOOKUP(B334,「工具标准名」映射表!B:I,2,0) -> VR/AR技术 | D334: =VLOOKUP(C334,「工具标准名」映射表!$C$1:$O$2046,2,0) -> VR/AR技术 | E334: 上海市 | F334: =VLOOKUP(E334,省份映射!$B$1:$C$472,2,0) -> 上海市 | H334: AI黑猫警长 | I334: 1
A335: 第194号案例_《智能交互·数据驱动·精准赋能：校园智慧体育应用场景构建》案例申报书.docx | C335: =VLOOKUP(B335,「工具标准名」映射表!B:I,2,0) -> #N/A | D335: =VLOOKUP(C335,「工具标准名」映射表!$C$1:$O$2046,2,0) -> #N/A | E335: 未提及 | F335: =VLOOKUP(E335,省份映射!$B$1:$C$472,2,0) -> 未提及 | H335: AI动画工具 | I335: 3
A336: 第195号案例_重庆市聚奎中学校 案例申报书.docx | B336: 生成式教学智能体 | C336: =VLOOKUP(B336,「工具标准名」映射表!B:I,2,0) -> 生成式教学智能体 | D336: =VLOOKUP(C336,「工具标准名」映射表!$C$1:$O$2046,2,0) -> 生成式教学智能体 | E336: 重庆市 | F336: =VLOOKUP(E336,省份映射!$B$1:$C$472,2,0) -> 重庆市 | H336: 智能研修平台 | I336: 5
A337: 第195号案例_重庆市聚奎中学校 案例申报书.docx | B337: 扣子(coze.cn) | C337: =VLOOKUP(B337,「工具标准名」映射表!B:I,2,0) -> 扣子AI | D337: =VLOOKUP(C337,「工具标准名」映射表!$C$1:$O$2046,2,0) -> 扣子AI | E337: 重庆市 | F337: =VLOOKUP(E337,省份映射!$B$1:$C$472,2,0) -> 重庆市 | H337: AI教学平台 | I337: 1
A338: 第196号案例_196北京实验学校附属中学 王永洪 人工智能终端小猿学练机教学应用与过程性评价实践研究.docx | B338: 小猿学练机 | C338: =VLOOKUP(B338,「工具标准名」映射表!B:I,2,0) -> 小猿AI | D338: =VLOOKUP(C338,「工具标准名」映射表!$C$1:$O$2046,2,0) -> 小猿AI | E338: 北京 | F338: =VLOOKUP(E338,省份映射!$B$1:$C$472,2,0) -> 北京市 | H338: 教师数字画像系统 | I338: 1
A339: 第198号案例_198和田洛浦县三中+郑巧灵+ 智能学情诊断与个性化辅导25.10.23.docx | B339: 智能学情诊断与个性化辅导系统 | C339: =VLOOKUP(B339,「工具标准名」映射表!B:I,2,0) -> 智能学情诊断与个性化辅导系统 | D339: =VLOOKUP(C339,「工具标准名」映射表!$C$1:$O$2046,2,0) -> 智能学情诊断与个性化辅导系统 | E339: 新疆和田洛浦县 | F339: =VLOOKUP(E339,省份映射!$B$1:$C$472,2,0) -> 新疆维吾尔自治区 | H339: 听评课数字化系统 | I339: 1
A340: 第199号案例_199徽山县韩庄镇中心小学-数据驱动下的农村小学精准教学与个性化辅导实践案例.docx | B340: AI作业本 | C340: =VLOOKUP(B340,「工具标准名」映射表!B:I,2,0) -> AI作业本 | D340: =VLOOKUP(C340,「工具标准名」映射表!$C$1:$O$2046,2,0) -> AI作业本 | E340: 微山县 | F340: =VLOOKUP(E340,省份映射!$B$1:$C$472,2,0) -> 山东省 | H340: 希沃智能体 | I340: 3
A341: 第199号案例_199徽山县韩庄镇中心小学-数据驱动下的农村小学精准教学与个性化辅导实践案例.docx | B341: 学情快评 | C341: =VLOOKUP(B341,「工具标准名」映射表!B:I,2,0) -> 学情快评 | D341: =VLOOKUP(C341,「工具标准名」映射表!$C$1:$O$2046,2,0) -> 学情快评 | E341: 微山县 | F341: =VLOOKUP(E341,省份映射!$B$1:$C$472,2,0) -> 山东省 | H341: 智能课堂反馈系统 | I341: 1
A342: 第200号案例_200济南实验高级中学.“人工智能+基础教育”典型应.docx | B342: 麻吉星教学系统 | C342: =VLOOKUP(B342,「工具标准名」映射表!B:I,2,0) -> 麻吉星教学系统 | D342: =VLOOKUP(C342,「工具标准名」映射表!$C$1:$O$2046,2,0) -> 麻吉星教学系统 | E342: 济南 | F342: =VLOOKUP(E342,省份映射!$B$1:$C$472,2,0) -> 山东省 | H342: AI课堂智慧分析平台 | I342: 3
A343: 第200号案例_200济南实验高级中学.“人工智能+基础教育”典型应.docx | B343: AI错题本平台 | C343: =VLOOKUP(B343,「工具标准名」映射表!B:I,2,0) -> AI错题本平台 | D343: =VLOOKUP(C343,「工具标准名」映射表!$C$1:$O$2046,2,0) -> AI错题本平台 | E343: 济南 | F343: =VLOOKUP(E343,省份映射!$B$1:$C$472,2,0) -> 山东省 | H343: 学情智能诊断系统 | I343: 1
A344: 第201号案例_201山东师范大学附属中学-李成金-“人工智能+基础教育”典型案例申报书.docx | B344: 辅立码课平台 | C344: =VLOOKUP(B344,「工具标准名」映射表!B:I,2,0) -> 辅立码课平台 | D344: =VLOOKUP(C344,「工具标准名」映射表!$C$1:$O$2046,2,0) -> 辅立码课平台 | E344: 山东 | F344: =VLOOKUP(E344,省份映射!$B$1:$C$472,2,0) -> 山东省 | H344: 个性化学习路径平台 | I344: 1
A345: 第202号案例_202申报书_“设计机车动力系统”课时案例_“自制热力机车竞赛”AI-PBL单元教学.pdf | B345: Deep Seek | C345: =VLOOKUP(B345,「工具标准名」映射表!B:I,2,0) -> DeepSeek 大模型 | D345: =VLOOKUP(C345,「工具标准名」映射表!$C$1:$O$2046,2,0) -> DeepSeek 大模型 | E345: 重庆市江津区 | F345: =VLOOKUP(E345,省份映射!$B$1:$C$472,2,0) -> 重庆市 | H345: 沉浸式互动学习场景 | I345: 1
A346: 第202号案例_202申报书_“设计机车动力系统”课时案例_“自制热力机车竞赛”AI-PBL单元教学.pdf | B346: 豆包 | C346: =VLOOKUP(B346,「工具标准名」映射表!B:I,2,0) -> 豆包 | D346: =VLOOKUP(C346,「工具标准名」映射表!$C$1:$O$2046,2,0) -> 豆包 | E346: 重庆市江津区 | F346: =VLOOKUP(E346,省份映射!$B$1:$C$472,2,0) -> 重庆市 | H346: PhET虚拟仿真平台 | I346: 1
A347: 第202号案例_202申报书_“设计机车动力系统”课时案例_“自制热力机车竞赛”AI-PBL单元教学.pdf | B347: Padlet | C347: =VLOOKUP(B347,「工具标准名」映射表!B:I,2,0) -> Padlet | D347: =VLOOKUP(C347,「工具标准名」映射表!$C$1:$O$2046,2,0) -> Padlet | E347: 重庆市江津区 | F347: =VLOOKUP(E347,省份映射!$B$1:$C$472,2,0) -> 重庆市 | H347: AI智能课堂评价系统 | I347: 1
... A445: 第245号案例_（俞鹰）“人工智能+基础教育”典型应用场景案例申报书+案例.docx | B445: AI星火 | C445: =VLOOKUP(B445,「工具标准名」映射表!B:I,2,0) -> AI星火 | D445: =VLOOKUP(C445,「工具标准名」映射表!$C$1:$O$2046,2,0) -> AI星火 | E445: 嘉兴市 | F445: =VLOOKUP(E445,省份映射!$B$1:$C$472,2,0) -> 浙江省 | H445: AI听说课堂平台 | I445: 1
A446: 第246号案例_附件1.“人工智能+基础教育”典型应用场景案例申报书.docx | C446: =VLOOKUP(B446,「工具标准名」映射表!B:I,2,0) -> #N/A | D446: =VLOOKUP(C446,「工具标准名」映射表!$C$1:$O$2046,2,0) -> #N/A | E446: 嘉兴市 | F446: =VLOOKUP(E446,省份映射!$B$1:$C$472,2,0) -> 浙江省 | H446: AI English100 | I446: 1
A447: 第247号案例_（苏贤芳）人工智能+基础教育”典型应用场景案例申报书.docx | B447: AI情境创设工具 | C447: =VLOOKUP(B447,「工具标准名」映射表!B:I,2,0) -> AI情境创设工具 | D447: =VLOOKUP(C447,「工具标准名」映射表!$C$1:$O$2046,2,0) -> AI情境创设工具 | E447: 嘉兴市南湖区 | F447: =VLOOKUP(E447,省份映射!$B$1:$C$472,2,0) -> 浙江省 | H447: Ms.Aryn | I447: 1
A448: 第247号案例_（苏贤芳）人工智能+基础教育”典型应用场景案例申报书.docx | B448: AI数字人互动系统 | C448: =VLOOKUP(B448,「工具标准名」映射表!B:I,2,0) -> 数字人 | D448: =VLOOKUP(C448,「工具标准名」映射表!$C$1:$O$2046,2,0) -> AI数字人 | E448: 嘉兴市南湖区 | F448: =VLOOKUP(E448,省份映射!$B$1:$C$472,2,0) -> 浙江省 | H448: 万彩动画大师 | I448: 2
A449: 第247号案例_（苏贤芳）人工智能+基础教育”典型应用场景案例申报书.docx | B449: AI智能反馈系统 | C449: =VLOOKUP(B449,「工具标准名」映射表!B:I,2,0) -> AI智能反馈系统 | D449: =VLOOKUP(C449,「工具标准名」映射表!$C$1:$O$2046,2,0) -> AI智能反馈系统 | E449: 嘉兴市南湖区 | F449: =VLOOKUP(E449,省份映射!$B$1:$C$472,2,0) -> 浙江省 | H449: 学科网 | I449: 1
A450: 第248号案例_包头市田家炳中学+云多+AI学助力高中物理力学三大观点教学案例.pdf | B450: 科大讯飞智慧教育平台 | C450: =VLOOKUP(B450,「工具标准名」映射表!B:I,2,0) -> 科大讯飞智慧教育平台 | D450: =VLOOKUP(C450,「工具标准名」映射表!$C$1:$O$2046,2,0) -> 科大讯飞智慧教育平台 | E450: 包头市 | F450: =VLOOKUP(E450,省份映射!$B$1:$C$472,2,0) -> 内蒙古自治区 | H450: 音创未来 | I450: 1
A451: 第248号案例_包头市田家炳中学+云多+AI学助力高中物理力学三大观点教学案例.pdf | B451: 即梦AI | C451: =VLOOKUP(B451,「工具标准名」映射表!B:I,2,0) -> 即梦AI | D451: =VLOOKUP(C451,「工具标准名」映射表!$C$1:$O$2046,2,0) -> 即梦AI | E451: 包头市 | F451: =VLOOKUP(E451,省份映射!$B$1:$C$472,2,0) -> 内蒙古自治区 | H451: AI辅助创作工具 | I451: 1
A452: 第248号案例_包头市田家炳中学+云多+AI学助力高中物理力学三大观点教学案例.pdf | B452: DeepSeek | C452: =VLOOKUP(B452,「工具标准名」映射表!B:I,2,0) -> DeepSeek 大模型 | D452: =VLOOKUP(C452,「工具标准名」映射表!$C$1:$O$2046,2,0) -> DeepSeek 大模型 | E452: 包头市 | F452: =VLOOKUP(E452,省份映射!$B$1:$C$472,2,0) -> 内蒙古自治区 | H452: 平板辅助英语教学系统 | I452: 2
A453: 第248号案例_包头市田家炳中学+云多+AI学助力高中物理力学三大观点教学案例.pdf | B453: 剪辑 | C453: =VLOOKUP(B453,「工具标准名」映射表!B:I,2,0) -> #N/A | D453: =VLOOKUP(C453,「工具标准名」映射表!$C$1:$O$2046,2,0) -> #N/A | E453: 包头市 | F453: =VLOOKUP(E453,省份映射!$B$1:$C$472,2,0) -> 内蒙古自治区 | H453: 济南市教育资源公共服务平台 | I453: 2
A454: 第249号案例_AI 破界・丈量亿度：《一亿有多大》创新实践案例（闻爱丽）.docx | B454: 豆包 | C454: =VLOOKUP(B454,「工具标准名」映射表!B:I,2,0) -> 豆包 | D454: =VLOOKUP(C454,「工具标准名」映射表!$C$1:$O$2046,2,0) -> 豆包 | E454: 嘉兴市 | F454: =VLOOKUP(E454,省份映射!$B$1:$C$472,2,0) -> 浙江省 | H454: AI生成式创作工具 | I454: 1
A455: 第251号案例_附件1人工智能基础教育典型应用案例申报书.docx | B455: AI课堂循证系统 | C455: =VLOOKUP(B455,「工具标准名」映射表!B:I,2,0) -> AI课堂循证系统 | D455: =VLOOKUP(C455,「工具标准名」映射表!$C$1:$O$2046,2,0) -> AI课堂循证系统 | E455: 宝山区 | F455: =VLOOKUP(E455,省份映射!$B$1:$C$472,2,0) -> 上海市 | H455: VR画展平台 | I455: 1
A456: 第252号案例_范佳慧 附件1.“人工智能+基础教育”典型应用场景案例申报书.pdf | B456: AI听说课堂 | C456: =VLOOKUP(B456,「工具标准名」映射表!B:I,2,0) -> AI听说课堂 | D456: =VLOOKUP(C456,「工具标准名」映射表!$C$1:$O$2046,2,0) -> AI听说课堂 | E456: 嘉兴市 | F456: =VLOOKUP(E456,省份映射!$B$1:$C$472,2,0) -> 浙江省 | H456: 智能备课系统 | I456: 4
...

Sheet 「工具标准名」映射表
A1: 案例名对应 | B1: 原始工具名称（去重后） | C1: 工具标准名 | D1: 产品名（校准） | E1: 分类标准_产业角度（一级） | F1: 分类标准_产业角度（二级） | G1: 分类标准_[教育角度] | H1: 产品属性 | I1: 产品名_是否大模型 | J1: 应用场景（一级） | K1: 应用场景（二级） | M1: 培养方向 | N1: 学科 | O1: 企业名（不填）
A2: 案例 1 | C2: AIGC | J2: 助学 | K2: 智能辅导系统 | M2: 智育 | N2: =VLOOKUP($A2,Sheet1!$A$1:$T$2589,6,0) -> #N/A
A3: 第997号案例_997常州市清潭中学＋”智“影鉴史——AI助力”看电影，学历史“实践探索.docx | B3: 360AI | C3: 360AI | D3: 360AI | E3: 功能应用层 | F3: 功能应用（教学辅助工具） | G3: 软件工具 | H3: AI智能体 | I3: 是 | J3: 助学 | K3: 智能辅导系统 | M3: 智育 | N3: =VLOOKUP($A3,Sheet1!$A$1:$T$2589,6,0) -> 历史
A4: 第1517号案例_1517数字赋能高中思政课堂教学—以实践是认识的基础为例 案例申报书.docx | B4: 3D地图WebGL技术 | C4: 3D地图WebGL技术 | D4: 3D地图WebGL技术 | E4: 功能应用层 | F4: 功能应用（教学辅助工具） | G4: 软件工具 | H4: AI智能体 | I4: 是 | J4: 助学 | K4: 智能辅导系统 | M4: 智育 | N4: =VLOOKUP($A4,Sheet1!$A$1:$T$2589,6,0) -> 政治
A5: 第571号案例_扎兰屯市柴河学校+李艳宇+ AI赋能初中物理实验教学案例.docx | B5: 3D建模工具 | C5: 3D建模工具 | D5: 3D建模工具 | E5: 功能应用层 | F5: 功能应用（教学辅助工具） | G5: 软件工具 | H5: AI智能体 | I5: 是 | J5: 助学 | K5: 游戏化学习 | M5: 体育 | N5: =VLOOKUP($A5,Sheet1!$A$1:$T$2589,6,0) -> 物理
A6: 第826号案例_重庆树人凤天小学+姜永宏+“AI赋能少儿美术家风家训传承与创新实践”典型应用场景案例申报书.pdf | B6: 3D打印技术 | C6: 3D打印技术 | D6: 3D打印技术 | E6: 功能应用层 | F6: 功能应用（教学辅助工具） | G6: 软件工具 | H6: AI智能体 | I6: 是 | J6: 助学 | K6: 游戏化学习 | M6: 体育 | N6: =VLOOKUP($A6,Sheet1!$A$1:$T$2589,6,0) -> 美术
A7: 第1323号案例_AI小车启智，创客空间赋能.docx | B7: 3D打印机 | C7: 3D打印机 | D7: 3D打印机 | E7: 功能应用层 | F7: 功能应用（教学辅助工具） | G7: 硬件设备 | H7: AI智能体 | I7: 否 | J7: 助教 | K7: 智能学情诊断与个性化辅导 | M7: 智育 | N7: =VLOOKUP($A7,Sheet1!$A$1:$T$2589,6,0) -> 人工智能
A8: 第477号案例_“人工智能+基础教育”典型应用 场景案例申报书——上海市盲童学校.docx | B8: 3D打印配子自由组合模型 | C8: 3D打印配子自由组合模型 | D8: 3D打印配子自由组合模型 | E8: 功能应用层 | F8: 功能应用（教学辅助工具） | G8: 软件工具 | H8: AI智能体 | I8: 是 | J8: 助学 | K8: 智能辅导系统 | M8: 智育 | N8: =VLOOKUP($A8,Sheet1!$A$1:$T$2589,6,0) -> 生物
A9: 第1590号案例_附件1：基于3D虚拟交互技术的高中生物复杂操作实验应用案例申报书.docx | B9: 3D虚拟实验室 | C9: 3D虚拟实验室 | D9: 3D虚拟实验室 | E9: 功能应用层 | F9: 功能应用（教学辅助工具） | G9: 软件工具 | H9: AI智能体 | I9: 否 | J9: 助教 | K9: 课堂管理 | M9: 智育 | N9: =VLOOKUP($A9,Sheet1!$A$1:$T$2589,6,0) -> 生物
A10: 第1563号案例_“人工智能+基础教育”典型应用场景案例申报书.pdf | B10: 4K智能跟拍系统 | C10: 4K智能跟拍系统 | D10: 4K智能跟拍系统 | E10: 功能应用层 | F10: 功能应用（校级 / 区域级系统） | G10: 软件工具 | H10: AI智能体 | I10: 否 | J10: 助教 | K10: 课堂管理 | M10: 智育 | N10: =VLOOKUP($A10,Sheet1!$A$1:$T$2589,6,0) -> 数学/语文/信息技术
A11: 第1311号案例_以AI为“眼” 护童心—— 学生情绪监测与心理健康预警数字化应用实践案例.docx | B11: 5G AI相机 | C11: 5G AI相机 | D11: 5G AI相机 | E11: 功能应用层 | F11: 功能应用（校级 / 区域级系统） | G11: 软件工具 | H11: AI智能体 | I11: 否 | J11: 助教 | K11: 课堂管理 | M11: 智育 | N11: =VLOOKUP($A11,Sheet1!$A$1:$T$2589,6,0) -> 心理健康教育
A12: 第1682号案例_1682银川市金凤区第十八小学+马婷+智赋诗教·情浸江南——AI赋能小学语文古典诗词沉浸式教学实践.pdf | B12: 720云VR全景 | C12: 720云VR全景 | D12: 720云VR全景 | E12: 功能应用层 | F12: 功能应用（教学辅助工具） | G12: 软件工具 | H12: AI智能体 | I12: 是 | J12: 助学 | K12: 智能辅导系统 | M12: 智育 | N12: =VLOOKUP($A12,Sheet1!$A$1:$T$2589,6,0) -> 语文
A13: 第26号案例_26重庆市第八中学校+人工智能赋能学生评价——AI助力教师撰写评语的实践探索.pdf | B13: AA班级助手 | C13: AA班级助手 | D13: 豆包 | E13: 功能应用层 | F13: 功能应用（教学辅助工具） | G13: 软件工具 | H13: AI智能体 | I13: 是 | J13: 助学 | K13: 智能辅导系统 | M13: 智育 | N13: =VLOOKUP($A13,Sheet1!$A$1:$T$2589,6,0) -> 未提及
A14: 第563号案例_银川市金凤区第十八小学 沙小娜 AI助力数字编码大侦探.docx | B14: Adobe Audition | C14: Adobe Audition | D14: Adobe Audition | E14: 功能应用层 | F14: 功能应用（教学辅助工具） | G14: 软件工具 | H14: AI智能体 | I14: 是 | J14: 助学 | K14: 情境式学习 | M14: 美育 | N14: =VLOOKUP($A14,Sheet1!$A$1:$T$2589,6,0) -> #N/A
... A126: 第968号案例_附件1.“人工智能+基础教育”典型应用场景案例申报书.docx | B126: AI备课系统 | C126: AI备课系统 | D126: AI备课系统 | E126: 功能应用层 | F126: 功能应用（教学辅助工具） | G126: 软件工具 | H126: AI智能体 | I126: 否 | J126: 助学 | K126: 智能辅导系统 | M126: 智育 | N126: =VLOOKUP($A126,Sheet1!$A$1:$T$2589,6,0) -> 未提及
A127: 第1299号案例_附件1.“人工智能+基础教育”典型应用场景案例申报书.docx | B127: AI大模型（如豆包） | C127: 豆包 | D127: 豆包 | E127: 功能应用层 | F127: 功能应用（教学辅助工具） | G127: 软件工具 | H127: AI智能体 | I127: 否 | J127: 助学 | K127: 智能辅导系统 | M127: 智育 | N127: =VLOOKUP($A127,Sheet1!$A$1:$T$2589,6,0) -> 道德与法治 | O127: 北京春田知韵科技有限公司
A128: 第1805号案例_北京市西城区棉花胡同幼儿园-周思贤-AI赋能幼儿园跨领域探究的循迹小车轨道游戏实践.docx | B128: AI学习分析工具 | C128: AI学习分析工具 | D128: AI学习分析工具 | E128: 功能应用层 | F128: 功能应用层（机器人） | G128: 硬件设备 | H128: AI智能体 | I128: 否 | J128: 助学 | K128: 智能辅导系统 | M128: 智育 | N128: =VLOOKUP($A128,Sheet1!$A$1:$T$2589,6,0) -> 科学/艺术/数学/社会
A129: 第848号案例_848重庆市第九十五初级中学校 梁宇涵 AI驱动初中数学‘三维作业生态’：分层精准化、评阅即时化、学情智控化实践.docx | B129: AI学习分析平台 | C129: AI学习分析平台 | D129: AI学习分析平台 | E129: 功能应用层 | F129: 功能应用（教学辅助工具） | G129: 软件工具 | H129: AI智能体 | I129: 否 | J129: 助学 | K129: 智能辅导系统 | M129: 智育 | N129: =VLOOKUP($A129,Sheet1!$A$1:$T$2589,6,0) -> #N/A
A130: 第401号案例_“人工智能+基础教育”典型应用场景案例申报书.docx | B130: AI学习分析技术 | C130: AI学习分析技术 | D130: AI学习分析技术 | E130: 功能应用层 | F130: 功能应用（校级 / 区域级系统） | G130: 软件工具 | H130: AI智能体 | I130: 否 | J130: 助学 | K130: 智能辅导系统 | M130: 智育 | N130: =VLOOKUP($A130,Sheet1!$A$1:$T$2589,6,0) -> 科学
A131: 第334号案例_大同市云州区城镇第二小学校刘玉琴AI 驱动下《伯牙鼓琴》深度教学实践案例.docx | B131: AI学习分析系统 | C131: AI学习分析系统 | D131: AI学习分析系统 | E131: 功能应用层 | F131: 功能应用（教学辅助工具） | G131: 软件工具 | H131: AI智能体 | I131: 是 | J131: 助学 | K131: 智能辅导系统 | M131: 智育 | N131: =VLOOKUP($A131,Sheet1!$A$1:$T$2589,6,0) -> 语文
A132: 第94号案例_94上海市奉贤区青少年业余体育学校 曹冰清 《从“使用AI”到“领导AI”：构建培养学生“AI领导力”的语文作业新范式》.docx | B132: AI学习单 | C132: AI学习单 | D132: AI学习单 | E132: 功能应用层 | F132: 功能应用（教学辅助工具） | G132: 软件工具 | H132: 大语言模型 | I132: 是 | J132: 助学 | K132: 智能辅导系统 | M132: 智育 | N132: =VLOOKUP($A132,Sheet1!$A$1:$T$2589,6,0) -> 语文
A133: 第1607号案例_莆田实验小学-刘建平-“人工智能+基础教育”典型应用场景案例申报书.docx | B133: AI学习平台 | C133: AI学习平台 | D133: AI学习平台 | E133: 功能应用层 | F133: 功能应用（教学辅助工具） | G133: 软件工具 | H133: AI智能体 | I133: 否 | J133: 助学 | K133: 智能辅导系统 | M133: 智育 | N133: =VLOOKUP($A133,Sheet1!$A$1:$T$2589,6,0) -> 美术
A134: 第01号案例_1温州市新田园小学 叶诗婧《数“算”生“动”：AI赋能下运算律教学的新样态》.pdf | B134: AI学习机 | C134: AI学习机 | D134: AI学习机 | E134: 功能应用层 | F134: 功能应用（教学辅助工具） | G134: 软件工具 | H134: 大语言模型 | I134: 是 | J134: 助学 | K134: 智能辅导系统 | M134: 智育 | N134: =VLOOKUP($A134,Sheet1!$A$1:$T$2589,6,0) -> 数学
